Workbook

Sheet START HERE
B2: WEEKLY BILLING REPORT · BPO
B4: =" Week: "&TEXT(Config!$C$7,"dd/mm/yyyy")&" to "&TEXT(Config!$C$8,"dd/mm/yyyy")&" · Target: "&TEXT(Config!$C$9,"0")&" hours per day = 1.0 billing unit" -> Week: 31/08/2026 to 04/09/2026 · Target: 8 hours per day = 1.0 billing unit
B6: THE GOLDEN RULE
B7: Every BPO landman must close EXACTLY 8 HOURS per business day. In BTabs that is written as 1.0 in "Time Worked". Each hour is worth 0.125 (1 h = 0.125 · 2 h = 0.25 · 4 h = 0.5 · 8 h = 1.0). If someone did not work (medical leave, personal day, vacation) they must ALSO log the day as Time Off / BPO Vacation and write the hours at the start of the detail. That way the day still adds up to 8.
B11: HOW TO USE IT EACH WEEK (3 steps)
B12: STEP 1 | D12: Export the BTabs report and paste everything into the RawBtabs tab, starting at cell A2. Do not change the headers in row 1. | F12: Tab RawBtabs
B14: STEP 2 | D14: Go to the Config tab and type the MONDAY of the week you want to review into the yellow cell. That is the only thing you change. | F14: Tab Config
B16: STEP 3 | D16: Open Dashboard, Alerts, TimeOff and SeniorReview. Already calculated. Check DataHealth first, then fill the yellow sign-off cells. | F16: Tab Dashboard
B19: WHAT IS IN EACH TAB
C20: Dashboard | D20: The main board. A traffic light per person per day + the status of the week.
C21: Alerts | D21: Only the days with a problem, with the concrete action to take. This is the work list.
C22: TimeOff | D22: Who did not work billable hours (personal, medical leave, vacation) and whether the day still closed at 8 h.
C23: SeniorReview | D23: Summary by Team Lead + a 7-point control checklist + space for the senior sign-off.
C24: DataHealth | D24: Checks the pasted data itself: missing roster names, weekend entries, duplicates, unapproved rows.
C25: Legend | D25: Every colour, every message and every column explained, plus the glossary. Read this once.
C26: Historical | D26: How many alerts each person accumulates week over week, with a risk indicator.
C27: Detail | D27: Calculation engine: one row per person per day. Technical sheet, no need to touch it.
C28: Config | D28: The parameters: week to report, target hours, tolerance and time off types.
C29: BPOworkers | D29: The roster: who belongs to BPO and who their Team Lead is. Add or remove people here.
B30: COLOR CODE
B31: Yellow | D31: A cell YOU can edit.
B32: Green | D32: Meets the target. All good.
B33: Light red | D33: Under 8 h. There is billing being lost.
B34: Blue | D34: Over 8 h. Check for duplicates.
B35: Dark red | D35: Logged nothing in BTabs that day. The most serious case.
B37: WHERE EVERY NUMBER COMES FROM (the report formula)
B38: TOTAL COUNTED FOR THE DAY = ( Time Worked x 8 ) + Time off hours · "Time Worked" is column K of the BTabs export (1.0 = a full day). · "Time off hours" is the first number in the "Work Performed Detail" field whenever the Work Type is Time Off, BPO Vacation or Holiday. · This is the same logic as the calculated field in the original file; here it is written in native Excel formulas so it works without Google Sheets.
B43: IMPORTANT · This file does NOT use the Google Sheets FILTER or REGEXEXTRACT functions that the original relied on. Everything is in native Excel formulas, so it opens and recalculates in desktop Excel with nothing lost.

Sheet Dashboard
T1: _aux
B2: WEEKLY BILLING DASHBOARD - BPO | T2: =Config!$C$9 -> 8
B3: Green = closed 8 h. Red = under target. Blue = over 8 h. Dark red = no entry in BTabs that day. | T3: =Config!$C$10 -> 0
B5: PEOPLE IN ROSTER | D5: PERFECT WEEK | F5: TO REVIEW | H5: CRITICAL | J5: % COMPLIANCE | L5: BILLED HOURS | N5: TARGET HOURS
B6: =Config!$C$14 -> 38 | D6: =COUNTIF($Q$10:$Q$69,0) -> 33 | F6: =COUNTIF($Q$10:$Q$69,1)+COUNTIF($Q$10:$Q$69,2) -> 3 | H6: =COUNTIF($Q$10:$Q$69,3) -> 2 | J6: =IFERROR($D$6/$B$6,0) -> 0.86842105 | L6: =SUM($J$10:$J$69) -> 1528 | N6: =SUM($K$10:$K$69) -> 1520
B8: # | C8: LANDMAN | D8: TEAM LEAD | E8: HOURS COUNTED PER DAY (target 8 h = 1.0 unit) | J8: TOTAL week | K8: TARGET week | L8: DIFF. vs target | M8: Days with entries | N8: Days on target | O8: Days with alert | P8: WEEK STATUS | Q8: Sev. | R8: WHY - exactly which day is off, and by how much
E9: =LEFT(INDEX(Config!$F$7:$F$11,1),3)&" "&TEXT(Config!$C$7+0,"dd/mm") -> Mon 31/08 | F9: =LEFT(INDEX(Config!$F$7:$F$11,2),3)&" "&TEXT(Config!$C$7+1,"dd/mm") -> Tue 01/09 | G9: =LEFT(INDEX(Config!$F$7:$F$11,3),3)&" "&TEXT(Config!$C$7+2,"dd/mm") -> Wed 02/09 | H9: =LEFT(INDEX(Config!$F$7:$F$11,4),3)&" "&TEXT(Config!$C$7+3,"dd/mm") -> Thu 03/09 | I9: =LEFT(INDEX(Config!$F$7:$F$11,5),3)&" "&TEXT(Config!$C$7+4,"dd/mm") -> Fri 04/09
B10: =IF($C10="","",ROW()-9) -> 1 | C10: =IF(ROW()-9>Config!$C$14,"",INDEX(BPOworkers!$B$6:$B$105,ROW()-9)) -> A Camargo | D10: =IF($C10="","",IFERROR(INDEX(BPOworkers!$E$6:$E$105,MATCH($C10,BPOworkers!$B$6:$B$105,0)),"")) -> BPO Management | E10: =IF($C10="","",IF(INDEX(Detail!$G$4:$G$303,(ROW()-10)*5+1)=0,"",INDEX(Detail!$J$4:$J$303,(ROW()-10)*5+1))) -> 8 | F10: =IF($C10="","",IF(INDEX(Detail!$G$4:$G$303,(ROW()-10)*5+2)=0,"",INDEX(Detail!$J$4:$J$303,(ROW()-10)*5+2))) -> 8 | G10: =IF($C10="","",IF(INDEX(Detail!$G$4:$G$303,(ROW()-10)*5+3)=0,"",INDEX(Detail!$J$4:$J$303,(ROW()-10)*5+3))) -> 8 | H10: =IF($C10="","",IF(INDEX(Detail!$G$4:$G$303,(ROW()-10)*5+4)=0,"",INDEX(Detail!$J$4:$J$303,(ROW()-10)*5+4))) -> 8 | I10: =IF($C10="","",IF(INDEX(Detail!$G$4:$G$303,(ROW()-10)*5+5)=0,"",INDEX(Detail!$J$4:$J$303,(ROW()-10)*5+5))) -> 8 | J10: =IF($C10="","",SUM($E10:$I10)) -> 40 | K10: =IF($C10="","",Config!$C$16) -> 40 | L10: =IF($C10="","",$J10-$K10) -> 0 | M10: =IF($C10="","",COUNT($E10:$I10)) -> 5 | N10: =IF($C10="","",COUNTIFS(Detail!$C$4:$C$303,$C10,Detail!$N$4:$N$303,0)) -> 5 | O10: =IF($C10="","",COUNTIFS(Detail!$C$4:$C$303,$C10,Detail!$N$4:$N$303,">0")) -> 0 | P10: =IF($C10="","",IF($M10=0,"⛔ BILLED NOTHING",IF($M10<5,"⛔ MISSING "&TEXT(5-$M10,"0")&" DAY(S) IN BTABS",IF($O10=0,"✅ PERFECT WEEK",IF($L10<0,"🔻 UNDER TARGET ("&TEXT($L10,"0.##")&" h)",IF($L10>0,"🔺 OVER TARGET (+"&TEXT($L10,"0.##")&" h)","⚠️ CHECK THE DAYS")))))) -> ✅ PERFECT WEEK | Q10: =IF($C10="","",IF($M10<5,3,IF($O10=0,0,IF($L10>0,1,2)))) -> 0 | R10: =IF($C10="","",IF($O10=0,"All 5 days closed at target. Nothing to fix.",TRIM(IF(E10="",LEFT(INDEX(Config!$F$7:$F$11,1),3)&": no entry in BTabs. ",IF(ABS(E10-$T$2)>$T$3,LEFT(INDEX(Config!$F$7:$F$11,1),3)&": "&TEXT(E10,"0.##")&" h instead of "&TEXT($T$2,"0")&" h. ",""))&IF(F10="",LEFT(INDEX(Config!$F$7:$F$11,2),3)&": no entry in BTabs. ",IF(ABS(F10-$T$2)>$T$3,LEFT(INDEX(Config!$F$7:$F$11,2),3)&": "&TEXT(F10,"0.##")&" h instead of "&TEXT($T$2,"0")&" h. ",""))&IF(G10="",LEFT(INDEX(Config!$F$7:$F$11,3),3)&": no entry in BTabs. ",IF(ABS(G10-$T$2)>$T$3,LEFT(INDEX(Config!$F$7:$F$11,3),3)&": "&TEXT(G10,"0.##")&" h instead of "&TEXT($T$2,"0")&" h. ",""))&IF(H10="",LEFT(INDEX(Config!$F$7:$F$11,4),3)&": no entry in BTabs. ",IF(ABS(H10-$T$2)>$T$3,LEFT(INDEX(Config!$F$7:$F$11,4),3)&": "&TEXT(H10,"0.##")&" h instead of "&TEXT($T$2,"0")&" h. ",""))&IF(I10="",LEFT(INDEX(Config!$F$7:$F$11,5),3)&": no entry in BTabs. ",IF(ABS(I10-$T$2)>$T$3,LEFT(INDEX(Config!$F$7:$F$11,5),3)&": "&TEXT(I10,"0.##")&" h instead of "&TEXT($T$2,"0")&" h. ",""))))) -> All 5 days closed at target. Nothing to fix.
B11: =IF($C11="","",ROW()-9) -> 2 | C11: =IF(ROW()-9>Config!$C$14,"",INDEX(BPOworkers!$B$6:$B$105,ROW()-9)) -> A Lopez | D11: =IF($C11="","",IFERROR(INDEX(BPOworkers!$E$6:$E$105,MATCH($C11,BPOworkers!$B$6:$B$105,0)),"")) -> S Romero | E11: =IF($C11="","",IF(INDEX(Detail!$G$4:$G$303,(ROW()-10)*5+1)=0,"",INDEX(Detail!$J$4:$J$303,(ROW()-10)*5+1))) -> 8 | F11: =IF($C11="","",IF(INDEX(Detail!$G$4:$G$303,(ROW()-10)*5+2)=0,"",INDEX(Detail!$J$4:$J$303,(ROW()-10)*5+2))) -> 8 | G11: =IF($C11="","",IF(INDEX(Detail!$G$4:$G$303,(ROW()-10)*5+3)=0,"",INDEX(Detail!$J$4:$J$303,(ROW()-10)*5+3))) -> 8 | H11: =IF($C11="","",IF(INDEX(Detail!$G$4:$G$303,(ROW()-10)*5+4)=0,"",INDEX(Detail!$J$4:$J$303,(ROW()-10)*5+4))) -> 8 | I11: =IF($C11="","",IF(INDEX(Detail!$G$4:$G$303,(ROW()-10)*5+5)=0,"",INDEX(Detail!$J$4:$J$303,(ROW()-10)*5+5))) -> 8 | J11: =IF($C11="","",SUM($E11:$I11)) -> 40 | K11: =IF($C11="","",Config!$C$16) -> 40 | L11: =IF($C11="","",$J11-$K11) -> 0 | M11: =IF($C11="","",COUNT($E11:$I11)) -> 5 | N11: =IF($C11="","",COUNTIFS(Detail!$C$4:$C$303,$C11,Detail!$N$4:$N$303,0)) -> 5 | O11: =IF($C11="","",COUNTIFS(Detail!$C$4:$C$303,$C11,Detail!$N$4:$N$303,">0")) -> 0 | P11: =IF($C11="","",IF($M11=0,"⛔ BILLED NOTHING",IF($M11<5,"⛔ MISSING "&TEXT(5-$M11,"0")&" DAY(S) IN BTABS",IF($O11=0,"✅ PERFECT WEEK",IF($L11<0,"🔻 UNDER TARGET ("&TEXT($L11,"0.##")&" h)",IF($L11>0,"🔺 OVER TARGET (+"&TEXT($L11,"0.##")&" h)","⚠️ CHECK THE DAYS")))))) -> ✅ PERFECT WEEK | Q11: =IF($C11="","",IF($M11<5,3,IF($O11=0,0,IF($L11>0,1,2)))) -> 0 | R11: =IF($C11="","",IF($O11=0,"All 5 days closed at target. Nothing to fix.",TRIM(IF(E11="",LEFT(INDEX(Config!$F$7:$F$11,1),3)&": no entry in BTabs. ",IF(ABS(E11-$T$2)>$T$3,LEFT(INDEX(Config!$F$7:$F$11,1),3)&": "&TEXT(E11,"0.##")&" h instead of "&TEXT($T$2,"0")&" h. ",""))&IF(F11="",LEFT(INDEX(Config!$F$7:$F$11,2),3)&": no entry in BTabs. ",IF(ABS(F11-$T$2)>$T$3,LEFT(INDEX(Config!$F$7:$F$11,2),3)&": "&TEXT(F11,"0.##")&" h instead of "&TEXT($T$2,"0")&" h. ",""))&IF(G11="",LEFT(INDEX(Config!$F$7:$F$11,3),3)&": no entry in BTabs. ",IF(ABS(G11-$T$2)>$T$3,LEFT(INDEX(Config!$F$7:$F$11,3),3)&": "&TEXT(G11,"0.##")&" h instead of "&TEXT($T$2,"0")&" h. ",""))&IF(H11="",LEFT(INDEX(Config!$F$7:$F$11,4),3)&": no entry in BTabs. ",IF(ABS(H11-$T$2)>$T$3,LEFT(INDEX(Config!$F$7:$F$11,4),3)&": "&TEXT(H11,"0.##")&" h instead of "&TEXT($T$2,"0")&" h. ",""))&IF(I11="",LEFT(INDEX(Config!$F$7:$F$11,5),3)&": no entry in BTabs. ",IF(ABS(I11-$T$2)>$T$3,LEFT(INDEX(Config!$F$7:$F$11,5),3)&": "&TEXT(I11,"0.##")&" h instead of "&TEXT($T$2,"0")&" h. ",""))))) -> All 5 days closed at target. Nothing to fix.
B12: =IF($C12="","",ROW()-9) -> 3 | C12: =IF(ROW()-9>Config!$C$14,"",INDEX(BPOworkers!$B$6:$B$105,ROW()-9)) -> A Lorenzo | D12: =IF($C12="","",IFERROR(INDEX(BPOworkers!$E$6:$E$105,MATCH($C12,BPOworkers!$B$6:$B$105,0)),"")) -> BPO Management | E12: =IF($C12="","",IF(INDEX(Detail!$G$4:$G$303,(ROW()-10)*5+1)=0,"",INDEX(Detail!$J$4:$J$303,(ROW()-10)*5+1))) -> 8 | F12: =IF($C12="","",IF(INDEX(Detail!$G$4:$G$303,(ROW()-10)*5+2)=0,"",INDEX(Detail!$J$4:$J$303,(ROW()-10)*5+2))) -> 8 | G12: =IF($C12="","",IF(INDEX(Detail!$G$4:$G$303,(ROW()-10)*5+3)=0,"",INDEX(Detail!$J$4:$J$303,(ROW()-10)*5+3))) -> 8 | H12: =IF($C12="","",IF(INDEX(Detail!$G$4:$G$303,(ROW()-10)*5+4)=0,"",INDEX(Detail!$J$4:$J$303,(ROW()-10)*5+4))) -> 8 | I12: =IF($C12="","",IF(INDEX(Detail!$G$4:$G$303,(ROW()-10)*5+5)=0,"",INDEX(Detail!$J$4:$J$303,(ROW()-10)*5+5))) -> 8 | J12: =IF($C12="","",SUM($E12:$I12)) -> 40 | K12: =IF($C12="","",Config!$C$16) -> 40 | L12: =IF($C12="","",$J12-$K12) -> 0 | M12: =IF($C12="","",COUNT($E12:$I12)) -> 5 | N12: =IF($C12="","",COUNTIFS(Detail!$C$4:$C$303,$C12,Detail!$N$4:$N$303,0)) -> 5 | O12: =IF($C12="","",COUNTIFS(Detail!$C$4:$C$303,$C12,Detail!$N$4:$N$303,">0")) -> 0 | P12: =IF($C12="","",IF($M12=0,"⛔ BILLED NOTHING",IF($M12<5,"⛔ MISSING "&TEXT(5-$M12,"0")&" DAY(S) IN BTABS",IF($O12=0,"✅ PERFECT WEEK",IF($L12<0,"🔻 UNDER TARGET ("&TEXT($L12,"0.##")&" h)",IF($L12>0,"🔺 OVER TARGET (+"&TEXT($L12,"0.##")&" h)","⚠️ CHECK THE DAYS")))))) -> ✅ PERFECT WEEK | Q12: =IF($C12="","",IF($M12<5,3,IF($O12=0,0,IF($L12>0,1,2)))) -> 0 | R12: =IF($C12="","",IF($O12=0,"All 5 days closed at target. Nothing to fix.",TRIM(IF(E12="",LEFT(INDEX(Config!$F$7:$F$11,1),3)&": no entry in BTabs. ",IF(ABS(E12-$T$2)>$T$3,LEFT(INDEX(Config!$F$7:$F$11,1),3)&": "&TEXT(E12,"0.##")&" h instead of "&TEXT($T$2,"0")&" h. ",""))&IF(F12="",LEFT(INDEX(Config!$F$7:$F$11,2),3)&": no entry in BTabs. ",IF(ABS(F12-$T$2)>$T$3,LEFT(INDEX(Config!$F$7:$F$11,2),3)&": "&TEXT(F12,"0.##")&" h instead of "&TEXT($T$2,"0")&" h. ",""))&IF(G12="",LEFT(INDEX(Config!$F$7:$F$11,3),3)&": no entry in BTabs. ",IF(ABS(G12-$T$2)>$T$3,LEFT(INDEX(Config!$F$7:$F$11,3),3)&": "&TEXT(G12,"0.##")&" h instead of "&TEXT($T$2,"0")&" h. ",""))&IF(H12="",LEFT(INDEX(Config!$F$7:$F$11,4),3)&": no entry in BTabs. ",IF(ABS(H12-$T$2)>$T$3,LEFT(INDEX(Config!$F$7:$F$11,4),3)&": "&TEXT(H12,"0.##")&" h instead of "&TEXT($T$2,"0")&" h. ",""))&IF(I12="",LEFT(INDEX(Config!$F$7:$F$11,5),3)&": no entry in BTabs. ",IF(ABS(I12-$T$2)>$T$3,LEFT(INDEX(Config!$F$7:$F$11,5),3)&": "&TEXT(I12,"0.##")&" h instead of "&TEXT($T$2,"0")&" h. ",""))))) -> All 5 days closed at target. Nothing to fix.
B13: =IF($C13="","",ROW()-9) -> 4 | C13: =IF(ROW()-9>Config!$C$14,"",INDEX(BPOworkers!$B$6:$B$105,ROW()-9)) -> C Mesa | D13: =IF($C13="","",IFERROR(INDEX(BPOworkers!$E$6:$E$105,MATCH($C13,BPOworkers!$B$6:$B$105,0)),"")) -> M Leon | E13: =IF($C13="","",IF(INDEX(Detail!$G$4:$G$303,(ROW()-10)*5+1)=0,"",INDEX(Detail!$J$4:$J$303,(ROW()-10)*5+1))) -> 8 | F13: =IF($C13="","",IF(INDEX(Detail!$G$4:$G$303,(ROW()-10)*5+2)=0,"",INDEX(Detail!$J$4:$J$303,(ROW()-10)*5+2))) -> 8 | G13: =IF($C13="","",IF(INDEX(Detail!$G$4:$G$303,(ROW()-10)*5+3)=0,"",INDEX(Detail!$J$4:$J$303,(ROW()-10)*5+3))) -> 8 | H13: =IF($C13="","",IF(INDEX(Detail!$G$4:$G$303,(ROW()-10)*5+4)=0,"",INDEX(Detail!$J$4:$J$303,(ROW()-10)*5+4))) -> 8 | I13: =IF($C13="","",IF(INDEX(Detail!$G$4:$G$303,(ROW()-10)*5+5)=0,"",INDEX(Detail!$J$4:$J$303,(ROW()-10)*5+5))) -> 8 | J13: =IF($C13="","",SUM($E13:$I13)) -> 40 | K13: =IF($C13="","",Config!$C$16) -> 40 | L13: =IF($C13="","",$J13-$K13) -> 0 | M13: =IF($C13="","",COUNT($E13:$I13)) -> 5 | N13: =IF($C13="","",COUNTIFS(Detail!$C$4:$C$303,$C13,Detail!$N$4:$N$303,0)) -> 5 | O13: =IF($C13="","",COUNTIFS(Detail!$C$4:$C$303,$C13,Detail!$N$4:$N$303,">0")) -> 0 | P13: =IF($C13="","",IF($M13=0,"⛔ BILLED NOTHING",IF($M13<5,"⛔ MISSING "&TEXT(5-$M13,"0")&" DAY(S) IN BTABS",IF($O13=0,"✅ PERFECT WEEK",IF($L13<0,"🔻 UNDER TARGET ("&TEXT($L13,"0.##")&" h)",IF($L13>0,"🔺 OVER TARGET (+"&TEXT($L13,"0.##")&" h)","⚠️ CHECK THE DAYS")))))) -> ✅ PERFECT WEEK | Q13: =IF($C13="","",IF($M13<5,3,IF($O13=0,0,IF($L13>0,1,2)))) -> 0 | R13: =IF($C13="","",IF($O13=0,"All 5 days closed at target. Nothing to fix.",TRIM(IF(E13="",LEFT(INDEX(Config!$F$7:$F$11,1),3)&": no entry in BTabs. ",IF(ABS(E13-$T$2)>$T$3,LEFT(INDEX(Config!$F$7:$F$11,1),3)&": "&TEXT(E13,"0.##")&" h instead of "&TEXT($T$2,"0")&" h. ",""))&IF(F13="",LEFT(INDEX(Config!$F$7:$F$11,2),3)&": no entry in BTabs. ",IF(ABS(F13-$T$2)>$T$3,LEFT(INDEX(Config!$F$7:$F$11,2),3)&": "&TEXT(F13,"0.##")&" h instead of "&TEXT($T$2,"0")&" h. ",""))&IF(G13="",LEFT(INDEX(Config!$F$7:$F$11,3),3)&": no entry in BTabs. ",IF(ABS(G13-$T$2)>$T$3,LEFT(INDEX(Config!$F$7:$F$11,3),3)&": "&TEXT(G13,"0.##")&" h instead of "&TEXT($T$2,"0")&" h. ",""))&IF(H13="",LEFT(INDEX(Config!$F$7:$F$11,4),3)&": no entry in BTabs. ",IF(ABS(H13-$T$2)>$T$3,LEFT(INDEX(Config!$F$7:$F$11,4),3)&": "&TEXT(H13,"0.##")&" h instead of "&TEXT($T$2,"0")&" h. ",""))&IF(I13="",LEFT(INDEX(Config!$F$7:$F$11,5),3)&": no entry in BTabs. ",IF(ABS(I13-$T$2)>$T$3,LEFT(INDEX(Config!$F$7:$F$11,5),3)&": "&TEXT(I13,"0.##")&" h instead of "&TEXT($T$2,"0")&" h. ",""))))) -> All 5 days closed at target. Nothing to fix.
B14: =IF($C14="","",ROW()-9) -> 5 | C14: =IF(ROW()-9>Config!$C$14,"",INDEX(BPOworkers!$B$6:$B$105,ROW()-9)) -> H Daza | D14: =IF($C14="","",IFERROR(INDEX(BPOworkers!$E$6:$E$105,MATCH($C14,BPOworkers!$B$6:$B$105,0)),"")) -> BPO Management | E14: =IF($C14="","",IF(INDEX(Detail!$G$4:$G$303,(ROW()-10)*5+1)=0,"",INDEX(Detail!$J$4:$J$303,(ROW()-10)*5+1))) -> 8 | F14: =IF($C14="","",IF(INDEX(Detail!$G$4:$G$303,(ROW()-10)*5+2)=0,"",INDEX(Detail!$J$4:$J$303,(ROW()-10)*5+2))) -> 8 | G14: =IF($C14="","",IF(INDEX(Detail!$G$4:$G$303,(ROW()-10)*5+3)=0,"",INDEX(Detail!$J$4:$J$303,(ROW()-10)*5+3))) -> 8 | H14: =IF($C14="","",IF(INDEX(Detail!$G$4:$G$303,(ROW()-10)*5+4)=0,"",INDEX(Detail!$J$4:$J$303,(ROW()-10)*5+4))) -> 8 | I14: =IF($C14="","",IF(INDEX(Detail!$G$4:$G$303,(ROW()-10)*5+5)=0,"",INDEX(Detail!$J$4:$J$303,(ROW()-10)*5+5))) -> 8 | J14: =IF($C14="","",SUM($E14:$I14)) -> 40 | K14: =IF($C14="","",Config!$C$16) -> 40 | L14: =IF($C14="","",$J14-$K14) -> 0 | M14: =IF($C14="","",COUNT($E14:$I14)) -> 5 | N14: =IF($C14="","",COUNTIFS(Detail!$C$4:$C$303,$C14,Detail!$N$4:$N$303,0)) -> 5 | O14: =IF($C14="","",COUNTIFS(Detail!$C$4:$C$303,$C14,Detail!$N$4:$N$303,">0")) -> 0 | P14: =IF($C14="","",IF($M14=0,"⛔ BILLED NOTHING",IF($M14<5,"⛔ MISSING "&TEXT(5-$M14,"0")&" DAY(S) IN BTABS",IF($O14=0,"✅ PERFECT WEEK",IF($L14<0,"🔻 UNDER TARGET ("&TEXT($L14,"0.##")&" h)",IF($L14>0,"🔺 OVER TARGET (+"&TEXT($L14,"0.##")&" h)","⚠️ CHECK THE DAYS")))))) -> ✅ PERFECT WEEK | Q14: =IF($C14="","",IF($M14<5,3,IF($O14=0,0,IF($L14>0,1,2)))) -> 0 | R14: =IF($C14="","",IF($O14=0,"All 5 days closed at target. Nothing to fix.",TRIM(IF(E14="",LEFT(INDEX(Config!$F$7:$F$11,1),3)&": no entry in BTabs. ",IF(ABS(E14-$T$2)>$T$3,LEFT(INDEX(Config!$F$7:$F$11,1),3)&": "&TEXT(E14,"0.##")&" h instead of "&TEXT($T$2,"0")&" h. ",""))&IF(F14="",LEFT(INDEX(Config!$F$7:$F$11,2),3)&": no entry in BTabs. ",IF(ABS(F14-$T$2)>$T$3,LEFT(INDEX(Config!$F$7:$F$11,2),3)&": "&TEXT(F14,"0.##")&" h instead of "&TEXT($T$2,"0")&" h. ",""))&IF(G14="",LEFT(INDEX(Config!$F$7:$F$11,3),3)&": no entry in BTabs. ",IF(ABS(G14-$T$2)>$T$3,LEFT(INDEX(Config!$F$7:$F$11,3),3)&": "&TEXT(G14,"0.##")&" h instead of "&TEXT($T$2,"0")&" h. ",""))&IF(H14="",LEFT(INDEX(Config!$F$7:$F$11,4),3)&": no entry in BTabs. ",IF(ABS(H14-$T$2)>$T$3,LEFT(INDEX(Config!$F$7:$F$11,4),3)&": "&TEXT(H14,"0.##")&" h instead of "&TEXT($T$2,"0")&" h. ",""))&IF(I14="",LEFT(INDEX(Config!$F$7:$F$11,5),3)&": no entry in BTabs. ",IF(ABS(I14-$T$2)>$T$3,LEFT(INDEX(Config!$F$7:$F$11,5),3)&": "&TEXT(I14,"0.##")&" h instead of "&TEXT($T$2,"0")&" h. ",""))))) -> All 5 days closed at target. Nothing to fix.
B15: =IF($C15="","",ROW()-9) -> 6 | C15: =IF(ROW()-9>Config!$C$14,"",INDEX(BPOworkers!$B$6:$B$105,ROW()-9)) -> I De La Parra | D15: =IF($C15="","",IFERROR(INDEX(BPOworkers!$E$6:$E$105,MATCH($C15,BPOworkers!$B$6:$B$105,0)),"")) -> A Lorenzo | E15: =IF($C15="","",IF(INDEX(Detail!$G$4:$G$303,(ROW()-10)*5+1)=0,"",INDEX(Detail!$J$4:$J$303,(ROW()-10)*5+1))) -> 8 | F15: =IF($C15="","",IF(INDEX(Detail!$G$4:$G$303,(ROW()-10)*5+2)=0,"",INDEX(Detail!$J$4:$J$303,(ROW()-10)*5+2))) -> 8 | G15: =IF($C15="","",IF(INDEX(Detail!$G$4:$G$303,(ROW()-10)*5+3)=0,"",INDEX(Detail!$J$4:$J$303,(ROW()-10)*5+3))) -> 8 | H15: =IF($C15="","",IF(INDEX(Detail!$G$4:$G$303,(ROW()-10)*5+4)=0,"",INDEX(Detail!$J$4:$J$303,(ROW()-10)*5+4))) -> 8 | I15: =IF($C15="","",IF(INDEX(Detail!$G$4:$G$303,(ROW()-10)*5+5)=0,"",INDEX(Detail!$J$4:$J$303,(ROW()-10)*5+5))) -> 8 | J15: =IF($C15="","",SUM($E15:$I15)) -> 40 | K15: =IF($C15="","",Config!$C$16) -> 40 | L15: =IF($C15="","",$J15-$K15) -> 0 | M15: =IF($C15="","",COUNT($E15:$I15)) -> 5 | N15: =IF($C15="","",COUNTIFS(Detail!$C$4:$C$303,$C15,Detail!$N$4:$N$303,0)) -> 5 | O15: =IF($C15="","",COUNTIFS(Detail!$C$4:$C$303,$C15,Detail!$N$4:$N$303,">0")) -> 0 | P15: =IF($C15="","",IF($M15=0,"⛔ BILLED NOTHING",IF($M15<5,"⛔ MISSING "&TEXT(5-$M15,"0")&" DAY(S) IN BTABS",IF($O15=0,"✅ PERFECT WEEK",IF($L15<0,"🔻 UNDER TARGET ("&TEXT($L15,"0.##")&" h)",IF($L15>0,"🔺 OVER TARGET (+"&TEXT($L15,"0.##")&" h)","⚠️ CHECK THE DAYS")))))) -> ✅ PERFECT WEEK | Q15: =IF($C15="","",IF($M15<5,3,IF($O15=0,0,IF($L15>0,1,2)))) -> 0 | R15: =IF($C15="","",IF($O15=0,"All 5 days closed at target. Nothing to fix.",TRIM(IF(E15="",LEFT(INDEX(Config!$F$7:$F$11,1),3)&": no entry in BTabs. ",IF(ABS(E15-$T$2)>$T$3,LEFT(INDEX(Config!$F$7:$F$11,1),3)&": "&TEXT(E15,"0.##")&" h instead of "&TEXT($T$2,"0")&" h. ",""))&IF(F15="",LEFT(INDEX(Config!$F$7:$F$11,2),3)&": no entry in BTabs. ",IF(ABS(F15-$T$2)>$T$3,LEFT(INDEX(Config!$F$7:$F$11,2),3)&": "&TEXT(F15,"0.##")&" h instead of "&TEXT($T$2,"0")&" h. ",""))&IF(G15="",LEFT(INDEX(Config!$F$7:$F$11,3),3)&": no entry in BTabs. ",IF(ABS(G15-$T$2)>$T$3,LEFT(INDEX(Config!$F$7:$F$11,3),3)&": "&TEXT(G15,"0.##")&" h instead of "&TEXT($T$2,"0")&" h. ",""))&IF(H15="",LEFT(INDEX(Config!$F$7:$F$11,4),3)&": no entry in BTabs. ",IF(ABS(H15-$T$2)>$T$3,LEFT(INDEX(Config!$F$7:$F$11,4),3)&": "&TEXT(H15,"0.##")&" h instead of "&TEXT($T$2,"0")&" h. ",""))&IF(I15="",LEFT(INDEX(Config!$F$7:$F$11,5),3)&": no entry in BTabs. ",IF(ABS(I15-$T$2)>$T$3,LEFT(INDEX(Config!$F$7:$F$11,5),3)&": "&TEXT(I15,"0.##")&" h instead of "&TEXT($T$2,"0")&" h. ",""))))) -> All 5 days closed at target. Nothing to fix.
B16: =IF($C16="","",ROW()-9) -> 7 | C16: =IF(ROW()-9>Config!$C$14,"",INDEX(BPOworkers!$B$6:$B$105,ROW()-9)) -> J Castillo | D16: =IF($C16="","",IFERROR(INDEX(BPOworkers!$E$6:$E$105,MATCH($C16,BPOworkers!$B$6:$B$105,0)),"")) -> J S Bermudez | E16: =IF($C16="","",IF(INDEX(Detail!$G$4:$G$303,(ROW()-10)*5+1)=0,"",INDEX(Detail!$J$4:$J$303,(ROW()-10)*5+1))) | F16: =IF($C16="","",IF(INDEX(Detail!$G$4:$G$303,(ROW()-10)*5+2)=0,"",INDEX(Detail!$J$4:$J$303,(ROW()-10)*5+2))) -> 8 | G16: =IF($C16="","",IF(INDEX(Detail!$G$4:$G$303,(ROW()-10)*5+3)=0,"",INDEX(Detail!$J$4:$J$303,(ROW()-10)*5+3))) -> 8 | H16: =IF($C16="","",IF(INDEX(Detail!$G$4:$G$303,(ROW()-10)*5+4)=0,"",INDEX(Detail!$J$4:$J$303,(ROW()-10)*5+4))) -> 8 | I16: =IF($C16="","",IF(INDEX(Detail!$G$4:$G$303,(ROW()-10)*5+5)=0,"",INDEX(Detail!$J$4:$J$303,(ROW()-10)*5+5))) -> 8 | J16: =IF($C16="","",SUM($E16:$I16)) -> 32 | K16: =IF($C16="","",Config!$C$16) -> 40 | L16: =IF($C16="","",$J16-$K16) -> -8 | M16: =IF($C16="","",COUNT($E16:$I16)) -> 4 | N16: =IF($C16="","",COUNTIFS(Detail!$C$4:$C$303,$C16,Detail!$N$4:$N$303,0)) -> 4 | O16: =IF($C16="","",COUNTIFS(Detail!$C$4:$C$303,$C16,Detail!$N$4:$N$303,">0")) -> 1 | P16: =IF($C16="","",IF($M16=0,"⛔ BILLED NOTHING",IF($M16<5,"⛔ MISSING "&TEXT(5-$M16,"0")&" DAY(S) IN BTABS",IF($O16=0,"✅ PERFECT WEEK",IF($L16<0,"🔻 UNDER TARGET ("&TEXT($L16,"0.##")&" h)",IF($L16>0,"🔺 OVER TARGET (+"&TEXT($L16,"0.##")&" h)","⚠️ CHECK THE DAYS")))))) -> ⛔ MISSING 1 DAY(S) IN BTABS | Q16: =IF($C16="","",IF($M16<5,3,IF($O16=0,0,IF($L16>0,1,2)))) -> 3 | R16: =IF($C16="","",IF($O16=0,"All 5 days closed at target. Nothing to fix.",TRIM(IF(E16="",LEFT(INDEX(Config!$F$7:$F$11,1),3)&": no entry in BTabs. ",IF(ABS(E16-$T$2)>$T$3,LEFT(INDEX(Config!$F$7:$F$11,1),3)&": "&TEXT(E16,"0.##")&" h instead of "&TEXT($T$2,"0")&" h. ",""))&IF(F16="",LEFT(INDEX(Config!$F$7:$F$11,2),3)&": no entry in BTabs. ",IF(ABS(F16-$T$2)>$T$3,LEFT(INDEX(Config!$F$7:$F$11,2),3)&": "&TEXT(F16,"0.##")&" h instead of "&TEXT($T$2,"0")&" h. ",""))&IF(G16="",LEFT(INDEX(Config!$F$7:$F$11,3),3)&": no entry in BTabs. ",IF(ABS(G16-$T$2)>$T$3,LEFT(INDEX(Config!$F$7:$F$11,3),3)&": "&TEXT(G16,"0.##")&" h instead of "&TEXT($T$2,"0")&" h. ",""))&IF(H16="",LEFT(INDEX(Config!$F$7:$F$11,4),3)&": no entry in BTabs. ",IF(ABS(H16-$T$2)>$T$3,LEFT(INDEX(Config!$F$7:$F$11,4),3)&": "&TEXT(H16,"0.##")&" h instead of "&TEXT($T$2,"0")&" h. ",""))&IF(I16="",LEFT(INDEX(Config!$F$7:$F$11,5),3)&": no entry in BTabs. ",IF(ABS(I16-$T$2)>$T$3,LEFT(INDEX(Config!$F$7:$F$11,5),3)&": "&TEXT(I16,"0.##")&" h instead of "&TEXT($T$2,"0")&" h. ",""))))) -> Mon: no entry in BTabs.
B17: =IF($C17="","",ROW()-9) -> 8 | C17: =IF(ROW()-9>Config!$C$14,"",INDEX(BPOworkers!$B$6:$B$105,ROW()-9)) -> J Valbuena | D17: =IF($C17="","",IFERROR(INDEX(BPOworkers!$E$6:$E$105,MATCH($C17,BPOworkers!$B$6:$B$105,0)),"")) -> H Daza | E17: =IF($C17="","",IF(INDEX(Detail!$G$4:$G$303,(ROW()-10)*5+1)=0,"",INDEX(Detail!$J$4:$J$303,(ROW()-10)*5+1))) -> 8 | F17: =IF($C17="","",IF(INDEX(Detail!$G$4:$G$303,(ROW()-10)*5+2)=0,"",INDEX(Detail!$J$4:$J$303,(ROW()-10)*5+2))) -> 8 | G17: =IF($C17="","",IF(INDEX(Detail!$G$4:$G$303,(ROW()-10)*5+3)=0,"",INDEX(Detail!$J$4:$J$303,(ROW()-10)*5+3))) -> 8 | H17: =IF($C17="","",IF(INDEX(Detail!$G$4:$G$303,(ROW()-10)*5+4)=0,"",INDEX(Detail!$J$4:$J$303,(ROW()-10)*5+4))) -> 8 | I17: =IF($C17="","",IF(INDEX(Detail!$G$4:$G$303,(ROW()-10)*5+5)=0,"",INDEX(Detail!$J$4:$J$303,(ROW()-10)*5+5))) -> 8 | J17: =IF($C17="","",SUM($E17:$I17)) -> 40 | K17: =IF($C17="","",Config!$C$16) -> 40 | L17: =IF($C17="","",$J17-$K17) -> 0 | M17: =IF($C17="","",COUNT($E17:$I17)) -> 5 | N17: =IF($C17="","",COUNTIFS(Detail!$C$4:$C$303,$C17,Detail!$N$4:$N$303,0)) -> 5 | O17: =IF($C17="","",COUNTIFS(Detail!$C$4:$C$303,$C17,Detail!$N$4:$N$303,">0")) -> 0 | P17: =IF($C17="","",IF($M17=0,"⛔ BILLED NOTHING",IF($M17<5,"⛔ MISSING "&TEXT(5-$M17,"0")&" DAY(S) IN BTABS",IF($O17=0,"✅ PERFECT WEEK",IF($L17<0,"🔻 UNDER TARGET ("&TEXT($L17,"0.##")&" h)",IF($L17>0,"🔺 OVER TARGET (+"&TEXT($L17,"0.##")&" h)","⚠️ CHECK THE DAYS")))))) -> ✅ PERFECT WEEK | Q17: =IF($C17="","",IF($M17<5,3,IF($O17=0,0,IF($L17>0,1,2)))) -> 0 | R17: =IF($C17="","",IF($O17=0,"All 5 days closed at target. Nothing to fix.",TRIM(IF(E17="",LEFT(INDEX(Config!$F$7:$F$11,1),3)&": no entry in BTabs. ",IF(ABS(E17-$T$2)>$T$3,LEFT(INDEX(Config!$F$7:$F$11,1),3)&": "&TEXT(E17,"0.##")&" h instead of "&TEXT($T$2,"0")&" h. ",""))&IF(F17="",LEFT(INDEX(Config!$F$7:$F$11,2),3)&": no entry in BTabs. ",IF(ABS(F17-$T$2)>$T$3,LEFT(INDEX(Config!$F$7:$F$11,2),3)&": "&TEXT(F17,"0.##")&" h instead of "&TEXT($T$2,"0")&" h. ",""))&IF(G17="",LEFT(INDEX(Config!$F$7:$F$11,3),3)&": no entry in BTabs. ",IF(ABS(G17-$T$2)>$T$3,LEFT(INDEX(Config!$F$7:$F$11,3),3)&": "&TEXT(G17,"0.##")&" h instead of "&TEXT($T$2,"0")&" h. ",""))&IF(H17="",LEFT(INDEX(Config!$F$7:$F$11,4),3)&": no entry in BTabs. ",IF(ABS(H17-$T$2)>$T$3,LEFT(INDEX(Config!$F$7:$F$11,4),3)&": "&TEXT(H17,"0.##")&" h instead of "&TEXT($T$2,"0")&" h. ",""))&IF(I17="",LEFT(INDEX(Config!$F$7:$F$11,5),3)&": no entry in BTabs. ",IF(ABS(I17-$T$2)>$T$3,LEFT(INDEX(Config!$F$7:$F$11,5),3)&": "&TEXT(I17,"0.##")&" h instead of "&TEXT($T$2,"0")&" h. ",""))))) -> All 5 days closed at target. Nothing to fix.
B18: =IF($C18="","",ROW()-9) -> 9 | C18: =IF(ROW()-9>Config!$C$14,"",INDEX(BPOworkers!$B$6:$B$105,ROW()-9)) -> J Gonzalez | D18: =IF($C18="","",IFERROR(INDEX(BPOworkers!$E$6:$E$105,MATCH($C18,BPOworkers!$B$6:$B$105,0)),"")) -> R Sanchez | E18: =IF($C18="","",IF(INDEX(Detail!$G$4:$G$303,(ROW()-10)*5+1)=0,"",INDEX(Detail!$J$4:$J$303,(ROW()-10)*5+1))) -> 8 | F18: =IF($C18="","",IF(INDEX(Detail!$G$4:$G$303,(ROW()-10)*5+2)=0,"",INDEX(Detail!$J$4:$J$303,(ROW()-10)*5+2))) -> 8 | G18: =IF($C18="","",IF(INDEX(Detail!$G$4:$G$303,(ROW()-10)*5+3)=0,"",INDEX(Detail!$J$4:$J$303,(ROW()-10)*5+3))) -> 8 | H18: =IF($C18="","",IF(INDEX(Detail!$G$4:$G$303,(ROW()-10)*5+4)=0,"",INDEX(Detail!$J$4:$J$303,(ROW()-10)*5+4))) -> 8 | I18: =IF($C18="","",IF(INDEX(Detail!$G$4:$G$303,(ROW()-10)*5+5)=0,"",INDEX(Detail!$J$4:$J$303,(ROW()-10)*5+5))) -> 8 | J18: =IF($C18="","",SUM($E18:$I18)) -> 40 | K18: =IF($C18="","",Config!$C$16) -> 40 | L18: =IF($C18="","",$J18-$K18) -> 0 | M18: =IF($C18="","",COUNT($E18:$I18)) -> 5 | N18: =IF($C18="","",COUNTIFS(Detail!$C$4:$C$303,$C18,Detail!$N$4:$N$303,0)) -> 5 | O18: =IF($C18="","",COUNTIFS(Detail!$C$4:$C$303,$C18,Detail!$N$4:$N$303,">0")) -> 0 | P18: =IF($C18="","",IF($M18=0,"⛔ BILLED NOTHING",IF($M18<5,"⛔ MISSING "&TEXT(5-$M18,"0")&" DAY(S) IN BTABS",IF($O18=0,"✅ PERFECT WEEK",IF($L18<0,"🔻 UNDER TARGET ("&TEXT($L18,"0.##")&" h)",IF($L18>0,"🔺 OVER TARGET (+"&TEXT($L18,"0.##")&" h)","⚠️ CHECK THE DAYS")))))) -> ✅ PERFECT WEEK | Q18: =IF($C18="","",IF($M18<5,3,IF($O18=0,0,IF($L18>0,1,2)))) -> 0 | R18: =IF($C18="","",IF($O18=0,"All 5 days closed at target. Nothing to fix.",TRIM(IF(E18="",LEFT(INDEX(Config!$F$7:$F$11,1),3)&": no entry in BTabs. ",IF(ABS(E18-$T$2)>$T$3,LEFT(INDEX(Config!$F$7:$F$11,1),3)&": "&TEXT(E18,"0.##")&" h instead of "&TEXT($T$2,"0")&" h. ",""))&IF(F18="",LEFT(INDEX(Config!$F$7:$F$11,2),3)&": no entry in BTabs. ",IF(ABS(F18-$T$2)>$T$3,LEFT(INDEX(Config!$F$7:$F$11,2),3)&": "&TEXT(F18,"0.##")&" h instead of "&TEXT($T$2,"0")&" h. ",""))&IF(G18="",LEFT(INDEX(Config!$F$7:$F$11,3),3)&": no entry in BTabs. ",IF(ABS(G18-$T$2)>$T$3,LEFT(INDEX(Config!$F$7:$F$11,3),3)&": "&TEXT(G18,"0.##")&" h instead of "&TEXT($T$2,"0")&" h. ",""))&IF(H18="",LEFT(INDEX(Config!$F$7:$F$11,4),3)&": no entry in BTabs. ",IF(ABS(H18-$T$2)>$T$3,LEFT(INDEX(Config!$F$7:$F$11,4),3)&": "&TEXT(H18,"0.##")&" h instead of "&TEXT($T$2,"0")&" h. ",""))&IF(I18="",LEFT(INDEX(Config!$F$7:$F$11,5),3)&": no entry in BTabs. ",IF(ABS(I18-$T$2)>$T$3,LEFT(INDEX(Config!$F$7:$F$11,5),3)&": "&TEXT(I18,"0.##")&" h instead of "&TEXT($T$2,"0")&" h. ",""))))) -> All 5 days closed at target. Nothing to fix.
B19: =IF($C19="","",ROW()-9) -> 10 | C19: =IF(ROW()-9>Config!$C$14,"",INDEX(BPOworkers!$B$6:$B$105,ROW()-9)) -> J Rincon | D19: =IF($C19="","",IFERROR(INDEX(BPOworkers!$E$6:$E$105,MATCH($C19,BPOworkers!$B$6:$B$105,0)),"")) -> A Camargo | E19: =IF($C19="","",IF(INDEX(Detail!$G$4:$G$303,(ROW()-10)*5+1)=0,"",INDEX(Detail!$J$4:$J$303,(ROW()-10)*5+1))) -> 8 | F19: =IF($C19="","",IF(INDEX(Detail!$G$4:$G$303,(ROW()-10)*5+2)=0,"",INDEX(Detail!$J$4:$J$303,(ROW()-10)*5+2))) -> 8 | G19: =IF($C19="","",IF(INDEX(Detail!$G$4:$G$303,(ROW()-10)*5+3)=0,"",INDEX(Detail!$J$4:$J$303,(ROW()-10)*5+3))) -> 8 | H19: =IF($C19="","",IF(INDEX(Detail!$G$4:$G$303,(ROW()-10)*5+4)=0,"",INDEX(Detail!$J$4:$J$303,(ROW()-10)*5+4))) -> 8 | I19: =IF($C19="","",IF(INDEX(Detail!$G$4:$G$303,(ROW()-10)*5+5)=0,"",INDEX(Detail!$J$4:$J$303,(ROW()-10)*5+5))) -> 8 | J19: =IF($C19="","",SUM($E19:$I19)) -> 40 | K19: =IF($C19="","",Config!$C$16) -> 40 | L19: =IF($C19="","",$J19-$K19) -> 0 | M19: =IF($C19="","",COUNT($E19:$I19)) -> 5 | N19: =IF($C19="","",COUNTIFS(Detail!$C$4:$C$303,$C19,Detail!$N$4:$N$303,0)) -> 5 | O19: =IF($C19="","",COUNTIFS(Detail!$C$4:$C$303,$C19,Detail!$N$4:$N$303,">0")) -> 0 | P19: =IF($C19="","",IF($M19=0,"⛔ BILLED NOTHING",IF($M19<5,"⛔ MISSING "&TEXT(5-$M19,"0")&" DAY(S) IN BTABS",IF($O19=0,"✅ PERFECT WEEK",IF($L19<0,"🔻 UNDER TARGET ("&TEXT($L19,"0.##")&" h)",IF($L19>0,"🔺 OVER TARGET (+"&TEXT($L19,"0.##")&" h)","⚠️ CHECK THE DAYS")))))) -> ✅ PERFECT WEEK | Q19: =IF($C19="","",IF($M19<5,3,IF($O19=0,0,IF($L19>0,1,2)))) -> 0 | R19: =IF($C19="","",IF($O19=0,"All 5 days closed at target. Nothing to fix.",TRIM(IF(E19="",LEFT(INDEX(Config!$F$7:$F$11,1),3)&": no entry in BTabs. ",IF(ABS(E19-$T$2)>$T$3,LEFT(INDEX(Config!$F$7:$F$11,1),3)&": "&TEXT(E19,"0.##")&" h instead of "&TEXT($T$2,"0")&" h. ",""))&IF(F19="",LEFT(INDEX(Config!$F$7:$F$11,2),3)&": no entry in BTabs. ",IF(ABS(F19-$T$2)>$T$3,LEFT(INDEX(Config!$F$7:$F$11,2),3)&": "&TEXT(F19,"0.##")&" h instead of "&TEXT($T$2,"0")&" h. ",""))&IF(G19="",LEFT(INDEX(Config!$F$7:$F$11,3),3)&": no entry in BTabs. ",IF(ABS(G19-$T$2)>$T$3,LEFT(INDEX(Config!$F$7:$F$11,3),3)&": "&TEXT(G19,"0.##")&" h instead of "&TEXT($T$2,"0")&" h. ",""))&IF(H19="",LEFT(INDEX(Config!$F$7:$F$11,4),3)&": no entry in BTabs. ",IF(ABS(H19-$T$2)>$T$3,LEFT(INDEX(Config!$F$7:$F$11,4),3)&": "&TEXT(H19,"0.##")&" h instead of "&TEXT($T$2,"0")&" h. ",""))&IF(I19="",LEFT(INDEX(Config!$F$7:$F$11,5),3)&": no entry in BTabs. ",IF(ABS(I19-$T$2)>$T$3,LEFT(INDEX(Config!$F$7:$F$11,5),3)&": "&TEXT(I19,"0.##")&" h instead of "&TEXT($T$2,"0")&" h. ",""))))) -> All 5 days closed at target. Nothing to fix.
B20: =IF($C20="","",ROW()-9) -> 11 | C20: =IF(ROW()-9>Config!$C$14,"",INDEX(BPOworkers!$B$6:$B$105,ROW()-9)) -> L Silva | D20: =IF($C20="","",IFERROR(INDEX(BPOworkers!$E$6:$E$105,MATCH($C20,BPOworkers!$B$6:$B$105,0)),"")) -> BPO Management | E20: =IF($C20="","",IF(INDEX(Detail!$G$4:$G$303,(ROW()-10)*5+1)=0,"",INDEX(Detail!$J$4:$J$303,(ROW()-10)*5+1))) -> 8 | F20: =IF($C20="","",IF(INDEX(Detail!$G$4:$G$303,(ROW()-10)*5+2)=0,"",INDEX(Detail!$J$4:$J$303,(ROW()-10)*5+2))) -> 8 | G20: =IF($C20="","",IF(INDEX(Detail!$G$4:$G$303,(ROW()-10)*5+3)=0,"",INDEX(Detail!$J$4:$J$303,(ROW()-10)*5+3))) -> 8 | H20: =IF($C20="","",IF(INDEX(Detail!$G$4:$G$303,(ROW()-10)*5+4)=0,"",INDEX(Detail!$J$4:$J$303,(ROW()-10)*5+4))) -> 8 | I20: =IF($C20="","",IF(INDEX(Detail!$G$4:$G$303,(ROW()-10)*5+5)=0,"",INDEX(Detail!$J$4:$J$303,(ROW()-10)*5+5))) -> 8 | J20: =IF($C20="","",SUM($E20:$I20)) -> 40 | K20: =IF($C20="","",Config!$C$16) -> 40 | L20: =IF($C20="","",$J20-$K20) -> 0 | M20: =IF($C20="","",COUNT($E20:$I20)) -> 5 | N20: =IF($C20="","",COUNTIFS(Detail!$C$4:$C$303,$C20,Detail!$N$4:$N$303,0)) -> 5 | O20: =IF($C20="","",COUNTIFS(Detail!$C$4:$C$303,$C20,Detail!$N$4:$N$303,">0")) -> 0 | P20: =IF($C20="","",IF($M20=0,"⛔ BILLED NOTHING",IF($M20<5,"⛔ MISSING "&TEXT(5-$M20,"0")&" DAY(S) IN BTABS",IF($O20=0,"✅ PERFECT WEEK",IF($L20<0,"🔻 UNDER TARGET ("&TEXT($L20,"0.##")&" h)",IF($L20>0,"🔺 OVER TARGET (+"&TEXT($L20,"0.##")&" h)","⚠️ CHECK THE DAYS")))))) -> ✅ PERFECT WEEK | Q20: =IF($C20="","",IF($M20<5,3,IF($O20=0,0,IF($L20>0,1,2)))) -> 0 | R20: =IF($C20="","",IF($O20=0,"All 5 days closed at target. Nothing to fix.",TRIM(IF(E20="",LEFT(INDEX(Config!$F$7:$F$11,1),3)&": no entry in BTabs. ",IF(ABS(E20-$T$2)>$T$3,LEFT(INDEX(Config!$F$7:$F$11,1),3)&": "&TEXT(E20,"0.##")&" h instead of "&TEXT($T$2,"0")&" h. ",""))&IF(F20="",LEFT(INDEX(Config!$F$7:$F$11,2),3)&": no entry in BTabs. ",IF(ABS(F20-$T$2)>$T$3,LEFT(INDEX(Config!$F$7:$F$11,2),3)&": "&TEXT(F20,"0.##")&" h instead of "&TEXT($T$2,"0")&" h. ",""))&IF(G20="",LEFT(INDEX(Config!$F$7:$F$11,3),3)&": no entry in BTabs. ",IF(ABS(G20-$T$2)>$T$3,LEFT(INDEX(Config!$F$7:$F$11,3),3)&": "&TEXT(G20,"0.##")&" h instead of "&TEXT($T$2,"0")&" h. ",""))&IF(H20="",LEFT(INDEX(Config!$F$7:$F$11,4),3)&": no entry in BTabs. ",IF(ABS(H20-$T$2)>$T$3,LEFT(INDEX(Config!$F$7:$F$11,4),3)&": "&TEXT(H20,"0.##")&" h instead of "&TEXT($T$2,"0")&" h. ",""))&IF(I20="",LEFT(INDEX(Config!$F$7:$F$11,5),3)&": no entry in BTabs. ",IF(ABS(I20-$T$2)>$T$3,LEFT(INDEX(Config!$F$7:$F$11,5),3)&": "&TEXT(I20,"0.##")&" h instead of "&TEXT($T$2,"0")&" h. ",""))))) -> All 5 days closed at target. Nothing to fix.
B21: =IF($C21="","",ROW()-9) -> 12 | C21: =IF(ROW()-9>Config!$C$14,"",INDEX(BPOworkers!$B$6:$B$105,ROW()-9)) -> M Grazziani | D21: =IF($C21="","",IFERROR(INDEX(BPOworkers!$E$6:$E$105,MATCH($C21,BPOworkers!$B$6:$B$105,0)),"")) -> J S Bermudez | E21: =IF($C21="","",IF(INDEX(Detail!$G$4:$G$303,(ROW()-10)*5+1)=0,"",INDEX(Detail!$J$4:$J$303,(ROW()-10)*5+1))) -> 8 | F21: =IF($C21="","",IF(INDEX(Detail!$G$4:$G$303,(ROW()-10)*5+2)=0,"",INDEX(Detail!$J$4:$J$303,(ROW()-10)*5+2))) -> 8 | G21: =IF($C21="","",IF(INDEX(Detail!$G$4:$G$303,(ROW()-10)*5+3)=0,"",INDEX(Detail!$J$4:$J$303,(ROW()-10)*5+3))) -> 8 | H21: =IF($C21="","",IF(INDEX(Detail!$G$4:$G$303,(ROW()-10)*5+4)=0,"",INDEX(Detail!$J$4:$J$303,(ROW()-10)*5+4))) -> 8 | I21: =IF($C21="","",IF(INDEX(Detail!$G$4:$G$303,(ROW()-10)*5+5)=0,"",INDEX(Detail!$J$4:$J$303,(ROW()-10)*5+5))) -> 8 | J21: =IF($C21="","",SUM($E21:$I21)) -> 40 | K21: =IF($C21="","",Config!$C$16) -> 40 | L21: =IF($C21="","",$J21-$K21) -> 0 | M21: =IF($C21="","",COUNT($E21:$I21)) -> 5 | N21: =IF($C21="","",COUNTIFS(Detail!$C$4:$C$303,$C21,Detail!$N$4:$N$303,0)) -> 5 | O21: =IF($C21="","",COUNTIFS(Detail!$C$4:$C$303,$C21,Detail!$N$4:$N$303,">0")) -> 0 | P21: =IF($C21="","",IF($M21=0,"⛔ BILLED NOTHING",IF($M21<5,"⛔ MISSING "&TEXT(5-$M21,"0")&" DAY(S) IN BTABS",IF($O21=0,"✅ PERFECT WEEK",IF($L21<0,"🔻 UNDER TARGET ("&TEXT($L21,"0.##")&" h)",IF($L21>0,"🔺 OVER TARGET (+"&TEXT($L21,"0.##")&" h)","⚠️ CHECK THE DAYS")))))) -> ✅ PERFECT WEEK | Q21: =IF($C21="","",IF($M21<5,3,IF($O21=0,0,IF($L21>0,1,2)))) -> 0 | R21: =IF($C21="","",IF($O21=0,"All 5 days closed at target. Nothing to fix.",TRIM(IF(E21="",LEFT(INDEX(Config!$F$7:$F$11,1),3)&": no entry in BTabs. ",IF(ABS(E21-$T$2)>$T$3,LEFT(INDEX(Config!$F$7:$F$11,1),3)&": "&TEXT(E21,"0.##")&" h instead of "&TEXT($T$2,"0")&" h. ",""))&IF(F21="",LEFT(INDEX(Config!$F$7:$F$11,2),3)&": no entry in BTabs. ",IF(ABS(F21-$T$2)>$T$3,LEFT(INDEX(Config!$F$7:$F$11,2),3)&": "&TEXT(F21,"0.##")&" h instead of "&TEXT($T$2,"0")&" h. ",""))&IF(G21="",LEFT(INDEX(Config!$F$7:$F$11,3),3)&": no entry in BTabs. ",IF(ABS(G21-$T$2)>$T$3,LEFT(INDEX(Config!$F$7:$F$11,3),3)&": "&TEXT(G21,"0.##")&" h instead of "&TEXT($T$2,"0")&" h. ",""))&IF(H21="",LEFT(INDEX(Config!$F$7:$F$11,4),3)&": no entry in BTabs. ",IF(ABS(H21-$T$2)>$T$3,LEFT(INDEX(Config!$F$7:$F$11,4),3)&": "&TEXT(H21,"0.##")&" h instead of "&TEXT($T$2,"0")&" h. ",""))&IF(I21="",LEFT(INDEX(Config!$F$7:$F$11,5),3)&": no entry in BTabs. ",IF(ABS(I21-$T$2)>$T$3,LEFT(INDEX(Config!$F$7:$F$11,5),3)&": "&TEXT(I21,"0.##")&" h instead of "&TEXT($T$2,"0")&" h. ",""))))) -> All 5 days closed at target. Nothing to fix.
... B69: =IF($C69="","",ROW()-9) | C69: =IF(ROW()-9>Config!$C$14,"",INDEX(BPOworkers!$B$6:$B$105,ROW()-9)) | D69: =IF($C69="","",IFERROR(INDEX(BPOworkers!$E$6:$E$105,MATCH($C69,BPOworkers!$B$6:$B$105,0)),"")) | E69: =IF($C69="","",IF(INDEX(Detail!$G$4:$G$303,(ROW()-10)*5+1)=0,"",INDEX(Detail!$J$4:$J$303,(ROW()-10)*5+1))) | F69: =IF($C69="","",IF(INDEX(Detail!$G$4:$G$303,(ROW()-10)*5+2)=0,"",INDEX(Detail!$J$4:$J$303,(ROW()-10)*5+2))) | G69: =IF($C69="","",IF(INDEX(Detail!$G$4:$G$303,(ROW()-10)*5+3)=0,"",INDEX(Detail!$J$4:$J$303,(ROW()-10)*5+3))) | H69: =IF($C69="","",IF(INDEX(Detail!$G$4:$G$303,(ROW()-10)*5+4)=0,"",INDEX(Detail!$J$4:$J$303,(ROW()-10)*5+4))) | I69: =IF($C69="","",IF(INDEX(Detail!$G$4:$G$303,(ROW()-10)*5+5)=0,"",INDEX(Detail!$J$4:$J$303,(ROW()-10)*5+5))) | J69: =IF($C69="","",SUM($E69:$I69)) | K69: =IF($C69="","",Config!$C$16) | L69: =IF($C69="","",$J69-$K69) | M69: =IF($C69="","",COUNT($E69:$I69)) | N69: =IF($C69="","",COUNTIFS(Detail!$C$4:$C$303,$C69,Detail!$N$4:$N$303,0)) | O69: =IF($C69="","",COUNTIFS(Detail!$C$4:$C$303,$C69,Detail!$N$4:$N$303,">0")) | P69: =IF($C69="","",IF($M69=0,"⛔ BILLED NOTHING",IF($M69<5,"⛔ MISSING "&TEXT(5-$M69,"0")&" DAY(S) IN BTABS",IF($O69=0,"✅ PERFECT WEEK",IF($L69<0,"🔻 UNDER TARGET ("&TEXT($L69,"0.##")&" h)",IF($L69>0,"🔺 OVER TARGET (+"&TEXT($L69,"0.##")&" h)","⚠️ CHECK THE DAYS")))))) | Q69: =IF($C69="","",IF($M69<5,3,IF($O69=0,0,IF($L69>0,1,2)))) | R69: =IF($C69="","",IF($O69=0,"All 5 days closed at target. Nothing to fix.",TRIM(IF(E69="",LEFT(INDEX(Config!$F$7:$F$11,1),3)&": no entry in BTabs. ",IF(ABS(E69-$T$2)>$T$3,LEFT(INDEX(Config!$F$7:$F$11,1),3)&": "&TEXT(E69,"0.##")&" h instead of "&TEXT($T$2,"0")&" h. ",""))&IF(F69="",LEFT(INDEX(Config!$F$7:$F$11,2),3)&": no entry in BTabs. ",IF(ABS(F69-$T$2)>$T$3,LEFT(INDEX(Config!$F$7:$F$11,2),3)&": "&TEXT(F69,"0.##")&" h instead of "&TEXT($T$2,"0")&" h. ",""))&IF(G69="",LEFT(INDEX(Config!$F$7:$F$11,3),3)&": no entry in BTabs. ",IF(ABS(G69-$T$2)>$T$3,LEFT(INDEX(Config!$F$7:$F$11,3),3)&": "&TEXT(G69,"0.##")&" h instead of "&TEXT($T$2,"0")&" h. ",""))&IF(H69="",LEFT(INDEX(Config!$F$7:$F$11,4),3)&": no entry in BTabs. ",IF(ABS(H69-$T$2)>$T$3,LEFT(INDEX(Config!$F$7:$F$11,4),3)&": "&TEXT(H69,"0.##")&" h instead of "&TEXT($T$2,"0")&" h. ",""))&IF(I69="",LEFT(INDEX(Config!$F$7:$F$11,5),3)&": no entry in BTabs. ",IF(ABS(I69-$T$2)>$T$3,LEFT(INDEX(Config!$F$7:$F$11,5),3)&": "&TEXT(I69,"0.##")&" h instead of "&TEXT($T$2,"0")&" h. ","")))))
B71: HOW TO READ THIS DASHBOARD
B72: GREEN cell | D72: The landman closed exactly the daily target (8 h = 1.0 unit).
B73: LIGHT RED cell | D73: UNDER 8 h that day: there is billing being lost.
B74: BLUE cell | D74: Over 8 h that day. Check for a duplicate entry.
B75: DARK RED cell | D75: NO entry at all in BTabs that day. This is the most serious case.

Sheet Alerts
B2: WEEKLY ALERTS - ACTION LIST
B3: Only the days with a problem. If the table comes out empty, the week closed clean.
B5: TOTAL ALERTS: | E5: =COUNTIFS(Detail!$N$4:$N$303,">0") -> 6 | F5: =IF($E$5=0,"✅ Excellent: no landman missed the target this week.","Go through each row and talk to the landman or their Team Lead.") -> Go through each row and talk to the landman or their Team Lead.
B6: # | C6: Landman | D6: Team Lead | E6: Date | F6: Day | G6: BTabs entries | H6: Billed hours | I6: Time off hours | J6: TOTAL for the day | K6: Diff. vs target | L6: What happened | M6: Sev. | N6: WHAT TO DO
B7: =IF($R7="","",ROW()-6) -> 1 | C7: =IF($R7="","",INDEX(Detail!$C$4:$C$303,$R7)) -> J Castillo | D7: =IF($R7="","",INDEX(Detail!$D$4:$D$303,$R7)) -> J S Bermudez | E7: =IF($R7="","",INDEX(Detail!$E$4:$E$303,$R7)) -> 46265 | F7: =IF($R7="","",INDEX(Detail!$F$4:$F$303,$R7)) -> Monday | G7: =IF($R7="","",INDEX(Detail!$G$4:$G$303,$R7)) -> 0 | H7: =IF($R7="","",INDEX(Detail!$H$4:$H$303,$R7)) -> 0 | I7: =IF($R7="","",INDEX(Detail!$I$4:$I$303,$R7)) -> 0 | J7: =IF($R7="","",INDEX(Detail!$J$4:$J$303,$R7)) -> 0 | K7: =IF($R7="","",INDEX(Detail!$L$4:$L$303,$R7)) -> -8 | L7: =IF($R7="","",INDEX(Detail!$M$4:$M$303,$R7)) -> ⛔ NO ENTRY IN BTABS | M7: =IF($R7="","",INDEX(Detail!$N$4:$N$303,$R7)) -> 3 | N7: =IF($C7="","",IF($G7=0,"Ask the landman to log this day in BTabs: there is no entry at all.",IF($K7<0,"Missing "&TEXT(-$K7,"0.##")&" h. Confirm whether they worked and did not bill, or whether they need to log Time Off / BPO Vacation with the hours in the detail.","Over by "&TEXT($K7,"0.##")&" h. Check for a duplicate entry or a typo."))) -> Ask the landman to log this day in BTabs: there is no entry at all. | R7: =IFERROR(MATCH(ROW()-6,Detail!$O$4:$O$303,0),"") -> 31
B8: =IF($R8="","",ROW()-6) -> 2 | C8: =IF($R8="","",INDEX(Detail!$C$4:$C$303,$R8)) -> C Castellanos | D8: =IF($R8="","",INDEX(Detail!$D$4:$D$303,$R8)) -> J S Bermudez | E8: =IF($R8="","",INDEX(Detail!$E$4:$E$303,$R8)) -> 46265 | F8: =IF($R8="","",INDEX(Detail!$F$4:$F$303,$R8)) -> Monday | G8: =IF($R8="","",INDEX(Detail!$G$4:$G$303,$R8)) -> 2 | H8: =IF($R8="","",INDEX(Detail!$H$4:$H$303,$R8)) -> 16 | I8: =IF($R8="","",INDEX(Detail!$I$4:$I$303,$R8)) -> 0 | J8: =IF($R8="","",INDEX(Detail!$J$4:$J$303,$R8)) -> 16 | K8: =IF($R8="","",INDEX(Detail!$L$4:$L$303,$R8)) -> 8 | L8: =IF($R8="","",INDEX(Detail!$M$4:$M$303,$R8)) -> 🔺 OVER BY 8. h | M8: =IF($R8="","",INDEX(Detail!$N$4:$N$303,$R8)) -> 1 | N8: =IF($C8="","",IF($G8=0,"Ask the landman to log this day in BTabs: there is no entry at all.",IF($K8<0,"Missing "&TEXT(-$K8,"0.##")&" h. Confirm whether they worked and did not bill, or whether they need to log Time Off / BPO Vacation with the hours in the detail.","Over by "&TEXT($K8,"0.##")&" h. Check for a duplicate entry or a typo."))) -> Over by 8. h. Check for a duplicate entry or a typo. | R8: =IFERROR(MATCH(ROW()-6,Detail!$O$4:$O$303,0),"") -> 76
B9: =IF($R9="","",ROW()-6) -> 3 | C9: =IF($R9="","",INDEX(Detail!$C$4:$C$303,$R9)) -> F Montañez | D9: =IF($R9="","",INDEX(Detail!$D$4:$D$303,$R9)) -> H Daza | E9: =IF($R9="","",INDEX(Detail!$E$4:$E$303,$R9)) -> 46265 | F9: =IF($R9="","",INDEX(Detail!$F$4:$F$303,$R9)) -> Monday | G9: =IF($R9="","",INDEX(Detail!$G$4:$G$303,$R9)) -> 2 | H9: =IF($R9="","",INDEX(Detail!$H$4:$H$303,$R9)) -> 16 | I9: =IF($R9="","",INDEX(Detail!$I$4:$I$303,$R9)) -> 0 | J9: =IF($R9="","",INDEX(Detail!$J$4:$J$303,$R9)) -> 16 | K9: =IF($R9="","",INDEX(Detail!$L$4:$L$303,$R9)) -> 8 | L9: =IF($R9="","",INDEX(Detail!$M$4:$M$303,$R9)) -> 🔺 OVER BY 8. h | M9: =IF($R9="","",INDEX(Detail!$N$4:$N$303,$R9)) -> 1 | N9: =IF($C9="","",IF($G9=0,"Ask the landman to log this day in BTabs: there is no entry at all.",IF($K9<0,"Missing "&TEXT(-$K9,"0.##")&" h. Confirm whether they worked and did not bill, or whether they need to log Time Off / BPO Vacation with the hours in the detail.","Over by "&TEXT($K9,"0.##")&" h. Check for a duplicate entry or a typo."))) -> Over by 8. h. Check for a duplicate entry or a typo. | R9: =IFERROR(MATCH(ROW()-6,Detail!$O$4:$O$303,0),"") -> 131
B10: =IF($R10="","",ROW()-6) -> 4 | C10: =IF($R10="","",INDEX(Detail!$C$4:$C$303,$R10)) -> N Espitia | D10: =IF($R10="","",INDEX(Detail!$D$4:$D$303,$R10)) -> A Camargo | E10: =IF($R10="","",INDEX(Detail!$E$4:$E$303,$R10)) -> 46265 | F10: =IF($R10="","",INDEX(Detail!$F$4:$F$303,$R10)) -> Monday | G10: =IF($R10="","",INDEX(Detail!$G$4:$G$303,$R10)) -> 2 | H10: =IF($R10="","",INDEX(Detail!$H$4:$H$303,$R10)) -> 12 | I10: =IF($R10="","",INDEX(Detail!$I$4:$I$303,$R10)) -> 0 | J10: =IF($R10="","",INDEX(Detail!$J$4:$J$303,$R10)) -> 12 | K10: =IF($R10="","",INDEX(Detail!$L$4:$L$303,$R10)) -> 4 | L10: =IF($R10="","",INDEX(Detail!$M$4:$M$303,$R10)) -> 🔺 OVER BY 4. h | M10: =IF($R10="","",INDEX(Detail!$N$4:$N$303,$R10)) -> 1 | N10: =IF($C10="","",IF($G10=0,"Ask the landman to log this day in BTabs: there is no entry at all.",IF($K10<0,"Missing "&TEXT(-$K10,"0.##")&" h. Confirm whether they worked and did not bill, or whether they need to log Time Off / BPO Vacation with the hours in the detail.","Over by "&TEXT($K10,"0.##")&" h. Check for a duplicate entry or a typo."))) -> Over by 4. h. Check for a duplicate entry or a typo. | R10: =IFERROR(MATCH(ROW()-6,Detail!$O$4:$O$303,0),"") -> 146
B11: =IF($R11="","",ROW()-6) -> 5 | C11: =IF($R11="","",INDEX(Detail!$C$4:$C$303,$R11)) -> N Espitia | D11: =IF($R11="","",INDEX(Detail!$D$4:$D$303,$R11)) -> A Camargo | E11: =IF($R11="","",INDEX(Detail!$E$4:$E$303,$R11)) -> 46266 | F11: =IF($R11="","",INDEX(Detail!$F$4:$F$303,$R11)) -> Tuesday | G11: =IF($R11="","",INDEX(Detail!$G$4:$G$303,$R11)) -> 3 | H11: =IF($R11="","",INDEX(Detail!$H$4:$H$303,$R11)) -> 12 | I11: =IF($R11="","",INDEX(Detail!$I$4:$I$303,$R11)) -> 0 | J11: =IF($R11="","",INDEX(Detail!$J$4:$J$303,$R11)) -> 12 | K11: =IF($R11="","",INDEX(Detail!$L$4:$L$303,$R11)) -> 4 | L11: =IF($R11="","",INDEX(Detail!$M$4:$M$303,$R11)) -> 🔺 OVER BY 4. h | M11: =IF($R11="","",INDEX(Detail!$N$4:$N$303,$R11)) -> 1 | N11: =IF($C11="","",IF($G11=0,"Ask the landman to log this day in BTabs: there is no entry at all.",IF($K11<0,"Missing "&TEXT(-$K11,"0.##")&" h. Confirm whether they worked and did not bill, or whether they need to log Time Off / BPO Vacation with the hours in the detail.","Over by "&TEXT($K11,"0.##")&" h. Check for a duplicate entry or a typo."))) -> Over by 4. h. Check for a duplicate entry or a typo. | R11: =IFERROR(MATCH(ROW()-6,Detail!$O$4:$O$303,0),"") -> 147
B12: =IF($R12="","",ROW()-6) -> 6 | C12: =IF($R12="","",INDEX(Detail!$C$4:$C$303,$R12)) -> K Martínez | D12: =IF($R12="","",INDEX(Detail!$D$4:$D$303,$R12)) -> A Camargo | E12: =IF($R12="","",INDEX(Detail!$E$4:$E$303,$R12)) -> 46265 | F12: =IF($R12="","",INDEX(Detail!$F$4:$F$303,$R12)) -> Monday | G12: =IF($R12="","",INDEX(Detail!$G$4:$G$303,$R12)) -> 0 | H12: =IF($R12="","",INDEX(Detail!$H$4:$H$303,$R12)) -> 0 | I12: =IF($R12="","",INDEX(Detail!$I$4:$I$303,$R12)) -> 0 | J12: =IF($R12="","",INDEX(Detail!$J$4:$J$303,$R12)) -> 0 | K12: =IF($R12="","",INDEX(Detail!$L$4:$L$303,$R12)) -> -8 | L12: =IF($R12="","",INDEX(Detail!$M$4:$M$303,$R12)) -> ⛔ NO ENTRY IN BTABS | M12: =IF($R12="","",INDEX(Detail!$N$4:$N$303,$R12)) -> 3 | N12: =IF($C12="","",IF($G12=0,"Ask the landman to log this day in BTabs: there is no entry at all.",IF($K12<0,"Missing "&TEXT(-$K12,"0.##")&" h. Confirm whether they worked and did not bill, or whether they need to log Time Off / BPO Vacation with the hours in the detail.","Over by "&TEXT($K12,"0.##")&" h. Check for a duplicate entry or a typo."))) -> Ask the landman to log this day in BTabs: there is no entry at all. | R12: =IFERROR(MATCH(ROW()-6,Detail!$O$4:$O$303,0),"") -> 161
B13: =IF($R13="","",ROW()-6) | C13: =IF($R13="","",INDEX(Detail!$C$4:$C$303,$R13)) | D13: =IF($R13="","",INDEX(Detail!$D$4:$D$303,$R13)) | E13: =IF($R13="","",INDEX(Detail!$E$4:$E$303,$R13)) | F13: =IF($R13="","",INDEX(Detail!$F$4:$F$303,$R13)) | G13: =IF($R13="","",INDEX(Detail!$G$4:$G$303,$R13)) | H13: =IF($R13="","",INDEX(Detail!$H$4:$H$303,$R13)) | I13: =IF($R13="","",INDEX(Detail!$I$4:$I$303,$R13)) | J13: =IF($R13="","",INDEX(Detail!$J$4:$J$303,$R13)) | K13: =IF($R13="","",INDEX(Detail!$L$4:$L$303,$R13)) | L13: =IF($R13="","",INDEX(Detail!$M$4:$M$303,$R13)) | M13: =IF($R13="","",INDEX(Detail!$N$4:$N$303,$R13)) | N13: =IF($C13="","",IF($G13=0,"Ask the landman to log this day in BTabs: there is no entry at all.",IF($K13<0,"Missing "&TEXT(-$K13,"0.##")&" h. Confirm whether they worked and did not bill, or whether they need to log Time Off / BPO Vacation with the hours in the detail.","Over by "&TEXT($K13,"0.##")&" h. Check for a duplicate entry or a typo."))) | R13: =IFERROR(MATCH(ROW()-6,Detail!$O$4:$O$303,0),"")
B14: =IF($R14="","",ROW()-6) | C14: =IF($R14="","",INDEX(Detail!$C$4:$C$303,$R14)) | D14: =IF($R14="","",INDEX(Detail!$D$4:$D$303,$R14)) | E14: =IF($R14="","",INDEX(Detail!$E$4:$E$303,$R14)) | F14: =IF($R14="","",INDEX(Detail!$F$4:$F$303,$R14)) | G14: =IF($R14="","",INDEX(Detail!$G$4:$G$303,$R14)) | H14: =IF($R14="","",INDEX(Detail!$H$4:$H$303,$R14)) | I14: =IF($R14="","",INDEX(Detail!$I$4:$I$303,$R14)) | J14: =IF($R14="","",INDEX(Detail!$J$4:$J$303,$R14)) | K14: =IF($R14="","",INDEX(Detail!$L$4:$L$303,$R14)) | L14: =IF($R14="","",INDEX(Detail!$M$4:$M$303,$R14)) | M14: =IF($R14="","",INDEX(Detail!$N$4:$N$303,$R14)) | N14: =IF($C14="","",IF($G14=0,"Ask the landman to log this day in BTabs: there is no entry at all.",IF($K14<0,"Missing "&TEXT(-$K14,"0.##")&" h. Confirm whether they worked and did not bill, or whether they need to log Time Off / BPO Vacation with the hours in the detail.","Over by "&TEXT($K14,"0.##")&" h. Check for a duplicate entry or a typo."))) | R14: =IFERROR(MATCH(ROW()-6,Detail!$O$4:$O$303,0),"")
B15: =IF($R15="","",ROW()-6) | C15: =IF($R15="","",INDEX(Detail!$C$4:$C$303,$R15)) | D15: =IF($R15="","",INDEX(Detail!$D$4:$D$303,$R15)) | E15: =IF($R15="","",INDEX(Detail!$E$4:$E$303,$R15)) | F15: =IF($R15="","",INDEX(Detail!$F$4:$F$303,$R15)) | G15: =IF($R15="","",INDEX(Detail!$G$4:$G$303,$R15)) | H15: =IF($R15="","",INDEX(Detail!$H$4:$H$303,$R15)) | I15: =IF($R15="","",INDEX(Detail!$I$4:$I$303,$R15)) | J15: =IF($R15="","",INDEX(Detail!$J$4:$J$303,$R15)) | K15: =IF($R15="","",INDEX(Detail!$L$4:$L$303,$R15)) | L15: =IF($R15="","",INDEX(Detail!$M$4:$M$303,$R15)) | M15: =IF($R15="","",INDEX(Detail!$N$4:$N$303,$R15)) | N15: =IF($C15="","",IF($G15=0,"Ask the landman to log this day in BTabs: there is no entry at all.",IF($K15<0,"Missing "&TEXT(-$K15,"0.##")&" h. Confirm whether they worked and did not bill, or whether they need to log Time Off / BPO Vacation with the hours in the detail.","Over by "&TEXT($K15,"0.##")&" h. Check for a duplicate entry or a typo."))) | R15: =IFERROR(MATCH(ROW()-6,Detail!$O$4:$O$303,0),"")
B16: =IF($R16="","",ROW()-6) | C16: =IF($R16="","",INDEX(Detail!$C$4:$C$303,$R16)) | D16: =IF($R16="","",INDEX(Detail!$D$4:$D$303,$R16)) | E16: =IF($R16="","",INDEX(Detail!$E$4:$E$303,$R16)) | F16: =IF($R16="","",INDEX(Detail!$F$4:$F$303,$R16)) | G16: =IF($R16="","",INDEX(Detail!$G$4:$G$303,$R16)) | H16: =IF($R16="","",INDEX(Detail!$H$4:$H$303,$R16)) | I16: =IF($R16="","",INDEX(Detail!$I$4:$I$303,$R16)) | J16: =IF($R16="","",INDEX(Detail!$J$4:$J$303,$R16)) | K16: =IF($R16="","",INDEX(Detail!$L$4:$L$303,$R16)) | L16: =IF($R16="","",INDEX(Detail!$M$4:$M$303,$R16)) | M16: =IF($R16="","",INDEX(Detail!$N$4:$N$303,$R16)) | N16: =IF($C16="","",IF($G16=0,"Ask the landman to log this day in BTabs: there is no entry at all.",IF($K16<0,"Missing "&TEXT(-$K16,"0.##")&" h. Confirm whether they worked and did not bill, or whether they need to log Time Off / BPO Vacation with the hours in the detail.","Over by "&TEXT($K16,"0.##")&" h. Check for a duplicate entry or a typo."))) | R16: =IFERROR(MATCH(ROW()-6,Detail!$O$4:$O$303,0),"")
B17: =IF($R17="","",ROW()-6) | C17: =IF($R17="","",INDEX(Detail!$C$4:$C$303,$R17)) | D17: =IF($R17="","",INDEX(Detail!$D$4:$D$303,$R17)) | E17: =IF($R17="","",INDEX(Detail!$E$4:$E$303,$R17)) | F17: =IF($R17="","",INDEX(Detail!$F$4:$F$303,$R17)) | G17: =IF($R17="","",INDEX(Detail!$G$4:$G$303,$R17)) | H17: =IF($R17="","",INDEX(Detail!$H$4:$H$303,$R17)) | I17: =IF($R17="","",INDEX(Detail!$I$4:$I$303,$R17)) | J17: =IF($R17="","",INDEX(Detail!$J$4:$J$303,$R17)) | K17: =IF($R17="","",INDEX(Detail!$L$4:$L$303,$R17)) | L17: =IF($R17="","",INDEX(Detail!$M$4:$M$303,$R17)) | M17: =IF($R17="","",INDEX(Detail!$N$4:$N$303,$R17)) | N17: =IF($C17="","",IF($G17=0,"Ask the landman to log this day in BTabs: there is no entry at all.",IF($K17<0,"Missing "&TEXT(-$K17,"0.##")&" h. Confirm whether they worked and did not bill, or whether they need to log Time Off / BPO Vacation with the hours in the detail.","Over by "&TEXT($K17,"0.##")&" h. Check for a duplicate entry or a typo."))) | R17: =IFERROR(MATCH(ROW()-6,Detail!$O$4:$O$303,0),"")
B18: =IF($R18="","",ROW()-6) | C18: =IF($R18="","",INDEX(Detail!$C$4:$C$303,$R18)) | D18: =IF($R18="","",INDEX(Detail!$D$4:$D$303,$R18)) | E18: =IF($R18="","",INDEX(Detail!$E$4:$E$303,$R18)) | F18: =IF($R18="","",INDEX(Detail!$F$4:$F$303,$R18)) | G18: =IF($R18="","",INDEX(Detail!$G$4:$G$303,$R18)) | H18: =IF($R18="","",INDEX(Detail!$H$4:$H$303,$R18)) | I18: =IF($R18="","",INDEX(Detail!$I$4:$I$303,$R18)) | J18: =IF($R18="","",INDEX(Detail!$J$4:$J$303,$R18)) | K18: =IF($R18="","",INDEX(Detail!$L$4:$L$303,$R18)) | L18: =IF($R18="","",INDEX(Detail!$M$4:$M$303,$R18)) | M18: =IF($R18="","",INDEX(Detail!$N$4:$N$303,$R18)) | N18: =IF($C18="","",IF($G18=0,"Ask the landman to log this day in BTabs: there is no entry at all.",IF($K18<0,"Missing "&TEXT(-$K18,"0.##")&" h. Confirm whether they worked and did not bill, or whether they need to log Time Off / BPO Vacation with the hours in the detail.","Over by "&TEXT($K18,"0.##")&" h. Check for a duplicate entry or a typo."))) | R18: =IFERROR(MATCH(ROW()-6,Detail!$O$4:$O$303,0),"")
... B96: =IF($R96="","",ROW()-6) | C96: =IF($R96="","",INDEX(Detail!$C$4:$C$303,$R96)) | D96: =IF($R96="","",INDEX(Detail!$D$4:$D$303,$R96)) | E96: =IF($R96="","",INDEX(Detail!$E$4:$E$303,$R96)) | F96: =IF($R96="","",INDEX(Detail!$F$4:$F$303,$R96)) | G96: =IF($R96="","",INDEX(Detail!$G$4:$G$303,$R96)) | H96: =IF($R96="","",INDEX(Detail!$H$4:$H$303,$R96)) | I96: =IF($R96="","",INDEX(Detail!$I$4:$I$303,$R96)) | J96: =IF($R96="","",INDEX(Detail!$J$4:$J$303,$R96)) | K96: =IF($R96="","",INDEX(Detail!$L$4:$L$303,$R96)) | L96: =IF($R96="","",INDEX(Detail!$M$4:$M$303,$R96)) | M96: =IF($R96="","",INDEX(Detail!$N$4:$N$303,$R96)) | N96: =IF($C96="","",IF($G96=0,"Ask the landman to log this day in BTabs: there is no entry at all.",IF($K96<0,"Missing "&TEXT(-$K96,"0.##")&" h. Confirm whether they worked and did not bill, or whether they need to log Time Off / BPO Vacation with the hours in the detail.","Over by "&TEXT($K96,"0.##")&" h. Check for a duplicate entry or a typo."))) | R96: =IFERROR(MATCH(ROW()-6,Detail!$O$4:$O$303,0),"")

Sheet TimeOff
B2: WEEKLY TIME OFF (Time Off / Vacation / Medical Leave) | S2: =Config!$C$9 -> 8
B3: People who logged in BTabs but did NOT work billable hours. Here we validate that the day still closes at 8 h. | S3: =Config!$C$10 -> 0
B5: TIME OFF HOURS | D5: TIME OFF ENTRIES | F5: TIME OFF (entries) | H5: BPO VACATION (entries) | J5: HOLIDAY (entries) | L5: NO HOURS IN THE DETAIL
B6: =SUMPRODUCT(RawBtabs!$U$2:$U$1500,RawBtabs!$W$2:$W$1500,RawBtabs!$S$2:$S$1500) -> 159 | D6: =SUMPRODUCT(RawBtabs!$X$2:$X$1500,RawBtabs!$W$2:$W$1500,RawBtabs!$S$2:$S$1500) -> 24 | F6: =SUMPRODUCT(--(RawBtabs!$H$2:$H$1500=Config!$C$21),RawBtabs!$W$2:$W$1500,RawBtabs!$S$2:$S$1500) -> 14 | H6: =SUMPRODUCT(--(RawBtabs!$H$2:$H$1500=Config!$C$22),RawBtabs!$W$2:$W$1500,RawBtabs!$S$2:$S$1500) -> 10 | J6: =SUMPRODUCT(--(RawBtabs!$H$2:$H$1500=Config!$C$23),RawBtabs!$W$2:$W$1500,RawBtabs!$S$2:$S$1500) -> 0 | L6: =SUMPRODUCT(RawBtabs!$X$2:$X$1500,RawBtabs!$W$2:$W$1500,RawBtabs!$S$2:$S$1500,--(RawBtabs!$U$2:$U$1500=0)) -> 0
B8: # | C8: Landman | D8: Team Lead | E8: Date | F8: Day | G8: Time off type | H8: BTabs status | I8: Hours declared | J8: Billed units | K8: TOTAL for the day | L8: DAY VALIDATION | M8: Detail written in BTabs
B9: =IF($R9="","",ROW()-8) -> 1 | C9: =IF($R9="","",INDEX(RawBtabs!$A$2:$A$1500,$R9)) -> J Castillo | D9: =IF($C9="","",IFERROR(INDEX(BPOworkers!$E$6:$E$105,MATCH($C9,BPOworkers!$B$6:$B$105,0)),"")) -> J S Bermudez | E9: =IF($R9="","",INDEX(RawBtabs!$C$2:$C$1500,$R9)) -> 46269 | F9: =IF($C9="","",IFERROR(INDEX(Config!$F$7:$F$11,$E9-Config!$C$7+1),"")) -> Friday | G9: =IF($R9="","",INDEX(RawBtabs!$H$2:$H$1500,$R9)) -> Time Off | H9: =IF($R9="","",INDEX(RawBtabs!$B$2:$B$1500,$R9)) -> Approved | I9: =IF($R9="","",INDEX(RawBtabs!$U$2:$U$1500,$R9)) -> 8 | J9: =IF($R9="","",INDEX(RawBtabs!$K$2:$K$1500,$R9)) -> 0 | K9: =IF($C9="","",SUMIFS(RawBtabs!$V$2:$V$1500,RawBtabs!$A$2:$A$1500,$C9,RawBtabs!$C$2:$C$1500,$E9)) -> 8 | L9: =IF($C9="","",IF($I9=0,"⚠️ The detail does not state the hours",IF(ABS($K9-Config!$C$9)<=Config!$C$10,"✅ Full day ("&TEXT($K9,"0.##")&" h)",IF($K9<Config!$C$9,"🔻 Incomplete day: "&TEXT($K9,"0.##")&" h of "&TEXT(Config!$C$9,"0")&" h","🔺 Day exceeded: "&TEXT($K9,"0.##")&" h")))) -> ✅ Full day (8. h) | M9: =IF($R9="","",INDEX(RawBtabs!$Q$2:$Q$1500,$R9)) -> 8 hours not worked medical leave. 8 Hours not billed | R9: =IFERROR(MATCH(ROW()-8,RawBtabs!$Z$2:$Z$1500,0),"") -> 167
B10: =IF($R10="","",ROW()-8) -> 2 | C10: =IF($R10="","",INDEX(RawBtabs!$A$2:$A$1500,$R10)) -> A Lopez | D10: =IF($C10="","",IFERROR(INDEX(BPOworkers!$E$6:$E$105,MATCH($C10,BPOworkers!$B$6:$B$105,0)),"")) -> S Romero | E10: =IF($R10="","",INDEX(RawBtabs!$C$2:$C$1500,$R10)) -> 46269 | F10: =IF($C10="","",IFERROR(INDEX(Config!$F$7:$F$11,$E10-Config!$C$7+1),"")) -> Friday | G10: =IF($R10="","",INDEX(RawBtabs!$H$2:$H$1500,$R10)) -> Time Off | H10: =IF($R10="","",INDEX(RawBtabs!$B$2:$B$1500,$R10)) -> Approved | I10: =IF($R10="","",INDEX(RawBtabs!$U$2:$U$1500,$R10)) -> 2 | J10: =IF($R10="","",INDEX(RawBtabs!$K$2:$K$1500,$R10)) -> 0 | K10: =IF($C10="","",SUMIFS(RawBtabs!$V$2:$V$1500,RawBtabs!$A$2:$A$1500,$C10,RawBtabs!$C$2:$C$1500,$E10)) -> 8 | L10: =IF($C10="","",IF($I10=0,"⚠️ The detail does not state the hours",IF(ABS($K10-Config!$C$9)<=Config!$C$10,"✅ Full day ("&TEXT($K10,"0.##")&" h)",IF($K10<Config!$C$9,"🔻 Incomplete day: "&TEXT($K10,"0.##")&" h of "&TEXT(Config!$C$9,"0")&" h","🔺 Day exceeded: "&TEXT($K10,"0.##")&" h")))) -> ✅ Full day (8. h) | M10: =IF($R10="","",INDEX(RawBtabs!$Q$2:$Q$1500,$R10)) -> 2 hours | R10: =IFERROR(MATCH(ROW()-8,RawBtabs!$Z$2:$Z$1500,0),"") -> 177
B11: =IF($R11="","",ROW()-8) -> 3 | C11: =IF($R11="","",INDEX(RawBtabs!$A$2:$A$1500,$R11)) -> C Mesa | D11: =IF($C11="","",IFERROR(INDEX(BPOworkers!$E$6:$E$105,MATCH($C11,BPOworkers!$B$6:$B$105,0)),"")) -> M Leon | E11: =IF($R11="","",INDEX(RawBtabs!$C$2:$C$1500,$R11)) -> 46269 | F11: =IF($C11="","",IFERROR(INDEX(Config!$F$7:$F$11,$E11-Config!$C$7+1),"")) -> Friday | G11: =IF($R11="","",INDEX(RawBtabs!$H$2:$H$1500,$R11)) -> BPO Vacation | H11: =IF($R11="","",INDEX(RawBtabs!$B$2:$B$1500,$R11)) -> Approved | I11: =IF($R11="","",INDEX(RawBtabs!$U$2:$U$1500,$R11)) -> 8 | J11: =IF($R11="","",INDEX(RawBtabs!$K$2:$K$1500,$R11)) -> 0 | K11: =IF($C11="","",SUMIFS(RawBtabs!$V$2:$V$1500,RawBtabs!$A$2:$A$1500,$C11,RawBtabs!$C$2:$C$1500,$E11)) -> 8 | L11: =IF($C11="","",IF($I11=0,"⚠️ The detail does not state the hours",IF(ABS($K11-Config!$C$9)<=Config!$C$10,"✅ Full day ("&TEXT($K11,"0.##")&" h)",IF($K11<Config!$C$9,"🔻 Incomplete day: "&TEXT($K11,"0.##")&" h of "&TEXT(Config!$C$9,"0")&" h","🔺 Day exceeded: "&TEXT($K11,"0.##")&" h")))) -> ✅ Full day (8. h) | M11: =IF($R11="","",INDEX(RawBtabs!$Q$2:$Q$1500,$R11)) -> 8 hours of paid vacations | R11: =IFERROR(MATCH(ROW()-8,RawBtabs!$Z$2:$Z$1500,0),"") -> 181
B12: =IF($R12="","",ROW()-8) -> 4 | C12: =IF($R12="","",INDEX(RawBtabs!$A$2:$A$1500,$R12)) -> O Moreno | D12: =IF($C12="","",IFERROR(INDEX(BPOworkers!$E$6:$E$105,MATCH($C12,BPOworkers!$B$6:$B$105,0)),"")) -> R Sanchez | E12: =IF($R12="","",INDEX(RawBtabs!$C$2:$C$1500,$R12)) -> 46269 | F12: =IF($C12="","",IFERROR(INDEX(Config!$F$7:$F$11,$E12-Config!$C$7+1),"")) -> Friday | G12: =IF($R12="","",INDEX(RawBtabs!$H$2:$H$1500,$R12)) -> Time Off | H12: =IF($R12="","",INDEX(RawBtabs!$B$2:$B$1500,$R12)) -> Approved | I12: =IF($R12="","",INDEX(RawBtabs!$U$2:$U$1500,$R12)) -> 8 | J12: =IF($R12="","",INDEX(RawBtabs!$K$2:$K$1500,$R12)) -> 0 | K12: =IF($C12="","",SUMIFS(RawBtabs!$V$2:$V$1500,RawBtabs!$A$2:$A$1500,$C12,RawBtabs!$C$2:$C$1500,$E12)) -> 8 | L12: =IF($C12="","",IF($I12=0,"⚠️ The detail does not state the hours",IF(ABS($K12-Config!$C$9)<=Config!$C$10,"✅ Full day ("&TEXT($K12,"0.##")&" h)",IF($K12<Config!$C$9,"🔻 Incomplete day: "&TEXT($K12,"0.##")&" h of "&TEXT(Config!$C$9,"0")&" h","🔺 Day exceeded: "&TEXT($K12,"0.##")&" h")))) -> ✅ Full day (8. h) | M12: =IF($R12="","",INDEX(RawBtabs!$Q$2:$Q$1500,$R12)) -> 8 hours nor billed for medical leave. | R12: =IFERROR(MATCH(ROW()-8,RawBtabs!$Z$2:$Z$1500,0),"") -> 214
B13: =IF($R13="","",ROW()-8) -> 5 | C13: =IF($R13="","",INDEX(RawBtabs!$A$2:$A$1500,$R13)) -> J Castillo | D13: =IF($C13="","",IFERROR(INDEX(BPOworkers!$E$6:$E$105,MATCH($C13,BPOworkers!$B$6:$B$105,0)),"")) -> J S Bermudez | E13: =IF($R13="","",INDEX(RawBtabs!$C$2:$C$1500,$R13)) -> 46268 | F13: =IF($C13="","",IFERROR(INDEX(Config!$F$7:$F$11,$E13-Config!$C$7+1),"")) -> Thursday | G13: =IF($R13="","",INDEX(RawBtabs!$H$2:$H$1500,$R13)) -> Time Off | H13: =IF($R13="","",INDEX(RawBtabs!$B$2:$B$1500,$R13)) -> Approved | I13: =IF($R13="","",INDEX(RawBtabs!$U$2:$U$1500,$R13)) -> 8 | J13: =IF($R13="","",INDEX(RawBtabs!$K$2:$K$1500,$R13)) -> 0 | K13: =IF($C13="","",SUMIFS(RawBtabs!$V$2:$V$1500,RawBtabs!$A$2:$A$1500,$C13,RawBtabs!$C$2:$C$1500,$E13)) -> 8 | L13: =IF($C13="","",IF($I13=0,"⚠️ The detail does not state the hours",IF(ABS($K13-Config!$C$9)<=Config!$C$10,"✅ Full day ("&TEXT($K13,"0.##")&" h)",IF($K13<Config!$C$9,"🔻 Incomplete day: "&TEXT($K13,"0.##")&" h of "&TEXT(Config!$C$9,"0")&" h","🔺 Day exceeded: "&TEXT($K13,"0.##")&" h")))) -> ✅ Full day (8. h) | M13: =IF($R13="","",INDEX(RawBtabs!$Q$2:$Q$1500,$R13)) -> 8 hours not worked medical leave. 8 Hours not billed | R13: =IFERROR(MATCH(ROW()-8,RawBtabs!$Z$2:$Z$1500,0),"") -> 312
B14: =IF($R14="","",ROW()-8) -> 6 | C14: =IF($R14="","",INDEX(RawBtabs!$A$2:$A$1500,$R14)) -> C Mesa | D14: =IF($C14="","",IFERROR(INDEX(BPOworkers!$E$6:$E$105,MATCH($C14,BPOworkers!$B$6:$B$105,0)),"")) -> M Leon | E14: =IF($R14="","",INDEX(RawBtabs!$C$2:$C$1500,$R14)) -> 46268 | F14: =IF($C14="","",IFERROR(INDEX(Config!$F$7:$F$11,$E14-Config!$C$7+1),"")) -> Thursday | G14: =IF($R14="","",INDEX(RawBtabs!$H$2:$H$1500,$R14)) -> BPO Vacation | H14: =IF($R14="","",INDEX(RawBtabs!$B$2:$B$1500,$R14)) -> Approved | I14: =IF($R14="","",INDEX(RawBtabs!$U$2:$U$1500,$R14)) -> 8 | J14: =IF($R14="","",INDEX(RawBtabs!$K$2:$K$1500,$R14)) -> 0 | K14: =IF($C14="","",SUMIFS(RawBtabs!$V$2:$V$1500,RawBtabs!$A$2:$A$1500,$C14,RawBtabs!$C$2:$C$1500,$E14)) -> 8 | L14: =IF($C14="","",IF($I14=0,"⚠️ The detail does not state the hours",IF(ABS($K14-Config!$C$9)<=Config!$C$10,"✅ Full day ("&TEXT($K14,"0.##")&" h)",IF($K14<Config!$C$9,"🔻 Incomplete day: "&TEXT($K14,"0.##")&" h of "&TEXT(Config!$C$9,"0")&" h","🔺 Day exceeded: "&TEXT($K14,"0.##")&" h")))) -> ✅ Full day (8. h) | M14: =IF($R14="","",INDEX(RawBtabs!$Q$2:$Q$1500,$R14)) -> 8 hours of paid vacations | R14: =IFERROR(MATCH(ROW()-8,RawBtabs!$Z$2:$Z$1500,0),"") -> 325
B15: =IF($R15="","",ROW()-8) -> 7 | C15: =IF($R15="","",INDEX(RawBtabs!$A$2:$A$1500,$R15)) -> J Castillo | D15: =IF($C15="","",IFERROR(INDEX(BPOworkers!$E$6:$E$105,MATCH($C15,BPOworkers!$B$6:$B$105,0)),"")) -> J S Bermudez | E15: =IF($R15="","",INDEX(RawBtabs!$C$2:$C$1500,$R15)) -> 46267 | F15: =IF($C15="","",IFERROR(INDEX(Config!$F$7:$F$11,$E15-Config!$C$7+1),"")) -> Wednesday | G15: =IF($R15="","",INDEX(RawBtabs!$H$2:$H$1500,$R15)) -> Time Off | H15: =IF($R15="","",INDEX(RawBtabs!$B$2:$B$1500,$R15)) -> Approved | I15: =IF($R15="","",INDEX(RawBtabs!$U$2:$U$1500,$R15)) -> 8 | J15: =IF($R15="","",INDEX(RawBtabs!$K$2:$K$1500,$R15)) -> 0 | K15: =IF($C15="","",SUMIFS(RawBtabs!$V$2:$V$1500,RawBtabs!$A$2:$A$1500,$C15,RawBtabs!$C$2:$C$1500,$E15)) -> 8 | L15: =IF($C15="","",IF($I15=0,"⚠️ The detail does not state the hours",IF(ABS($K15-Config!$C$9)<=Config!$C$10,"✅ Full day ("&TEXT($K15,"0.##")&" h)",IF($K15<Config!$C$9,"🔻 Incomplete day: "&TEXT($K15,"0.##")&" h of "&TEXT(Config!$C$9,"0")&" h","🔺 Day exceeded: "&TEXT($K15,"0.##")&" h")))) -> ✅ Full day (8. h) | M15: =IF($R15="","",INDEX(RawBtabs!$Q$2:$Q$1500,$R15)) -> 8 hours not worked medical leave. 8 Hours not billed | R15: =IFERROR(MATCH(ROW()-8,RawBtabs!$Z$2:$Z$1500,0),"") -> 461
B16: =IF($R16="","",ROW()-8) -> 8 | C16: =IF($R16="","",INDEX(RawBtabs!$A$2:$A$1500,$R16)) -> A Lopez | D16: =IF($C16="","",IFERROR(INDEX(BPOworkers!$E$6:$E$105,MATCH($C16,BPOworkers!$B$6:$B$105,0)),"")) -> S Romero | E16: =IF($R16="","",INDEX(RawBtabs!$C$2:$C$1500,$R16)) -> 46267 | F16: =IF($C16="","",IFERROR(INDEX(Config!$F$7:$F$11,$E16-Config!$C$7+1),"")) -> Wednesday | G16: =IF($R16="","",INDEX(RawBtabs!$H$2:$H$1500,$R16)) -> Time Off | H16: =IF($R16="","",INDEX(RawBtabs!$B$2:$B$1500,$R16)) -> Approved | I16: =IF($R16="","",INDEX(RawBtabs!$U$2:$U$1500,$R16)) -> 3 | J16: =IF($R16="","",INDEX(RawBtabs!$K$2:$K$1500,$R16)) -> 0 | K16: =IF($C16="","",SUMIFS(RawBtabs!$V$2:$V$1500,RawBtabs!$A$2:$A$1500,$C16,RawBtabs!$C$2:$C$1500,$E16)) -> 8 | L16: =IF($C16="","",IF($I16=0,"⚠️ The detail does not state the hours",IF(ABS($K16-Config!$C$9)<=Config!$C$10,"✅ Full day ("&TEXT($K16,"0.##")&" h)",IF($K16<Config!$C$9,"🔻 Incomplete day: "&TEXT($K16,"0.##")&" h of "&TEXT(Config!$C$9,"0")&" h","🔺 Day exceeded: "&TEXT($K16,"0.##")&" h")))) -> ✅ Full day (8. h) | M16: =IF($R16="","",INDEX(RawBtabs!$Q$2:$Q$1500,$R16)) -> 3 hours | R16: =IFERROR(MATCH(ROW()-8,RawBtabs!$Z$2:$Z$1500,0),"") -> 470
B17: =IF($R17="","",ROW()-8) -> 9 | C17: =IF($R17="","",INDEX(RawBtabs!$A$2:$A$1500,$R17)) -> C Mesa | D17: =IF($C17="","",IFERROR(INDEX(BPOworkers!$E$6:$E$105,MATCH($C17,BPOworkers!$B$6:$B$105,0)),"")) -> M Leon | E17: =IF($R17="","",INDEX(RawBtabs!$C$2:$C$1500,$R17)) -> 46267 | F17: =IF($C17="","",IFERROR(INDEX(Config!$F$7:$F$11,$E17-Config!$C$7+1),"")) -> Wednesday | G17: =IF($R17="","",INDEX(RawBtabs!$H$2:$H$1500,$R17)) -> BPO Vacation | H17: =IF($R17="","",INDEX(RawBtabs!$B$2:$B$1500,$R17)) -> Approved | I17: =IF($R17="","",INDEX(RawBtabs!$U$2:$U$1500,$R17)) -> 8 | J17: =IF($R17="","",INDEX(RawBtabs!$K$2:$K$1500,$R17)) -> 0 | K17: =IF($C17="","",SUMIFS(RawBtabs!$V$2:$V$1500,RawBtabs!$A$2:$A$1500,$C17,RawBtabs!$C$2:$C$1500,$E17)) -> 8 | L17: =IF($C17="","",IF($I17=0,"⚠️ The detail does not state the hours",IF(ABS($K17-Config!$C$9)<=Config!$C$10,"✅ Full day ("&TEXT($K17,"0.##")&" h)",IF($K17<Config!$C$9,"🔻 Incomplete day: "&TEXT($K17,"0.##")&" h of "&TEXT(Config!$C$9,"0")&" h","🔺 Day exceeded: "&TEXT($K17,"0.##")&" h")))) -> ✅ Full day (8. h) | M17: =IF($R17="","",INDEX(RawBtabs!$Q$2:$Q$1500,$R17)) -> 8 hours of paid vacations | R17: =IFERROR(MATCH(ROW()-8,RawBtabs!$Z$2:$Z$1500,0),"") -> 474
B18: =IF($R18="","",ROW()-8) -> 10 | C18: =IF($R18="","",INDEX(RawBtabs!$A$2:$A$1500,$R18)) -> J Gonzalez | D18: =IF($C18="","",IFERROR(INDEX(BPOworkers!$E$6:$E$105,MATCH($C18,BPOworkers!$B$6:$B$105,0)),"")) -> R Sanchez | E18: =IF($R18="","",INDEX(RawBtabs!$C$2:$C$1500,$R18)) -> 46267 | F18: =IF($C18="","",IFERROR(INDEX(Config!$F$7:$F$11,$E18-Config!$C$7+1),"")) -> Wednesday | G18: =IF($R18="","",INDEX(RawBtabs!$H$2:$H$1500,$R18)) -> BPO Vacation | H18: =IF($R18="","",INDEX(RawBtabs!$B$2:$B$1500,$R18)) -> Approved | I18: =IF($R18="","",INDEX(RawBtabs!$U$2:$U$1500,$R18)) -> 8 | J18: =IF($R18="","",INDEX(RawBtabs!$K$2:$K$1500,$R18)) -> 0 | K18: =IF($C18="","",SUMIFS(RawBtabs!$V$2:$V$1500,RawBtabs!$A$2:$A$1500,$C18,RawBtabs!$C$2:$C$1500,$E18)) -> 8 | L18: =IF($C18="","",IF($I18=0,"⚠️ The detail does not state the hours",IF(ABS($K18-Config!$C$9)<=Config!$C$10,"✅ Full day ("&TEXT($K18,"0.##")&" h)",IF($K18<Config!$C$9,"🔻 Incomplete day: "&TEXT($K18,"0.##")&" h of "&TEXT(Config!$C$9,"0")&" h","🔺 Day exceeded: "&TEXT($K18,"0.##")&" h")))) -> ✅ Full day (8. h) | M18: =IF($R18="","",INDEX(RawBtabs!$Q$2:$Q$1500,$R18)) -> 8 hours of paid vacations | R18: =IFERROR(MATCH(ROW()-8,RawBtabs!$Z$2:$Z$1500,0),"") -> 475
B19: =IF($R19="","",ROW()-8) -> 11 | C19: =IF($R19="","",INDEX(RawBtabs!$A$2:$A$1500,$R19)) -> A Camargo | D19: =IF($C19="","",IFERROR(INDEX(BPOworkers!$E$6:$E$105,MATCH($C19,BPOworkers!$B$6:$B$105,0)),"")) -> BPO Management | E19: =IF($R19="","",INDEX(RawBtabs!$C$2:$C$1500,$R19)) -> 46266 | F19: =IF($C19="","",IFERROR(INDEX(Config!$F$7:$F$11,$E19-Config!$C$7+1),"")) -> Tuesday | G19: =IF($R19="","",INDEX(RawBtabs!$H$2:$H$1500,$R19)) -> Time Off | H19: =IF($R19="","",INDEX(RawBtabs!$B$2:$B$1500,$R19)) -> Approved | I19: =IF($R19="","",INDEX(RawBtabs!$U$2:$U$1500,$R19)) -> 4 | J19: =IF($R19="","",INDEX(RawBtabs!$K$2:$K$1500,$R19)) -> 0 | K19: =IF($C19="","",SUMIFS(RawBtabs!$V$2:$V$1500,RawBtabs!$A$2:$A$1500,$C19,RawBtabs!$C$2:$C$1500,$E19)) -> 8 | L19: =IF($C19="","",IF($I19=0,"⚠️ The detail does not state the hours",IF(ABS($K19-Config!$C$9)<=Config!$C$10,"✅ Full day ("&TEXT($K19,"0.##")&" h)",IF($K19<Config!$C$9,"🔻 Incomplete day: "&TEXT($K19,"0.##")&" h of "&TEXT(Config!$C$9,"0")&" h","🔺 Day exceeded: "&TEXT($K19,"0.##")&" h")))) -> ✅ Full day (8. h) | M19: =IF($R19="","",INDEX(RawBtabs!$Q$2:$Q$1500,$R19)) -> 4 hours not billed. | R19: =IFERROR(MATCH(ROW()-8,RawBtabs!$Z$2:$Z$1500,0),"") -> 609
B20: =IF($R20="","",ROW()-8) -> 12 | C20: =IF($R20="","",INDEX(RawBtabs!$A$2:$A$1500,$R20)) -> J Castillo | D20: =IF($C20="","",IFERROR(INDEX(BPOworkers!$E$6:$E$105,MATCH($C20,BPOworkers!$B$6:$B$105,0)),"")) -> J S Bermudez | E20: =IF($R20="","",INDEX(RawBtabs!$C$2:$C$1500,$R20)) -> 46266 | F20: =IF($C20="","",IFERROR(INDEX(Config!$F$7:$F$11,$E20-Config!$C$7+1),"")) -> Tuesday | G20: =IF($R20="","",INDEX(RawBtabs!$H$2:$H$1500,$R20)) -> Time Off | H20: =IF($R20="","",INDEX(RawBtabs!$B$2:$B$1500,$R20)) -> Approved | I20: =IF($R20="","",INDEX(RawBtabs!$U$2:$U$1500,$R20)) -> 2 | J20: =IF($R20="","",INDEX(RawBtabs!$K$2:$K$1500,$R20)) -> 0 | K20: =IF($C20="","",SUMIFS(RawBtabs!$V$2:$V$1500,RawBtabs!$A$2:$A$1500,$C20,RawBtabs!$C$2:$C$1500,$E20)) -> 8 | L20: =IF($C20="","",IF($I20=0,"⚠️ The detail does not state the hours",IF(ABS($K20-Config!$C$9)<=Config!$C$10,"✅ Full day ("&TEXT($K20,"0.##")&" h)",IF($K20<Config!$C$9,"🔻 Incomplete day: "&TEXT($K20,"0.##")&" h of "&TEXT(Config!$C$9,"0")&" h","🔺 Day exceeded: "&TEXT($K20,"0.##")&" h")))) -> ✅ Full day (8. h) | M20: =IF($R20="","",INDEX(RawBtabs!$Q$2:$Q$1500,$R20)) -> 2 hours not worked medical leave. 2 Hours not billed | R20: =IFERROR(MATCH(ROW()-8,RawBtabs!$Z$2:$Z$1500,0),"") -> 615
... B98: =IF($R98="","",ROW()-8) | C98: =IF($R98="","",INDEX(RawBtabs!$A$2:$A$1500,$R98)) | D98: =IF($C98="","",IFERROR(INDEX(BPOworkers!$E$6:$E$105,MATCH($C98,BPOworkers!$B$6:$B$105,0)),"")) | E98: =IF($R98="","",INDEX(RawBtabs!$C$2:$C$1500,$R98)) | F98: =IF($C98="","",IFERROR(INDEX(Config!$F$7:$F$11,$E98-Config!$C$7+1),"")) | G98: =IF($R98="","",INDEX(RawBtabs!$H$2:$H$1500,$R98)) | H98: =IF($R98="","",INDEX(RawBtabs!$B$2:$B$1500,$R98)) | I98: =IF($R98="","",INDEX(RawBtabs!$U$2:$U$1500,$R98)) | J98: =IF($R98="","",INDEX(RawBtabs!$K$2:$K$1500,$R98)) | K98: =IF($C98="","",SUMIFS(RawBtabs!$V$2:$V$1500,RawBtabs!$A$2:$A$1500,$C98,RawBtabs!$C$2:$C$1500,$E98)) | L98: =IF($C98="","",IF($I98=0,"⚠️ The detail does not state the hours",IF(ABS($K98-Config!$C$9)<=Config!$C$10,"✅ Full day ("&TEXT($K98,"0.##")&" h)",IF($K98<Config!$C$9,"🔻 Incomplete day: "&TEXT($K98,"0.##")&" h of "&TEXT(Config!$C$9,"0")&" h","🔺 Day exceeded: "&TEXT($K98,"0.##")&" h")))) | M98: =IF($R98="","",INDEX(RawBtabs!$Q$2:$Q$1500,$R98)) | R98: =IFERROR(MATCH(ROW()-8,RawBtabs!$Z$2:$Z$1500,0),"")

Sheet SeniorReview
B2: WEEKLY SENIOR REVIEW
B3: One single place to close the week: summary by Team Lead, control checklist and sign-off.
B5: BLOCK 1 - SUMMARY BY TEAM LEAD
B6: TEAM LEAD | C6: # people | D6: Perfect week | E6: To review | F6: Critical | G6: Billed hours | H6: Target hours | I6: % people OK | J6: Days with alert | K6: SIGN-OFF | L6: Reviewed by | M6: Date | N6: Comments
B7: A Camargo | C7: =COUNTIF(Dashboard!$D$10:$D$69,$B7) -> 4 | D7: =COUNTIFS(Dashboard!$D$10:$D$69,$B7,Dashboard!$Q$10:$Q$69,0) -> 2 | E7: =COUNTIFS(Dashboard!$D$10:$D$69,$B7,Dashboard!$Q$10:$Q$69,1)+COUNTIFS(Dashboard!$D$10:$D$69,$B7,Dashboard!$Q$10:$Q$69,2) -> 1 | F7: =COUNTIFS(Dashboard!$D$10:$D$69,$B7,Dashboard!$Q$10:$Q$69,3) -> 1 | G7: =SUMIFS(Dashboard!$J$10:$J$69,Dashboard!$D$10:$D$69,$B7) -> 160 | H7: =SUMIFS(Dashboard!$K$10:$K$69,Dashboard!$D$10:$D$69,$B7) -> 160 | I7: =IFERROR($D7/$C7,0) -> 0.5 | J7: =COUNTIFS(Detail!$D$4:$D$303,$B7,Detail!$N$4:$N$303,">0") -> 3 | K7: Pending
B8: A Lorenzo | C8: =COUNTIF(Dashboard!$D$10:$D$69,$B8) -> 1 | D8: =COUNTIFS(Dashboard!$D$10:$D$69,$B8,Dashboard!$Q$10:$Q$69,0) -> 1 | E8: =COUNTIFS(Dashboard!$D$10:$D$69,$B8,Dashboard!$Q$10:$Q$69,1)+COUNTIFS(Dashboard!$D$10:$D$69,$B8,Dashboard!$Q$10:$Q$69,2) -> 0 | F8: =COUNTIFS(Dashboard!$D$10:$D$69,$B8,Dashboard!$Q$10:$Q$69,3) -> 0 | G8: =SUMIFS(Dashboard!$J$10:$J$69,Dashboard!$D$10:$D$69,$B8) -> 40 | H8: =SUMIFS(Dashboard!$K$10:$K$69,Dashboard!$D$10:$D$69,$B8) -> 40 | I8: =IFERROR($D8/$C8,0) -> 1 | J8: =COUNTIFS(Detail!$D$4:$D$303,$B8,Detail!$N$4:$N$303,">0") -> 0 | K8: Pending
B9: H Daza | C9: =COUNTIF(Dashboard!$D$10:$D$69,$B9) -> 4 | D9: =COUNTIFS(Dashboard!$D$10:$D$69,$B9,Dashboard!$Q$10:$Q$69,0) -> 3 | E9: =COUNTIFS(Dashboard!$D$10:$D$69,$B9,Dashboard!$Q$10:$Q$69,1)+COUNTIFS(Dashboard!$D$10:$D$69,$B9,Dashboard!$Q$10:$Q$69,2) -> 1 | F9: =COUNTIFS(Dashboard!$D$10:$D$69,$B9,Dashboard!$Q$10:$Q$69,3) -> 0 | G9: =SUMIFS(Dashboard!$J$10:$J$69,Dashboard!$D$10:$D$69,$B9) -> 168 | H9: =SUMIFS(Dashboard!$K$10:$K$69,Dashboard!$D$10:$D$69,$B9) -> 160 | I9: =IFERROR($D9/$C9,0) -> 0.75 | J9: =COUNTIFS(Detail!$D$4:$D$303,$B9,Detail!$N$4:$N$303,">0") -> 1 | K9: Pending
B10: J S Bermudez | C10: =COUNTIF(Dashboard!$D$10:$D$69,$B10) -> 5 | D10: =COUNTIFS(Dashboard!$D$10:$D$69,$B10,Dashboard!$Q$10:$Q$69,0) -> 3 | E10: =COUNTIFS(Dashboard!$D$10:$D$69,$B10,Dashboard!$Q$10:$Q$69,1)+COUNTIFS(Dashboard!$D$10:$D$69,$B10,Dashboard!$Q$10:$Q$69,2) -> 1 | F10: =COUNTIFS(Dashboard!$D$10:$D$69,$B10,Dashboard!$Q$10:$Q$69,3) -> 1 | G10: =SUMIFS(Dashboard!$J$10:$J$69,Dashboard!$D$10:$D$69,$B10) -> 200 | H10: =SUMIFS(Dashboard!$K$10:$K$69,Dashboard!$D$10:$D$69,$B10) -> 200 | I10: =IFERROR($D10/$C10,0) -> 0.6 | J10: =COUNTIFS(Detail!$D$4:$D$303,$B10,Detail!$N$4:$N$303,">0") -> 2 | K10: Pending
B11: M Leon | C11: =COUNTIF(Dashboard!$D$10:$D$69,$B11) -> 5 | D11: =COUNTIFS(Dashboard!$D$10:$D$69,$B11,Dashboard!$Q$10:$Q$69,0) -> 5 | E11: =COUNTIFS(Dashboard!$D$10:$D$69,$B11,Dashboard!$Q$10:$Q$69,1)+COUNTIFS(Dashboard!$D$10:$D$69,$B11,Dashboard!$Q$10:$Q$69,2) -> 0 | F11: =COUNTIFS(Dashboard!$D$10:$D$69,$B11,Dashboard!$Q$10:$Q$69,3) -> 0 | G11: =SUMIFS(Dashboard!$J$10:$J$69,Dashboard!$D$10:$D$69,$B11) -> 200 | H11: =SUMIFS(Dashboard!$K$10:$K$69,Dashboard!$D$10:$D$69,$B11) -> 200 | I11: =IFERROR($D11/$C11,0) -> 1 | J11: =COUNTIFS(Detail!$D$4:$D$303,$B11,Detail!$N$4:$N$303,">0") -> 0 | K11: Pending
B12: R Sanchez | C12: =COUNTIF(Dashboard!$D$10:$D$69,$B12) -> 5 | D12: =COUNTIFS(Dashboard!$D$10:$D$69,$B12,Dashboard!$Q$10:$Q$69,0) -> 5 | E12: =COUNTIFS(Dashboard!$D$10:$D$69,$B12,Dashboard!$Q$10:$Q$69,1)+COUNTIFS(Dashboard!$D$10:$D$69,$B12,Dashboard!$Q$10:$Q$69,2) -> 0 | F12: =COUNTIFS(Dashboard!$D$10:$D$69,$B12,Dashboard!$Q$10:$Q$69,3) -> 0 | G12: =SUMIFS(Dashboard!$J$10:$J$69,Dashboard!$D$10:$D$69,$B12) -> 200 | H12: =SUMIFS(Dashboard!$K$10:$K$69,Dashboard!$D$10:$D$69,$B12) -> 200 | I12: =IFERROR($D12/$C12,0) -> 1 | J12: =COUNTIFS(Detail!$D$4:$D$303,$B12,Detail!$N$4:$N$303,">0") -> 0 | K12: Pending
B13: S Romero | C13: =COUNTIF(Dashboard!$D$10:$D$69,$B13) -> 5 | D13: =COUNTIFS(Dashboard!$D$10:$D$69,$B13,Dashboard!$Q$10:$Q$69,0) -> 5 | E13: =COUNTIFS(Dashboard!$D$10:$D$69,$B13,Dashboard!$Q$10:$Q$69,1)+COUNTIFS(Dashboard!$D$10:$D$69,$B13,Dashboard!$Q$10:$Q$69,2) -> 0 | F13: =COUNTIFS(Dashboard!$D$10:$D$69,$B13,Dashboard!$Q$10:$Q$69,3) -> 0 | G13: =SUMIFS(Dashboard!$J$10:$J$69,Dashboard!$D$10:$D$69,$B13) -> 200 | H13: =SUMIFS(Dashboard!$K$10:$K$69,Dashboard!$D$10:$D$69,$B13) -> 200 | I13: =IFERROR($D13/$C13,0) -> 1 | J13: =COUNTIFS(Detail!$D$4:$D$303,$B13,Detail!$N$4:$N$303,">0") -> 0 | K13: Pending
B14: BPO Management | C14: =COUNTIF(Dashboard!$D$10:$D$69,$B14) -> 9 | D14: =COUNTIFS(Dashboard!$D$10:$D$69,$B14,Dashboard!$Q$10:$Q$69,0) -> 9 | E14: =COUNTIFS(Dashboard!$D$10:$D$69,$B14,Dashboard!$Q$10:$Q$69,1)+COUNTIFS(Dashboard!$D$10:$D$69,$B14,Dashboard!$Q$10:$Q$69,2) -> 0 | F14: =COUNTIFS(Dashboard!$D$10:$D$69,$B14,Dashboard!$Q$10:$Q$69,3) -> 0 | G14: =SUMIFS(Dashboard!$J$10:$J$69,Dashboard!$D$10:$D$69,$B14) -> 360 | H14: =SUMIFS(Dashboard!$K$10:$K$69,Dashboard!$D$10:$D$69,$B14) -> 360 | I14: =IFERROR($D14/$C14,0) -> 1 | J14: =COUNTIFS(Detail!$D$4:$D$303,$B14,Detail!$N$4:$N$303,">0") -> 0 | K14: Pending
B15: TOTAL BPO | C15: =SUM(C7:C14) -> 38 | D15: =SUM(D7:D14) -> 33 | E15: =SUM(E7:E14) -> 3 | F15: =SUM(F7:F14) -> 2 | G15: =SUM(G7:G14) -> 1528 | H15: =SUM(H7:H14) -> 1520 | I15: =IFERROR($D15/$C15,0) -> 0.86842105 | J15: =SUM(J7:J14) -> 6
B17: BLOCK 2 - BILLING CONTROL CHECKLIST (answers itself)
B18: # | C18: CONTROL QUESTION | G18: Result | H18: STATUS | I18: Where to check | J18: What it means / what to do | K18: SIGN-OFF
B19: 1 | C19: Did every landman log all 5 days in BTabs? | G19: =COUNTIF(Detail!$G$4:$G$303,0) -> 2 | H19: =IF($G19=0,"✅ ALL GOOD","⚠️ REVIEW") -> ⚠️ REVIEW | I19: Tab: Alerts | J19: Every day without an entry is a day without billing. Ask for the entry retroactively. | K19: Pending
B20: 2 | C20: Did anyone end up UNDER the target on any day? | G20: =COUNTIFS(Detail!$G$4:$G$303,">0",Detail!$L$4:$L$303,"<0") -> 0 | H20: =IF($G20=0,"✅ ALL GOOD","⚠️ REVIEW") -> ✅ ALL GOOD | I20: Tab: Alerts | J20: Hours worked that were never billed. Confirm if they forgot to bill or to log time off. | K20: Pending
B21: 3 | C21: Did anyone end up OVER the target on any day? | G21: =COUNTIFS(Detail!$G$4:$G$303,">0",Detail!$L$4:$L$303,">0") -> 4 | H21: =IF($G21=0,"✅ ALL GOOD","⚠️ REVIEW") -> ⚠️ REVIEW | I21: Tab: Alerts | J21: Usually a duplicate entry or a typo. Verify with the landman. | K21: Pending
B22: 4 | C22: Do all time off entries state the hours in the detail? | G22: =SUMPRODUCT(RawBtabs!$X$2:$X$1500,RawBtabs!$W$2:$W$1500,RawBtabs!$S$2:$S$1500,--(RawBtabs!$U$2:$U$1500=0)) -> 0 | H22: =IF($G22=0,"✅ ALL GOOD","⚠️ REVIEW") -> ✅ ALL GOOD | I22: Tab: TimeOff | J22: The detail must start with the number of hours, e.g. "8 hours of paid vacations". | K22: Pending
B23: 5 | C23: Are there entries from this week still unapproved in BTabs? | G23: =SUMPRODUCT(--(RawBtabs!$B$2:$B$1500="Unapproved"),RawBtabs!$W$2:$W$1500,RawBtabs!$S$2:$S$1500) -> 14 | H23: =IF($G23=0,"✅ ALL GOOD","⚠️ REVIEW") -> ⚠️ REVIEW | I23: Tab: RawBtabs | J23: The Team Lead must approve or reject before the weekly close. | K23: Pending
B24: 6 | C24: Is there anyone in the roster who billed NOTHING this week? | G24: =COUNTIF(Dashboard!$M$10:$M$69,0) -> 0 | H24: =IF($G24=0,"✅ ALL GOOD","⚠️ REVIEW") -> ✅ ALL GOOD | I24: Tab: Dashboard | J24: Could be unlogged vacation, someone who left the company, or an outdated roster. | K24: Pending
B25: 7 | C25: How many people closed a perfect week? | G25: =COUNTIF(Dashboard!$Q$10:$Q$69,0) -> 33 | H25: =IF($G25=Config!$C$14,"✅ ALL GOOD","⚠️ REVIEW") -> ⚠️ REVIEW | I25: Tab: Dashboard | J25: Goal: this number should equal the total number of people in the roster. | K25: Pending
B27: BLOCK 3 - WEEK CLOSE AND SIGN-OFF
B28: Week reviewed | E28: =TEXT(Config!$C$7,"dd/mm/yyyy")&" to "&TEXT(Config!$C$8,"dd/mm/yyyy") -> 31/08/2026 to 04/09/2026
B29: Reviewed by (senior name) | E29: Type your name here
B30: Review date
B31: Overall conclusion for the week | E31: Type the conclusion here
B32: Agreed actions / follow-up | E32: Type the commitments here

Sheet DataHealth
B2: DATA HEALTH - CHECK THIS BEFORE YOU TRUST THE NUMBERS
B3: The Dashboard can only be right if the pasted data is right. These 13 checks look at the data itself.
B5: STEP 0 - DID THE PASTE ACTUALLY LAND? | J5: ⛔ RawBtabs is empty. Paste the BTabs export into RawBtabs, starting at cell A2.
B6: =IF(Config!$C$15=0,$J$5,IF(Config!$C$17=0,$J$6,IF(Config!$C$18=0,$J$7,$J$8&" "&TEXT(Config!$C$15,"0")&" rows pasted · "&TEXT(Config!$C$17,"0")&" inside the selected week · "&TEXT(Config!$C$18,"0")&" of those belong to the BPO roster."))) -> ✅ Data looks loaded. 858 rows pasted · 733 inside the selected week · 283 of those belong to the BPO roster. | J6: ⛔ Rows were pasted, but NONE of them fall inside the week selected in Config. Either the export is from a different week, or the Monday in Config is wrong.
J7: ⛔ There is data for the selected week, but none of it belongs to anyone in the roster. Check the BPOworkers tab.
J8: ✅ Data looks loaded.
B9: THE 13 CHECKS - every one of them explains itself
B10: # | C10: WHAT WE CHECK | D10: COUNT | E10: STATUS | F10: WHY IT MATTERS | G10: WHAT TO DO ABOUT IT | H10: WHERE TO LOOK
B11: 1 | C11: Rows pasted into RawBtabs | D11: =Config!$C$15 -> 858 | E11: =IF($D11>0,"✅ ALL GOOD","⛔ NO DATA") -> ✅ ALL GOOD | F11: If this is zero there is simply nothing to report on. | G11: Paste the BTabs export into RawBtabs starting at cell A2. | H11: RawBtabs | J11: =IF($D11>0,0,2) -> 0
B12: 2 | C12: Rows dated inside the selected week | D12: =Config!$C$17 -> 733 | E12: =IF($D12>0,"✅ ALL GOOD","⛔ NO DATA") -> ✅ ALL GOOD | F12: The report only looks at Monday to Friday of the week set in Config. Rows outside that window are ignored. | G12: If this is zero, fix the Monday in Config or paste the right export. | H12: Config | J12: =IF($D12>0,0,2) -> 0
B13: 3 | C13: Rows of the selected week that belong to the roster | D13: =Config!$C$18 -> 283 | E13: =IF($D13>0,"✅ ALL GOOD","⛔ NO DATA") -> ✅ ALL GOOD | F13: BTabs exports mix BPO landmen with US TLS landmen. Only roster names are counted. | G13: If this looks too low, someone may be missing from the BPOworkers tab. | H13: BPOworkers | J13: =IF($D13>0,0,2) -> 0
B14: 4 | C14: People billing with a BPO-style name who are NOT in the roster | D14: =SUM(RawBtabs!$AC$2:$AC$1500) -> 1 | E14: =IF($D14=0,"✅ ALL GOOD","⚠️ REVIEW") -> ⚠️ REVIEW | F14: A BPO name written without a dot that is not in the roster is almost always a landman who was never added. Their billing is being excluded from the whole report and nobody is reviewing it. | G14: Look at the list below. If the person really is BPO, add them to the BPOworkers tab. | H14: List below | J14: =IF($D14=0,0,1) -> 1
B15: 5 | C15: BPO entries logged on a Saturday or Sunday | D15: =SUM(RawBtabs!$AF$2:$AF$1500) -> 11 | E15: =IF($D15=0,"✅ ALL GOOD","⚠️ REVIEW") -> ⚠️ REVIEW | F15: The report counts Monday to Friday only, so weekend billing is invisible here even though it was billed. | G15: Decide whether weekend work should count. If it should, review those rows by hand. | H15: RawBtabs, filter the Weekend column | J15: =IF($D15=0,0,1) -> 1
B16: 6 | C16: BPO entries in the paste but outside the selected week | D16: =SUM(RawBtabs!$AG$2:$AG$1500) -> 50 | E16: ="ℹ️ FOR INFO" -> ℹ️ FOR INFO | F16: Normal if your export covers more than one week. These rows are simply not part of this week’s numbers. | G16: Nothing to do, unless the number is suspiciously large. | H16: RawBtabs, filter Outside week | J16: =3 -> 3
B17: 7 | C17: Suspected duplicate entries inside the week | D17: =SUM(RawBtabs!$AI$2:$AI$1500) -> 8 | E17: =IF($D17=0,"✅ ALL GOOD","⚠️ REVIEW") -> ⚠️ REVIEW | F17: Same person, same date, same Work Type, same hours and same opening text. This is the usual reason somebody shows OVER TARGET on the Dashboard. | G17: Open those rows and delete the copy in BTabs, then re-export and re-paste. | H17: RawBtabs, filter Duplicate | J17: =IF($D17=0,0,1) -> 1
B18: 8 | C18: Entries whose hours are not a whole hour | D18: =SUM(RawBtabs!$AJ$2:$AJ$1500) -> 0 | E18: =IF($D18=0,"✅ ALL GOOD","⚠️ REVIEW") -> ✅ ALL GOOD | F18: Billing moves in steps of 0.125 = 1 hour. Anything in between is a typo. | G18: Correct the Time Worked value in BTabs. | H18: RawBtabs, filter Not whole hour | J18: =IF($D18=0,0,1) -> 0
B19: 9 | C19: Time off entries declaring MORE than the daily target | D19: =SUM(RawBtabs!$AK$2:$AK$1500) -> 0 | E19: =IF($D19=0,"✅ ALL GOOD","⚠️ REVIEW") -> ✅ ALL GOOD | F19: Somebody wrote more hours of absence than a working day has, so their day would count as over target. | G19: Fix the number at the start of the Work Performed Detail in BTabs. | H19: RawBtabs, filter Time off over target | J19: =IF($D19=0,0,1) -> 0
B20: 10 | C20: Time off entries with no hours written in the detail | D20: =SUM(RawBtabs!$AL$2:$AL$1500) -> 0 | E20: =IF($D20=0,"✅ ALL GOOD","⚠️ REVIEW") -> ✅ ALL GOOD | F20: The system reads the FIRST NUMBER of the detail to know how long the absence was. With no number it reads zero and the day looks under target even though the person was legitimately away. | G20: Ask the landman to start the detail with the hours, e.g. "8 hours of paid vacations". | H20: TimeOff | J20: =IF($D20=0,0,1) -> 0
B21: 11 | C21: Entries of the week still Unapproved in BTabs | D21: =SUMPRODUCT(--(RawBtabs!$B$2:$B$1500="Unapproved"),RawBtabs!$W$2:$W$1500,RawBtabs!$S$2:$S$1500) -> 14 | E21: =IF($D21=0,"✅ ALL GOOD","⚠️ REVIEW") -> ⚠️ REVIEW | F21: Unapproved hours still count in this report but they are not yet locked in for invoicing. | G21: The Team Lead approves or rejects them before the weekly close. | H21: RawBtabs, Status column | J21: =IF($D21=0,0,1) -> 1
B22: 12 | C22: Entries of the week marked Rejected | D22: =SUMPRODUCT(--(RawBtabs!$B$2:$B$1500="Rejected"),RawBtabs!$W$2:$W$1500,RawBtabs!$S$2:$S$1500) -> 0 | E22: =IF($D22=0,"✅ ALL GOOD","⚠️ REVIEW") -> ✅ ALL GOOD | F22: A rejected entry is still added up here, so a rejected day can look complete when it is not. | G22: Have the landman correct and resubmit the entry, then re-paste the export. | H22: RawBtabs, Status column | J22: =IF($D22=0,0,1) -> 0
B23: 13 | C23: Roster people with no entries at all in the paste | D23: =SUMPRODUCT(--(BPOworkers!$B$6:$B$105<>""),--(COUNTIF(RawBtabs!$A$2:$A$1500,BPOworkers!$B$6:$B$105)=0)) -> 0 | E23: =IF($D23=0,"✅ ALL GOOD","⚠️ REVIEW") -> ✅ ALL GOOD | F23: Either they were away all week without logging it, they left the company, or the roster is out of date. | G23: Check with their Team Lead and update the BPOworkers tab if needed. | H23: Dashboard | J23: =IF($D23=0,0,1) -> 0
B25: PEOPLE FOUND IN BTABS WHO ARE NOT IN THE ROSTER (check #4 above)
B26: # | C26: Name as written in BTabs | D26: Entries | E26: Hours this week | F26: WHY THIS MATTERS | G26: WHAT TO DO
B27: =IF($C27="","",ROW()-26) -> 1 | C27: =IFERROR(INDEX(RawBtabs!$A$2:$A$1500,MATCH(ROW()-26,RawBtabs!$AE$2:$AE$1500,0)),"") -> C Lara | D27: =IF($C27="","",COUNTIF(RawBtabs!$A$2:$A$1500,$C27)) -> 10 | E27: =IF($C27="","",SUMIFS(RawBtabs!$T$2:$T$1500,RawBtabs!$A$2:$A$1500,$C27,RawBtabs!$C$2:$C$1500,">="&Config!$C$7,RawBtabs!$C$2:$C$1500,"<="&Config!$C$8)) -> 32 | F27: =IF($C27="","","This person is billing in BTabs but is invisible to the whole report.") -> This person is billing in BTabs but is invisible to the whole report. | G27: =IF($C27="","","If they belong to BPO, add them to the BPOworkers tab. If not, ignore - the dot-less name is just a coincidence.") -> If they belong to BPO, add them to the BPOworkers tab. If not, ignore - the dot-less name is just a coincidence.
B28: =IF($C28="","",ROW()-26) | C28: =IFERROR(INDEX(RawBtabs!$A$2:$A$1500,MATCH(ROW()-26,RawBtabs!$AE$2:$AE$1500,0)),"") | D28: =IF($C28="","",COUNTIF(RawBtabs!$A$2:$A$1500,$C28)) | E28: =IF($C28="","",SUMIFS(RawBtabs!$T$2:$T$1500,RawBtabs!$A$2:$A$1500,$C28,RawBtabs!$C$2:$C$1500,">="&Config!$C$7,RawBtabs!$C$2:$C$1500,"<="&Config!$C$8)) | F28: =IF($C28="","","This person is billing in BTabs but is invisible to the whole report.") | G28: =IF($C28="","","If they belong to BPO, add them to the BPOworkers tab. If not, ignore - the dot-less name is just a coincidence.")
B29: =IF($C29="","",ROW()-26) | C29: =IFERROR(INDEX(RawBtabs!$A$2:$A$1500,MATCH(ROW()-26,RawBtabs!$AE$2:$AE$1500,0)),"") | D29: =IF($C29="","",COUNTIF(RawBtabs!$A$2:$A$1500,$C29)) | E29: =IF($C29="","",SUMIFS(RawBtabs!$T$2:$T$1500,RawBtabs!$A$2:$A$1500,$C29,RawBtabs!$C$2:$C$1500,">="&Config!$C$7,RawBtabs!$C$2:$C$1500,"<="&Config!$C$8)) | F29: =IF($C29="","","This person is billing in BTabs but is invisible to the whole report.") | G29: =IF($C29="","","If they belong to BPO, add them to the BPOworkers tab. If not, ignore - the dot-less name is just a coincidence.")
B30: =IF($C30="","",ROW()-26) | C30: =IFERROR(INDEX(RawBtabs!$A$2:$A$1500,MATCH(ROW()-26,RawBtabs!$AE$2:$AE$1500,0)),"") | D30: =IF($C30="","",COUNTIF(RawBtabs!$A$2:$A$1500,$C30)) | E30: =IF($C30="","",SUMIFS(RawBtabs!$T$2:$T$1500,RawBtabs!$A$2:$A$1500,$C30,RawBtabs!$C$2:$C$1500,">="&Config!$C$7,RawBtabs!$C$2:$C$1500,"<="&Config!$C$8)) | F30: =IF($C30="","","This person is billing in BTabs but is invisible to the whole report.") | G30: =IF($C30="","","If they belong to BPO, add them to the BPOworkers tab. If not, ignore - the dot-less name is just a coincidence.")
B31: =IF($C31="","",ROW()-26) | C31: =IFERROR(INDEX(RawBtabs!$A$2:$A$1500,MATCH(ROW()-26,RawBtabs!$AE$2:$AE$1500,0)),"") | D31: =IF($C31="","",COUNTIF(RawBtabs!$A$2:$A$1500,$C31)) | E31: =IF($C31="","",SUMIFS(RawBtabs!$T$2:$T$1500,RawBtabs!$A$2:$A$1500,$C31,RawBtabs!$C$2:$C$1500,">="&Config!$C$7,RawBtabs!$C$2:$C$1500,"<="&Config!$C$8)) | F31: =IF($C31="","","This person is billing in BTabs but is invisible to the whole report.") | G31: =IF($C31="","","If they belong to BPO, add them to the BPOworkers tab. If not, ignore - the dot-less name is just a coincidence.")
B32: =IF($C32="","",ROW()-26) | C32: =IFERROR(INDEX(RawBtabs!$A$2:$A$1500,MATCH(ROW()-26,RawBtabs!$AE$2:$AE$1500,0)),"") | D32: =IF($C32="","",COUNTIF(RawBtabs!$A$2:$A$1500,$C32)) | E32: =IF($C32="","",SUMIFS(RawBtabs!$T$2:$T$1500,RawBtabs!$A$2:$A$1500,$C32,RawBtabs!$C$2:$C$1500,">="&Config!$C$7,RawBtabs!$C$2:$C$1500,"<="&Config!$C$8)) | F32: =IF($C32="","","This person is billing in BTabs but is invisible to the whole report.") | G32: =IF($C32="","","If they belong to BPO, add them to the BPOworkers tab. If not, ignore - the dot-less name is just a coincidence.")
B33: =IF($C33="","",ROW()-26) | C33: =IFERROR(INDEX(RawBtabs!$A$2:$A$1500,MATCH(ROW()-26,RawBtabs!$AE$2:$AE$1500,0)),"") | D33: =IF($C33="","",COUNTIF(RawBtabs!$A$2:$A$1500,$C33)) | E33: =IF($C33="","",SUMIFS(RawBtabs!$T$2:$T$1500,RawBtabs!$A$2:$A$1500,$C33,RawBtabs!$C$2:$C$1500,">="&Config!$C$7,RawBtabs!$C$2:$C$1500,"<="&Config!$C$8)) | F33: =IF($C33="","","This person is billing in BTabs but is invisible to the whole report.") | G33: =IF($C33="","","If they belong to BPO, add them to the BPOworkers tab. If not, ignore - the dot-less name is just a coincidence.")
B34: =IF($C34="","",ROW()-26) | C34: =IFERROR(INDEX(RawBtabs!$A$2:$A$1500,MATCH(ROW()-26,RawBtabs!$AE$2:$AE$1500,0)),"") | D34: =IF($C34="","",COUNTIF(RawBtabs!$A$2:$A$1500,$C34)) | E34: =IF($C34="","",SUMIFS(RawBtabs!$T$2:$T$1500,RawBtabs!$A$2:$A$1500,$C34,RawBtabs!$C$2:$C$1500,">="&Config!$C$7,RawBtabs!$C$2:$C$1500,"<="&Config!$C$8)) | F34: =IF($C34="","","This person is billing in BTabs but is invisible to the whole report.") | G34: =IF($C34="","","If they belong to BPO, add them to the BPOworkers tab. If not, ignore - the dot-less name is just a coincidence.")
B36: WHAT THIS REPORT DELIBERATELY DOES NOT COUNT
B37: Anyone not in the BPOworkers roster | D37: The BTabs export mixes BPO landmen with US TLS landmen. The report keeps only the names listed in BPOworkers, so a missing roster row silently removes that person from every tab. That is what check #4 is for.
B38: Saturdays and Sundays | D38: The weekly target is 8 hours across 5 business days (40 hours). Weekend rows are excluded from every total. Check #5 tells you how many exist so they never go unnoticed.
B39: Any date outside the Monday-to-Friday window set in Config | D39: Change the Monday in Config to move the whole report to a different week. Nothing else needs to change.
B40: The Status column (Approved / Unapproved / Rejected) | D40: Hours are added up regardless of approval status, because the point of this report is whether the TIME was logged. Checks #11 and #12 surface the approval problems separately.

Sheet Legend
B2: LEGEND - WHAT EVERY COLOUR, MESSAGE AND COLUMN MEANS
B3: Read this once and the whole report becomes obvious. Nothing here needs to be edited.
B6: 1. THE ONE FORMULA THE WHOLE REPORT IS BUILT ON
B7: TOTAL COUNTED FOR A DAY = ( Time Worked × 8 ) + Time off hours Time Worked is column K of the BTabs export. It is expressed in DAYS, not hours: 1.0 means a full day. Multiplying by 8 turns it into hours. Time off hours is the first number written in the Work Performed Detail, and it only counts when the Work Type is Time Off, BPO Vacation or Holiday. A day is correct when that total equals the target in Config (8 by default). A week is correct when all five days are.
B13: 2. BILLING UNITS → HOURS (this is the "8 or 1" rule)
B14: Time Worked in BTabs | C14: Equals | D14: Meaning
B15: 0 | C15: 0 h | D15: No time worked at all
B16: 0.125 | C16: 1 h | D16: Partial day
B17: 0.25 | C17: 2 h | D17: Partial day
B18: 0.375 | C18: 3 h | D18: Partial day
B19: 0.5 | C19: 4 h | D19: Partial day
B20: 0.625 | C20: 5 h | D20: Partial day
B21: 0.75 | C21: 6 h | D21: Partial day
B22: 0.875 | C22: 7 h | D22: Partial day
B23: 1 | C23: 8 h | D23: Full day - this is the target
B26: 3. COLOUR CODE - why a cell is the colour it is
B27: COLOUR | C27: Where you see it | D27: WHY it is that colour | E27: WHAT TO DO
B28: GREEN | C28: Dashboard day cells, statuses | D28: The day (or the week) closed exactly on target, within the tolerance set in Config. | E28: Nothing. This is what every cell should look like.
B29: LIGHT RED | C29: Dashboard day cells, differences | D29: The day came in UNDER the target. Hours were worked but not billed, or an absence was never logged. | E29: Open the Alerts tab: it names the day and says how many hours are missing.
B30: BLUE | C30: Dashboard day cells | D30: The day came in OVER the target. Almost always a duplicated entry or a typo in Time Worked. | E30: Check DataHealth check #7 (duplicate suspects), then fix the entry in BTabs.
B31: DARK RED | C31: Dashboard day cells, week status | D31: There is NO entry at all in BTabs for that person on that day. This is the most serious case because the hours were never even claimed. | E31: Ask the landman to log the day retroactively, then re-export and re-paste.
B32: YELLOW | C32: Config, BPOworkers, sign-off cells | D32: A cell you are meant to type into. Everything else in the workbook calculates itself. | E32: Type freely. Never put data in a non-yellow cell.
B33: GREY / no fill | C33: Empty rows in Alerts and TimeOff | D33: Spare capacity. A row only draws its border once it has data, so a short list really means a short list. | E33: Nothing.
B36: 4. WEEK STATUS MESSAGES (Dashboard, column "WEEK STATUS")
B37: MESSAGE | C37: What it means | D37: Most common cause | E37: What to do
B38: ✅ PERFECT WEEK | C38: All five days closed on target. | D38: The landman did everything right. | E38: Nothing.
B39: ⛔ BILLED NOTHING | C39: Not a single entry all week. | D39: Away all week without logging it, has left the company, or the roster is out of date. | E39: Check with their Team Lead and update BPOworkers if needed.
B40: ⛔ MISSING n DAY(S) IN BTABS | C40: One or more days have no entry at all. | D40: Forgot to log a day, or logged it after the export was taken. | E40: Ask for the missing day, re-export, re-paste.
B41: 🔻 UNDER TARGET (-n h) | C41: Every day has entries, but the week adds up to less than the target. | D41: Hours worked and never billed, or an absence with no hours in the detail. | E41: See the WHY column for the exact day.
B42: 🔺 OVER TARGET (+n h) | C42: The week adds up to more than the target. | D42: A duplicated entry, or a typo in Time Worked. | E42: Check DataHealth #7, then fix in BTabs.
B43: ⚠️ CHECK THE DAYS | C43: The week total lands on target, but individual days do not. | D43: One day short and another long, cancelling each other out. | E43: See the WHY column - both days need fixing.
B46: 5. DAY MESSAGES (Alerts and Detail tabs, column "What happened")
B47: MESSAGE | C47: What it means | D47: What to do
B48: ⛔ NO ENTRY IN BTABS | C48: Zero entries for that person on that date. | D48: The landman must log the day.
B49: ✅ OK (8 h) | C49: That day is exactly on target. | D49: Nothing.
B50: 🔻 MISSING n h | C50: The day is short by n hours. | D50: Confirm whether they worked and did not bill, or need to log time off.
B51: 🔺 OVER BY n h | C51: The day exceeds the target by n hours. | D51: Look for a duplicate entry or a typo.
B54: 6. TIME OFF MESSAGES (TimeOff tab, column "DAY VALIDATION")
B55: MESSAGE | C55: What it means | D55: What to do
B56: ✅ Full day (8 h) | C56: The absence plus whatever was billed adds up to a full day. This is correct. | D56: Nothing.
B57: ⚠️ The detail does not state the hours | C57: The Work Performed Detail does not start with a number, so the system read 0 hours and the day looks short even though the absence was legitimate. | D57: Ask the landman to rewrite it as "8 hours of paid vacations" (number first).
B58: 🔻 Incomplete day: n h of 8 h | C58: Absence plus billed hours still fall short of a full day. | D58: Either more absence hours need declaring, or hours are missing.
B59: 🔺 Day exceeded: n h | C59: Absence plus billed hours exceed a full day. | D59: Usually the absence hours are overstated.
B62: 7. THE SEVERITY SCALE (hidden "Sev." columns, used by the colours)
B63: Sev. | C63: Meaning | D63: Colour it produces
B64: 0 | C64: On target. Nothing to do. | D64: Green
B65: 1 | C65: Over target. Worth a look, but no billing was lost. | D65: Blue
B66: 2 | C66: Under target. Billing was lost. | D66: Light red
B67: 3 | C67: A whole day has no entry in BTabs. Worst case. | D67: Dark red
B70: 8. DASHBOARD COLUMN DICTIONARY - where each number comes from
B71: COLUMN | C71: Where it comes from | D71: In plain English
B72: LANDMAN | C72: BPOworkers, column B | D72: The roster, in the order you typed it. Add a name there and a row appears here.
B73: TEAM LEAD | C73: BPOworkers, matched by email | D73: Whoever the landman reports to. Blank in the roster means BPO Management.
B74: Mon - Fri | C74: Sum of ( Time Worked × 8 ) + time off hours for that person on that date | D74: The hours that day is worth. An EMPTY cell means no entry existed at all - that is why it turns dark red.
B75: TOTAL week | C75: Sum of the five day cells | D75: Hours the week is worth. The little bar behind the number is just a visual scale.
B76: TARGET week | C76: Config: target per day × 5 | D76: What the week should have been. 40 by default.
B77: DIFF. vs target | C77: TOTAL week minus TARGET week | D77: Negative means billing was lost. Positive means something was over-counted.
B78: Days with entries | C78: How many of the five day cells contain a number | D78: Below 5 means at least one day was never logged in BTabs.
B79: Days on target | C79: Days whose severity is 0 | D79: How many days landed on target, respecting the tolerance in Config.
B80: Days with alert | C80: Days whose severity is above 0 | D80: How many days need attention. This is the number that feeds the Historical tab.
B81: WEEK STATUS | C81: Decided from the three columns above | D81: The one-line verdict. Section 4 above lists every possible message.
B82: WHY | C82: Built from the five day cells | D82: Names the exact days that are off and by how much, so you do not have to hunt.
B85: 9. ALERTS AND TIMEOFF COLUMN DICTIONARY
B86: COLUMN | C86: Tab | D86: In plain English
B87: BTabs entries | C87: Alerts | D87: How many rows that person logged that day. Zero is the dark-red case.
B88: Billed hours | C88: Alerts | D88: Time Worked × 8. Actual billable work.
B89: Time off hours | C89: Alerts | D89: Declared absence hours read from the detail text.
B90: TOTAL for the day | C90: Alerts / TimeOff | D90: Billed hours plus time off hours. This is what gets compared to the target.
B91: WHAT TO DO | C91: Alerts | D91: The concrete action, written out. Work the list top to bottom.
B92: Hours declared | C92: TimeOff | D92: The first number the system found in the Work Performed Detail.
B93: Billed units | C93: TimeOff | D93: The raw Time Worked value of the absence row, normally 0.000.
B94: BTabs status | C94: TimeOff | D94: Approved / Unapproved / Rejected, straight from the export.
B95: Detail written in BTabs | C95: TimeOff | D95: The exact text the landman typed, so you can judge it yourself.
B98: 10. GLOSSARY
B99: TERM | C99: Meaning
B100: BTabs | C100: The billing system the hours are logged in. Everything here starts as a BTabs export.
B101: Landman | C101: The person doing the billable work. One row per landman on the Dashboard.
B102: Time Worked | C102: BTabs field measured in days: 1.0 = 8 hours, 0.125 = 1 hour.
B103: Billing unit | C103: Another name for the Time Worked value. 1 unit = 1 full day = 8 hours.
B104: Work Type | C104: What the hours were spent on. Three of them count as absence: Time Off, BPO Vacation, Holiday.
B105: Time Off / BPO Vacation / Holiday | C105: Absence rows. Time Worked is 0 and the hours live in the detail text instead.
B106: Approved / Unapproved | C106: Whether the Team Lead has signed the entry off in BTabs. Both still count here.
B107: Rejected | C107: The Team Lead sent the entry back. It still adds up here, so DataHealth flags it separately.
B108: Target | C108: Hours a day must add up to. Set in Config, 8 by default.
B109: Tolerance | C109: How far from the target still counts as fine. Set in Config, 0 by default.
B110: Severity | C110: Internal 0-3 score that drives all the colours. See section 7.
B111: Roster | C111: The BPOworkers tab. The single source of truth for who belongs to BPO.

Sheet Historical
B2: ALERT HISTORY BY WEEK
B3: Each number = how many days that person had an alert that week. The last column calculates itself.
B5: Landman | C5: Total on record (historical) | D5: Sum of weeks | E5: RISK | F5: 02/02 - 02/06 | G5: 02/09 - 02/13 | H5: 02/16 - 02/20 | I5: 02/23 - 02/27 | J5: 03/02 - 03/06 | K5: 03/09 - 03/13 | L5: 03/16 - 03/20 | M5: 03/23 - 03/27 | N5: 04/06 - 04/10 | O5: 04/13 - 04/17 | P5: 04/20 - 04/24 | Q5: 04/27 - 05/01 | R5: 05/04 - 05/08 | S5: 05/11 - 05/15 | T5: 05/18 - 05/22 | U5: 05/25 - 05/29 | V5: 06/01 - 06/05 | W5: 06/08 - 06/12 | X5: 06/15 - 06/19 | Y5: 06/22 - 06/26 | Z5: 06/29 - 07/03 | AA5: 07/06 - 07/10 | AB5: 07/13 - 07/17 | AC5: 07/20 - 07/24 | AD5: 07/27 - 07/31 | AE5: 08/03 - 08/07 | AF5: 08/10 - 08/14 | AG5: 08/17 - 08/21 | AH5: 08/24 - 08/28 | AI5: 08/31 - 09/04 | AJ5: 09/07 - 09/11 | AK5: CURRENT WEEK (auto)
B6: A Camargo | C6: 2 | D6: =IF($B6="","",SUM(F6:AK6)) -> 1 | E6: =IF($B6="","",IF($D6>=15,"🔴 HIGH",IF($D6>=6,"🟠 MEDIUM","🟢 LOW"))) -> 🟢 LOW | AI6: 1 | AK6: =IF($B6="","",IFERROR(INDEX(Dashboard!$O$10:$O$69,MATCH($B6,Dashboard!$C$10:$C$69,0)),"")) -> 0
B7: A Criollo | C7: 1 | D7: =IF($B7="","",SUM(F7:AK7)) -> 1 | E7: =IF($B7="","",IF($D7>=15,"🔴 HIGH",IF($D7>=6,"🟠 MEDIUM","🟢 LOW"))) -> 🟢 LOW | L7: 1 | AK7: =IF($B7="","",IFERROR(INDEX(Dashboard!$O$10:$O$69,MATCH($B7,Dashboard!$C$10:$C$69,0)),""))
B8: A Lopez | C8: 8 | D8: =IF($B8="","",SUM(F8:AK8)) -> 7 | E8: =IF($B8="","",IF($D8>=15,"🔴 HIGH",IF($D8>=6,"🟠 MEDIUM","🟢 LOW"))) -> 🟠 MEDIUM | F8: 2 | J8: 1 | S8: 1 | AB8: 1 | AH8: 2 | AK8: =IF($B8="","",IFERROR(INDEX(Dashboard!$O$10:$O$69,MATCH($B8,Dashboard!$C$10:$C$69,0)),"")) -> 0
B9: A Lorenzo | C9: 17 | D9: =IF($B9="","",SUM(F9:AK9)) -> 15 | E9: =IF($B9="","",IF($D9>=15,"🔴 HIGH",IF($D9>=6,"🟠 MEDIUM","🟢 LOW"))) -> 🔴 HIGH | K9: 1 | L9: 1 | N9: 1 | O9: 2 | S9: 1 | W9: 1 | Y9: 1 | AA9: 1 | AB9: 1 | AE9: 1 | AH9: 1 | AI9: 2 | AJ9: 1 | AK9: =IF($B9="","",IFERROR(INDEX(Dashboard!$O$10:$O$69,MATCH($B9,Dashboard!$C$10:$C$69,0)),"")) -> 0
B10: C Castellanos | C10: 18 | D10: =IF($B10="","",SUM(F10:AK10)) -> 18 | E10: =IF($B10="","",IF($D10>=15,"🔴 HIGH",IF($D10>=6,"🟠 MEDIUM","🟢 LOW"))) -> 🔴 HIGH | G10: 3 | J10: 7 | L10: 1 | P10: 1 | Q10: 1 | V10: 2 | AD10: 1 | AH10: 1 | AK10: =IF($B10="","",IFERROR(INDEX(Dashboard!$O$10:$O$69,MATCH($B10,Dashboard!$C$10:$C$69,0)),"")) -> 1
B11: C Lara | C11: 24 | D11: =IF($B11="","",SUM(F11:AK11)) -> 23 | E11: =IF($B11="","",IF($D11>=15,"🔴 HIGH",IF($D11>=6,"🟠 MEDIUM","🟢 LOW"))) -> 🔴 HIGH | F11: 1 | G11: 1 | H11: 2 | I11: 1 | J11: 1 | L11: 13 | S11: 1 | U11: 1 | AD11: 1 | AJ11: 1 | AK11: =IF($B11="","",IFERROR(INDEX(Dashboard!$O$10:$O$69,MATCH($B11,Dashboard!$C$10:$C$69,0)),""))
B12: C Mesa | C12: 4 | D12: =IF($B12="","",SUM(F12:AK12)) -> 3 | E12: =IF($B12="","",IF($D12>=15,"🔴 HIGH",IF($D12>=6,"🟠 MEDIUM","🟢 LOW"))) -> 🟢 LOW | G12: 1 | T12: 1 | Z12: 1 | AK12: =IF($B12="","",IFERROR(INDEX(Dashboard!$O$10:$O$69,MATCH($B12,Dashboard!$C$10:$C$69,0)),"")) -> 0
B13: D Trujillo | C13: 18 | D13: =IF($B13="","",SUM(F13:AK13)) -> 16 | E13: =IF($B13="","",IF($D13>=15,"🔴 HIGH",IF($D13>=6,"🟠 MEDIUM","🟢 LOW"))) -> 🔴 HIGH | H13: 1 | J13: 1 | N13: 1 | T13: 3 | U13: 1 | V13: 1 | W13: 1 | AA13: 1 | AD13: 1 | AH13: 2 | AI13: 2 | AJ13: 1 | AK13: =IF($B13="","",IFERROR(INDEX(Dashboard!$O$10:$O$69,MATCH($B13,Dashboard!$C$10:$C$69,0)),"")) -> 0
B14: F Montañez | C14: 5 | D14: =IF($B14="","",SUM(F14:AK14)) -> 5 | E14: =IF($B14="","",IF($D14>=15,"🔴 HIGH",IF($D14>=6,"🟠 MEDIUM","🟢 LOW"))) -> 🟢 LOW | J14: 2 | M14: 1 | S14: 1 | AK14: =IF($B14="","",IFERROR(INDEX(Dashboard!$O$10:$O$69,MATCH($B14,Dashboard!$C$10:$C$69,0)),"")) -> 1
B15: G Murillo | C15: 21 | D15: =IF($B15="","",SUM(F15:AK15)) -> 20 | E15: =IF($B15="","",IF($D15>=15,"🔴 HIGH",IF($D15>=6,"🟠 MEDIUM","🟢 LOW"))) -> 🔴 HIGH | H15: 1 | O15: 1 | P15: 1 | R15: 1 | S15: 3 | T15: 2 | V15: 3 | W15: 1 | Y15: 1 | Z15: 2 | AA15: 3 | AB15: 1 | AK15: =IF($B15="","",IFERROR(INDEX(Dashboard!$O$10:$O$69,MATCH($B15,Dashboard!$C$10:$C$69,0)),""))
B16: H Daza | C16: 10 | D16: =IF($B16="","",SUM(F16:AK16)) -> 10 | E16: =IF($B16="","",IF($D16>=15,"🔴 HIGH",IF($D16>=6,"🟠 MEDIUM","🟢 LOW"))) -> 🟠 MEDIUM | I16: 2 | Y16: 2 | AB16: 1 | AE16: 1 | AG16: 1 | AH16: 1 | AI16: 1 | AJ16: 1 | AK16: =IF($B16="","",IFERROR(INDEX(Dashboard!$O$10:$O$69,MATCH($B16,Dashboard!$C$10:$C$69,0)),"")) -> 0
B17: I De La Parra | C17: 3 | D17: =IF($B17="","",SUM(F17:AK17)) -> 2 | E17: =IF($B17="","",IF($D17>=15,"🔴 HIGH",IF($D17>=6,"🟠 MEDIUM","🟢 LOW"))) -> 🟢 LOW | G17: 1 | T17: 1 | AK17: =IF($B17="","",IFERROR(INDEX(Dashboard!$O$10:$O$69,MATCH($B17,Dashboard!$C$10:$C$69,0)),"")) -> 0
B18: I Salamanca | C18: 2 | D18: =IF($B18="","",SUM(F18:AK18)) -> 1 | E18: =IF($B18="","",IF($D18>=15,"🔴 HIGH",IF($D18>=6,"🟠 MEDIUM","🟢 LOW"))) -> 🟢 LOW | AA18: 1 | AK18: =IF($B18="","",IFERROR(INDEX(Dashboard!$O$10:$O$69,MATCH($B18,Dashboard!$C$10:$C$69,0)),"")) -> 0
B19: J Abay | C19: 10 | D19: =IF($B19="","",SUM(F19:AK19)) -> 9 | E19: =IF($B19="","",IF($D19>=15,"🔴 HIGH",IF($D19>=6,"🟠 MEDIUM","🟢 LOW"))) -> 🟠 MEDIUM | H19: 1 | I19: 2 | L19: 1 | R19: 2 | W19: 2 | AB19: 1 | AK19: =IF($B19="","",IFERROR(INDEX(Dashboard!$O$10:$O$69,MATCH($B19,Dashboard!$C$10:$C$69,0)),"")) -> 0
B20: J Bermudez | C20: 1 | D20: =IF($B20="","",SUM(F20:AK20)) -> 1 | E20: =IF($B20="","",IF($D20>=15,"🔴 HIGH",IF($D20>=6,"🟠 MEDIUM","🟢 LOW"))) -> 🟢 LOW | H20: 1 | AK20: =IF($B20="","",IFERROR(INDEX(Dashboard!$O$10:$O$69,MATCH($B20,Dashboard!$C$10:$C$69,0)),""))
B21: J Castillo | C21: 11 | D21: =IF($B21="","",SUM(F21:AK21)) -> 11 | E21: =IF($B21="","",IF($D21>=15,"🔴 HIGH",IF($D21>=6,"🟠 MEDIUM","🟢 LOW"))) -> 🟠 MEDIUM | G21: 6 | I21: 1 | Z21: 1 | AH21: 1 | AI21: 1 | AK21: =IF($B21="","",IFERROR(INDEX(Dashboard!$O$10:$O$69,MATCH($B21,Dashboard!$C$10:$C$69,0)),"")) -> 1
B22: J Gomez | C22: 6 | D22: =IF($B22="","",SUM(F22:AK22)) -> 4 | E22: =IF($B22="","",IF($D22>=15,"🔴 HIGH",IF($D22>=6,"🟠 MEDIUM","🟢 LOW"))) -> 🟢 LOW | G22: 1 | I22: 1 | L22: 1 | N22: 1 | AK22: =IF($B22="","",IFERROR(INDEX(Dashboard!$O$10:$O$69,MATCH($B22,Dashboard!$C$10:$C$69,0)),""))
B23: J Gonzalez | C23: 15 | D23: =IF($B23="","",SUM(F23:AK23)) -> 14 | E23: =IF($B23="","",IF($D23>=15,"🔴 HIGH",IF($D23>=6,"🟠 MEDIUM","🟢 LOW"))) -> 🟠 MEDIUM | G23: 2 | H23: 2 | I23: 3 | J23: 3 | L23: 1 | M23: 1 | R23: 1 | AI23: 1 | AK23: =IF($B23="","",IFERROR(INDEX(Dashboard!$O$10:$O$69,MATCH($B23,Dashboard!$C$10:$C$69,0)),"")) -> 0
B24: J Patino | C24: 2 | D24: =IF($B24="","",SUM(F24:AK24)) -> 1 | E24: =IF($B24="","",IF($D24>=15,"🔴 HIGH",IF($D24>=6,"🟠 MEDIUM","🟢 LOW"))) -> 🟢 LOW | H24: 1 | AK24: =IF($B24="","",IFERROR(INDEX(Dashboard!$O$10:$O$69,MATCH($B24,Dashboard!$C$10:$C$69,0)),""))
B25: J Reyes | C25: 10 | D25: =IF($B25="","",SUM(F25:AK25)) -> 7 | E25: =IF($B25="","",IF($D25>=15,"🔴 HIGH",IF($D25>=6,"🟠 MEDIUM","🟢 LOW"))) -> 🟠 MEDIUM | G25: 1 | I25: 2 | AD25: 2 | AE25: 1 | AI25: 1 | AK25: =IF($B25="","",IFERROR(INDEX(Dashboard!$O$10:$O$69,MATCH($B25,Dashboard!$C$10:$C$69,0)),"")) -> 0
B26: J Rincon | C26: 4 | D26: =IF($B26="","",SUM(F26:AK26)) -> 3 | E26: =IF($B26="","",IF($D26>=15,"🔴 HIGH",IF($D26>=6,"🟠 MEDIUM","🟢 LOW"))) -> 🟢 LOW | G26: 1 | V26: 1 | AJ26: 1 | AK26: =IF($B26="","",IFERROR(INDEX(Dashboard!$O$10:$O$69,MATCH($B26,Dashboard!$C$10:$C$69,0)),"")) -> 0
B27: J S Bermudez | C27: 15 | D27: =IF($B27="","",SUM(F27:AK27)) -> 14 | E27: =IF($B27="","",IF($D27>=15,"🔴 HIGH",IF($D27>=6,"🟠 MEDIUM","🟢 LOW"))) -> 🟠 MEDIUM | G27: 2 | J27: 2 | O27: 1 | W27: 1 | AA27: 3 | AB27: 1 | AD27: 2 | AE27: 1 | AI27: 1 | AK27: =IF($B27="","",IFERROR(INDEX(Dashboard!$O$10:$O$69,MATCH($B27,Dashboard!$C$10:$C$69,0)),"")) -> 0
B28: J Valbuena | C28: 3 | D28: =IF($B28="","",SUM(F28:AK28)) -> 3 | E28: =IF($B28="","",IF($D28>=15,"🔴 HIGH",IF($D28>=6,"🟠 MEDIUM","🟢 LOW"))) -> 🟢 LOW | T28: 2 | AB28: 1 | AK28: =IF($B28="","",IFERROR(INDEX(Dashboard!$O$10:$O$69,MATCH($B28,Dashboard!$C$10:$C$69,0)),"")) -> 0
B29: L Alfonso | C29: 5 | D29: =IF($B29="","",SUM(F29:AK29)) -> 4 | E29: =IF($B29="","",IF($D29>=15,"🔴 HIGH",IF($D29>=6,"🟠 MEDIUM","🟢 LOW"))) -> 🟢 LOW | H29: 1 | P29: 1 | AE29: 1 | AF29: 1 | AK29: =IF($B29="","",IFERROR(INDEX(Dashboard!$O$10:$O$69,MATCH($B29,Dashboard!$C$10:$C$69,0)),"")) -> 0
B30: L Diaz | C30: 27 | D30: =IF($B30="","",SUM(F30:AK30)) -> 26 | E30: =IF($B30="","",IF($D30>=15,"🔴 HIGH",IF($D30>=6,"🟠 MEDIUM","🟢 LOW"))) -> 🔴 HIGH | G30: 1 | H30: 2 | J30: 2 | K30: 1 | L30: 4 | O30: 1 | P30: 1 | Q30: 1 | R30: 3 | S30: 3 | T30: 2 | U30: 1 | V30: 3 | W30: 1 | AK30: =IF($B30="","",IFERROR(INDEX(Dashboard!$O$10:$O$69,MATCH($B30,Dashboard!$C$10:$C$69,0)),""))
B31: L Escobar | C31: 9 | D31: =IF($B31="","",SUM(F31:AK31)) -> 8 | E31: =IF($B31="","",IF($D31>=15,"🔴 HIGH",IF($D31>=6,"🟠 MEDIUM","🟢 LOW"))) -> 🟠 MEDIUM | G31: 3 | W31: 2 | AB31: 2 | AJ31: 1 | AK31: =IF($B31="","",IFERROR(INDEX(Dashboard!$O$10:$O$69,MATCH($B31,Dashboard!$C$10:$C$69,0)),"")) -> 0
B32: L Silva | C32: 14 | D32: =IF($B32="","",SUM(F32:AK32)) -> 13 | E32: =IF($B32="","",IF($D32>=15,"🔴 HIGH",IF($D32>=6,"🟠 MEDIUM","🟢 LOW"))) -> 🟠 MEDIUM | H32: 1 | J32: 3 | O32: 1 | P32: 1 | T32: 1 | U32: 3 | AA32: 1 | AD32: 1 | AJ32: 1 | AK32: =IF($B32="","",IFERROR(INDEX(Dashboard!$O$10:$O$69,MATCH($B32,Dashboard!$C$10:$C$69,0)),"")) -> 0
B33: L Villamil | C33: 23 | D33: =IF($B33="","",SUM(F33:AK33)) -> 22 | E33: =IF($B33="","",IF($D33>=15,"🔴 HIGH",IF($D33>=6,"🟠 MEDIUM","🟢 LOW"))) -> 🔴 HIGH | H33: 3 | I33: 1 | J33: 1 | O33: 2 | P33: 3 | V33: 2 | X33: 1 | Y33: 2 | Z33: 1 | AA33: 2 | AB33: 3 | AC33: 1 | AK33: =IF($B33="","",IFERROR(INDEX(Dashboard!$O$10:$O$69,MATCH($B33,Dashboard!$C$10:$C$69,0)),""))
B34: L Zambrano | C34: 1 | D34: =IF($B34="","",SUM(F34:AK34)) -> 1 | E34: =IF($B34="","",IF($D34>=15,"🔴 HIGH",IF($D34>=6,"🟠 MEDIUM","🟢 LOW"))) -> 🟢 LOW | J34: 1 | AK34: =IF($B34="","",IFERROR(INDEX(Dashboard!$O$10:$O$69,MATCH($B34,Dashboard!$C$10:$C$69,0)),""))
B35: M Fernandez | C35: 9 | D35: =IF($B35="","",SUM(F35:AK35)) -> 8 | E35: =IF($B35="","",IF($D35>=15,"🔴 HIGH",IF($D35>=6,"🟠 MEDIUM","🟢 LOW"))) -> 🟠 MEDIUM | F35: 1 | I35: 1 | J35: 2 | K35: 1 | L35: 1 | AA35: 1 | AC35: 1 | AK35: =IF($B35="","",IFERROR(INDEX(Dashboard!$O$10:$O$69,MATCH($B35,Dashboard!$C$10:$C$69,0)),"")) -> 0
B36: M Grazziani | C36: 27 | D36: =IF($B36="","",SUM(F36:AK36)) -> 23 | E36: =IF($B36="","",IF($D36>=15,"🔴 HIGH",IF($D36>=6,"🟠 MEDIUM","🟢 LOW"))) -> 🔴 HIGH | G36: 4 | I36: 1 | J36: 5 | M36: 1 | P36: 1 | S36: 1 | T36: 1 | V36: 1 | Y36: 1 | Z36: 2 | AB36: 1 | AE36: 2 | AF36: 1 | AJ36: 1 | AK36: =IF($B36="","",IFERROR(INDEX(Dashboard!$O$10:$O$69,MATCH($B36,Dashboard!$C$10:$C$69,0)),"")) -> 0
B37: M Leon | C37: 9 | D37: =IF($B37="","",SUM(F37:AK37)) -> 8 | E37: =IF($B37="","",IF($D37>=15,"🔴 HIGH",IF($D37>=6,"🟠 MEDIUM","🟢 LOW"))) -> 🟠 MEDIUM | G37: 3 | H37: 3 | I37: 1 | S37: 1 | AK37: =IF($B37="","",IFERROR(INDEX(Dashboard!$O$10:$O$69,MATCH($B37,Dashboard!$C$10:$C$69,0)),"")) -> 0
B38: M Lopez | C38: 7 | D38: =IF($B38="","",SUM(F38:AK38)) -> 7 | E38: =IF($B38="","",IF($D38>=15,"🔴 HIGH",IF($D38>=6,"🟠 MEDIUM","🟢 LOW"))) -> 🟠 MEDIUM | I38: 2 | L38: 1 | AA38: 1 | AB38: 1 | AD38: 1 | AF38: 1 | AK38: =IF($B38="","",IFERROR(INDEX(Dashboard!$O$10:$O$69,MATCH($B38,Dashboard!$C$10:$C$69,0)),"")) -> 0
B39: M Verdooren | C39: 2 | D39: =IF($B39="","",SUM(F39:AK39)) -> 1 | E39: =IF($B39="","",IF($D39>=15,"🔴 HIGH",IF($D39>=6,"🟠 MEDIUM","🟢 LOW"))) -> 🟢 LOW | AD39: 1 | AK39: =IF($B39="","",IFERROR(INDEX(Dashboard!$O$10:$O$69,MATCH($B39,Dashboard!$C$10:$C$69,0)),"")) -> 0
B40: R Camelo | C40: 6 | D40: =IF($B40="","",SUM(F40:AK40)) -> 5 | E40: =IF($B40="","",IF($D40>=15,"🔴 HIGH",IF($D40>=6,"🟠 MEDIUM","🟢 LOW"))) -> 🟢 LOW | G40: 1 | H40: 1 | L40: 1 | P40: 1 | W40: 1 | AK40: =IF($B40="","",IFERROR(INDEX(Dashboard!$O$10:$O$69,MATCH($B40,Dashboard!$C$10:$C$69,0)),""))
B41: R Sanchez | C41: 6 | D41: =IF($B41="","",SUM(F41:AK41)) -> 6 | E41: =IF($B41="","",IF($D41>=15,"🔴 HIGH",IF($D41>=6,"🟠 MEDIUM","🟢 LOW"))) -> 🟠 MEDIUM | G41: 3 | P41: 1 | Z41: 1 | AB41: 1 | AK41: =IF($B41="","",IFERROR(INDEX(Dashboard!$O$10:$O$69,MATCH($B41,Dashboard!$C$10:$C$69,0)),"")) -> 0
B42: S Romero | C42: 1 | D42: =IF($B42="","",SUM(F42:AK42)) -> 0 | E42: =IF($B42="","",IF($D42>=15,"🔴 HIGH",IF($D42>=6,"🟠 MEDIUM","🟢 LOW"))) -> 🟢 LOW | AK42: =IF($B42="","",IFERROR(INDEX(Dashboard!$O$10:$O$69,MATCH($B42,Dashboard!$C$10:$C$69,0)),"")) -> 0
B43: Stephen Vargas | D43: =IF($B43="","",SUM(F43:AK43)) -> 0 | E43: =IF($B43="","",IF($D43>=15,"🔴 HIGH",IF($D43>=6,"🟠 MEDIUM","🟢 LOW"))) -> 🟢 LOW | AK43: =IF($B43="","",IFERROR(INDEX(Dashboard!$O$10:$O$69,MATCH($B43,Dashboard!$C$10:$C$69,0)),""))
B44: A Guerra | C44: 5 | D44: =IF($B44="","",SUM(F44:AK44)) -> 4 | E44: =IF($B44="","",IF($D44>=15,"🔴 HIGH",IF($D44>=6,"🟠 MEDIUM","🟢 LOW"))) -> 🟢 LOW | H44: 1 | J44: 1 | L44: 2 | AK44: =IF($B44="","",IFERROR(INDEX(Dashboard!$O$10:$O$69,MATCH($B44,Dashboard!$C$10:$C$69,0)),"")) -> 0
B45: D Chinchilla | C45: 5 | D45: =IF($B45="","",SUM(F45:AK45)) -> 4 | E45: =IF($B45="","",IF($D45>=15,"🔴 HIGH",IF($D45>=6,"🟠 MEDIUM","🟢 LOW"))) -> 🟢 LOW | H45: 1 | J45: 1 | K45: 1 | X45: 1 | AK45: =IF($B45="","",IFERROR(INDEX(Dashboard!$O$10:$O$69,MATCH($B45,Dashboard!$C$10:$C$69,0)),"")) -> 0
B46: G Pereira | C46: 9 | D46: =IF($B46="","",SUM(F46:AK46)) -> 7 | E46: =IF($B46="","",IF($D46>=15,"🔴 HIGH",IF($D46>=6,"🟠 MEDIUM","🟢 LOW"))) -> 🟠 MEDIUM | H46: 2 | M46: 1 | N46: 1 | AA46: 1 | AB46: 1 | AD46: 1 | AK46: =IF($B46="","",IFERROR(INDEX(Dashboard!$O$10:$O$69,MATCH($B46,Dashboard!$C$10:$C$69,0)),"")) -> 0
B47: M Cañón | C47: 3 | D47: =IF($B47="","",SUM(F47:AK47)) -> 2 | E47: =IF($B47="","",IF($D47>=15,"🔴 HIGH",IF($D47>=6,"🟠 MEDIUM","🟢 LOW"))) -> 🟢 LOW | H47: 2 | AK47: =IF($B47="","",IFERROR(INDEX(Dashboard!$O$10:$O$69,MATCH($B47,Dashboard!$C$10:$C$69,0)),""))
B48: N Lozano | C48: 12 | D48: =IF($B48="","",SUM(F48:AK48)) -> 11 | E48: =IF($B48="","",IF($D48>=15,"🔴 HIGH",IF($D48>=6,"🟠 MEDIUM","🟢 LOW"))) -> 🟠 MEDIUM | I48: 3 | U48: 1 | V48: 2 | W48: 1 | AA48: 1 | AC48: 2 | AD48: 1 | AK48: =IF($B48="","",IFERROR(INDEX(Dashboard!$O$10:$O$69,MATCH($B48,Dashboard!$C$10:$C$69,0)),"")) -> 0
B49: D Castro | C49: 3 | D49: =IF($B49="","",SUM(F49:AK49)) -> 3 | E49: =IF($B49="","",IF($D49>=15,"🔴 HIGH",IF($D49>=6,"🟠 MEDIUM","🟢 LOW"))) -> 🟢 LOW | I49: 1 | J49: 2 | AK49: =IF($B49="","",IFERROR(INDEX(Dashboard!$O$10:$O$69,MATCH($B49,Dashboard!$C$10:$C$69,0)),""))
B50: J Macias | C50: 5 | D50: =IF($B50="","",SUM(F50:AK50)) -> 4 | E50: =IF($B50="","",IF($D50>=15,"🔴 HIGH",IF($D50>=6,"🟠 MEDIUM","🟢 LOW"))) -> 🟢 LOW | I50: 1 | K50: 1 | AA50: 1 | AB50: 1 | AK50: =IF($B50="","",IFERROR(INDEX(Dashboard!$O$10:$O$69,MATCH($B50,Dashboard!$C$10:$C$69,0)),"")) -> 0
B51: J Ramos | C51: 6 | D51: =IF($B51="","",SUM(F51:AK51)) -> 5 | E51: =IF($B51="","",IF($D51>=15,"🔴 HIGH",IF($D51>=6,"🟠 MEDIUM","🟢 LOW"))) -> 🟢 LOW | J51: 2 | K51: 2 | Q51: 1 | AK51: =IF($B51="","",IFERROR(INDEX(Dashboard!$O$10:$O$69,MATCH($B51,Dashboard!$C$10:$C$69,0)),"")) -> 0
B52: San Vargas | C52: 1 | D52: =IF($B52="","",SUM(F52:AK52)) -> 1 | E52: =IF($B52="","",IF($D52>=15,"🔴 HIGH",IF($D52>=6,"🟠 MEDIUM","🟢 LOW"))) -> 🟢 LOW | J52: 1 | AK52: =IF($B52="","",IFERROR(INDEX(Dashboard!$O$10:$O$69,MATCH($B52,Dashboard!$C$10:$C$69,0)),""))
B53: N Espitia | C53: 7 | D53: =IF($B53="","",SUM(F53:AK53)) -> 8 | E53: =IF($B53="","",IF($D53>=15,"🔴 HIGH",IF($D53>=6,"🟠 MEDIUM","🟢 LOW"))) -> 🟠 MEDIUM | L53: 1 | Q53: 1 | T53: 1 | V53: 1 | AD53: 1 | AH53: 1 | AK53: =IF($B53="","",IFERROR(INDEX(Dashboard!$O$10:$O$69,MATCH($B53,Dashboard!$C$10:$C$69,0)),"")) -> 2
B54: G Tabima | C54: 2 | D54: =IF($B54="","",SUM(F54:AK54)) -> 1 | E54: =IF($B54="","",IF($D54>=15,"🔴 HIGH",IF($D54>=6,"🟠 MEDIUM","🟢 LOW"))) -> 🟢 LOW | L54: 1 | AK54: =IF($B54="","",IFERROR(INDEX(Dashboard!$O$10:$O$69,MATCH($B54,Dashboard!$C$10:$C$69,0)),""))
B55: M Marin | C55: 1 | D55: =IF($B55="","",SUM(F55:AK55)) -> 1 | E55: =IF($B55="","",IF($D55>=15,"🔴 HIGH",IF($D55>=6,"🟠 MEDIUM","🟢 LOW"))) -> 🟢 LOW | L55: 1 | AK55: =IF($B55="","",IFERROR(INDEX(Dashboard!$O$10:$O$69,MATCH($B55,Dashboard!$C$10:$C$69,0)),""))
B56: G Cardozo | C56: 1 | D56: =IF($B56="","",SUM(F56:AK56)) -> 0 | E56: =IF($B56="","",IF($D56>=15,"🔴 HIGH",IF($D56>=6,"🟠 MEDIUM","🟢 LOW"))) -> 🟢 LOW | AK56: =IF($B56="","",IFERROR(INDEX(Dashboard!$O$10:$O$69,MATCH($B56,Dashboard!$C$10:$C$69,0)),""))
B57: K Martínez | C57: 1 | D57: =IF($B57="","",SUM(F57:AK57)) -> 1 | E57: =IF($B57="","",IF($D57>=15,"🔴 HIGH",IF($D57>=6,"🟠 MEDIUM","🟢 LOW"))) -> 🟢 LOW | AK57: =IF($B57="","",IFERROR(INDEX(Dashboard!$O$10:$O$69,MATCH($B57,Dashboard!$C$10:$C$69,0)),"")) -> 1
B58: O Moreno | C58: 4 | D58: =IF($B58="","",SUM(F58:AK58)) -> 3 | E58: =IF($B58="","",IF($D58>=15,"🔴 HIGH",IF($D58>=6,"🟠 MEDIUM","🟢 LOW"))) -> 🟢 LOW | AB58: 1 | AG58: 1 | AI58: 1 | AK58: =IF($B58="","",IFERROR(INDEX(Dashboard!$O$10:$O$69,MATCH($B58,Dashboard!$C$10:$C$69,0)),"")) -> 0
B59: S Calderon | C59: 4 | D59: =IF($B59="","",SUM(F59:AK59)) -> 3 | E59: =IF($B59="","",IF($D59>=15,"🔴 HIGH",IF($D59>=6,"🟠 MEDIUM","🟢 LOW"))) -> 🟢 LOW | R59: 1 | AC59: 1 | AH59: 1 | AK59: =IF($B59="","",IFERROR(INDEX(Dashboard!$O$10:$O$69,MATCH($B59,Dashboard!$C$10:$C$69,0)),"")) -> 0
B60: T Vargas | C60: 1 | D60: =IF($B60="","",SUM(F60:AK60)) -> 0 | E60: =IF($B60="","",IF($D60>=15,"🔴 HIGH",IF($D60>=6,"🟠 MEDIUM","🟢 LOW"))) -> 🟢 LOW | AK60: =IF($B60="","",IFERROR(INDEX(Dashboard!$O$10:$O$69,MATCH($B60,Dashboard!$C$10:$C$69,0)),"")) -> 0
B61: TOTAL | C61: =SUM(C6:C60) -> 426 | D61: =SUM(D6:D60) -> 379 | F61: =SUM(F6:F60) -> 4 | G61: =SUM(G6:G60) -> 34 | H61: =SUM(H6:H60) -> 26 | I61: =SUM(I6:I60) -> 23 | J61: =SUM(J6:J60) -> 38 | K61: =SUM(K6:K60) -> 7 | L61: =SUM(L6:L60) -> 31 | M61: =SUM(M6:M60) -> 4 | ... AK61: =SUM(AK6:AK60) -> 6
B63: NOTE: "Total on record" holds the historical values that already came in the original file and were left untouched (yellow cells, editable). "Sum of weeks" recalculates them. If the two numbers do not match, it is because the original file counted weeks in the Total that have no column of their own. Reconcile by hand when you get a chance.

Sheet Detail
B2: DETAIL (calculation engine)
B3: Technical sheet: one row per person per day. No need to touch it.
B4: =IF($C4="","",INT((ROW()-4)/5)+1) -> 1 | C4: =IF(INT((ROW()-4)/5)+1>Config!$C$14,"",INDEX(BPOworkers!$B$6:$B$105,INT((ROW()-4)/5)+1)) -> A Camargo | D4: =IF($C4="","",IFERROR(INDEX(BPOworkers!$E$6:$E$105,MATCH($C4,BPOworkers!$B$6:$B$105,0)),"")) -> BPO Management | E4: =IF($C4="","",Config!$C$7+MOD(ROW()-4,5)) -> 46265 | F4: =IF($C4="","",INDEX(Config!$F$7:$F$11,MOD(ROW()-4,5)+1)) -> Monday | G4: =IF($C4="","",COUNTIFS(RawBtabs!$A$2:$A$1500,$C4,RawBtabs!$C$2:$C$1500,$E4)) -> 2 | H4: =IF($C4="","",SUMIFS(RawBtabs!$T$2:$T$1500,RawBtabs!$A$2:$A$1500,$C4,RawBtabs!$C$2:$C$1500,$E4)) -> 2 | I4: =IF($C4="","",SUMIFS(RawBtabs!$U$2:$U$1500,RawBtabs!$A$2:$A$1500,$C4,RawBtabs!$C$2:$C$1500,$E4)) -> 6 | J4: =IF($C4="","",$H4+$I4) -> 8 | K4: =IF($C4="","",$J4/Config!$C$9) -> 1 | L4: =IF($C4="","",$J4-Config!$C$9) -> 0 | M4: =IF($C4="","",IF($G4=0,"⛔ NO ENTRY IN BTABS",IF(ABS($L4)<=Config!$C$10,"✅ OK ("&TEXT($J4,"0.##")&" h)",IF($L4<0,"🔻 MISSING "&TEXT(-$L4,"0.##")&" h","🔺 OVER BY "&TEXT($L4,"0.##")&" h")))) -> ✅ OK (8. h) | N4: =IF($C4="","",IF($G4=0,3,IF(ABS($L4)<=Config!$C$10,0,IF($L4<0,2,1)))) -> 0 | O4: =IF($C4="","",IF($N4>0,COUNTIFS($N$4:$N4,">0"),""))
B5: =IF($C5="","",INT((ROW()-4)/5)+1) -> 1 | C5: =IF(INT((ROW()-4)/5)+1>Config!$C$14,"",INDEX(BPOworkers!$B$6:$B$105,INT((ROW()-4)/5)+1)) -> A Camargo | D5: =IF($C5="","",IFERROR(INDEX(BPOworkers!$E$6:$E$105,MATCH($C5,BPOworkers!$B$6:$B$105,0)),"")) -> BPO Management | E5: =IF($C5="","",Config!$C$7+MOD(ROW()-4,5)) -> 46266 | F5: =IF($C5="","",INDEX(Config!$F$7:$F$11,MOD(ROW()-4,5)+1)) -> Tuesday | G5: =IF($C5="","",COUNTIFS(RawBtabs!$A$2:$A$1500,$C5,RawBtabs!$C$2:$C$1500,$E5)) -> 2 | H5: =IF($C5="","",SUMIFS(RawBtabs!$T$2:$T$1500,RawBtabs!$A$2:$A$1500,$C5,RawBtabs!$C$2:$C$1500,$E5)) -> 4 | I5: =IF($C5="","",SUMIFS(RawBtabs!$U$2:$U$1500,RawBtabs!$A$2:$A$1500,$C5,RawBtabs!$C$2:$C$1500,$E5)) -> 4 | J5: =IF($C5="","",$H5+$I5) -> 8 | K5: =IF($C5="","",$J5/Config!$C$9) -> 1 | L5: =IF($C5="","",$J5-Config!$C$9) -> 0 | M5: =IF($C5="","",IF($G5=0,"⛔ NO ENTRY IN BTABS",IF(ABS($L5)<=Config!$C$10,"✅ OK ("&TEXT($J5,"0.##")&" h)",IF($L5<0,"🔻 MISSING "&TEXT(-$L5,"0.##")&" h","🔺 OVER BY "&TEXT($L5,"0.##")&" h")))) -> ✅ OK (8. h) | N5: =IF($C5="","",IF($G5=0,3,IF(ABS($L5)<=Config!$C$10,0,IF($L5<0,2,1)))) -> 0 | O5: =IF($C5="","",IF($N5>0,COUNTIFS($N$4:$N5,">0"),""))
B6: =IF($C6="","",INT((ROW()-4)/5)+1) -> 1 | C6: =IF(INT((ROW()-4)/5)+1>Config!$C$14,"",INDEX(BPOworkers!$B$6:$B$105,INT((ROW()-4)/5)+1)) -> A Camargo | D6: =IF($C6="","",IFERROR(INDEX(BPOworkers!$E$6:$E$105,MATCH($C6,BPOworkers!$B$6:$B$105,0)),"")) -> BPO Management | E6: =IF($C6="","",Config!$C$7+MOD(ROW()-4,5)) -> 46267 | F6: =IF($C6="","",INDEX(Config!$F$7:$F$11,MOD(ROW()-4,5)+1)) -> Wednesday | G6: =IF($C6="","",COUNTIFS(RawBtabs!$A$2:$A$1500,$C6,RawBtabs!$C$2:$C$1500,$E6)) -> 2 | H6: =IF($C6="","",SUMIFS(RawBtabs!$T$2:$T$1500,RawBtabs!$A$2:$A$1500,$C6,RawBtabs!$C$2:$C$1500,$E6)) -> 8 | I6: =IF($C6="","",SUMIFS(RawBtabs!$U$2:$U$1500,RawBtabs!$A$2:$A$1500,$C6,RawBtabs!$C$2:$C$1500,$E6)) -> 0 | J6: =IF($C6="","",$H6+$I6) -> 8 | K6: =IF($C6="","",$J6/Config!$C$9) -> 1 | L6: =IF($C6="","",$J6-Config!$C$9) -> 0 | M6: =IF($C6="","",IF($G6=0,"⛔ NO ENTRY IN BTABS",IF(ABS($L6)<=Config!$C$10,"✅ OK ("&TEXT($J6,"0.##")&" h)",IF($L6<0,"🔻 MISSING "&TEXT(-$L6,"0.##")&" h","🔺 OVER BY "&TEXT($L6,"0.##")&" h")))) -> ✅ OK (8. h) | N6: =IF($C6="","",IF($G6=0,3,IF(ABS($L6)<=Config!$C$10,0,IF($L6<0,2,1)))) -> 0 | O6: =IF($C6="","",IF($N6>0,COUNTIFS($N$4:$N6,">0"),""))
B7: =IF($C7="","",INT((ROW()-4)/5)+1) -> 1 | C7: =IF(INT((ROW()-4)/5)+1>Config!$C$14,"",INDEX(BPOworkers!$B$6:$B$105,INT((ROW()-4)/5)+1)) -> A Camargo | D7: =IF($C7="","",IFERROR(INDEX(BPOworkers!$E$6:$E$105,MATCH($C7,BPOworkers!$B$6:$B$105,0)),"")) -> BPO Management | E7: =IF($C7="","",Config!$C$7+MOD(ROW()-4,5)) -> 46268 | F7: =IF($C7="","",INDEX(Config!$F$7:$F$11,MOD(ROW()-4,5)+1)) -> Thursday | G7: =IF($C7="","",COUNTIFS(RawBtabs!$A$2:$A$1500,$C7,RawBtabs!$C$2:$C$1500,$E7)) -> 3 | H7: =IF($C7="","",SUMIFS(RawBtabs!$T$2:$T$1500,RawBtabs!$A$2:$A$1500,$C7,RawBtabs!$C$2:$C$1500,$E7)) -> 8 | I7: =IF($C7="","",SUMIFS(RawBtabs!$U$2:$U$1500,RawBtabs!$A$2:$A$1500,$C7,RawBtabs!$C$2:$C$1500,$E7)) -> 0 | J7: =IF($C7="","",$H7+$I7) -> 8 | K7: =IF($C7="","",$J7/Config!$C$9) -> 1 | L7: =IF($C7="","",$J7-Config!$C$9) -> 0 | M7: =IF($C7="","",IF($G7=0,"⛔ NO ENTRY IN BTABS",IF(ABS($L7)<=Config!$C$10,"✅ OK ("&TEXT($J7,"0.##")&" h)",IF($L7<0,"🔻 MISSING "&TEXT(-$L7,"0.##")&" h","🔺 OVER BY "&TEXT($L7,"0.##")&" h")))) -> ✅ OK (8. h) | N7: =IF($C7="","",IF($G7=0,3,IF(ABS($L7)<=Config!$C$10,0,IF($L7<0,2,1)))) -> 0 | O7: =IF($C7="","",IF($N7>0,COUNTIFS($N$4:$N7,">0"),""))
B8: =IF($C8="","",INT((ROW()-4)/5)+1) -> 1 | C8: =IF(INT((ROW()-4)/5)+1>Config!$C$14,"",INDEX(BPOworkers!$B$6:$B$105,INT((ROW()-4)/5)+1)) -> A Camargo | D8: =IF($C8="","",IFERROR(INDEX(BPOworkers!$E$6:$E$105,MATCH($C8,BPOworkers!$B$6:$B$105,0)),"")) -> BPO Management | E8: =IF($C8="","",Config!$C$7+MOD(ROW()-4,5)) -> 46269 | F8: =IF($C8="","",INDEX(Config!$F$7:$F$11,MOD(ROW()-4,5)+1)) -> Friday | G8: =IF($C8="","",COUNTIFS(RawBtabs!$A$2:$A$1500,$C8,RawBtabs!$C$2:$C$1500,$E8)) -> 2 | H8: =IF($C8="","",SUMIFS(RawBtabs!$T$2:$T$1500,RawBtabs!$A$2:$A$1500,$C8,RawBtabs!$C$2:$C$1500,$E8)) -> 8 | I8: =IF($C8="","",SUMIFS(RawBtabs!$U$2:$U$1500,RawBtabs!$A$2:$A$1500,$C8,RawBtabs!$C$2:$C$1500,$E8)) -> 0 | J8: =IF($C8="","",$H8+$I8) -> 8 | K8: =IF($C8="","",$J8/Config!$C$9) -> 1 | L8: =IF($C8="","",$J8-Config!$C$9) -> 0 | M8: =IF($C8="","",IF($G8=0,"⛔ NO ENTRY IN BTABS",IF(ABS($L8)<=Config!$C$10,"✅ OK ("&TEXT($J8,"0.##")&" h)",IF($L8<0,"🔻 MISSING "&TEXT(-$L8,"0.##")&" h","🔺 OVER BY "&TEXT($L8,"0.##")&" h")))) -> ✅ OK (8. h) | N8: =IF($C8="","",IF($G8=0,3,IF(ABS($L8)<=Config!$C$10,0,IF($L8<0,2,1)))) -> 0 | O8: =IF($C8="","",IF($N8>0,COUNTIFS($N$4:$N8,">0"),""))
B9: =IF($C9="","",INT((ROW()-4)/5)+1) -> 2 | C9: =IF(INT((ROW()-4)/5)+1>Config!$C$14,"",INDEX(BPOworkers!$B$6:$B$105,INT((ROW()-4)/5)+1)) -> A Lopez | D9: =IF($C9="","",IFERROR(INDEX(BPOworkers!$E$6:$E$105,MATCH($C9,BPOworkers!$B$6:$B$105,0)),"")) -> S Romero | E9: =IF($C9="","",Config!$C$7+MOD(ROW()-4,5)) -> 46265 | F9: =IF($C9="","",INDEX(Config!$F$7:$F$11,MOD(ROW()-4,5)+1)) -> Monday | G9: =IF($C9="","",COUNTIFS(RawBtabs!$A$2:$A$1500,$C9,RawBtabs!$C$2:$C$1500,$E9)) -> 2 | H9: =IF($C9="","",SUMIFS(RawBtabs!$T$2:$T$1500,RawBtabs!$A$2:$A$1500,$C9,RawBtabs!$C$2:$C$1500,$E9)) -> 3 | I9: =IF($C9="","",SUMIFS(RawBtabs!$U$2:$U$1500,RawBtabs!$A$2:$A$1500,$C9,RawBtabs!$C$2:$C$1500,$E9)) -> 5 | J9: =IF($C9="","",$H9+$I9) -> 8 | K9: =IF($C9="","",$J9/Config!$C$9) -> 1 | L9: =IF($C9="","",$J9-Config!$C$9) -> 0 | M9: =IF($C9="","",IF($G9=0,"⛔ NO ENTRY IN BTABS",IF(ABS($L9)<=Config!$C$10,"✅ OK ("&TEXT($J9,"0.##")&" h)",IF($L9<0,"🔻 MISSING "&TEXT(-$L9,"0.##")&" h","🔺 OVER BY "&TEXT($L9,"0.##")&" h")))) -> ✅ OK (8. h) | N9: =IF($C9="","",IF($G9=0,3,IF(ABS($L9)<=Config!$C$10,0,IF($L9<0,2,1)))) -> 0 | O9: =IF($C9="","",IF($N9>0,COUNTIFS($N$4:$N9,">0"),""))
B10: =IF($C10="","",INT((ROW()-4)/5)+1) -> 2 | C10: =IF(INT((ROW()-4)/5)+1>Config!$C$14,"",INDEX(BPOworkers!$B$6:$B$105,INT((ROW()-4)/5)+1)) -> A Lopez | D10: =IF($C10="","",IFERROR(INDEX(BPOworkers!$E$6:$E$105,MATCH($C10,BPOworkers!$B$6:$B$105,0)),"")) -> S Romero | E10: =IF($C10="","",Config!$C$7+MOD(ROW()-4,5)) -> 46266 | F10: =IF($C10="","",INDEX(Config!$F$7:$F$11,MOD(ROW()-4,5)+1)) -> Tuesday | G10: =IF($C10="","",COUNTIFS(RawBtabs!$A$2:$A$1500,$C10,RawBtabs!$C$2:$C$1500,$E10)) -> 4 | H10: =IF($C10="","",SUMIFS(RawBtabs!$T$2:$T$1500,RawBtabs!$A$2:$A$1500,$C10,RawBtabs!$C$2:$C$1500,$E10)) -> 7 | I10: =IF($C10="","",SUMIFS(RawBtabs!$U$2:$U$1500,RawBtabs!$A$2:$A$1500,$C10,RawBtabs!$C$2:$C$1500,$E10)) -> 1 | J10: =IF($C10="","",$H10+$I10) -> 8 | K10: =IF($C10="","",$J10/Config!$C$9) -> 1 | L10: =IF($C10="","",$J10-Config!$C$9) -> 0 | M10: =IF($C10="","",IF($G10=0,"⛔ NO ENTRY IN BTABS",IF(ABS($L10)<=Config!$C$10,"✅ OK ("&TEXT($J10,"0.##")&" h)",IF($L10<0,"🔻 MISSING "&TEXT(-$L10,"0.##")&" h","🔺 OVER BY "&TEXT($L10,"0.##")&" h")))) -> ✅ OK (8. h) | N10: =IF($C10="","",IF($G10=0,3,IF(ABS($L10)<=Config!$C$10,0,IF($L10<0,2,1)))) -> 0 | O10: =IF($C10="","",IF($N10>0,COUNTIFS($N$4:$N10,">0"),""))
B11: =IF($C11="","",INT((ROW()-4)/5)+1) -> 2 | C11: =IF(INT((ROW()-4)/5)+1>Config!$C$14,"",INDEX(BPOworkers!$B$6:$B$105,INT((ROW()-4)/5)+1)) -> A Lopez | D11: =IF($C11="","",IFERROR(INDEX(BPOworkers!$E$6:$E$105,MATCH($C11,BPOworkers!$B$6:$B$105,0)),"")) -> S Romero | E11: =IF($C11="","",Config!$C$7+MOD(ROW()-4,5)) -> 46267 | F11: =IF($C11="","",INDEX(Config!$F$7:$F$11,MOD(ROW()-4,5)+1)) -> Wednesday | G11: =IF($C11="","",COUNTIFS(RawBtabs!$A$2:$A$1500,$C11,RawBtabs!$C$2:$C$1500,$E11)) -> 2 | H11: =IF($C11="","",SUMIFS(RawBtabs!$T$2:$T$1500,RawBtabs!$A$2:$A$1500,$C11,RawBtabs!$C$2:$C$1500,$E11)) -> 5 | I11: =IF($C11="","",SUMIFS(RawBtabs!$U$2:$U$1500,RawBtabs!$A$2:$A$1500,$C11,RawBtabs!$C$2:$C$1500,$E11)) -> 3 | J11: =IF($C11="","",$H11+$I11) -> 8 | K11: =IF($C11="","",$J11/Config!$C$9) -> 1 | L11: =IF($C11="","",$J11-Config!$C$9) -> 0 | M11: =IF($C11="","",IF($G11=0,"⛔ NO ENTRY IN BTABS",IF(ABS($L11)<=Config!$C$10,"✅ OK ("&TEXT($J11,"0.##")&" h)",IF($L11<0,"🔻 MISSING "&TEXT(-$L11,"0.##")&" h","🔺 OVER BY "&TEXT($L11,"0.##")&" h")))) -> ✅ OK (8. h) | N11: =IF($C11="","",IF($G11=0,3,IF(ABS($L11)<=Config!$C$10,0,IF($L11<0,2,1)))) -> 0 | O11: =IF($C11="","",IF($N11>0,COUNTIFS($N$4:$N11,">0"),""))
B12: =IF($C12="","",INT((ROW()-4)/5)+1) -> 2 | C12: =IF(INT((ROW()-4)/5)+1>Config!$C$14,"",INDEX(BPOworkers!$B$6:$B$105,INT((ROW()-4)/5)+1)) -> A Lopez | D12: =IF($C12="","",IFERROR(INDEX(BPOworkers!$E$6:$E$105,MATCH($C12,BPOworkers!$B$6:$B$105,0)),"")) -> S Romero | E12: =IF($C12="","",Config!$C$7+MOD(ROW()-4,5)) -> 46268 | F12: =IF($C12="","",INDEX(Config!$F$7:$F$11,MOD(ROW()-4,5)+1)) -> Thursday | G12: =IF($C12="","",COUNTIFS(RawBtabs!$A$2:$A$1500,$C12,RawBtabs!$C$2:$C$1500,$E12)) -> 1 | H12: =IF($C12="","",SUMIFS(RawBtabs!$T$2:$T$1500,RawBtabs!$A$2:$A$1500,$C12,RawBtabs!$C$2:$C$1500,$E12)) -> 8 | I12: =IF($C12="","",SUMIFS(RawBtabs!$U$2:$U$1500,RawBtabs!$A$2:$A$1500,$C12,RawBtabs!$C$2:$C$1500,$E12)) -> 0 | J12: =IF($C12="","",$H12+$I12) -> 8 | K12: =IF($C12="","",$J12/Config!$C$9) -> 1 | L12: =IF($C12="","",$J12-Config!$C$9) -> 0 | M12: =IF($C12="","",IF($G12=0,"⛔ NO ENTRY IN BTABS",IF(ABS($L12)<=Config!$C$10,"✅ OK ("&TEXT($J12,"0.##")&" h)",IF($L12<0,"🔻 MISSING "&TEXT(-$L12,"0.##")&" h","🔺 OVER BY "&TEXT($L12,"0.##")&" h")))) -> ✅ OK (8. h) | N12: =IF($C12="","",IF($G12=0,3,IF(ABS($L12)<=Config!$C$10,0,IF($L12<0,2,1)))) -> 0 | O12: =IF($C12="","",IF($N12>0,COUNTIFS($N$4:$N12,">0"),""))
B13: =IF($C13="","",INT((ROW()-4)/5)+1) -> 2 | C13: =IF(INT((ROW()-4)/5)+1>Config!$C$14,"",INDEX(BPOworkers!$B$6:$B$105,INT((ROW()-4)/5)+1)) -> A Lopez | D13: =IF($C13="","",IFERROR(INDEX(BPOworkers!$E$6:$E$105,MATCH($C13,BPOworkers!$B$6:$B$105,0)),"")) -> S Romero | E13: =IF($C13="","",Config!$C$7+MOD(ROW()-4,5)) -> 46269 | F13: =IF($C13="","",INDEX(Config!$F$7:$F$11,MOD(ROW()-4,5)+1)) -> Friday | G13: =IF($C13="","",COUNTIFS(RawBtabs!$A$2:$A$1500,$C13,RawBtabs!$C$2:$C$1500,$E13)) -> 2 | H13: =IF($C13="","",SUMIFS(RawBtabs!$T$2:$T$1500,RawBtabs!$A$2:$A$1500,$C13,RawBtabs!$C$2:$C$1500,$E13)) -> 6 | I13: =IF($C13="","",SUMIFS(RawBtabs!$U$2:$U$1500,RawBtabs!$A$2:$A$1500,$C13,RawBtabs!$C$2:$C$1500,$E13)) -> 2 | J13: =IF($C13="","",$H13+$I13) -> 8 | K13: =IF($C13="","",$J13/Config!$C$9) -> 1 | L13: =IF($C13="","",$J13-Config!$C$9) -> 0 | M13: =IF($C13="","",IF($G13=0,"⛔ NO ENTRY IN BTABS",IF(ABS($L13)<=Config!$C$10,"✅ OK ("&TEXT($J13,"0.##")&" h)",IF($L13<0,"🔻 MISSING "&TEXT(-$L13,"0.##")&" h","🔺 OVER BY "&TEXT($L13,"0.##")&" h")))) -> ✅ OK (8. h) | N13: =IF($C13="","",IF($G13=0,3,IF(ABS($L13)<=Config!$C$10,0,IF($L13<0,2,1)))) -> 0 | O13: =IF($C13="","",IF($N13>0,COUNTIFS($N$4:$N13,">0"),""))
B14: =IF($C14="","",INT((ROW()-4)/5)+1) -> 3 | C14: =IF(INT((ROW()-4)/5)+1>Config!$C$14,"",INDEX(BPOworkers!$B$6:$B$105,INT((ROW()-4)/5)+1)) -> A Lorenzo | D14: =IF($C14="","",IFERROR(INDEX(BPOworkers!$E$6:$E$105,MATCH($C14,BPOworkers!$B$6:$B$105,0)),"")) -> BPO Management | E14: =IF($C14="","",Config!$C$7+MOD(ROW()-4,5)) -> 46265 | F14: =IF($C14="","",INDEX(Config!$F$7:$F$11,MOD(ROW()-4,5)+1)) -> Monday | G14: =IF($C14="","",COUNTIFS(RawBtabs!$A$2:$A$1500,$C14,RawBtabs!$C$2:$C$1500,$E14)) -> 1 | H14: =IF($C14="","",SUMIFS(RawBtabs!$T$2:$T$1500,RawBtabs!$A$2:$A$1500,$C14,RawBtabs!$C$2:$C$1500,$E14)) -> 8 | I14: =IF($C14="","",SUMIFS(RawBtabs!$U$2:$U$1500,RawBtabs!$A$2:$A$1500,$C14,RawBtabs!$C$2:$C$1500,$E14)) -> 0 | J14: =IF($C14="","",$H14+$I14) -> 8 | K14: =IF($C14="","",$J14/Config!$C$9) -> 1 | L14: =IF($C14="","",$J14-Config!$C$9) -> 0 | M14: =IF($C14="","",IF($G14=0,"⛔ NO ENTRY IN BTABS",IF(ABS($L14)<=Config!$C$10,"✅ OK ("&TEXT($J14,"0.##")&" h)",IF($L14<0,"🔻 MISSING "&TEXT(-$L14,"0.##")&" h","🔺 OVER BY "&TEXT($L14,"0.##")&" h")))) -> ✅ OK (8. h) | N14: =IF($C14="","",IF($G14=0,3,IF(ABS($L14)<=Config!$C$10,0,IF($L14<0,2,1)))) -> 0 | O14: =IF($C14="","",IF($N14>0,COUNTIFS($N$4:$N14,">0"),""))
B15: =IF($C15="","",INT((ROW()-4)/5)+1) -> 3 | C15: =IF(INT((ROW()-4)/5)+1>Config!$C$14,"",INDEX(BPOworkers!$B$6:$B$105,INT((ROW()-4)/5)+1)) -> A Lorenzo | D15: =IF($C15="","",IFERROR(INDEX(BPOworkers!$E$6:$E$105,MATCH($C15,BPOworkers!$B$6:$B$105,0)),"")) -> BPO Management | E15: =IF($C15="","",Config!$C$7+MOD(ROW()-4,5)) -> 46266 | F15: =IF($C15="","",INDEX(Config!$F$7:$F$11,MOD(ROW()-4,5)+1)) -> Tuesday | G15: =IF($C15="","",COUNTIFS(RawBtabs!$A$2:$A$1500,$C15,RawBtabs!$C$2:$C$1500,$E15)) -> 1 | H15: =IF($C15="","",SUMIFS(RawBtabs!$T$2:$T$1500,RawBtabs!$A$2:$A$1500,$C15,RawBtabs!$C$2:$C$1500,$E15)) -> 8 | I15: =IF($C15="","",SUMIFS(RawBtabs!$U$2:$U$1500,RawBtabs!$A$2:$A$1500,$C15,RawBtabs!$C$2:$C$1500,$E15)) -> 0 | J15: =IF($C15="","",$H15+$I15) -> 8 | K15: =IF($C15="","",$J15/Config!$C$9) -> 1 | L15: =IF($C15="","",$J15-Config!$C$9) -> 0 | M15: =IF($C15="","",IF($G15=0,"⛔ NO ENTRY IN BTABS",IF(ABS($L15)<=Config!$C$10,"✅ OK ("&TEXT($J15,"0.##")&" h)",IF($L15<0,"🔻 MISSING "&TEXT(-$L15,"0.##")&" h","🔺 OVER BY "&TEXT($L15,"0.##")&" h")))) -> ✅ OK (8. h) | N15: =IF($C15="","",IF($G15=0,3,IF(ABS($L15)<=Config!$C$10,0,IF($L15<0,2,1)))) -> 0 | O15: =IF($C15="","",IF($N15>0,COUNTIFS($N$4:$N15,">0"),""))
... B303: =IF($C303="","",INT((ROW()-4)/5)+1) | C303: =IF(INT((ROW()-4)/5)+1>Config!$C$14,"",INDEX(BPOworkers!$B$6:$B$105,INT((ROW()-4)/5)+1)) | D303: =IF($C303="","",IFERROR(INDEX(BPOworkers!$E$6:$E$105,MATCH($C303,BPOworkers!$B$6:$B$105,0)),"")) | E303: =IF($C303="","",Config!$C$7+MOD(ROW()-4,5)) | F303: =IF($C303="","",INDEX(Config!$F$7:$F$11,MOD(ROW()-4,5)+1)) | G303: =IF($C303="","",COUNTIFS(RawBtabs!$A$2:$A$1500,$C303,RawBtabs!$C$2:$C$1500,$E303)) | H303: =IF($C303="","",SUMIFS(RawBtabs!$T$2:$T$1500,RawBtabs!$A$2:$A$1500,$C303,RawBtabs!$C$2:$C$1500,$E303)) | I303: =IF($C303="","",SUMIFS(RawBtabs!$U$2:$U$1500,RawBtabs!$A$2:$A$1500,$C303,RawBtabs!$C$2:$C$1500,$E303)) | J303: =IF($C303="","",$H303+$I303) | K303: =IF($C303="","",$J303/Config!$C$9) | L303: =IF($C303="","",$J303-Config!$C$9) | M303: =IF($C303="","",IF($G303=0,"⛔ NO ENTRY IN BTABS",IF(ABS($L303)<=Config!$C$10,"✅ OK ("&TEXT($J303,"0.##")&" h)",IF($L303<0,"🔻 MISSING "&TEXT(-$L303,"0.##")&" h","🔺 OVER BY "&TEXT($L303,"0.##")&" h")))) | N303: =IF($C303="","",IF($G303=0,3,IF(ABS($L303)<=Config!$C$10,0,IF($L303<0,2,1)))) | O303: =IF($C303="","",IF($N303>0,COUNTIFS($N$4:$N303,">0"),""))

Sheet Config
B2: SETTINGS
B3: Change ONLY the yellow cells. Everything else calculates itself.
B6: 1) EDITABLE PARAMETERS | F6: DAYS
B7: Week to report - start (MONDAY) | C7: 46265 | F7: Monday
B8: Week end (FRIDAY) - automatic | C8: =$C$7+4 -> 46269 | F8: Tuesday
B9: Target hours per day | C9: 8 | F9: Wednesday
B10: Allowed tolerance (+/- hours) | C10: 0 | F10: Thursday
B11: 1 hour = how many billing units | C11: =1/$C$9 -> 0.125 | F11: Friday
B13: 2) CALCULATED VALUES (do not edit)
B14: Active people in the roster | C14: =COUNTA(BPOworkers!$B$6:$B$105) -> 38
B15: Rows pasted into RawBtabs | C15: =COUNTA(RawBtabs!$A$2:$A$1500) -> 858
B16: Weekly target per person (hours) | C16: =$C$9*5 -> 40
B17: RawBtabs rows inside the week | C17: =SUM(RawBtabs!$W$2:$W$1500) -> 733
B18: Rows of the week that belong to BPO | C18: =SUMPRODUCT(RawBtabs!$W$2:$W$1500,RawBtabs!$S$2:$S$1500) -> 283
B20: 3) WORK TYPES THAT COUNT AS TIME OFF
B21: Time off type 1 | C21: Time Off
B22: Time off type 2 | C22: BPO Vacation
B23: Time off type 3 | C23: Holiday
B25: For these work types the system reads the FIRST NUMBER in the "Work Performed Detail" field and treats it as time off hours. Real examples from the file: "8 hours of paid vacations" -> 8 h · "4 hours not billed." -> 4 h That is why the detail must ALWAYS start with the number of hours.

Sheet BPOworkers
B2: ROSTER - BPOworkers
B3: Master BPO list. Add or remove people here and the whole report adjusts.
B5: Landman's name | C5: Landman's email | D5: Team Lead email | E5: Team Lead (name) - automatic | G5: Yellow cells = editable. Column E calculates itself.
B6: A Camargo | C6: acamargo@tractsbpo.com | E6: =IF($B6="","",IF($D6="","BPO Management",IFERROR(INDEX(BPOworkers!$B$6:$B$105,MATCH($D6,BPOworkers!$C$6:$C$105,0)),"[!] email not in roster"))) -> BPO Management
B7: A Lopez | C7: alopez@tractsbpo.com | D7: sromero@tractsbpo.com | E7: =IF($B7="","",IF($D7="","BPO Management",IFERROR(INDEX(BPOworkers!$B$6:$B$105,MATCH($D7,BPOworkers!$C$6:$C$105,0)),"[!] email not in roster"))) -> S Romero
B8: A Lorenzo | C8: alorenzo@tractsbpo.com | E8: =IF($B8="","",IF($D8="","BPO Management",IFERROR(INDEX(BPOworkers!$B$6:$B$105,MATCH($D8,BPOworkers!$C$6:$C$105,0)),"[!] email not in roster"))) -> BPO Management
B9: C Mesa | C9: cmesa@tractsbpo.com | D9: mcleon@tractsbpo.com | E9: =IF($B9="","",IF($D9="","BPO Management",IFERROR(INDEX(BPOworkers!$B$6:$B$105,MATCH($D9,BPOworkers!$C$6:$C$105,0)),"[!] email not in roster"))) -> M Leon
B10: H Daza | C10: hdaza@tractsbpo.com | E10: =IF($B10="","",IF($D10="","BPO Management",IFERROR(INDEX(BPOworkers!$B$6:$B$105,MATCH($D10,BPOworkers!$C$6:$C$105,0)),"[!] email not in roster"))) -> BPO Management
B11: I De La Parra | C11: iparra@tractsbpo.com | D11: alorenzo@tractsbpo.com | E11: =IF($B11="","",IF($D11="","BPO Management",IFERROR(INDEX(BPOworkers!$B$6:$B$105,MATCH($D11,BPOworkers!$C$6:$C$105,0)),"[!] email not in roster"))) -> A Lorenzo
B12: J Castillo | C12: jdcastillo@tractsbpo.com | D12: jsbermudez@tractsbpo.com | E12: =IF($B12="","",IF($D12="","BPO Management",IFERROR(INDEX(BPOworkers!$B$6:$B$105,MATCH($D12,BPOworkers!$C$6:$C$105,0)),"[!] email not in roster"))) -> J S Bermudez
B13: J Valbuena | C13: jdvalbuena@tractsbpo.com | D13: hdaza@tractsbpo.com | E13: =IF($B13="","",IF($D13="","BPO Management",IFERROR(INDEX(BPOworkers!$B$6:$B$105,MATCH($D13,BPOworkers!$C$6:$C$105,0)),"[!] email not in roster"))) -> H Daza
B14: J Gonzalez | C14: jpgonzalez@tractsbpo.com | D14: rsanchez@tractsbpo.com | E14: =IF($B14="","",IF($D14="","BPO Management",IFERROR(INDEX(BPOworkers!$B$6:$B$105,MATCH($D14,BPOworkers!$C$6:$C$105,0)),"[!] email not in roster"))) -> R Sanchez
B15: J Rincon | C15: jrincon@tractsbpo.com | D15: acamargo@tractsbpo.com | E15: =IF($B15="","",IF($D15="","BPO Management",IFERROR(INDEX(BPOworkers!$B$6:$B$105,MATCH($D15,BPOworkers!$C$6:$C$105,0)),"[!] email not in roster"))) -> A Camargo
B16: L Silva | C16: lsilva@tractsbpo.com | E16: =IF($B16="","",IF($D16="","BPO Management",IFERROR(INDEX(BPOworkers!$B$6:$B$105,MATCH($D16,BPOworkers!$C$6:$C$105,0)),"[!] email not in roster"))) -> BPO Management
B17: M Grazziani | C17: mcgrazziani@tractsbpo.com | D17: jsbermudez@tractsbpo.com | E17: =IF($B17="","",IF($D17="","BPO Management",IFERROR(INDEX(BPOworkers!$B$6:$B$105,MATCH($D17,BPOworkers!$C$6:$C$105,0)),"[!] email not in roster"))) -> J S Bermudez
B18: M Leon | C18: mcleon@tractsbpo.com | E18: =IF($B18="","",IF($D18="","BPO Management",IFERROR(INDEX(BPOworkers!$B$6:$B$105,MATCH($D18,BPOworkers!$C$6:$C$105,0)),"[!] email not in roster"))) -> BPO Management
B19: R Sanchez | C19: rsanchez@tractsbpo.com | E19: =IF($B19="","",IF($D19="","BPO Management",IFERROR(INDEX(BPOworkers!$B$6:$B$105,MATCH($D19,BPOworkers!$C$6:$C$105,0)),"[!] email not in roster"))) -> BPO Management
B20: S Romero | C20: sromero@tractsbpo.com | E20: =IF($B20="","",IF($D20="","BPO Management",IFERROR(INDEX(BPOworkers!$B$6:$B$105,MATCH($D20,BPOworkers!$C$6:$C$105,0)),"[!] email not in roster"))) -> BPO Management
B21: C Castellanos | C21: ccastellanos@tractsbpo.com | D21: jsbermudez@tractsbpo.com | E21: =IF($B21="","",IF($D21="","BPO Management",IFERROR(INDEX(BPOworkers!$B$6:$B$105,MATCH($D21,BPOworkers!$C$6:$C$105,0)),"[!] email not in roster"))) -> J S Bermudez
B22: D Trujillo | C22: dtrujillo@tractsbpo.com | E22: =IF($B22="","",IF($D22="","BPO Management",IFERROR(INDEX(BPOworkers!$B$6:$B$105,MATCH($D22,BPOworkers!$C$6:$C$105,0)),"[!] email not in roster"))) -> BPO Management
B23: I Salamanca | C23: isalamanca@tractsbpo.com | D23: mcleon@tractsbpo.com | E23: =IF($B23="","",IF($D23="","BPO Management",IFERROR(INDEX(BPOworkers!$B$6:$B$105,MATCH($D23,BPOworkers!$C$6:$C$105,0)),"[!] email not in roster"))) -> M Leon
B24: J Abay | C24: jeabay@tractsbpo.com | D24: sromero@tractsbpo.com | E24: =IF($B24="","",IF($D24="","BPO Management",IFERROR(INDEX(BPOworkers!$B$6:$B$105,MATCH($D24,BPOworkers!$C$6:$C$105,0)),"[!] email not in roster"))) -> S Romero
B25: J Reyes | C25: jjreyes@tractsbpo.com | D25: mcleon@tractsbpo.com | E25: =IF($B25="","",IF($D25="","BPO Management",IFERROR(INDEX(BPOworkers!$B$6:$B$105,MATCH($D25,BPOworkers!$C$6:$C$105,0)),"[!] email not in roster"))) -> M Leon
B26: J S Bermudez | C26: jsbermudez@tractsbpo.com | E26: =IF($B26="","",IF($D26="","BPO Management",IFERROR(INDEX(BPOworkers!$B$6:$B$105,MATCH($D26,BPOworkers!$C$6:$C$105,0)),"[!] email not in roster"))) -> BPO Management
B27: L Alfonso | C27: lalfonso@tractsbpo.com | D27: rsanchez@tractsbpo.com | E27: =IF($B27="","",IF($D27="","BPO Management",IFERROR(INDEX(BPOworkers!$B$6:$B$105,MATCH($D27,BPOworkers!$C$6:$C$105,0)),"[!] email not in roster"))) -> R Sanchez
B28: L Escobar | C28: lescobar@tractsbpo.com | D28: jsbermudez@tractsbpo.com | E28: =IF($B28="","",IF($D28="","BPO Management",IFERROR(INDEX(BPOworkers!$B$6:$B$105,MATCH($D28,BPOworkers!$C$6:$C$105,0)),"[!] email not in roster"))) -> J S Bermudez
B29: M Lopez | C29: mflopez@tractsbpo.com | D29: hdaza@tractsbpo.com | E29: =IF($B29="","",IF($D29="","BPO Management",IFERROR(INDEX(BPOworkers!$B$6:$B$105,MATCH($D29,BPOworkers!$C$6:$C$105,0)),"[!] email not in roster"))) -> H Daza
B30: M Verdooren | C30: miverdooren@tractsbpo.com | D30: rsanchez@tractsbpo.com | E30: =IF($B30="","",IF($D30="","BPO Management",IFERROR(INDEX(BPOworkers!$B$6:$B$105,MATCH($D30,BPOworkers!$C$6:$C$105,0)),"[!] email not in roster"))) -> R Sanchez
B31: M Fernandez | C31: mffernandez@tractsbpo.com | D31: hdaza@tractsbpo.com | E31: =IF($B31="","",IF($D31="","BPO Management",IFERROR(INDEX(BPOworkers!$B$6:$B$105,MATCH($D31,BPOworkers!$C$6:$C$105,0)),"[!] email not in roster"))) -> H Daza
B32: F Montañez | C32: fmontanez@tractsbpo.com | D32: hdaza@tractsbpo.com | E32: =IF($B32="","",IF($D32="","BPO Management",IFERROR(INDEX(BPOworkers!$B$6:$B$105,MATCH($D32,BPOworkers!$C$6:$C$105,0)),"[!] email not in roster"))) -> H Daza
B33: J Ramos | C33: jsramos@tractsbpo.com | D33: rsanchez@tractsbpo.com | E33: =IF($B33="","",IF($D33="","BPO Management",IFERROR(INDEX(BPOworkers!$B$6:$B$105,MATCH($D33,BPOworkers!$C$6:$C$105,0)),"[!] email not in roster"))) -> R Sanchez
B34: J Macias | C34: jmacias@tractsbpo.com | D34: sromero@tractsbpo.com | E34: =IF($B34="","",IF($D34="","BPO Management",IFERROR(INDEX(BPOworkers!$B$6:$B$105,MATCH($D34,BPOworkers!$C$6:$C$105,0)),"[!] email not in roster"))) -> S Romero
B35: N Espitia | C35: nespitia@tractsbpo.com | D35: acamargo@tractsbpo.com | E35: =IF($B35="","",IF($D35="","BPO Management",IFERROR(INDEX(BPOworkers!$B$6:$B$105,MATCH($D35,BPOworkers!$C$6:$C$105,0)),"[!] email not in roster"))) -> A Camargo
B36: N Lozano | C36: nlozano@tractsbpo.com | D36: jsbermudez@tractsbpo.com | E36: =IF($B36="","",IF($D36="","BPO Management",IFERROR(INDEX(BPOworkers!$B$6:$B$105,MATCH($D36,BPOworkers!$C$6:$C$105,0)),"[!] email not in roster"))) -> J S Bermudez
B37: T Vargas | C37: savargas@tractsbpo.com | D37: mcleon@tractsbpo.com | E37: =IF($B37="","",IF($D37="","BPO Management",IFERROR(INDEX(BPOworkers!$B$6:$B$105,MATCH($D37,BPOworkers!$C$6:$C$105,0)),"[!] email not in roster"))) -> M Leon
B38: K Martínez | C38: ksmartinez@tractsbpo.com | D38: acamargo@tractsbpo.com | E38: =IF($B38="","",IF($D38="","BPO Management",IFERROR(INDEX(BPOworkers!$B$6:$B$105,MATCH($D38,BPOworkers!$C$6:$C$105,0)),"[!] email not in roster"))) -> A Camargo
... B43: S Calderon | C43: scalderon@tractsbpo.com | D43: sromero@tractsbpo.com | E43: =IF($B43="","",IF($D43="","BPO Management",IFERROR(INDEX(BPOworkers!$B$6:$B$105,MATCH($D43,BPOworkers!$C$6:$C$105,0)),"[!] email not in roster"))) -> S Romero
E44: =IF($B44="","",IF($D44="","BPO Management",IFERROR(INDEX(BPOworkers!$B$6:$B$105,MATCH($D44,BPOworkers!$C$6:$C$105,0)),"[!] email not in roster")))
E45: =IF($B45="","",IF($D45="","BPO Management",IFERROR(INDEX(BPOworkers!$B$6:$B$105,MATCH($D45,BPOworkers!$C$6:$C$105,0)),"[!] email not in roster")))
E46: =IF($B46="","",IF($D46="","BPO Management",IFERROR(INDEX(BPOworkers!$B$6:$B$105,MATCH($D46,BPOworkers!$C$6:$C$105,0)),"[!] email not in roster")))
E47: =IF($B47="","",IF($D47="","BPO Management",IFERROR(INDEX(BPOworkers!$B$6:$B$105,MATCH($D47,BPOworkers!$C$6:$C$105,0)),"[!] email not in roster")))
E48: =IF($B48="","",IF($D48="","BPO Management",IFERROR(INDEX(BPOworkers!$B$6:$B$105,MATCH($D48,BPOworkers!$C$6:$C$105,0)),"[!] email not in roster")))
E49: =IF($B49="","",IF($D49="","BPO Management",IFERROR(INDEX(BPOworkers!$B$6:$B$105,MATCH($D49,BPOworkers!$C$6:$C$105,0)),"[!] email not in roster")))
E50: =IF($B50="","",IF($D50="","BPO Management",IFERROR(INDEX(BPOworkers!$B$6:$B$105,MATCH($D50,BPOworkers!$C$6:$C$105,0)),"[!] email not in roster")))
E51: =IF($B51="","",IF($D51="","BPO Management",IFERROR(INDEX(BPOworkers!$B$6:$B$105,MATCH($D51,BPOworkers!$C$6:$C$105,0)),"[!] email not in roster")))
E52: =IF($B52="","",IF($D52="","BPO Management",IFERROR(INDEX(BPOworkers!$B$6:$B$105,MATCH($D52,BPOworkers!$C$6:$C$105,0)),"[!] email not in roster")))
E53: =IF($B53="","",IF($D53="","BPO Management",IFERROR(INDEX(BPOworkers!$B$6:$B$105,MATCH($D53,BPOworkers!$C$6:$C$105,0)),"[!] email not in roster")))
E54: =IF($B54="","",IF($D54="","BPO Management",IFERROR(INDEX(BPOworkers!$B$6:$B$105,MATCH($D54,BPOworkers!$C$6:$C$105,0)),"[!] email not in roster")))
E55: =IF($B55="","",IF($D55="","BPO Management",IFERROR(INDEX(BPOworkers!$B$6:$B$105,MATCH($D55,BPOworkers!$C$6:$C$105,0)),"[!] email not in roster")))
... E105: =IF($B105="","",IF($D105="","BPO Management",IFERROR(INDEX(BPOworkers!$B$6:$B$105,MATCH($D105,BPOworkers!$C$6:$C$105,0)),"[!] email not in roster")))

Sheet RawBtabs
A1: Time | B1: Status | C1: Date | D1: Client | E1: Prospect | F1: County | G1: Legal Description | H1: Work Type | I1: Project | J1: Well Name | K1: Time Worked | L1: Miles | M1: Miles Quantity | N1: Miles Rate | O1: Miles Description | P1: Expense Total | Q1: Work Performed Detail | S1: _EsBPO | T1: _HrsBilleadas | U1: _HrsAusencia | V1: _TotalContado | W1: _EnSemana | X1: _EsAusencia | Y1: _Contador | Z1: _RankAusencia | AB1: [!] Name not in roster | AC1: _NoRosterFirst | AD1: _NoRosterCounter | AE1: _NoRosterRank | AF1: [!] Weekend entry | AG1: [!] Outside selected week | AH1: _DupKey | AI1: [!] Duplicate suspect | AJ1: [!] Not a whole hour | AK1: [!] Time off over target | AL1: [!] Time off without hours
A2: V. Toran | B2: Unapproved | C2: 46272 | D2: Time Off | E2: Time Off | F2: Abbeville, SC | H2: Time Off | K2: 0 | L2: 0 | M2: 0 | P2: 0 | Q2: 8 hours not billed (Labor Day) | S2: =IF($A2="","",COUNTIF(BPOworkers!$B$6:$B$105,$A2)) -> 0 | T2: =IF($A2="","",$K2*Config!$C$9) -> 0 | U2: =IF($A2="","",IF(COUNTIF(Config!$C$21:$C$23,$H2)>0,IFERROR(VALUE(LEFT(TRIM($Q2),FIND(" ",TRIM($Q2)&" ")-1)),0),0)) -> 8 | V2: =IF($A2="","",$T2+$U2) -> 8 | W2: =IF($A2="",0,IF(AND($C2>=Config!$C$7,$C2<=Config!$C$8),1,0)) -> 0 | X2: =IF($A2="",0,IF(COUNTIF(Config!$C$21:$C$23,$H2)>0,1,0)) -> 1 | Y2: =IF($A2="",MAX(0,Y1),MAX(0,Y1)+IF(AND($W2=1,$X2=1,$S2=1),1,0)) -> 0 | Z2: =IF($A2="","",IF(AND($W2=1,$X2=1,$S2=1),$Y2,"")) | AB2: =IF($A2="",0,IF(AND($S2=0,ISERROR(FIND(".",$A2))),1,0)) -> 0 | AC2: =IF($A2="",0,IF(AND($AB2=1,COUNTIF($A$2:$A2,$A2)=1),1,0)) -> 0 | AD2: =IF($A2="",MAX(0,AD1),MAX(0,AD1)+$AC2) -> 0 | AE2: =IF($AC2=1,$AD2,"") | AF2: =IF($A2="",0,IFERROR(IF(AND($S2=1,WEEKDAY($C2,2)>5),1,0),0)) -> 0 | AG2: =IF($A2="",0,IF(AND($S2=1,$W2=0),1,0)) -> 0 | AH2: =IF($A2="","",$A2&"|"&TEXT($C2,"yyyymmdd")&"|"&$H2&"|"&TEXT($K2,"0.000")&"|"&SUBSTITUTE(SUBSTITUTE(SUBSTITUTE(LEFT($Q2,120),"~",""),"*",""),"?","")) -> V. Toran|20260907|Time Off|0.000|8 hours not billed (Labor Day) | AI2: =IF($A2="",0,IF(AND($S2=1,$W2=1,COUNTIF($AH$2:$AH$1500,$AH2)>1),1,0)) -> 0 | AJ2: =IF($A2="",0,IF(AND($S2=1,$W2=1,ABS($K2*8-ROUND($K2*8,0))>0.0001),1,0)) -> 0 | AK2: =IF($A2="",0,IF(AND($S2=1,$W2=1,$X2=1,$U2>Config!$C$9),1,0)) -> 0 | AL2: =IF($A2="",0,IF(AND($S2=1,$W2=1,$X2=1,$U2=0),1,0)) -> 0
A3: P. Tamez | B3: Approved | C3: 46272 | D3: Time Off | E3: Time Off | F3: Abbeville, SC | H3: Time Off | K3: 0 | L3: 0 | M3: 0 | P3: 0 | Q3: 8 hours off for Labor Day. | S3: =IF($A3="","",COUNTIF(BPOworkers!$B$6:$B$105,$A3)) -> 0 | T3: =IF($A3="","",$K3*Config!$C$9) -> 0 | U3: =IF($A3="","",IF(COUNTIF(Config!$C$21:$C$23,$H3)>0,IFERROR(VALUE(LEFT(TRIM($Q3),FIND(" ",TRIM($Q3)&" ")-1)),0),0)) -> 8 | V3: =IF($A3="","",$T3+$U3) -> 8 | W3: =IF($A3="",0,IF(AND($C3>=Config!$C$7,$C3<=Config!$C$8),1,0)) -> 0 | X3: =IF($A3="",0,IF(COUNTIF(Config!$C$21:$C$23,$H3)>0,1,0)) -> 1 | Y3: =IF($A3="",MAX(0,Y2),MAX(0,Y2)+IF(AND($W3=1,$X3=1,$S3=1),1,0)) -> 0 | Z3: =IF($A3="","",IF(AND($W3=1,$X3=1,$S3=1),$Y3,"")) | AB3: =IF($A3="",0,IF(AND($S3=0,ISERROR(FIND(".",$A3))),1,0)) -> 0 | AC3: =IF($A3="",0,IF(AND($AB3=1,COUNTIF($A$2:$A3,$A3)=1),1,0)) -> 0 | AD3: =IF($A3="",MAX(0,AD2),MAX(0,AD2)+$AC3) -> 0 | AE3: =IF($AC3=1,$AD3,"") | AF3: =IF($A3="",0,IFERROR(IF(AND($S3=1,WEEKDAY($C3,2)>5),1,0),0)) -> 0 | AG3: =IF($A3="",0,IF(AND($S3=1,$W3=0),1,0)) -> 0 | AH3: =IF($A3="","",$A3&"|"&TEXT($C3,"yyyymmdd")&"|"&$H3&"|"&TEXT($K3,"0.000")&"|"&SUBSTITUTE(SUBSTITUTE(SUBSTITUTE(LEFT($Q3,120),"~",""),"*",""),"?","")) -> P. Tamez|20260907|Time Off|0.000|8 hours off for Labor Day. | AI3: =IF($A3="",0,IF(AND($S3=1,$W3=1,COUNTIF($AH$2:$AH$1500,$AH3)>1),1,0)) -> 0 | AJ3: =IF($A3="",0,IF(AND($S3=1,$W3=1,ABS($K3*8-ROUND($K3*8,0))>0.0001),1,0)) -> 0 | AK3: =IF($A3="",0,IF(AND($S3=1,$W3=1,$X3=1,$U3>Config!$C$9),1,0)) -> 0 | AL3: =IF($A3="",0,IF(AND($S3=1,$W3=1,$X3=1,$U3=0),1,0)) -> 0
A4: I. Rice | B4: Unapproved | C4: 46272 | D4: Time Off | E4: Time Off | F4: Abbeville, SC | H4: Time Off | K4: 0 | L4: 0 | M4: 0 | P4: 0 | Q4: 8 hours unbilled- Labor Day | S4: =IF($A4="","",COUNTIF(BPOworkers!$B$6:$B$105,$A4)) -> 0 | T4: =IF($A4="","",$K4*Config!$C$9) -> 0 | U4: =IF($A4="","",IF(COUNTIF(Config!$C$21:$C$23,$H4)>0,IFERROR(VALUE(LEFT(TRIM($Q4),FIND(" ",TRIM($Q4)&" ")-1)),0),0)) -> 8 | V4: =IF($A4="","",$T4+$U4) -> 8 | W4: =IF($A4="",0,IF(AND($C4>=Config!$C$7,$C4<=Config!$C$8),1,0)) -> 0 | X4: =IF($A4="",0,IF(COUNTIF(Config!$C$21:$C$23,$H4)>0,1,0)) -> 1 | Y4: =IF($A4="",MAX(0,Y3),MAX(0,Y3)+IF(AND($W4=1,$X4=1,$S4=1),1,0)) -> 0 | Z4: =IF($A4="","",IF(AND($W4=1,$X4=1,$S4=1),$Y4,"")) | AB4: =IF($A4="",0,IF(AND($S4=0,ISERROR(FIND(".",$A4))),1,0)) -> 0 | AC4: =IF($A4="",0,IF(AND($AB4=1,COUNTIF($A$2:$A4,$A4)=1),1,0)) -> 0 | AD4: =IF($A4="",MAX(0,AD3),MAX(0,AD3)+$AC4) -> 0 | AE4: =IF($AC4=1,$AD4,"") | AF4: =IF($A4="",0,IFERROR(IF(AND($S4=1,WEEKDAY($C4,2)>5),1,0),0)) -> 0 | AG4: =IF($A4="",0,IF(AND($S4=1,$W4=0),1,0)) -> 0 | AH4: =IF($A4="","",$A4&"|"&TEXT($C4,"yyyymmdd")&"|"&$H4&"|"&TEXT($K4,"0.000")&"|"&SUBSTITUTE(SUBSTITUTE(SUBSTITUTE(LEFT($Q4,120),"~",""),"*",""),"?","")) -> I. Rice|20260907|Time Off|0.000|8 hours unbilled- Labor Day | AI4: =IF($A4="",0,IF(AND($S4=1,$W4=1,COUNTIF($AH$2:$AH$1500,$AH4)>1),1,0)) -> 0 | AJ4: =IF($A4="",0,IF(AND($S4=1,$W4=1,ABS($K4*8-ROUND($K4*8,0))>0.0001),1,0)) -> 0 | AK4: =IF($A4="",0,IF(AND($S4=1,$W4=1,$X4=1,$U4>Config!$C$9),1,0)) -> 0 | AL4: =IF($A4="",0,IF(AND($S4=1,$W4=1,$X4=1,$U4=0),1,0)) -> 0
A5: K. Milcarzyk | B5: Approved | C5: 46272 | D5: TLS | E5: TLS (Non-Billable) | F5: Abbeville, SC | G5: 01-01N-01W | H5: Holiday | K5: 1 | L5: 0 | M5: 0 | P5: 0 | Q5: 8 hours PTO Holiday. | S5: =IF($A5="","",COUNTIF(BPOworkers!$B$6:$B$105,$A5)) -> 0 | T5: =IF($A5="","",$K5*Config!$C$9) -> 8 | U5: =IF($A5="","",IF(COUNTIF(Config!$C$21:$C$23,$H5)>0,IFERROR(VALUE(LEFT(TRIM($Q5),FIND(" ",TRIM($Q5)&" ")-1)),0),0)) -> 8 | V5: =IF($A5="","",$T5+$U5) -> 16 | W5: =IF($A5="",0,IF(AND($C5>=Config!$C$7,$C5<=Config!$C$8),1,0)) -> 0 | X5: =IF($A5="",0,IF(COUNTIF(Config!$C$21:$C$23,$H5)>0,1,0)) -> 1 | Y5: =IF($A5="",MAX(0,Y4),MAX(0,Y4)+IF(AND($W5=1,$X5=1,$S5=1),1,0)) -> 0 | Z5: =IF($A5="","",IF(AND($W5=1,$X5=1,$S5=1),$Y5,"")) | AB5: =IF($A5="",0,IF(AND($S5=0,ISERROR(FIND(".",$A5))),1,0)) -> 0 | AC5: =IF($A5="",0,IF(AND($AB5=1,COUNTIF($A$2:$A5,$A5)=1),1,0)) -> 0 | AD5: =IF($A5="",MAX(0,AD4),MAX(0,AD4)+$AC5) -> 0 | AE5: =IF($AC5=1,$AD5,"") | AF5: =IF($A5="",0,IFERROR(IF(AND($S5=1,WEEKDAY($C5,2)>5),1,0),0)) -> 0 | AG5: =IF($A5="",0,IF(AND($S5=1,$W5=0),1,0)) -> 0 | AH5: =IF($A5="","",$A5&"|"&TEXT($C5,"yyyymmdd")&"|"&$H5&"|"&TEXT($K5,"0.000")&"|"&SUBSTITUTE(SUBSTITUTE(SUBSTITUTE(LEFT($Q5,120),"~",""),"*",""),"?","")) -> K. Milcarzyk|20260907|Holiday|1.000|8 hours PTO Holiday. | AI5: =IF($A5="",0,IF(AND($S5=1,$W5=1,COUNTIF($AH$2:$AH$1500,$AH5)>1),1,0)) -> 0 | AJ5: =IF($A5="",0,IF(AND($S5=1,$W5=1,ABS($K5*8-ROUND($K5*8,0))>0.0001),1,0)) -> 0 | AK5: =IF($A5="",0,IF(AND($S5=1,$W5=1,$X5=1,$U5>Config!$C$9),1,0)) -> 0 | AL5: =IF($A5="",0,IF(AND($S5=1,$W5=1,$X5=1,$U5=0),1,0)) -> 0
A6: G. Bond | B6: Unapproved | C6: 46272 | D6: Crescent Energy | E6: DTO Project | F6: Glasscock, TX | H6: Title | K6: 0.5 | L6: 0 | M6: 0 | P6: 0 | Q6: Helped pull docs for Sec 28 Blk 34 | S6: =IF($A6="","",COUNTIF(BPOworkers!$B$6:$B$105,$A6)) -> 0 | T6: =IF($A6="","",$K6*Config!$C$9) -> 4 | U6: =IF($A6="","",IF(COUNTIF(Config!$C$21:$C$23,$H6)>0,IFERROR(VALUE(LEFT(TRIM($Q6),FIND(" ",TRIM($Q6)&" ")-1)),0),0)) -> 0 | V6: =IF($A6="","",$T6+$U6) -> 4 | W6: =IF($A6="",0,IF(AND($C6>=Config!$C$7,$C6<=Config!$C$8),1,0)) -> 0 | X6: =IF($A6="",0,IF(COUNTIF(Config!$C$21:$C$23,$H6)>0,1,0)) -> 0 | Y6: =IF($A6="",MAX(0,Y5),MAX(0,Y5)+IF(AND($W6=1,$X6=1,$S6=1),1,0)) -> 0 | Z6: =IF($A6="","",IF(AND($W6=1,$X6=1,$S6=1),$Y6,"")) | AB6: =IF($A6="",0,IF(AND($S6=0,ISERROR(FIND(".",$A6))),1,0)) -> 0 | AC6: =IF($A6="",0,IF(AND($AB6=1,COUNTIF($A$2:$A6,$A6)=1),1,0)) -> 0 | AD6: =IF($A6="",MAX(0,AD5),MAX(0,AD5)+$AC6) -> 0 | AE6: =IF($AC6=1,$AD6,"") | AF6: =IF($A6="",0,IFERROR(IF(AND($S6=1,WEEKDAY($C6,2)>5),1,0),0)) -> 0 | AG6: =IF($A6="",0,IF(AND($S6=1,$W6=0),1,0)) -> 0 | AH6: =IF($A6="","",$A6&"|"&TEXT($C6,"yyyymmdd")&"|"&$H6&"|"&TEXT($K6,"0.000")&"|"&SUBSTITUTE(SUBSTITUTE(SUBSTITUTE(LEFT($Q6,120),"~",""),"*",""),"?","")) -> G. Bond|20260907|Title|0.500|Helped pull docs for Sec 28 Blk 34 | AI6: =IF($A6="",0,IF(AND($S6=1,$W6=1,COUNTIF($AH$2:$AH$1500,$AH6)>1),1,0)) -> 0 | AJ6: =IF($A6="",0,IF(AND($S6=1,$W6=1,ABS($K6*8-ROUND($K6*8,0))>0.0001),1,0)) -> 0 | AK6: =IF($A6="",0,IF(AND($S6=1,$W6=1,$X6=1,$U6>Config!$C$9),1,0)) -> 0 | AL6: =IF($A6="",0,IF(AND($S6=1,$W6=1,$X6=1,$U6=0),1,0)) -> 0
A7: G. Bond | B7: Unapproved | C7: 46272 | D7: Time Off | E7: Time Off | F7: Abbeville, SC | H7: Time Off | K7: 0 | L7: 0 | M7: 0 | P7: 0 | Q7: 4 hours not billed. | S7: =IF($A7="","",COUNTIF(BPOworkers!$B$6:$B$105,$A7)) -> 0 | T7: =IF($A7="","",$K7*Config!$C$9) -> 0 | U7: =IF($A7="","",IF(COUNTIF(Config!$C$21:$C$23,$H7)>0,IFERROR(VALUE(LEFT(TRIM($Q7),FIND(" ",TRIM($Q7)&" ")-1)),0),0)) -> 4 | V7: =IF($A7="","",$T7+$U7) -> 4 | W7: =IF($A7="",0,IF(AND($C7>=Config!$C$7,$C7<=Config!$C$8),1,0)) -> 0 | X7: =IF($A7="",0,IF(COUNTIF(Config!$C$21:$C$23,$H7)>0,1,0)) -> 1 | Y7: =IF($A7="",MAX(0,Y6),MAX(0,Y6)+IF(AND($W7=1,$X7=1,$S7=1),1,0)) -> 0 | Z7: =IF($A7="","",IF(AND($W7=1,$X7=1,$S7=1),$Y7,"")) | AB7: =IF($A7="",0,IF(AND($S7=0,ISERROR(FIND(".",$A7))),1,0)) -> 0 | AC7: =IF($A7="",0,IF(AND($AB7=1,COUNTIF($A$2:$A7,$A7)=1),1,0)) -> 0 | AD7: =IF($A7="",MAX(0,AD6),MAX(0,AD6)+$AC7) -> 0 | AE7: =IF($AC7=1,$AD7,"") | AF7: =IF($A7="",0,IFERROR(IF(AND($S7=1,WEEKDAY($C7,2)>5),1,0),0)) -> 0 | AG7: =IF($A7="",0,IF(AND($S7=1,$W7=0),1,0)) -> 0 | AH7: =IF($A7="","",$A7&"|"&TEXT($C7,"yyyymmdd")&"|"&$H7&"|"&TEXT($K7,"0.000")&"|"&SUBSTITUTE(SUBSTITUTE(SUBSTITUTE(LEFT($Q7,120),"~",""),"*",""),"?","")) -> G. Bond|20260907|Time Off|0.000|4 hours not billed. | AI7: =IF($A7="",0,IF(AND($S7=1,$W7=1,COUNTIF($AH$2:$AH$1500,$AH7)>1),1,0)) -> 0 | AJ7: =IF($A7="",0,IF(AND($S7=1,$W7=1,ABS($K7*8-ROUND($K7*8,0))>0.0001),1,0)) -> 0 | AK7: =IF($A7="",0,IF(AND($S7=1,$W7=1,$X7=1,$U7>Config!$C$9),1,0)) -> 0 | AL7: =IF($A7="",0,IF(AND($S7=1,$W7=1,$X7=1,$U7=0),1,0)) -> 0
A8: L. Bailiff | B8: Unapproved | C8: 46272 | D8: Jetstream Oil and Gas Partners, LP | E8: FreeH Project | F8: Lea, NM | G8: 28-19S-34E: S2SE, SESW | H8: Review | K8: 1 | L8: 0 | M8: 0 | P8: 0 | Q8: Finished reviewing AOI for Section 28, Township 19 South, Range 34 East in Lea County, NM associated with Federal Lease NM057285. Indexed parties to the chain of title. Compared documents attached to notecards with those provided in the project folder. Added and edited notecards as needed. Updated and uploaded landman statement. | S8: =IF($A8="","",COUNTIF(BPOworkers!$B$6:$B$105,$A8)) -> 0 | T8: =IF($A8="","",$K8*Config!$C$9) -> 8 | U8: =IF($A8="","",IF(COUNTIF(Config!$C$21:$C$23,$H8)>0,IFERROR(VALUE(LEFT(TRIM($Q8),FIND(" ",TRIM($Q8)&" ")-1)),0),0)) -> 0 | V8: =IF($A8="","",$T8+$U8) -> 8 | W8: =IF($A8="",0,IF(AND($C8>=Config!$C$7,$C8<=Config!$C$8),1,0)) -> 0 | X8: =IF($A8="",0,IF(COUNTIF(Config!$C$21:$C$23,$H8)>0,1,0)) -> 0 | Y8: =IF($A8="",MAX(0,Y7),MAX(0,Y7)+IF(AND($W8=1,$X8=1,$S8=1),1,0)) -> 0 | Z8: =IF($A8="","",IF(AND($W8=1,$X8=1,$S8=1),$Y8,"")) | AB8: =IF($A8="",0,IF(AND($S8=0,ISERROR(FIND(".",$A8))),1,0)) -> 0 | AC8: =IF($A8="",0,IF(AND($AB8=1,COUNTIF($A$2:$A8,$A8)=1),1,0)) -> 0 | AD8: =IF($A8="",MAX(0,AD7),MAX(0,AD7)+$AC8) -> 0 | AE8: =IF($AC8=1,$AD8,"") | AF8: =IF($A8="",0,IFERROR(IF(AND($S8=1,WEEKDAY($C8,2)>5),1,0),0)) -> 0 | AG8: =IF($A8="",0,IF(AND($S8=1,$W8=0),1,0)) -> 0 | AH8: =IF($A8="","",$A8&"|"&TEXT($C8,"yyyymmdd")&"|"&$H8&"|"&TEXT($K8,"0.000")&"|"&SUBSTITUTE(SUBSTITUTE(SUBSTITUTE(LEFT($Q8,120),"~",""),"*",""),"?","")) -> L. Bailiff|20260907|Review|1.000|Finished reviewing AOI for Section 28, Township 19 South, Range 34 East in Lea County, NM associated with Federal Lease | AI8: =IF($A8="",0,IF(AND($S8=1,$W8=1,COUNTIF($AH$2:$AH$1500,$AH8)>1),1,0)) -> 0 | AJ8: =IF($A8="",0,IF(AND($S8=1,$W8=1,ABS($K8*8-ROUND($K8*8,0))>0.0001),1,0)) -> 0 | AK8: =IF($A8="",0,IF(AND($S8=1,$W8=1,$X8=1,$U8>Config!$C$9),1,0)) -> 0 | AL8: =IF($A8="",0,IF(AND($S8=1,$W8=1,$X8=1,$U8=0),1,0)) -> 0
A9: M. Young | B9: Approved | C9: 46272 | D9: Time Off | E9: Time Off | F9: Abbeville, SC | H9: Time Off | K9: 0 | L9: 0 | M9: 0 | P9: 0 | Q9: Not Billed - 6 hours | S9: =IF($A9="","",COUNTIF(BPOworkers!$B$6:$B$105,$A9)) -> 0 | T9: =IF($A9="","",$K9*Config!$C$9) -> 0 | U9: =IF($A9="","",IF(COUNTIF(Config!$C$21:$C$23,$H9)>0,IFERROR(VALUE(LEFT(TRIM($Q9),FIND(" ",TRIM($Q9)&" ")-1)),0),0)) -> 0 | V9: =IF($A9="","",$T9+$U9) -> 0 | W9: =IF($A9="",0,IF(AND($C9>=Config!$C$7,$C9<=Config!$C$8),1,0)) -> 0 | X9: =IF($A9="",0,IF(COUNTIF(Config!$C$21:$C$23,$H9)>0,1,0)) -> 1 | Y9: =IF($A9="",MAX(0,Y8),MAX(0,Y8)+IF(AND($W9=1,$X9=1,$S9=1),1,0)) -> 0 | Z9: =IF($A9="","",IF(AND($W9=1,$X9=1,$S9=1),$Y9,"")) | AB9: =IF($A9="",0,IF(AND($S9=0,ISERROR(FIND(".",$A9))),1,0)) -> 0 | AC9: =IF($A9="",0,IF(AND($AB9=1,COUNTIF($A$2:$A9,$A9)=1),1,0)) -> 0 | AD9: =IF($A9="",MAX(0,AD8),MAX(0,AD8)+$AC9) -> 0 | AE9: =IF($AC9=1,$AD9,"") | AF9: =IF($A9="",0,IFERROR(IF(AND($S9=1,WEEKDAY($C9,2)>5),1,0),0)) -> 0 | AG9: =IF($A9="",0,IF(AND($S9=1,$W9=0),1,0)) -> 0 | AH9: =IF($A9="","",$A9&"|"&TEXT($C9,"yyyymmdd")&"|"&$H9&"|"&TEXT($K9,"0.000")&"|"&SUBSTITUTE(SUBSTITUTE(SUBSTITUTE(LEFT($Q9,120),"~",""),"*",""),"?","")) -> M. Young|20260907|Time Off|0.000|Not Billed - 6 hours | AI9: =IF($A9="",0,IF(AND($S9=1,$W9=1,COUNTIF($AH$2:$AH$1500,$AH9)>1),1,0)) -> 0 | AJ9: =IF($A9="",0,IF(AND($S9=1,$W9=1,ABS($K9*8-ROUND($K9*8,0))>0.0001),1,0)) -> 0 | AK9: =IF($A9="",0,IF(AND($S9=1,$W9=1,$X9=1,$U9>Config!$C$9),1,0)) -> 0 | AL9: =IF($A9="",0,IF(AND($S9=1,$W9=1,$X9=1,$U9=0),1,0)) -> 0
A10: M. Young | B10: Approved | C10: 46272 | D10: EOG Resources - OK | E10: Pilot | F10: McClain, OK | G10: 19-07N-03W | H10: Review | K10: 0.25 | L10: 0 | M10: 0 | P10: 0 | Q10: Review cards | S10: =IF($A10="","",COUNTIF(BPOworkers!$B$6:$B$105,$A10)) -> 0 | T10: =IF($A10="","",$K10*Config!$C$9) -> 2 | U10: =IF($A10="","",IF(COUNTIF(Config!$C$21:$C$23,$H10)>0,IFERROR(VALUE(LEFT(TRIM($Q10),FIND(" ",TRIM($Q10)&" ")-1)),0),0)) -> 0 | V10: =IF($A10="","",$T10+$U10) -> 2 | W10: =IF($A10="",0,IF(AND($C10>=Config!$C$7,$C10<=Config!$C$8),1,0)) -> 0 | X10: =IF($A10="",0,IF(COUNTIF(Config!$C$21:$C$23,$H10)>0,1,0)) -> 0 | Y10: =IF($A10="",MAX(0,Y9),MAX(0,Y9)+IF(AND($W10=1,$X10=1,$S10=1),1,0)) -> 0 | Z10: =IF($A10="","",IF(AND($W10=1,$X10=1,$S10=1),$Y10,"")) | AB10: =IF($A10="",0,IF(AND($S10=0,ISERROR(FIND(".",$A10))),1,0)) -> 0 | AC10: =IF($A10="",0,IF(AND($AB10=1,COUNTIF($A$2:$A10,$A10)=1),1,0)) -> 0 | AD10: =IF($A10="",MAX(0,AD9),MAX(0,AD9)+$AC10) -> 0 | AE10: =IF($AC10=1,$AD10,"") | AF10: =IF($A10="",0,IFERROR(IF(AND($S10=1,WEEKDAY($C10,2)>5),1,0),0)) -> 0 | AG10: =IF($A10="",0,IF(AND($S10=1,$W10=0),1,0)) -> 0 | AH10: =IF($A10="","",$A10&"|"&TEXT($C10,"yyyymmdd")&"|"&$H10&"|"&TEXT($K10,"0.000")&"|"&SUBSTITUTE(SUBSTITUTE(SUBSTITUTE(LEFT($Q10,120),"~",""),"*",""),"?","")) -> M. Young|20260907|Review|0.250|Review cards | AI10: =IF($A10="",0,IF(AND($S10=1,$W10=1,COUNTIF($AH$2:$AH$1500,$AH10)>1),1,0)) -> 0 | AJ10: =IF($A10="",0,IF(AND($S10=1,$W10=1,ABS($K10*8-ROUND($K10*8,0))>0.0001),1,0)) -> 0 | AK10: =IF($A10="",0,IF(AND($S10=1,$W10=1,$X10=1,$U10>Config!$C$9),1,0)) -> 0 | AL10: =IF($A10="",0,IF(AND($S10=1,$W10=1,$X10=1,$U10=0),1,0)) -> 0
A11: M. Witheridge | B11: Unapproved | C11: 46272 | D11: Time Off | E11: Time Off | F11: Abbeville, SC | H11: Time Off | K11: 0 | L11: 0 | M11: 0 | P11: 0 | Q11: 8 hours unpaid | S11: =IF($A11="","",COUNTIF(BPOworkers!$B$6:$B$105,$A11)) -> 0 | T11: =IF($A11="","",$K11*Config!$C$9) -> 0 | U11: =IF($A11="","",IF(COUNTIF(Config!$C$21:$C$23,$H11)>0,IFERROR(VALUE(LEFT(TRIM($Q11),FIND(" ",TRIM($Q11)&" ")-1)),0),0)) -> 8 | V11: =IF($A11="","",$T11+$U11) -> 8 | W11: =IF($A11="",0,IF(AND($C11>=Config!$C$7,$C11<=Config!$C$8),1,0)) -> 0 | X11: =IF($A11="",0,IF(COUNTIF(Config!$C$21:$C$23,$H11)>0,1,0)) -> 1 | Y11: =IF($A11="",MAX(0,Y10),MAX(0,Y10)+IF(AND($W11=1,$X11=1,$S11=1),1,0)) -> 0 | Z11: =IF($A11="","",IF(AND($W11=1,$X11=1,$S11=1),$Y11,"")) | AB11: =IF($A11="",0,IF(AND($S11=0,ISERROR(FIND(".",$A11))),1,0)) -> 0 | AC11: =IF($A11="",0,IF(AND($AB11=1,COUNTIF($A$2:$A11,$A11)=1),1,0)) -> 0 | AD11: =IF($A11="",MAX(0,AD10),MAX(0,AD10)+$AC11) -> 0 | AE11: =IF($AC11=1,$AD11,"") | AF11: =IF($A11="",0,IFERROR(IF(AND($S11=1,WEEKDAY($C11,2)>5),1,0),0)) -> 0 | AG11: =IF($A11="",0,IF(AND($S11=1,$W11=0),1,0)) -> 0 | AH11: =IF($A11="","",$A11&"|"&TEXT($C11,"yyyymmdd")&"|"&$H11&"|"&TEXT($K11,"0.000")&"|"&SUBSTITUTE(SUBSTITUTE(SUBSTITUTE(LEFT($Q11,120),"~",""),"*",""),"?","")) -> M. Witheridge|20260907|Time Off|0.000|8 hours unpaid | AI11: =IF($A11="",0,IF(AND($S11=1,$W11=1,COUNTIF($AH$2:$AH$1500,$AH11)>1),1,0)) -> 0 | AJ11: =IF($A11="",0,IF(AND($S11=1,$W11=1,ABS($K11*8-ROUND($K11*8,0))>0.0001),1,0)) -> 0 | AK11: =IF($A11="",0,IF(AND($S11=1,$W11=1,$X11=1,$U11>Config!$C$9),1,0)) -> 0 | AL11: =IF($A11="",0,IF(AND($S11=1,$W11=1,$X11=1,$U11=0),1,0)) -> 0
A12: P. Elliott | B12: Unapproved | C12: 46272 | D12: Time Off | E12: Time Off | F12: Abbeville, SC | H12: Time Off | K12: 0 | L12: 0 | M12: 0 | P12: 0 | Q12: 8 hours time off. | S12: =IF($A12="","",COUNTIF(BPOworkers!$B$6:$B$105,$A12)) -> 0 | T12: =IF($A12="","",$K12*Config!$C$9) -> 0 | U12: =IF($A12="","",IF(COUNTIF(Config!$C$21:$C$23,$H12)>0,IFERROR(VALUE(LEFT(TRIM($Q12),FIND(" ",TRIM($Q12)&" ")-1)),0),0)) -> 8 | V12: =IF($A12="","",$T12+$U12) -> 8 | W12: =IF($A12="",0,IF(AND($C12>=Config!$C$7,$C12<=Config!$C$8),1,0)) -> 0 | X12: =IF($A12="",0,IF(COUNTIF(Config!$C$21:$C$23,$H12)>0,1,0)) -> 1 | Y12: =IF($A12="",MAX(0,Y11),MAX(0,Y11)+IF(AND($W12=1,$X12=1,$S12=1),1,0)) -> 0 | Z12: =IF($A12="","",IF(AND($W12=1,$X12=1,$S12=1),$Y12,"")) | AB12: =IF($A12="",0,IF(AND($S12=0,ISERROR(FIND(".",$A12))),1,0)) -> 0 | AC12: =IF($A12="",0,IF(AND($AB12=1,COUNTIF($A$2:$A12,$A12)=1),1,0)) -> 0 | AD12: =IF($A12="",MAX(0,AD11),MAX(0,AD11)+$AC12) -> 0 | AE12: =IF($AC12=1,$AD12,"") | AF12: =IF($A12="",0,IFERROR(IF(AND($S12=1,WEEKDAY($C12,2)>5),1,0),0)) -> 0 | AG12: =IF($A12="",0,IF(AND($S12=1,$W12=0),1,0)) -> 0 | AH12: =IF($A12="","",$A12&"|"&TEXT($C12,"yyyymmdd")&"|"&$H12&"|"&TEXT($K12,"0.000")&"|"&SUBSTITUTE(SUBSTITUTE(SUBSTITUTE(LEFT($Q12,120),"~",""),"*",""),"?","")) -> P. Elliott|20260907|Time Off|0.000|8 hours time off. | AI12: =IF($A12="",0,IF(AND($S12=1,$W12=1,COUNTIF($AH$2:$AH$1500,$AH12)>1),1,0)) -> 0 | AJ12: =IF($A12="",0,IF(AND($S12=1,$W12=1,ABS($K12*8-ROUND($K12*8,0))>0.0001),1,0)) -> 0 | AK12: =IF($A12="",0,IF(AND($S12=1,$W12=1,$X12=1,$U12>Config!$C$9),1,0)) -> 0 | AL12: =IF($A12="",0,IF(AND($S12=1,$W12=1,$X12=1,$U12=0),1,0)) -> 0
A13: J. Greenlee | B13: Approved | C13: 46272 | D13: Time Off | E13: Time Off | F13: Abbeville, SC | H13: Time Off | K13: 0 | L13: 0 | M13: 0 | P13: 0 | Q13: 8 hours unpaid | S13: =IF($A13="","",COUNTIF(BPOworkers!$B$6:$B$105,$A13)) -> 0 | T13: =IF($A13="","",$K13*Config!$C$9) -> 0 | U13: =IF($A13="","",IF(COUNTIF(Config!$C$21:$C$23,$H13)>0,IFERROR(VALUE(LEFT(TRIM($Q13),FIND(" ",TRIM($Q13)&" ")-1)),0),0)) -> 8 | V13: =IF($A13="","",$T13+$U13) -> 8 | W13: =IF($A13="",0,IF(AND($C13>=Config!$C$7,$C13<=Config!$C$8),1,0)) -> 0 | X13: =IF($A13="",0,IF(COUNTIF(Config!$C$21:$C$23,$H13)>0,1,0)) -> 1 | Y13: =IF($A13="",MAX(0,Y12),MAX(0,Y12)+IF(AND($W13=1,$X13=1,$S13=1),1,0)) -> 0 | Z13: =IF($A13="","",IF(AND($W13=1,$X13=1,$S13=1),$Y13,"")) | AB13: =IF($A13="",0,IF(AND($S13=0,ISERROR(FIND(".",$A13))),1,0)) -> 0 | AC13: =IF($A13="",0,IF(AND($AB13=1,COUNTIF($A$2:$A13,$A13)=1),1,0)) -> 0 | AD13: =IF($A13="",MAX(0,AD12),MAX(0,AD12)+$AC13) -> 0 | AE13: =IF($AC13=1,$AD13,"") | AF13: =IF($A13="",0,IFERROR(IF(AND($S13=1,WEEKDAY($C13,2)>5),1,0),0)) -> 0 | AG13: =IF($A13="",0,IF(AND($S13=1,$W13=0),1,0)) -> 0 | AH13: =IF($A13="","",$A13&"|"&TEXT($C13,"yyyymmdd")&"|"&$H13&"|"&TEXT($K13,"0.000")&"|"&SUBSTITUTE(SUBSTITUTE(SUBSTITUTE(LEFT($Q13,120),"~",""),"*",""),"?","")) -> J. Greenlee|20260907|Time Off|0.000|8 hours unpaid | AI13: =IF($A13="",0,IF(AND($S13=1,$W13=1,COUNTIF($AH$2:$AH$1500,$AH13)>1),1,0)) -> 0 | AJ13: =IF($A13="",0,IF(AND($S13=1,$W13=1,ABS($K13*8-ROUND($K13*8,0))>0.0001),1,0)) -> 0 | AK13: =IF($A13="",0,IF(AND($S13=1,$W13=1,$X13=1,$U13>Config!$C$9),1,0)) -> 0 | AL13: =IF($A13="",0,IF(AND($S13=1,$W13=1,$X13=1,$U13=0),1,0)) -> 0
A14: J. Howell | B14: Unapproved | C14: 46272 | D14: Holiday | E14: Holiday | F14: Abbeville, SC | G14: 00-01N-02W | H14: Holiday | K14: 1 | L14: 0 | M14: 0 | P14: 0 | S14: =IF($A14="","",COUNTIF(BPOworkers!$B$6:$B$105,$A14)) -> 0 | T14: =IF($A14="","",$K14*Config!$C$9) -> 8 | U14: =IF($A14="","",IF(COUNTIF(Config!$C$21:$C$23,$H14)>0,IFERROR(VALUE(LEFT(TRIM($Q14),FIND(" ",TRIM($Q14)&" ")-1)),0),0)) -> 0 | V14: =IF($A14="","",$T14+$U14) -> 8 | W14: =IF($A14="",0,IF(AND($C14>=Config!$C$7,$C14<=Config!$C$8),1,0)) -> 0 | X14: =IF($A14="",0,IF(COUNTIF(Config!$C$21:$C$23,$H14)>0,1,0)) -> 1 | Y14: =IF($A14="",MAX(0,Y13),MAX(0,Y13)+IF(AND($W14=1,$X14=1,$S14=1),1,0)) -> 0 | Z14: =IF($A14="","",IF(AND($W14=1,$X14=1,$S14=1),$Y14,"")) | AB14: =IF($A14="",0,IF(AND($S14=0,ISERROR(FIND(".",$A14))),1,0)) -> 0 | AC14: =IF($A14="",0,IF(AND($AB14=1,COUNTIF($A$2:$A14,$A14)=1),1,0)) -> 0 | AD14: =IF($A14="",MAX(0,AD13),MAX(0,AD13)+$AC14) -> 0 | AE14: =IF($AC14=1,$AD14,"") | AF14: =IF($A14="",0,IFERROR(IF(AND($S14=1,WEEKDAY($C14,2)>5),1,0),0)) -> 0 | AG14: =IF($A14="",0,IF(AND($S14=1,$W14=0),1,0)) -> 0 | AH14: =IF($A14="","",$A14&"|"&TEXT($C14,"yyyymmdd")&"|"&$H14&"|"&TEXT($K14,"0.000")&"|"&SUBSTITUTE(SUBSTITUTE(SUBSTITUTE(LEFT($Q14,120),"~",""),"*",""),"?","")) -> J. Howell|20260907|Holiday|1.000| | AI14: =IF($A14="",0,IF(AND($S14=1,$W14=1,COUNTIF($AH$2:$AH$1500,$AH14)>1),1,0)) -> 0 | AJ14: =IF($A14="",0,IF(AND($S14=1,$W14=1,ABS($K14*8-ROUND($K14*8,0))>0.0001),1,0)) -> 0 | AK14: =IF($A14="",0,IF(AND($S14=1,$W14=1,$X14=1,$U14>Config!$C$9),1,0)) -> 0 | AL14: =IF($A14="",0,IF(AND($S14=1,$W14=1,$X14=1,$U14=0),1,0)) -> 0
A15: A. Beato | B15: Unapproved | C15: 46272 | D15: TLS | E15: TLS (Non-Billable) | F15: Abbeville, SC | G15: 01-01N-01W | H15: Project Management | I15: Project Admin | J15: TCC — Staffing management | K15: 1 | L15: 0 | M15: 0 | P15: 0 | Q15: Continued development and refinement of the Tracts Command Center, with a primary focus on building out and integrating the Staffing page to improve visibility into current project assignments, available personnel, and future staffing needs. Updated the site navigation and overall page flow to make movement between key Command Center sections more intuitive and efficient. Reviewed, adjusted, and corrected the TLS Client Intake Form to address existing issues and improve reliability, then tested the intake workflow to verify that newly submitted prospect information was being recorded accurately and routed correctly for review and approval. Also performed general troubleshooting and validation across the affected pages and workflows to ensure the latest updates were functioning as intended. | S15: =IF($A15="","",COUNTIF(BPOworkers!$B$6:$B$105,$A15)) -> 0 | T15: =IF($A15="","",$K15*Config!$C$9) -> 8 | U15: =IF($A15="","",IF(COUNTIF(Config!$C$21:$C$23,$H15)>0,IFERROR(VALUE(LEFT(TRIM($Q15),FIND(" ",TRIM($Q15)&" ")-1)),0),0)) -> 0 | V15: =IF($A15="","",$T15+$U15) -> 8 | W15: =IF($A15="",0,IF(AND($C15>=Config!$C$7,$C15<=Config!$C$8),1,0)) -> 0 | X15: =IF($A15="",0,IF(COUNTIF(Config!$C$21:$C$23,$H15)>0,1,0)) -> 0 | Y15: =IF($A15="",MAX(0,Y14),MAX(0,Y14)+IF(AND($W15=1,$X15=1,$S15=1),1,0)) -> 0 | Z15: =IF($A15="","",IF(AND($W15=1,$X15=1,$S15=1),$Y15,"")) | AB15: =IF($A15="",0,IF(AND($S15=0,ISERROR(FIND(".",$A15))),1,0)) -> 0 | AC15: =IF($A15="",0,IF(AND($AB15=1,COUNTIF($A$2:$A15,$A15)=1),1,0)) -> 0 | AD15: =IF($A15="",MAX(0,AD14),MAX(0,AD14)+$AC15) -> 0 | AE15: =IF($AC15=1,$AD15,"") | AF15: =IF($A15="",0,IFERROR(IF(AND($S15=1,WEEKDAY($C15,2)>5),1,0),0)) -> 0 | AG15: =IF($A15="",0,IF(AND($S15=1,$W15=0),1,0)) -> 0 | AH15: =IF($A15="","",$A15&"|"&TEXT($C15,"yyyymmdd")&"|"&$H15&"|"&TEXT($K15,"0.000")&"|"&SUBSTITUTE(SUBSTITUTE(SUBSTITUTE(LEFT($Q15,120),"~",""),"*",""),"?","")) -> A. Beato|20260907|Project Management|1.000|Continued development and refinement of the Tracts Command Center, with a primary focus on building out and integrating | AI15: =IF($A15="",0,IF(AND($S15=1,$W15=1,COUNTIF($AH$2:$AH$1500,$AH15)>1),1,0)) -> 0 | AJ15: =IF($A15="",0,IF(AND($S15=1,$W15=1,ABS($K15*8-ROUND($K15*8,0))>0.0001),1,0)) -> 0 | AK15: =IF($A15="",0,IF(AND($S15=1,$W15=1,$X15=1,$U15>Config!$C$9),1,0)) -> 0 | AL15: =IF($A15="",0,IF(AND($S15=1,$W15=1,$X15=1,$U15=0),1,0)) -> 0
A16: L. Yasir | B16: Unapproved | C16: 46272 | D16: Time Off | E16: Time Off | F16: Abbeville, SC | H16: Time Off | K16: 0 | L16: 0 | M16: 0 | P16: 0 | Q16: 8 hours not billed | S16: =IF($A16="","",COUNTIF(BPOworkers!$B$6:$B$105,$A16)) -> 0 | T16: =IF($A16="","",$K16*Config!$C$9) -> 0 | U16: =IF($A16="","",IF(COUNTIF(Config!$C$21:$C$23,$H16)>0,IFERROR(VALUE(LEFT(TRIM($Q16),FIND(" ",TRIM($Q16)&" ")-1)),0),0)) -> 8 | V16: =IF($A16="","",$T16+$U16) -> 8 | W16: =IF($A16="",0,IF(AND($C16>=Config!$C$7,$C16<=Config!$C$8),1,0)) -> 0 | X16: =IF($A16="",0,IF(COUNTIF(Config!$C$21:$C$23,$H16)>0,1,0)) -> 1 | Y16: =IF($A16="",MAX(0,Y15),MAX(0,Y15)+IF(AND($W16=1,$X16=1,$S16=1),1,0)) -> 0 | Z16: =IF($A16="","",IF(AND($W16=1,$X16=1,$S16=1),$Y16,"")) | AB16: =IF($A16="",0,IF(AND($S16=0,ISERROR(FIND(".",$A16))),1,0)) -> 0 | AC16: =IF($A16="",0,IF(AND($AB16=1,COUNTIF($A$2:$A16,$A16)=1),1,0)) -> 0 | AD16: =IF($A16="",MAX(0,AD15),MAX(0,AD15)+$AC16) -> 0 | AE16: =IF($AC16=1,$AD16,"") | AF16: =IF($A16="",0,IFERROR(IF(AND($S16=1,WEEKDAY($C16,2)>5),1,0),0)) -> 0 | AG16: =IF($A16="",0,IF(AND($S16=1,$W16=0),1,0)) -> 0 | AH16: =IF($A16="","",$A16&"|"&TEXT($C16,"yyyymmdd")&"|"&$H16&"|"&TEXT($K16,"0.000")&"|"&SUBSTITUTE(SUBSTITUTE(SUBSTITUTE(LEFT($Q16,120),"~",""),"*",""),"?","")) -> L. Yasir|20260907|Time Off|0.000|8 hours not billed | AI16: =IF($A16="",0,IF(AND($S16=1,$W16=1,COUNTIF($AH$2:$AH$1500,$AH16)>1),1,0)) -> 0 | AJ16: =IF($A16="",0,IF(AND($S16=1,$W16=1,ABS($K16*8-ROUND($K16*8,0))>0.0001),1,0)) -> 0 | AK16: =IF($A16="",0,IF(AND($S16=1,$W16=1,$X16=1,$U16>Config!$C$9),1,0)) -> 0 | AL16: =IF($A16="",0,IF(AND($S16=1,$W16=1,$X16=1,$U16=0),1,0)) -> 0
A17: M. Svatek | B17: Unapproved | C17: 46272 | D17: Time Off | E17: Time Off | F17: Abbeville, SC | H17: Time Off | K17: 0 | L17: 0 | M17: 0 | P17: 0 | Q17: 8 hours not billed | S17: =IF($A17="","",COUNTIF(BPOworkers!$B$6:$B$105,$A17)) -> 0 | T17: =IF($A17="","",$K17*Config!$C$9) -> 0 | U17: =IF($A17="","",IF(COUNTIF(Config!$C$21:$C$23,$H17)>0,IFERROR(VALUE(LEFT(TRIM($Q17),FIND(" ",TRIM($Q17)&" ")-1)),0),0)) -> 8 | V17: =IF($A17="","",$T17+$U17) -> 8 | W17: =IF($A17="",0,IF(AND($C17>=Config!$C$7,$C17<=Config!$C$8),1,0)) -> 0 | X17: =IF($A17="",0,IF(COUNTIF(Config!$C$21:$C$23,$H17)>0,1,0)) -> 1 | Y17: =IF($A17="",MAX(0,Y16),MAX(0,Y16)+IF(AND($W17=1,$X17=1,$S17=1),1,0)) -> 0 | Z17: =IF($A17="","",IF(AND($W17=1,$X17=1,$S17=1),$Y17,"")) | AB17: =IF($A17="",0,IF(AND($S17=0,ISERROR(FIND(".",$A17))),1,0)) -> 0 | AC17: =IF($A17="",0,IF(AND($AB17=1,COUNTIF($A$2:$A17,$A17)=1),1,0)) -> 0 | AD17: =IF($A17="",MAX(0,AD16),MAX(0,AD16)+$AC17) -> 0 | AE17: =IF($AC17=1,$AD17,"") | AF17: =IF($A17="",0,IFERROR(IF(AND($S17=1,WEEKDAY($C17,2)>5),1,0),0)) -> 0 | AG17: =IF($A17="",0,IF(AND($S17=1,$W17=0),1,0)) -> 0 | AH17: =IF($A17="","",$A17&"|"&TEXT($C17,"yyyymmdd")&"|"&$H17&"|"&TEXT($K17,"0.000")&"|"&SUBSTITUTE(SUBSTITUTE(SUBSTITUTE(LEFT($Q17,120),"~",""),"*",""),"?","")) -> M. Svatek|20260907|Time Off|0.000|8 hours not billed | AI17: =IF($A17="",0,IF(AND($S17=1,$W17=1,COUNTIF($AH$2:$AH$1500,$AH17)>1),1,0)) -> 0 | AJ17: =IF($A17="",0,IF(AND($S17=1,$W17=1,ABS($K17*8-ROUND($K17*8,0))>0.0001),1,0)) -> 0 | AK17: =IF($A17="",0,IF(AND($S17=1,$W17=1,$X17=1,$U17>Config!$C$9),1,0)) -> 0 | AL17: =IF($A17="",0,IF(AND($S17=1,$W17=1,$X17=1,$U17=0),1,0)) -> 0
A18: J. Jinkins | B18: Unapproved | C18: 46272 | D18: Time Off | E18: Time Off | F18: Abbeville, SC | H18: Time Off | K18: 0 | L18: 0 | M18: 0 | P18: 0 | Q18: 8 hours not billed. | S18: =IF($A18="","",COUNTIF(BPOworkers!$B$6:$B$105,$A18)) -> 0 | T18: =IF($A18="","",$K18*Config!$C$9) -> 0 | U18: =IF($A18="","",IF(COUNTIF(Config!$C$21:$C$23,$H18)>0,IFERROR(VALUE(LEFT(TRIM($Q18),FIND(" ",TRIM($Q18)&" ")-1)),0),0)) -> 8 | V18: =IF($A18="","",$T18+$U18) -> 8 | W18: =IF($A18="",0,IF(AND($C18>=Config!$C$7,$C18<=Config!$C$8),1,0)) -> 0 | X18: =IF($A18="",0,IF(COUNTIF(Config!$C$21:$C$23,$H18)>0,1,0)) -> 1 | Y18: =IF($A18="",MAX(0,Y17),MAX(0,Y17)+IF(AND($W18=1,$X18=1,$S18=1),1,0)) -> 0 | Z18: =IF($A18="","",IF(AND($W18=1,$X18=1,$S18=1),$Y18,"")) | AB18: =IF($A18="",0,IF(AND($S18=0,ISERROR(FIND(".",$A18))),1,0)) -> 0 | AC18: =IF($A18="",0,IF(AND($AB18=1,COUNTIF($A$2:$A18,$A18)=1),1,0)) -> 0 | AD18: =IF($A18="",MAX(0,AD17),MAX(0,AD17)+$AC18) -> 0 | AE18: =IF($AC18=1,$AD18,"") | AF18: =IF($A18="",0,IFERROR(IF(AND($S18=1,WEEKDAY($C18,2)>5),1,0),0)) -> 0 | AG18: =IF($A18="",0,IF(AND($S18=1,$W18=0),1,0)) -> 0 | AH18: =IF($A18="","",$A18&"|"&TEXT($C18,"yyyymmdd")&"|"&$H18&"|"&TEXT($K18,"0.000")&"|"&SUBSTITUTE(SUBSTITUTE(SUBSTITUTE(LEFT($Q18,120),"~",""),"*",""),"?","")) -> J. Jinkins|20260907|Time Off|0.000|8 hours not billed. | AI18: =IF($A18="",0,IF(AND($S18=1,$W18=1,COUNTIF($AH$2:$AH$1500,$AH18)>1),1,0)) -> 0 | AJ18: =IF($A18="",0,IF(AND($S18=1,$W18=1,ABS($K18*8-ROUND($K18*8,0))>0.0001),1,0)) -> 0 | AK18: =IF($A18="",0,IF(AND($S18=1,$W18=1,$X18=1,$U18>Config!$C$9),1,0)) -> 0 | AL18: =IF($A18="",0,IF(AND($S18=1,$W18=1,$X18=1,$U18=0),1,0)) -> 0
A19: M. Tamez | B19: Approved | C19: 46272 | D19: Jetstream Oil and Gas Partners, LP | E19: FreeH Project | F19: Lea, NM | H19: Review | K19: 0.625 | L19: 0 | M19: 0 | P19: 0 | Q19: Continued quality control work on completed AOIs per PM Instructions. | S19: =IF($A19="","",COUNTIF(BPOworkers!$B$6:$B$105,$A19)) -> 0 | T19: =IF($A19="","",$K19*Config!$C$9) -> 5 | U19: =IF($A19="","",IF(COUNTIF(Config!$C$21:$C$23,$H19)>0,IFERROR(VALUE(LEFT(TRIM($Q19),FIND(" ",TRIM($Q19)&" ")-1)),0),0)) -> 0 | V19: =IF($A19="","",$T19+$U19) -> 5 | W19: =IF($A19="",0,IF(AND($C19>=Config!$C$7,$C19<=Config!$C$8),1,0)) -> 0 | X19: =IF($A19="",0,IF(COUNTIF(Config!$C$21:$C$23,$H19)>0,1,0)) -> 0 | Y19: =IF($A19="",MAX(0,Y18),MAX(0,Y18)+IF(AND($W19=1,$X19=1,$S19=1),1,0)) -> 0 | Z19: =IF($A19="","",IF(AND($W19=1,$X19=1,$S19=1),$Y19,"")) | AB19: =IF($A19="",0,IF(AND($S19=0,ISERROR(FIND(".",$A19))),1,0)) -> 0 | AC19: =IF($A19="",0,IF(AND($AB19=1,COUNTIF($A$2:$A19,$A19)=1),1,0)) -> 0 | AD19: =IF($A19="",MAX(0,AD18),MAX(0,AD18)+$AC19) -> 0 | AE19: =IF($AC19=1,$AD19,"") | AF19: =IF($A19="",0,IFERROR(IF(AND($S19=1,WEEKDAY($C19,2)>5),1,0),0)) -> 0 | AG19: =IF($A19="",0,IF(AND($S19=1,$W19=0),1,0)) -> 0 | AH19: =IF($A19="","",$A19&"|"&TEXT($C19,"yyyymmdd")&"|"&$H19&"|"&TEXT($K19,"0.000")&"|"&SUBSTITUTE(SUBSTITUTE(SUBSTITUTE(LEFT($Q19,120),"~",""),"*",""),"?","")) -> M. Tamez|20260907|Review|0.625|Continued quality control work on completed AOIs per PM Instructions. | AI19: =IF($A19="",0,IF(AND($S19=1,$W19=1,COUNTIF($AH$2:$AH$1500,$AH19)>1),1,0)) -> 0 | AJ19: =IF($A19="",0,IF(AND($S19=1,$W19=1,ABS($K19*8-ROUND($K19*8,0))>0.0001),1,0)) -> 0 | AK19: =IF($A19="",0,IF(AND($S19=1,$W19=1,$X19=1,$U19>Config!$C$9),1,0)) -> 0 | AL19: =IF($A19="",0,IF(AND($S19=1,$W19=1,$X19=1,$U19=0),1,0)) -> 0
A20: M. Tamez | B20: Approved | C20: 46272 | D20: Time Off | E20: Time Off | F20: Abbeville, SC | H20: Time Off | K20: 0.375 | L20: 0 | M20: 0 | P20: 0 | Q20: 3 hours not worked. | S20: =IF($A20="","",COUNTIF(BPOworkers!$B$6:$B$105,$A20)) -> 0 | T20: =IF($A20="","",$K20*Config!$C$9) -> 3 | U20: =IF($A20="","",IF(COUNTIF(Config!$C$21:$C$23,$H20)>0,IFERROR(VALUE(LEFT(TRIM($Q20),FIND(" ",TRIM($Q20)&" ")-1)),0),0)) -> 3 | V20: =IF($A20="","",$T20+$U20) -> 6 | W20: =IF($A20="",0,IF(AND($C20>=Config!$C$7,$C20<=Config!$C$8),1,0)) -> 0 | X20: =IF($A20="",0,IF(COUNTIF(Config!$C$21:$C$23,$H20)>0,1,0)) -> 1 | Y20: =IF($A20="",MAX(0,Y19),MAX(0,Y19)+IF(AND($W20=1,$X20=1,$S20=1),1,0)) -> 0 | Z20: =IF($A20="","",IF(AND($W20=1,$X20=1,$S20=1),$Y20,"")) | AB20: =IF($A20="",0,IF(AND($S20=0,ISERROR(FIND(".",$A20))),1,0)) -> 0 | AC20: =IF($A20="",0,IF(AND($AB20=1,COUNTIF($A$2:$A20,$A20)=1),1,0)) -> 0 | AD20: =IF($A20="",MAX(0,AD19),MAX(0,AD19)+$AC20) -> 0 | AE20: =IF($AC20=1,$AD20,"") | AF20: =IF($A20="",0,IFERROR(IF(AND($S20=1,WEEKDAY($C20,2)>5),1,0),0)) -> 0 | AG20: =IF($A20="",0,IF(AND($S20=1,$W20=0),1,0)) -> 0 | AH20: =IF($A20="","",$A20&"|"&TEXT($C20,"yyyymmdd")&"|"&$H20&"|"&TEXT($K20,"0.000")&"|"&SUBSTITUTE(SUBSTITUTE(SUBSTITUTE(LEFT($Q20,120),"~",""),"*",""),"?","")) -> M. Tamez|20260907|Time Off|0.375|3 hours not worked. | AI20: =IF($A20="",0,IF(AND($S20=1,$W20=1,COUNTIF($AH$2:$AH$1500,$AH20)>1),1,0)) -> 0 | AJ20: =IF($A20="",0,IF(AND($S20=1,$W20=1,ABS($K20*8-ROUND($K20*8,0))>0.0001),1,0)) -> 0 | AK20: =IF($A20="",0,IF(AND($S20=1,$W20=1,$X20=1,$U20>Config!$C$9),1,0)) -> 0 | AL20: =IF($A20="",0,IF(AND($S20=1,$W20=1,$X20=1,$U20=0),1,0)) -> 0
A21: M. Bearrow | B21: Unapproved | C21: 46272 | D21: Title Notes | E21: Title Notes | F21: Upton, TX | H21: TitleNotes - Library | J21: Title Notes | K21: 1 | L21: 0 | M21: 0 | P21: 0 | Q21: I am currently training with Matt regarding the library title notes. I am encountering some issues with documents that reflect different interests in their legal descriptions, and there are also some documents that I have been marking as "reviewed." | S21: =IF($A21="","",COUNTIF(BPOworkers!$B$6:$B$105,$A21)) -> 0 | T21: =IF($A21="","",$K21*Config!$C$9) -> 8 | U21: =IF($A21="","",IF(COUNTIF(Config!$C$21:$C$23,$H21)>0,IFERROR(VALUE(LEFT(TRIM($Q21),FIND(" ",TRIM($Q21)&" ")-1)),0),0)) -> 0 | V21: =IF($A21="","",$T21+$U21) -> 8 | W21: =IF($A21="",0,IF(AND($C21>=Config!$C$7,$C21<=Config!$C$8),1,0)) -> 0 | X21: =IF($A21="",0,IF(COUNTIF(Config!$C$21:$C$23,$H21)>0,1,0)) -> 0 | Y21: =IF($A21="",MAX(0,Y20),MAX(0,Y20)+IF(AND($W21=1,$X21=1,$S21=1),1,0)) -> 0 | Z21: =IF($A21="","",IF(AND($W21=1,$X21=1,$S21=1),$Y21,"")) | AB21: =IF($A21="",0,IF(AND($S21=0,ISERROR(FIND(".",$A21))),1,0)) -> 0 | AC21: =IF($A21="",0,IF(AND($AB21=1,COUNTIF($A$2:$A21,$A21)=1),1,0)) -> 0 | AD21: =IF($A21="",MAX(0,AD20),MAX(0,AD20)+$AC21) -> 0 | AE21: =IF($AC21=1,$AD21,"") | AF21: =IF($A21="",0,IFERROR(IF(AND($S21=1,WEEKDAY($C21,2)>5),1,0),0)) -> 0 | AG21: =IF($A21="",0,IF(AND($S21=1,$W21=0),1,0)) -> 0 | AH21: =IF($A21="","",$A21&"|"&TEXT($C21,"yyyymmdd")&"|"&$H21&"|"&TEXT($K21,"0.000")&"|"&SUBSTITUTE(SUBSTITUTE(SUBSTITUTE(LEFT($Q21,120),"~",""),"*",""),"?","")) -> M. Bearrow|20260907|TitleNotes - Library|1.000|I am currently training with Matt regarding the library title notes. I am encountering some issues with documents that | AI21: =IF($A21="",0,IF(AND($S21=1,$W21=1,COUNTIF($AH$2:$AH$1500,$AH21)>1),1,0)) -> 0 | AJ21: =IF($A21="",0,IF(AND($S21=1,$W21=1,ABS($K21*8-ROUND($K21*8,0))>0.0001),1,0)) -> 0 | AK21: =IF($A21="",0,IF(AND($S21=1,$W21=1,$X21=1,$U21>Config!$C$9),1,0)) -> 0 | AL21: =IF($A21="",0,IF(AND($S21=1,$W21=1,$X21=1,$U21=0),1,0)) -> 0
A22: M. Bearrow | B22: Approved | C22: 46272 | D22: Title Notes | E22: Title Notes | F22: Upton, TX | H22: TitleNotes - Library | K22: 1 | L22: 0 | M22: 0 | P22: 0 | Q22: 41 documents reviewed 87 Transactions | S22: =IF($A22="","",COUNTIF(BPOworkers!$B$6:$B$105,$A22)) -> 0 | T22: =IF($A22="","",$K22*Config!$C$9) -> 8 | U22: =IF($A22="","",IF(COUNTIF(Config!$C$21:$C$23,$H22)>0,IFERROR(VALUE(LEFT(TRIM($Q22),FIND(" ",TRIM($Q22)&" ")-1)),0),0)) -> 0 | V22: =IF($A22="","",$T22+$U22) -> 8 | W22: =IF($A22="",0,IF(AND($C22>=Config!$C$7,$C22<=Config!$C$8),1,0)) -> 0 | X22: =IF($A22="",0,IF(COUNTIF(Config!$C$21:$C$23,$H22)>0,1,0)) -> 0 | Y22: =IF($A22="",MAX(0,Y21),MAX(0,Y21)+IF(AND($W22=1,$X22=1,$S22=1),1,0)) -> 0 | Z22: =IF($A22="","",IF(AND($W22=1,$X22=1,$S22=1),$Y22,"")) | AB22: =IF($A22="",0,IF(AND($S22=0,ISERROR(FIND(".",$A22))),1,0)) -> 0 | AC22: =IF($A22="",0,IF(AND($AB22=1,COUNTIF($A$2:$A22,$A22)=1),1,0)) -> 0 | AD22: =IF($A22="",MAX(0,AD21),MAX(0,AD21)+$AC22) -> 0 | AE22: =IF($AC22=1,$AD22,"") | AF22: =IF($A22="",0,IFERROR(IF(AND($S22=1,WEEKDAY($C22,2)>5),1,0),0)) -> 0 | AG22: =IF($A22="",0,IF(AND($S22=1,$W22=0),1,0)) -> 0 | AH22: =IF($A22="","",$A22&"|"&TEXT($C22,"yyyymmdd")&"|"&$H22&"|"&TEXT($K22,"0.000")&"|"&SUBSTITUTE(SUBSTITUTE(SUBSTITUTE(LEFT($Q22,120),"~",""),"*",""),"?","")) -> M. Bearrow|20260907|TitleNotes - Library|1.000|41 documents reviewed 87 Transactions | AI22: =IF($A22="",0,IF(AND($S22=1,$W22=1,COUNTIF($AH$2:$AH$1500,$AH22)>1),1,0)) -> 0 | AJ22: =IF($A22="",0,IF(AND($S22=1,$W22=1,ABS($K22*8-ROUND($K22*8,0))>0.0001),1,0)) -> 0 | AK22: =IF($A22="",0,IF(AND($S22=1,$W22=1,$X22=1,$U22>Config!$C$9),1,0)) -> 0 | AL22: =IF($A22="",0,IF(AND($S22=1,$W22=1,$X22=1,$U22=0),1,0)) -> 0
A23: M. Bearrow | B23: Unapproved | C23: 46272 | D23: Title Notes | E23: Title Notes | F23: Upton, TX | H23: TitleNotes - Client | K23: 1 | L23: 0 | M23: 0 | P23: 0 | Q23: Documents 56 Trnsactions 123 The Title Notes website was very glitchy today | S23: =IF($A23="","",COUNTIF(BPOworkers!$B$6:$B$105,$A23)) -> 0 | T23: =IF($A23="","",$K23*Config!$C$9) -> 8 | U23: =IF($A23="","",IF(COUNTIF(Config!$C$21:$C$23,$H23)>0,IFERROR(VALUE(LEFT(TRIM($Q23),FIND(" ",TRIM($Q23)&" ")-1)),0),0)) -> 0 | V23: =IF($A23="","",$T23+$U23) -> 8 | W23: =IF($A23="",0,IF(AND($C23>=Config!$C$7,$C23<=Config!$C$8),1,0)) -> 0 | X23: =IF($A23="",0,IF(COUNTIF(Config!$C$21:$C$23,$H23)>0,1,0)) -> 0 | Y23: =IF($A23="",MAX(0,Y22),MAX(0,Y22)+IF(AND($W23=1,$X23=1,$S23=1),1,0)) -> 0 | Z23: =IF($A23="","",IF(AND($W23=1,$X23=1,$S23=1),$Y23,"")) | AB23: =IF($A23="",0,IF(AND($S23=0,ISERROR(FIND(".",$A23))),1,0)) -> 0 | AC23: =IF($A23="",0,IF(AND($AB23=1,COUNTIF($A$2:$A23,$A23)=1),1,0)) -> 0 | AD23: =IF($A23="",MAX(0,AD22),MAX(0,AD22)+$AC23) -> 0 | AE23: =IF($AC23=1,$AD23,"") | AF23: =IF($A23="",0,IFERROR(IF(AND($S23=1,WEEKDAY($C23,2)>5),1,0),0)) -> 0 | AG23: =IF($A23="",0,IF(AND($S23=1,$W23=0),1,0)) -> 0 | AH23: =IF($A23="","",$A23&"|"&TEXT($C23,"yyyymmdd")&"|"&$H23&"|"&TEXT($K23,"0.000")&"|"&SUBSTITUTE(SUBSTITUTE(SUBSTITUTE(LEFT($Q23,120),"~",""),"*",""),"?","")) -> M. Bearrow|20260907|TitleNotes - Client|1.000|Documents 56 Trnsactions 123 The Title Notes website was very glitchy today | AI23: =IF($A23="",0,IF(AND($S23=1,$W23=1,COUNTIF($AH$2:$AH$1500,$AH23)>1),1,0)) -> 0 | AJ23: =IF($A23="",0,IF(AND($S23=1,$W23=1,ABS($K23*8-ROUND($K23*8,0))>0.0001),1,0)) -> 0 | AK23: =IF($A23="",0,IF(AND($S23=1,$W23=1,$X23=1,$U23>Config!$C$9),1,0)) -> 0 | AL23: =IF($A23="",0,IF(AND($S23=1,$W23=1,$X23=1,$U23=0),1,0)) -> 0
A24: M. Bearrow | B24: Approved | C24: 46272 | D24: Title Notes | E24: Title Notes | F24: Upton, TX | H24: TitleNotes - Library | K24: 1 | L24: 0 | M24: 0 | P24: 0 | Q24: 32 Documents 69 Transactions | S24: =IF($A24="","",COUNTIF(BPOworkers!$B$6:$B$105,$A24)) -> 0 | T24: =IF($A24="","",$K24*Config!$C$9) -> 8 | U24: =IF($A24="","",IF(COUNTIF(Config!$C$21:$C$23,$H24)>0,IFERROR(VALUE(LEFT(TRIM($Q24),FIND(" ",TRIM($Q24)&" ")-1)),0),0)) -> 0 | V24: =IF($A24="","",$T24+$U24) -> 8 | W24: =IF($A24="",0,IF(AND($C24>=Config!$C$7,$C24<=Config!$C$8),1,0)) -> 0 | X24: =IF($A24="",0,IF(COUNTIF(Config!$C$21:$C$23,$H24)>0,1,0)) -> 0 | Y24: =IF($A24="",MAX(0,Y23),MAX(0,Y23)+IF(AND($W24=1,$X24=1,$S24=1),1,0)) -> 0 | Z24: =IF($A24="","",IF(AND($W24=1,$X24=1,$S24=1),$Y24,"")) | AB24: =IF($A24="",0,IF(AND($S24=0,ISERROR(FIND(".",$A24))),1,0)) -> 0 | AC24: =IF($A24="",0,IF(AND($AB24=1,COUNTIF($A$2:$A24,$A24)=1),1,0)) -> 0 | AD24: =IF($A24="",MAX(0,AD23),MAX(0,AD23)+$AC24) -> 0 | AE24: =IF($AC24=1,$AD24,"") | AF24: =IF($A24="",0,IFERROR(IF(AND($S24=1,WEEKDAY($C24,2)>5),1,0),0)) -> 0 | AG24: =IF($A24="",0,IF(AND($S24=1,$W24=0),1,0)) -> 0 | AH24: =IF($A24="","",$A24&"|"&TEXT($C24,"yyyymmdd")&"|"&$H24&"|"&TEXT($K24,"0.000")&"|"&SUBSTITUTE(SUBSTITUTE(SUBSTITUTE(LEFT($Q24,120),"~",""),"*",""),"?","")) -> M. Bearrow|20260907|TitleNotes - Library|1.000|32 Documents 69 Transactions | AI24: =IF($A24="",0,IF(AND($S24=1,$W24=1,COUNTIF($AH$2:$AH$1500,$AH24)>1),1,0)) -> 0 | AJ24: =IF($A24="",0,IF(AND($S24=1,$W24=1,ABS($K24*8-ROUND($K24*8,0))>0.0001),1,0)) -> 0 | AK24: =IF($A24="",0,IF(AND($S24=1,$W24=1,$X24=1,$U24>Config!$C$9),1,0)) -> 0 | AL24: =IF($A24="",0,IF(AND($S24=1,$W24=1,$X24=1,$U24=0),1,0)) -> 0
A25: M. Bearrow | B25: Approved | C25: 46272 | D25: Title Notes | E25: Title Notes | F25: Upton, TX | H25: TitleNotes - Library | K25: 1 | L25: 0 | M25: 0 | P25: 0 | Q25: 22 notecards and 57 transactions | S25: =IF($A25="","",COUNTIF(BPOworkers!$B$6:$B$105,$A25)) -> 0 | T25: =IF($A25="","",$K25*Config!$C$9) -> 8 | U25: =IF($A25="","",IF(COUNTIF(Config!$C$21:$C$23,$H25)>0,IFERROR(VALUE(LEFT(TRIM($Q25),FIND(" ",TRIM($Q25)&" ")-1)),0),0)) -> 0 | V25: =IF($A25="","",$T25+$U25) -> 8 | W25: =IF($A25="",0,IF(AND($C25>=Config!$C$7,$C25<=Config!$C$8),1,0)) -> 0 | X25: =IF($A25="",0,IF(COUNTIF(Config!$C$21:$C$23,$H25)>0,1,0)) -> 0 | Y25: =IF($A25="",MAX(0,Y24),MAX(0,Y24)+IF(AND($W25=1,$X25=1,$S25=1),1,0)) -> 0 | Z25: =IF($A25="","",IF(AND($W25=1,$X25=1,$S25=1),$Y25,"")) | AB25: =IF($A25="",0,IF(AND($S25=0,ISERROR(FIND(".",$A25))),1,0)) -> 0 | AC25: =IF($A25="",0,IF(AND($AB25=1,COUNTIF($A$2:$A25,$A25)=1),1,0)) -> 0 | AD25: =IF($A25="",MAX(0,AD24),MAX(0,AD24)+$AC25) -> 0 | AE25: =IF($AC25=1,$AD25,"") | AF25: =IF($A25="",0,IFERROR(IF(AND($S25=1,WEEKDAY($C25,2)>5),1,0),0)) -> 0 | AG25: =IF($A25="",0,IF(AND($S25=1,$W25=0),1,0)) -> 0 | AH25: =IF($A25="","",$A25&"|"&TEXT($C25,"yyyymmdd")&"|"&$H25&"|"&TEXT($K25,"0.000")&"|"&SUBSTITUTE(SUBSTITUTE(SUBSTITUTE(LEFT($Q25,120),"~",""),"*",""),"?","")) -> M. Bearrow|20260907|TitleNotes - Library|1.000|22 notecards and 57 transactions | AI25: =IF($A25="",0,IF(AND($S25=1,$W25=1,COUNTIF($AH$2:$AH$1500,$AH25)>1),1,0)) -> 0 | AJ25: =IF($A25="",0,IF(AND($S25=1,$W25=1,ABS($K25*8-ROUND($K25*8,0))>0.0001),1,0)) -> 0 | AK25: =IF($A25="",0,IF(AND($S25=1,$W25=1,$X25=1,$U25>Config!$C$9),1,0)) -> 0 | AL25: =IF($A25="",0,IF(AND($S25=1,$W25=1,$X25=1,$U25=0),1,0)) -> 0
A26: M. Bearrow | B26: Unapproved | C26: 46272 | D26: TLS | E26: TLS (Non-Billable) | F26: Abbeville, SC | G26: 01-01N-01W | H26: Holiday | J26: Labor Day | K26: 1 | L26: 0 | M26: 0 | P26: 0 | Q26: Labor Day | S26: =IF($A26="","",COUNTIF(BPOworkers!$B$6:$B$105,$A26)) -> 0 | T26: =IF($A26="","",$K26*Config!$C$9) -> 8 | U26: =IF($A26="","",IF(COUNTIF(Config!$C$21:$C$23,$H26)>0,IFERROR(VALUE(LEFT(TRIM($Q26),FIND(" ",TRIM($Q26)&" ")-1)),0),0)) -> 0 | V26: =IF($A26="","",$T26+$U26) -> 8 | W26: =IF($A26="",0,IF(AND($C26>=Config!$C$7,$C26<=Config!$C$8),1,0)) -> 0 | X26: =IF($A26="",0,IF(COUNTIF(Config!$C$21:$C$23,$H26)>0,1,0)) -> 1 | Y26: =IF($A26="",MAX(0,Y25),MAX(0,Y25)+IF(AND($W26=1,$X26=1,$S26=1),1,0)) -> 0 | Z26: =IF($A26="","",IF(AND($W26=1,$X26=1,$S26=1),$Y26,"")) | AB26: =IF($A26="",0,IF(AND($S26=0,ISERROR(FIND(".",$A26))),1,0)) -> 0 | AC26: =IF($A26="",0,IF(AND($AB26=1,COUNTIF($A$2:$A26,$A26)=1),1,0)) -> 0 | AD26: =IF($A26="",MAX(0,AD25),MAX(0,AD25)+$AC26) -> 0 | AE26: =IF($AC26=1,$AD26,"") | AF26: =IF($A26="",0,IFERROR(IF(AND($S26=1,WEEKDAY($C26,2)>5),1,0),0)) -> 0 | AG26: =IF($A26="",0,IF(AND($S26=1,$W26=0),1,0)) -> 0 | AH26: =IF($A26="","",$A26&"|"&TEXT($C26,"yyyymmdd")&"|"&$H26&"|"&TEXT($K26,"0.000")&"|"&SUBSTITUTE(SUBSTITUTE(SUBSTITUTE(LEFT($Q26,120),"~",""),"*",""),"?","")) -> M. Bearrow|20260907|Holiday|1.000|Labor Day | AI26: =IF($A26="",0,IF(AND($S26=1,$W26=1,COUNTIF($AH$2:$AH$1500,$AH26)>1),1,0)) -> 0 | AJ26: =IF($A26="",0,IF(AND($S26=1,$W26=1,ABS($K26*8-ROUND($K26*8,0))>0.0001),1,0)) -> 0 | AK26: =IF($A26="",0,IF(AND($S26=1,$W26=1,$X26=1,$U26>Config!$C$9),1,0)) -> 0 | AL26: =IF($A26="",0,IF(AND($S26=1,$W26=1,$X26=1,$U26=0),1,0)) -> 0
A27: M. Soter | B27: Unapproved | C27: 46272 | D27: Tower Rock | E27: RPHOE-VAROH Project | F27: Columbiana, OH | G27: 75-00194.005 | H27: Title | J27: Sevek | K27: 0.5 | L27: 0 | M27: 0 | P27: 0 | Q27: Indexed for Parcel 75-00194.005 S 28 SW 1/4 T 13 R 3. | S27: =IF($A27="","",COUNTIF(BPOworkers!$B$6:$B$105,$A27)) -> 0 | T27: =IF($A27="","",$K27*Config!$C$9) -> 4 | U27: =IF($A27="","",IF(COUNTIF(Config!$C$21:$C$23,$H27)>0,IFERROR(VALUE(LEFT(TRIM($Q27),FIND(" ",TRIM($Q27)&" ")-1)),0),0)) -> 0 | V27: =IF($A27="","",$T27+$U27) -> 4 | W27: =IF($A27="",0,IF(AND($C27>=Config!$C$7,$C27<=Config!$C$8),1,0)) -> 0 | X27: =IF($A27="",0,IF(COUNTIF(Config!$C$21:$C$23,$H27)>0,1,0)) -> 0 | Y27: =IF($A27="",MAX(0,Y26),MAX(0,Y26)+IF(AND($W27=1,$X27=1,$S27=1),1,0)) -> 0 | Z27: =IF($A27="","",IF(AND($W27=1,$X27=1,$S27=1),$Y27,"")) | AB27: =IF($A27="",0,IF(AND($S27=0,ISERROR(FIND(".",$A27))),1,0)) -> 0 | AC27: =IF($A27="",0,IF(AND($AB27=1,COUNTIF($A$2:$A27,$A27)=1),1,0)) -> 0 | AD27: =IF($A27="",MAX(0,AD26),MAX(0,AD26)+$AC27) -> 0 | AE27: =IF($AC27=1,$AD27,"") | AF27: =IF($A27="",0,IFERROR(IF(AND($S27=1,WEEKDAY($C27,2)>5),1,0),0)) -> 0 | AG27: =IF($A27="",0,IF(AND($S27=1,$W27=0),1,0)) -> 0 | AH27: =IF($A27="","",$A27&"|"&TEXT($C27,"yyyymmdd")&"|"&$H27&"|"&TEXT($K27,"0.000")&"|"&SUBSTITUTE(SUBSTITUTE(SUBSTITUTE(LEFT($Q27,120),"~",""),"*",""),"?","")) -> M. Soter|20260907|Title|0.500|Indexed for Parcel 75-00194.005 S 28 SW 1/4 T 13 R 3. | AI27: =IF($A27="",0,IF(AND($S27=1,$W27=1,COUNTIF($AH$2:$AH$1500,$AH27)>1),1,0)) -> 0 | AJ27: =IF($A27="",0,IF(AND($S27=1,$W27=1,ABS($K27*8-ROUND($K27*8,0))>0.0001),1,0)) -> 0 | AK27: =IF($A27="",0,IF(AND($S27=1,$W27=1,$X27=1,$U27>Config!$C$9),1,0)) -> 0 | AL27: =IF($A27="",0,IF(AND($S27=1,$W27=1,$X27=1,$U27=0),1,0)) -> 0
A28: M. Soter | B28: Unapproved | C28: 46272 | D28: Tower Rock | E28: RPHOE-VAROH Project | F28: Carroll, OH | H28: Title | J28: SHC Enterprisess NE HN MON | K28: 0.5 | L28: 0 | M28: 0 | P28: 0 | Q28: Indexed for Parcel 25-0000194.001 S 4 PT SE T 14 R 4. The above is in Harrison and Carroll Counties. | S28: =IF($A28="","",COUNTIF(BPOworkers!$B$6:$B$105,$A28)) -> 0 | T28: =IF($A28="","",$K28*Config!$C$9) -> 4 | U28: =IF($A28="","",IF(COUNTIF(Config!$C$21:$C$23,$H28)>0,IFERROR(VALUE(LEFT(TRIM($Q28),FIND(" ",TRIM($Q28)&" ")-1)),0),0)) -> 0 | V28: =IF($A28="","",$T28+$U28) -> 4 | W28: =IF($A28="",0,IF(AND($C28>=Config!$C$7,$C28<=Config!$C$8),1,0)) -> 0 | X28: =IF($A28="",0,IF(COUNTIF(Config!$C$21:$C$23,$H28)>0,1,0)) -> 0 | Y28: =IF($A28="",MAX(0,Y27),MAX(0,Y27)+IF(AND($W28=1,$X28=1,$S28=1),1,0)) -> 0 | Z28: =IF($A28="","",IF(AND($W28=1,$X28=1,$S28=1),$Y28,"")) | AB28: =IF($A28="",0,IF(AND($S28=0,ISERROR(FIND(".",$A28))),1,0)) -> 0 | AC28: =IF($A28="",0,IF(AND($AB28=1,COUNTIF($A$2:$A28,$A28)=1),1,0)) -> 0 | AD28: =IF($A28="",MAX(0,AD27),MAX(0,AD27)+$AC28) -> 0 | AE28: =IF($AC28=1,$AD28,"") | AF28: =IF($A28="",0,IFERROR(IF(AND($S28=1,WEEKDAY($C28,2)>5),1,0),0)) -> 0 | AG28: =IF($A28="",0,IF(AND($S28=1,$W28=0),1,0)) -> 0 | AH28: =IF($A28="","",$A28&"|"&TEXT($C28,"yyyymmdd")&"|"&$H28&"|"&TEXT($K28,"0.000")&"|"&SUBSTITUTE(SUBSTITUTE(SUBSTITUTE(LEFT($Q28,120),"~",""),"*",""),"?","")) -> M. Soter|20260907|Title|0.500|Indexed for Parcel 25-0000194.001 S 4 PT SE T 14 R 4. The above is in Harrison and Carroll Counties. | AI28: =IF($A28="",0,IF(AND($S28=1,$W28=1,COUNTIF($AH$2:$AH$1500,$AH28)>1),1,0)) -> 0 | AJ28: =IF($A28="",0,IF(AND($S28=1,$W28=1,ABS($K28*8-ROUND($K28*8,0))>0.0001),1,0)) -> 0 | AK28: =IF($A28="",0,IF(AND($S28=1,$W28=1,$X28=1,$U28>Config!$C$9),1,0)) -> 0 | AL28: =IF($A28="",0,IF(AND($S28=1,$W28=1,$X28=1,$U28=0),1,0)) -> 0
A29: M. Avery | B29: Unapproved | C29: 46272 | D29: Time Off | E29: Time Off | F29: Abbeville, SC | H29: Time Off | K29: 0 | L29: 0 | M29: 0 | P29: 0 | Q29: 8 hours time off (Holiday) | S29: =IF($A29="","",COUNTIF(BPOworkers!$B$6:$B$105,$A29)) -> 0 | T29: =IF($A29="","",$K29*Config!$C$9) -> 0 | U29: =IF($A29="","",IF(COUNTIF(Config!$C$21:$C$23,$H29)>0,IFERROR(VALUE(LEFT(TRIM($Q29),FIND(" ",TRIM($Q29)&" ")-1)),0),0)) -> 8 | V29: =IF($A29="","",$T29+$U29) -> 8 | W29: =IF($A29="",0,IF(AND($C29>=Config!$C$7,$C29<=Config!$C$8),1,0)) -> 0 | X29: =IF($A29="",0,IF(COUNTIF(Config!$C$21:$C$23,$H29)>0,1,0)) -> 1 | Y29: =IF($A29="",MAX(0,Y28),MAX(0,Y28)+IF(AND($W29=1,$X29=1,$S29=1),1,0)) -> 0 | Z29: =IF($A29="","",IF(AND($W29=1,$X29=1,$S29=1),$Y29,"")) | AB29: =IF($A29="",0,IF(AND($S29=0,ISERROR(FIND(".",$A29))),1,0)) -> 0 | AC29: =IF($A29="",0,IF(AND($AB29=1,COUNTIF($A$2:$A29,$A29)=1),1,0)) -> 0 | AD29: =IF($A29="",MAX(0,AD28),MAX(0,AD28)+$AC29) -> 0 | AE29: =IF($AC29=1,$AD29,"") | AF29: =IF($A29="",0,IFERROR(IF(AND($S29=1,WEEKDAY($C29,2)>5),1,0),0)) -> 0 | AG29: =IF($A29="",0,IF(AND($S29=1,$W29=0),1,0)) -> 0 | AH29: =IF($A29="","",$A29&"|"&TEXT($C29,"yyyymmdd")&"|"&$H29&"|"&TEXT($K29,"0.000")&"|"&SUBSTITUTE(SUBSTITUTE(SUBSTITUTE(LEFT($Q29,120),"~",""),"*",""),"?","")) -> M. Avery|20260907|Time Off|0.000|8 hours time off (Holiday) | AI29: =IF($A29="",0,IF(AND($S29=1,$W29=1,COUNTIF($AH$2:$AH$1500,$AH29)>1),1,0)) -> 0 | AJ29: =IF($A29="",0,IF(AND($S29=1,$W29=1,ABS($K29*8-ROUND($K29*8,0))>0.0001),1,0)) -> 0 | AK29: =IF($A29="",0,IF(AND($S29=1,$W29=1,$X29=1,$U29>Config!$C$9),1,0)) -> 0 | AL29: =IF($A29="",0,IF(AND($S29=1,$W29=1,$X29=1,$U29=0),1,0)) -> 0
A30: L Silva | B30: Unapproved | C30: 46272 | D30: TLS | E30: TLS (Non-Billable) | F30: Abbeville, SC | G30: 01-01N-01W | H30: BPO Project Management | J30: Project management & Training | K30: 1 | L30: 0 | M30: 0 | P30: 0 | Q30: *Absences report. *Team leads meeting. *Helping out Juan Sebastián Bermudez with WV pilot. *Offboarding with catalina. *Solved new hires questions. | S30: =IF($A30="","",COUNTIF(BPOworkers!$B$6:$B$105,$A30)) -> 1 | T30: =IF($A30="","",$K30*Config!$C$9) -> 8 | U30: =IF($A30="","",IF(COUNTIF(Config!$C$21:$C$23,$H30)>0,IFERROR(VALUE(LEFT(TRIM($Q30),FIND(" ",TRIM($Q30)&" ")-1)),0),0)) -> 0 | V30: =IF($A30="","",$T30+$U30) -> 8 | W30: =IF($A30="",0,IF(AND($C30>=Config!$C$7,$C30<=Config!$C$8),1,0)) -> 0 | X30: =IF($A30="",0,IF(COUNTIF(Config!$C$21:$C$23,$H30)>0,1,0)) -> 0 | Y30: =IF($A30="",MAX(0,Y29),MAX(0,Y29)+IF(AND($W30=1,$X30=1,$S30=1),1,0)) -> 0 | Z30: =IF($A30="","",IF(AND($W30=1,$X30=1,$S30=1),$Y30,"")) | AB30: =IF($A30="",0,IF(AND($S30=0,ISERROR(FIND(".",$A30))),1,0)) -> 0 | AC30: =IF($A30="",0,IF(AND($AB30=1,COUNTIF($A$2:$A30,$A30)=1),1,0)) -> 0 | AD30: =IF($A30="",MAX(0,AD29),MAX(0,AD29)+$AC30) -> 0 | AE30: =IF($AC30=1,$AD30,"") | AF30: =IF($A30="",0,IFERROR(IF(AND($S30=1,WEEKDAY($C30,2)>5),1,0),0)) -> 0 | AG30: =IF($A30="",0,IF(AND($S30=1,$W30=0),1,0)) -> 1 | AH30: =IF($A30="","",$A30&"|"&TEXT($C30,"yyyymmdd")&"|"&$H30&"|"&TEXT($K30,"0.000")&"|"&SUBSTITUTE(SUBSTITUTE(SUBSTITUTE(LEFT($Q30,120),"~",""),"*",""),"?","")) -> L Silva|20260907|BPO Project Management|1.000|Absences report. Team leads meeting. Helping out Juan Sebastián Bermudez with WV pilot. Offboarding with ca | AI30: =IF($A30="",0,IF(AND($S30=1,$W30=1,COUNTIF($AH$2:$AH$1500,$AH30)>1),1,0)) -> 0 | AJ30: =IF($A30="",0,IF(AND($S30=1,$W30=1,ABS($K30*8-ROUND($K30*8,0))>0.0001),1,0)) -> 0 | AK30: =IF($A30="",0,IF(AND($S30=1,$W30=1,$X30=1,$U30>Config!$C$9),1,0)) -> 0 | AL30: =IF($A30="",0,IF(AND($S30=1,$W30=1,$X30=1,$U30=0),1,0)) -> 0
A31: S Romero | B31: Unapproved | C31: 46272 | D31: Arch Energy Management | E31: Mark Andrew, LLC | F31: Uintah, UT | G31: 30-02S-02E | H31: Review | K31: 0.625 | L31: 0 | M31: 0 | P31: 0 | Q31: Reviewed subject assignment | S31: =IF($A31="","",COUNTIF(BPOworkers!$B$6:$B$105,$A31)) -> 1 | T31: =IF($A31="","",$K31*Config!$C$9) -> 5 | U31: =IF($A31="","",IF(COUNTIF(Config!$C$21:$C$23,$H31)>0,IFERROR(VALUE(LEFT(TRIM($Q31),FIND(" ",TRIM($Q31)&" ")-1)),0),0)) -> 0 | V31: =IF($A31="","",$T31+$U31) -> 5 | W31: =IF($A31="",0,IF(AND($C31>=Config!$C$7,$C31<=Config!$C$8),1,0)) -> 0 | X31: =IF($A31="",0,IF(COUNTIF(Config!$C$21:$C$23,$H31)>0,1,0)) -> 0 | Y31: =IF($A31="",MAX(0,Y30),MAX(0,Y30)+IF(AND($W31=1,$X31=1,$S31=1),1,0)) -> 0 | Z31: =IF($A31="","",IF(AND($W31=1,$X31=1,$S31=1),$Y31,"")) | AB31: =IF($A31="",0,IF(AND($S31=0,ISERROR(FIND(".",$A31))),1,0)) -> 0 | AC31: =IF($A31="",0,IF(AND($AB31=1,COUNTIF($A$2:$A31,$A31)=1),1,0)) -> 0 | AD31: =IF($A31="",MAX(0,AD30),MAX(0,AD30)+$AC31) -> 0 | AE31: =IF($AC31=1,$AD31,"") | AF31: =IF($A31="",0,IFERROR(IF(AND($S31=1,WEEKDAY($C31,2)>5),1,0),0)) -> 0 | AG31: =IF($A31="",0,IF(AND($S31=1,$W31=0),1,0)) -> 1 | AH31: =IF($A31="","",$A31&"|"&TEXT($C31,"yyyymmdd")&"|"&$H31&"|"&TEXT($K31,"0.000")&"|"&SUBSTITUTE(SUBSTITUTE(SUBSTITUTE(LEFT($Q31,120),"~",""),"*",""),"?","")) -> S Romero|20260907|Review|0.625|Reviewed subject assignment | AI31: =IF($A31="",0,IF(AND($S31=1,$W31=1,COUNTIF($AH$2:$AH$1500,$AH31)>1),1,0)) -> 0 | AJ31: =IF($A31="",0,IF(AND($S31=1,$W31=1,ABS($K31*8-ROUND($K31*8,0))>0.0001),1,0)) -> 0 | AK31: =IF($A31="",0,IF(AND($S31=1,$W31=1,$X31=1,$U31>Config!$C$9),1,0)) -> 0 | AL31: =IF($A31="",0,IF(AND($S31=1,$W31=1,$X31=1,$U31=0),1,0)) -> 0
