Workbook

Sheet Roster
A1: ROSTER — PROJECT 1
C2: ← Name corto como aparece facturado en BTBS. Autogenerado; corrige a mano si no coincide.
A3: Full name | B3: Email | C3: BTBS name | D3: Active
A4: Laura Silva | B4: lsilva@tractsbpo.com | C4: =IF($A4="","",LEFT($A4,1)&" "&TRIM(RIGHT(SUBSTITUTE($A4," ",REPT(" ",50)),50))) -> L Silva | D4: Yes
A5: Leonidas Villamil | B5: lvillamil@tractsbpo.com | C5: =IF($A5="","",LEFT($A5,1)&" "&TRIM(RIGHT(SUBSTITUTE($A5," ",REPT(" ",50)),50))) -> L Villamil | D5: Yes
A6: Sebastian Romero | B6: sromero@tractsbpo.com | C6: =IF($A6="","",LEFT($A6,1)&" "&TRIM(RIGHT(SUBSTITUTE($A6," ",REPT(" ",50)),50))) -> S Romero | D6: Yes
A7: Hugo Daza | B7: hdaza@tractsbpo.com | C7: =IF($A7="","",LEFT($A7,1)&" "&TRIM(RIGHT(SUBSTITUTE($A7," ",REPT(" ",50)),50))) -> H Daza | D7: Yes
A8: Roberto Sanchez | B8: rsanchez@tractsbpo.com | C8: =IF($A8="","",LEFT($A8,1)&" "&TRIM(RIGHT(SUBSTITUTE($A8," ",REPT(" ",50)),50))) -> R Sanchez | D8: Yes
A9: Alejandra Lorenzo | B9: alorenzo@tractsbpo.com | C9: =IF($A9="","",LEFT($A9,1)&" "&TRIM(RIGHT(SUBSTITUTE($A9," ",REPT(" ",50)),50))) -> A Lorenzo | D9: Yes
A10: Andrea Camargo | B10: acamargo@tractsbpo.com | C10: =IF($A10="","",LEFT($A10,1)&" "&TRIM(RIGHT(SUBSTITUTE($A10," ",REPT(" ",50)),50))) -> A Camargo | D10: Yes
A11: Maria Camila Leon | B11: mcleon@tractsbpo.com | C11: =IF($A11="","",LEFT($A11,1)&" "&TRIM(RIGHT(SUBSTITUTE($A11," ",REPT(" ",50)),50))) -> M Leon | D11: Yes
A12: Juan David Castillo | B12: jdcastillo@tractsbpo.com | C12: =IF($A12="","",LEFT($A12,1)&" "&TRIM(RIGHT(SUBSTITUTE($A12," ",REPT(" ",50)),50))) -> J Castillo | D12: Yes
A13: Jeronimo Rincon | B13: jrincon@tractsbpo.com | C13: =IF($A13="","",LEFT($A13,1)&" "&TRIM(RIGHT(SUBSTITUTE($A13," ",REPT(" ",50)),50))) -> J Rincon | D13: Yes
A14: Jose David Valbuena | B14: jdvalbuena@tractsbpo.com | C14: =IF($A14="","",LEFT($A14,1)&" "&TRIM(RIGHT(SUBSTITUTE($A14," ",REPT(" ",50)),50))) -> J Valbuena | D14: Yes
A15: Angie Lopez | B15: alopez@tractsbpo.com | C15: =IF($A15="","",LEFT($A15,1)&" "&TRIM(RIGHT(SUBSTITUTE($A15," ",REPT(" ",50)),50))) -> A Lopez | D15: Yes
... A43: Sara Calderon | B43: scalderon@tractsbpo.com | C43: =IF($A43="","",LEFT($A43,1)&" "&TRIM(RIGHT(SUBSTITUTE($A43," ",REPT(" ",50)),50))) -> S Calderon | D43: Yes

Sheet Proposed Hours
A1: PROPOSED HOURS — Overtime declared by each person
A2: Each person writes their overtime per day on the row with their name. Thes fechas salen solas del periodo.
A3: From: | B3: 46253 | C3: To: | D3: 46264 | F3: ← Week loaded from 'Tentative Extra Hours' (Aug 19-23). Days align themselves with the headers.
F4: =IF($D$3<$B$3,"⚠ 'To' is earlier than 'From'",IF($D$3-$B$3>13,"⚠ The period exceeds 14 days: only the first 14 are validated",""))
A5: Name | B5: =IF($B$3="","",$B$3) -> 46253 | C5: =IF(OR(B5="",B5>=$D$3),"",B5+1) -> 46254 | D5: =IF(OR(C5="",C5>=$D$3),"",C5+1) -> 46255 | E5: =IF(OR(D5="",D5>=$D$3),"",D5+1) -> 46256 | F5: =IF(OR(E5="",E5>=$D$3),"",E5+1) -> 46257 | G5: =IF(OR(F5="",F5>=$D$3),"",F5+1) -> 46258 | H5: =IF(OR(G5="",G5>=$D$3),"",G5+1) -> 46259 | I5: =IF(OR(H5="",H5>=$D$3),"",H5+1) -> 46260 | J5: =IF(OR(I5="",I5>=$D$3),"",I5+1) -> 46261 | ... O5: =IF(OR(N5="",N5>=$D$3),"",N5+1) | P5: Total (h) | Q5: Warning
A6: =IF(Roster!A4="","",Roster!A4) -> Laura Silva | B6: 0 | C6: 0 | D6: 0 | E6: 0 | F6: 0 | P6: =IF($A6="","",SUMIF($B$5:$O$5,">0",B6:O6)) -> 0 | Q6: =IF($A6="","",IF(SUM(B6:O6)<>P6,"⚠ There are horas en columnas fuera del periodo",IF(COUNTIF(B6:O6,"<0")>0,"⚠ Negative values",IF(COUNTIF(B6:O6,">24")>0,"⚠ More than 24 h in one day",""))))
A7: =IF(Roster!A5="","",Roster!A5) -> Leonidas Villamil | P7: =IF($A7="","",SUMIF($B$5:$O$5,">0",B7:O7)) -> 0 | Q7: =IF($A7="","",IF(SUM(B7:O7)<>P7,"⚠ There are horas en columnas fuera del periodo",IF(COUNTIF(B7:O7,"<0")>0,"⚠ Negative values",IF(COUNTIF(B7:O7,">24")>0,"⚠ More than 24 h in one day",""))))
A8: =IF(Roster!A6="","",Roster!A6) -> Sebastian Romero | P8: =IF($A8="","",SUMIF($B$5:$O$5,">0",B8:O8)) -> 0 | Q8: =IF($A8="","",IF(SUM(B8:O8)<>P8,"⚠ There are horas en columnas fuera del periodo",IF(COUNTIF(B8:O8,"<0")>0,"⚠ Negative values",IF(COUNTIF(B8:O8,">24")>0,"⚠ More than 24 h in one day",""))))
A9: =IF(Roster!A7="","",Roster!A7) -> Hugo Daza | P9: =IF($A9="","",SUMIF($B$5:$O$5,">0",B9:O9)) -> 0 | Q9: =IF($A9="","",IF(SUM(B9:O9)<>P9,"⚠ There are horas en columnas fuera del periodo",IF(COUNTIF(B9:O9,"<0")>0,"⚠ Negative values",IF(COUNTIF(B9:O9,">24")>0,"⚠ More than 24 h in one day",""))))
A10: =IF(Roster!A8="","",Roster!A8) -> Roberto Sanchez | P10: =IF($A10="","",SUMIF($B$5:$O$5,">0",B10:O10)) -> 0 | Q10: =IF($A10="","",IF(SUM(B10:O10)<>P10,"⚠ There are horas en columnas fuera del periodo",IF(COUNTIF(B10:O10,"<0")>0,"⚠ Negative values",IF(COUNTIF(B10:O10,">24")>0,"⚠ More than 24 h in one day",""))))
A11: =IF(Roster!A9="","",Roster!A9) -> Alejandra Lorenzo | P11: =IF($A11="","",SUMIF($B$5:$O$5,">0",B11:O11)) -> 0 | Q11: =IF($A11="","",IF(SUM(B11:O11)<>P11,"⚠ There are horas en columnas fuera del periodo",IF(COUNTIF(B11:O11,"<0")>0,"⚠ Negative values",IF(COUNTIF(B11:O11,">24")>0,"⚠ More than 24 h in one day",""))))
A12: =IF(Roster!A10="","",Roster!A10) -> Andrea Camargo | P12: =IF($A12="","",SUMIF($B$5:$O$5,">0",B12:O12)) -> 0 | Q12: =IF($A12="","",IF(SUM(B12:O12)<>P12,"⚠ There are horas en columnas fuera del periodo",IF(COUNTIF(B12:O12,"<0")>0,"⚠ Negative values",IF(COUNTIF(B12:O12,">24")>0,"⚠ More than 24 h in one day",""))))
A13: =IF(Roster!A11="","",Roster!A11) -> Maria Camila Leon | P13: =IF($A13="","",SUMIF($B$5:$O$5,">0",B13:O13)) -> 0 | Q13: =IF($A13="","",IF(SUM(B13:O13)<>P13,"⚠ There are horas en columnas fuera del periodo",IF(COUNTIF(B13:O13,"<0")>0,"⚠ Negative values",IF(COUNTIF(B13:O13,">24")>0,"⚠ More than 24 h in one day",""))))
A14: =IF(Roster!A12="","",Roster!A12) -> Juan David Castillo | B14: 0 | C14: 2 | D14: 4 | E14: 12 | F14: 12 | P14: =IF($A14="","",SUMIF($B$5:$O$5,">0",B14:O14)) -> 30 | Q14: =IF($A14="","",IF(SUM(B14:O14)<>P14,"⚠ There are horas en columnas fuera del periodo",IF(COUNTIF(B14:O14,"<0")>0,"⚠ Negative values",IF(COUNTIF(B14:O14,">24")>0,"⚠ More than 24 h in one day",""))))
A15: =IF(Roster!A13="","",Roster!A13) -> Jeronimo Rincon | B15: 4 | C15: 4 | D15: 4 | E15: 12 | F15: 12 | P15: =IF($A15="","",SUMIF($B$5:$O$5,">0",B15:O15)) -> 36 | Q15: =IF($A15="","",IF(SUM(B15:O15)<>P15,"⚠ There are horas en columnas fuera del periodo",IF(COUNTIF(B15:O15,"<0")>0,"⚠ Negative values",IF(COUNTIF(B15:O15,">24")>0,"⚠ More than 24 h in one day",""))))
A16: =IF(Roster!A14="","",Roster!A14) -> Jose David Valbuena | B16: 2 | C16: 4 | D16: 4 | E16: 12 | F16: 12 | P16: =IF($A16="","",SUMIF($B$5:$O$5,">0",B16:O16)) -> 34 | Q16: =IF($A16="","",IF(SUM(B16:O16)<>P16,"⚠ There are horas en columnas fuera del periodo",IF(COUNTIF(B16:O16,"<0")>0,"⚠ Negative values",IF(COUNTIF(B16:O16,">24")>0,"⚠ More than 24 h in one day",""))))
A17: =IF(Roster!A15="","",Roster!A15) -> Angie Lopez | P17: =IF($A17="","",SUMIF($B$5:$O$5,">0",B17:O17)) -> 0 | Q17: =IF($A17="","",IF(SUM(B17:O17)<>P17,"⚠ There are horas en columnas fuera del periodo",IF(COUNTIF(B17:O17,"<0")>0,"⚠ Negative values",IF(COUNTIF(B17:O17,">24")>0,"⚠ More than 24 h in one day",""))))
A18: =IF(Roster!A16="","",Roster!A16) -> Carlos Mesa | B18: 0 | C18: 0 | D18: 0 | E18: 0 | F18: 0 | P18: =IF($A18="","",SUMIF($B$5:$O$5,">0",B18:O18)) -> 0 | Q18: =IF($A18="","",IF(SUM(B18:O18)<>P18,"⚠ There are horas en columnas fuera del periodo",IF(COUNTIF(B18:O18,"<0")>0,"⚠ Negative values",IF(COUNTIF(B18:O18,">24")>0,"⚠ More than 24 h in one day",""))))
A19: =IF(Roster!A17="","",Roster!A17) -> Isabella de la Parra | P19: =IF($A19="","",SUMIF($B$5:$O$5,">0",B19:O19)) -> 0 | Q19: =IF($A19="","",IF(SUM(B19:O19)<>P19,"⚠ There are horas en columnas fuera del periodo",IF(COUNTIF(B19:O19,"<0")>0,"⚠ Negative values",IF(COUNTIF(B19:O19,">24")>0,"⚠ More than 24 h in one day",""))))
A20: =IF(Roster!A18="","",Roster!A18) -> Juan Pablo Gonzalez | P20: =IF($A20="","",SUMIF($B$5:$O$5,">0",B20:O20)) -> 0 | Q20: =IF($A20="","",IF(SUM(B20:O20)<>P20,"⚠ There are horas en columnas fuera del periodo",IF(COUNTIF(B20:O20,"<0")>0,"⚠ Negative values",IF(COUNTIF(B20:O20,">24")>0,"⚠ More than 24 h in one day",""))))
A21: =IF(Roster!A19="","",Roster!A19) -> Maria Camila Grazziani | P21: =IF($A21="","",SUMIF($B$5:$O$5,">0",B21:O21)) -> 0 | Q21: =IF($A21="","",IF(SUM(B21:O21)<>P21,"⚠ There are horas en columnas fuera del periodo",IF(COUNTIF(B21:O21,"<0")>0,"⚠ Negative values",IF(COUNTIF(B21:O21,">24")>0,"⚠ More than 24 h in one day",""))))
A22: =IF(Roster!A20="","",Roster!A20) -> Carlos Castellanos | P22: =IF($A22="","",SUMIF($B$5:$O$5,">0",B22:O22)) -> 0 | Q22: =IF($A22="","",IF(SUM(B22:O22)<>P22,"⚠ There are horas en columnas fuera del periodo",IF(COUNTIF(B22:O22,"<0")>0,"⚠ Negative values",IF(COUNTIF(B22:O22,">24")>0,"⚠ More than 24 h in one day",""))))
A23: =IF(Roster!A21="","",Roster!A21) -> Catalina Lara | B23: 4 | C23: 4 | D23: 4 | E23: 12 | F23: 12 | P23: =IF($A23="","",SUMIF($B$5:$O$5,">0",B23:O23)) -> 36 | Q23: =IF($A23="","",IF(SUM(B23:O23)<>P23,"⚠ There are horas en columnas fuera del periodo",IF(COUNTIF(B23:O23,"<0")>0,"⚠ Negative values",IF(COUNTIF(B23:O23,">24")>0,"⚠ More than 24 h in one day",""))))
A24: =IF(Roster!A22="","",Roster!A22) -> Daniel Trujillo | P24: =IF($A24="","",SUMIF($B$5:$O$5,">0",B24:O24)) -> 0 | Q24: =IF($A24="","",IF(SUM(B24:O24)<>P24,"⚠ There are horas en columnas fuera del periodo",IF(COUNTIF(B24:O24,"<0")>0,"⚠ Negative values",IF(COUNTIF(B24:O24,">24")>0,"⚠ More than 24 h in one day",""))))
A25: =IF(Roster!A23="","",Roster!A23) -> Fernanda Montañez | B25: 3 | C25: 2 | D25: 4 | E25: 12 | F25: 8 | P25: =IF($A25="","",SUMIF($B$5:$O$5,">0",B25:O25)) -> 29 | Q25: =IF($A25="","",IF(SUM(B25:O25)<>P25,"⚠ There are horas en columnas fuera del periodo",IF(COUNTIF(B25:O25,"<0")>0,"⚠ Negative values",IF(COUNTIF(B25:O25,">24")>0,"⚠ More than 24 h in one day",""))))
A26: =IF(Roster!A24="","",Roster!A24) -> Juan Esteban Abay | B26: 4 | C26: 4 | D26: 4 | E26: 12 | F26: 12 | P26: =IF($A26="","",SUMIF($B$5:$O$5,">0",B26:O26)) -> 36 | Q26: =IF($A26="","",IF(SUM(B26:O26)<>P26,"⚠ There are horas en columnas fuera del periodo",IF(COUNTIF(B26:O26,"<0")>0,"⚠ Negative values",IF(COUNTIF(B26:O26,">24")>0,"⚠ More than 24 h in one day",""))))
A27: =IF(Roster!A25="","",Roster!A25) -> Juan José Reyes | P27: =IF($A27="","",SUMIF($B$5:$O$5,">0",B27:O27)) -> 0 | Q27: =IF($A27="","",IF(SUM(B27:O27)<>P27,"⚠ There are horas en columnas fuera del periodo",IF(COUNTIF(B27:O27,"<0")>0,"⚠ Negative values",IF(COUNTIF(B27:O27,">24")>0,"⚠ More than 24 h in one day",""))))
A28: =IF(Roster!A26="","",Roster!A26) -> Maria Isabella Verdooren | B28: 0 | C28: 0 | D28: 0 | E28: 0 | F28: 0 | P28: =IF($A28="","",SUMIF($B$5:$O$5,">0",B28:O28)) -> 0 | Q28: =IF($A28="","",IF(SUM(B28:O28)<>P28,"⚠ There are horas en columnas fuera del periodo",IF(COUNTIF(B28:O28,"<0")>0,"⚠ Negative values",IF(COUNTIF(B28:O28,">24")>0,"⚠ More than 24 h in one day",""))))
A29: =IF(Roster!A27="","",Roster!A27) -> Juan Sebastian Bermudez | P29: =IF($A29="","",SUMIF($B$5:$O$5,">0",B29:O29)) -> 0 | Q29: =IF($A29="","",IF(SUM(B29:O29)<>P29,"⚠ There are horas en columnas fuera del periodo",IF(COUNTIF(B29:O29,"<0")>0,"⚠ Negative values",IF(COUNTIF(B29:O29,">24")>0,"⚠ More than 24 h in one day",""))))
A30: =IF(Roster!A28="","",Roster!A28) -> Laura Alfonso | P30: =IF($A30="","",SUMIF($B$5:$O$5,">0",B30:O30)) -> 0 | Q30: =IF($A30="","",IF(SUM(B30:O30)<>P30,"⚠ There are horas en columnas fuera del periodo",IF(COUNTIF(B30:O30,"<0")>0,"⚠ Negative values",IF(COUNTIF(B30:O30,">24")>0,"⚠ More than 24 h in one day",""))))
A31: =IF(Roster!A29="","",Roster!A29) -> Laura Escobar | P31: =IF($A31="","",SUMIF($B$5:$O$5,">0",B31:O31)) -> 0 | Q31: =IF($A31="","",IF(SUM(B31:O31)<>P31,"⚠ There are horas en columnas fuera del periodo",IF(COUNTIF(B31:O31,"<0")>0,"⚠ Negative values",IF(COUNTIF(B31:O31,">24")>0,"⚠ More than 24 h in one day",""))))
A32: =IF(Roster!A30="","",Roster!A30) -> Maria Fernanda López | P32: =IF($A32="","",SUMIF($B$5:$O$5,">0",B32:O32)) -> 0 | Q32: =IF($A32="","",IF(SUM(B32:O32)<>P32,"⚠ There are horas en columnas fuera del periodo",IF(COUNTIF(B32:O32,"<0")>0,"⚠ Negative values",IF(COUNTIF(B32:O32,">24")>0,"⚠ More than 24 h in one day",""))))
A33: =IF(Roster!A31="","",Roster!A31) -> Martin Fernandez Fernandez | P33: =IF($A33="","",SUMIF($B$5:$O$5,">0",B33:O33)) -> 0 | Q33: =IF($A33="","",IF(SUM(B33:O33)<>P33,"⚠ There are horas en columnas fuera del periodo",IF(COUNTIF(B33:O33,"<0")>0,"⚠ Negative values",IF(COUNTIF(B33:O33,">24")>0,"⚠ More than 24 h in one day",""))))
A34: =IF(Roster!A32="","",Roster!A32) -> Andrés Guerra | P34: =IF($A34="","",SUMIF($B$5:$O$5,">0",B34:O34)) -> 0 | Q34: =IF($A34="","",IF(SUM(B34:O34)<>P34,"⚠ There are horas en columnas fuera del periodo",IF(COUNTIF(B34:O34,"<0")>0,"⚠ Negative values",IF(COUNTIF(B34:O34,">24")>0,"⚠ More than 24 h in one day",""))))
A35: =IF(Roster!A33="","",Roster!A33) -> David Santiago Chinchilla | P35: =IF($A35="","",SUMIF($B$5:$O$5,">0",B35:O35)) -> 0 | Q35: =IF($A35="","",IF(SUM(B35:O35)<>P35,"⚠ There are horas en columnas fuera del periodo",IF(COUNTIF(B35:O35,"<0")>0,"⚠ Negative values",IF(COUNTIF(B35:O35,">24")>0,"⚠ More than 24 h in one day",""))))
A36: =IF(Roster!A34="","",Roster!A34) -> Isabella Salamanca | P36: =IF($A36="","",SUMIF($B$5:$O$5,">0",B36:O36)) -> 0 | Q36: =IF($A36="","",IF(SUM(B36:O36)<>P36,"⚠ There are horas en columnas fuera del periodo",IF(COUNTIF(B36:O36,"<0")>0,"⚠ Negative values",IF(COUNTIF(B36:O36,">24")>0,"⚠ More than 24 h in one day",""))))
A37: =IF(Roster!A35="","",Roster!A35) -> Gianny Nicolás Pereira | B37: 0 | C37: 4 | D37: 4 | E37: 12 | F37: 12 | P37: =IF($A37="","",SUMIF($B$5:$O$5,">0",B37:O37)) -> 32 | Q37: =IF($A37="","",IF(SUM(B37:O37)<>P37,"⚠ There are horas en columnas fuera del periodo",IF(COUNTIF(B37:O37,"<0")>0,"⚠ Negative values",IF(COUNTIF(B37:O37,">24")>0,"⚠ More than 24 h in one day",""))))
A38: =IF(Roster!A36="","",Roster!A36) -> Juan Sebastian Ramos | P38: =IF($A38="","",SUMIF($B$5:$O$5,">0",B38:O38)) -> 0 | Q38: =IF($A38="","",IF(SUM(B38:O38)<>P38,"⚠ There are horas en columnas fuera del periodo",IF(COUNTIF(B38:O38,"<0")>0,"⚠ Negative values",IF(COUNTIF(B38:O38,">24")>0,"⚠ More than 24 h in one day",""))))
A39: =IF(Roster!A37="","",Roster!A37) -> Karen Sofía Martínez | P39: =IF($A39="","",SUMIF($B$5:$O$5,">0",B39:O39)) -> 0 | Q39: =IF($A39="","",IF(SUM(B39:O39)<>P39,"⚠ There are horas en columnas fuera del periodo",IF(COUNTIF(B39:O39,"<0")>0,"⚠ Negative values",IF(COUNTIF(B39:O39,">24")>0,"⚠ More than 24 h in one day",""))))
A40: =IF(Roster!A38="","",Roster!A38) -> Jaime Macias | P40: =IF($A40="","",SUMIF($B$5:$O$5,">0",B40:O40)) -> 0 | Q40: =IF($A40="","",IF(SUM(B40:O40)<>P40,"⚠ There are horas en columnas fuera del periodo",IF(COUNTIF(B40:O40,"<0")>0,"⚠ Negative values",IF(COUNTIF(B40:O40,">24")>0,"⚠ More than 24 h in one day",""))))
A41: =IF(Roster!A39="","",Roster!A39) -> Nicolás Espitia | B41: 4 | C41: 4 | D41: 4 | E41: 12 | F41: 12 | P41: =IF($A41="","",SUMIF($B$5:$O$5,">0",B41:O41)) -> 36 | Q41: =IF($A41="","",IF(SUM(B41:O41)<>P41,"⚠ There are horas en columnas fuera del periodo",IF(COUNTIF(B41:O41,"<0")>0,"⚠ Negative values",IF(COUNTIF(B41:O41,">24")>0,"⚠ More than 24 h in one day",""))))
A42: =IF(Roster!A40="","",Roster!A40) -> Nicolás Lozano | P42: =IF($A42="","",SUMIF($B$5:$O$5,">0",B42:O42)) -> 0 | Q42: =IF($A42="","",IF(SUM(B42:O42)<>P42,"⚠ There are horas en columnas fuera del periodo",IF(COUNTIF(B42:O42,"<0")>0,"⚠ Negative values",IF(COUNTIF(B42:O42,">24")>0,"⚠ More than 24 h in one day",""))))
A43: =IF(Roster!A41="","",Roster!A41) -> Oscar Moreno | P43: =IF($A43="","",SUMIF($B$5:$O$5,">0",B43:O43)) -> 0 | Q43: =IF($A43="","",IF(SUM(B43:O43)<>P43,"⚠ There are horas en columnas fuera del periodo",IF(COUNTIF(B43:O43,"<0")>0,"⚠ Negative values",IF(COUNTIF(B43:O43,">24")>0,"⚠ More than 24 h in one day",""))))
A44: =IF(Roster!A42="","",Roster!A42) -> Santiago Vargas | P44: =IF($A44="","",SUMIF($B$5:$O$5,">0",B44:O44)) -> 0 | Q44: =IF($A44="","",IF(SUM(B44:O44)<>P44,"⚠ There are horas en columnas fuera del periodo",IF(COUNTIF(B44:O44,"<0")>0,"⚠ Negative values",IF(COUNTIF(B44:O44,">24")>0,"⚠ More than 24 h in one day",""))))
A45: =IF(Roster!A43="","",Roster!A43) -> Sara Calderon | P45: =IF($A45="","",SUMIF($B$5:$O$5,">0",B45:O45)) -> 0 | Q45: =IF($A45="","",IF(SUM(B45:O45)<>P45,"⚠ There are horas en columnas fuera del periodo",IF(COUNTIF(B45:O45,"<0")>0,"⚠ Negative values",IF(COUNTIF(B45:O45,">24")>0,"⚠ More than 24 h in one day",""))))
A46: TOTAL | B46: =IF(B$5="","",SUM(B6:B45)) -> 21 | C46: =IF(C$5="","",SUM(C6:C45)) -> 28 | D46: =IF(D$5="","",SUM(D6:D45)) -> 32 | E46: =IF(E$5="","",SUM(E6:E45)) -> 96 | F46: =IF(F$5="","",SUM(F6:F45)) -> 92 | G46: =IF(G$5="","",SUM(G6:G45)) -> 0 | H46: =IF(H$5="","",SUM(H6:H45)) -> 0 | I46: =IF(I$5="","",SUM(I6:I45)) -> 0 | ... O46: =IF(O$5="","",SUM(O6:O45)) | P46: =SUM(P6:P45) -> 269

Sheet RAW BTBS
A1: Time | B1: Status | C1: Approved / Rejected By | D1: Approved / Rejected Date | E1: Invoice Number | F1: Date | G1: Client | H1: Prospect | I1: County | J1: Legal Description | K1: Work Type | L1: Project | M1: Well Name | N1: Time Worked | O1: Date Time Entry Created | P1: Invoice Date | Q1: Client Landman | R1: Created By | S1: Modified By | T1: Modified Date | U1: Work Performed Detail | W1: Date (norm) | X1: Hours | Y1: Name norm. | Z1: Match key | AA1: In Roster? | AB1: In period? | AC1: Fingerprint (dup.) | AD1: Duplicate? | AE1: Entry | AF1: Final key | AG1: Record status | AH1: Location | AI1: Surname | AJ1: How it matched | AK1: #Project | AL1: #Client | AM1: #Prospect | AN1: #County | AO1: #Landman
A2: C Lara | B2: Approved | C2: L. Carollo | D2: 8/19/2026 | F2: 8/19/2026 | G2: Rocking WW Minerals, LLC | H2: RWW PRB Asset VDR | I2: Campbell, WY | J2: 05-41N-71W | K2: Title | M2: W2, Lots 7, 8, 9, 10, 15, 16, 17, 18 | N2: 0.25 | O2: 8/19/2026 1:26:56 PM | Q2: Whitney Wicks | R2: C Lara | S2: C Lara | T2: 8/19/2026 | U2: Pruned interest for 45 notecards. Reviewed notecard by notecard and selected subject land for those who didn't have it selected. | W2: =IF($F2="",0,IFERROR(IF(ISNUMBER($F2),INT($F2),DATE(VALUE(MID(SUBSTITUTE(LEFT($F2,FIND(" ",$F2&" ")-1),"/",REPT(" ",20)),41,20)),VALUE(LEFT(SUBSTITUTE(LEFT($F2,FIND(" ",$F2&" ")-1),"/",REPT(" ",20)),20)),VALUE(MID(SUBSTITUTE(LEFT($F2,FIND(" ",$F2&" ")-1),"/",REPT(" ",20)),21,20)))),0)) -> 46253 | X2: =IF(ISNUMBER($N2),$N2*Validation!$B$5,"") -> 2 | Y2: =IF($A2="","",SUBSTITUTE(SUBSTITUTE(SUBSTITUTE(SUBSTITUTE(SUBSTITUTE(SUBSTITUTE(SUBSTITUTE(UPPER(TRIM($A2)),"Á","A"),"É","E"),"Í","I"),"Ó","O"),"Ú","U"),"Ñ","N"),"Ü","U")) -> C LARA | Z2: =IF($Y2="","",LEFT($Y2,1)&" "&TRIM(RIGHT(SUBSTITUTE($Y2," ",REPT(" ",50)),50))) -> C LARA | AA2: =IF($AF2="","",IF(COUNTIF(Validation!$U$19:$U$178,$AF2)>0,"OK","NO MATCH")) -> OK | AB2: =IF($W2=0,"",IF(AND($W2>=Validation!$B$3,$W2<=Validation!$C$3),"Yes","No")) -> Yes | AC2: =IF($A2="","",$AF2&"|"&TEXT($W2,"yyyy-mm-dd")&"|"&$J2&"|"&$N2) -> C LARA|2026-08-19|05-41N-71W|0.25 | AD2: =IF($AC2="","",IF(COUNTIF($AC$2:$AC$3000,$AC2)>1,"REVIEW","OK")) -> OK | AE2: =IF(OR($W2=0,$O2=""),"",IF(IFERROR(IF(ISNUMBER($O2),INT($O2),DATE(VALUE(MID(SUBSTITUTE(LEFT($O2,FIND(" ",$O2&" ")-1),"/",REPT(" ",20)),41,20)),VALUE(LEFT(SUBSTITUTE(LEFT($O2,FIND(" ",$O2&" ")-1),"/",REPT(" ",20)),20)),VALUE(MID(SUBSTITUTE(LEFT($O2,FIND(" ",$O2&" ")-1),"/",REPT(" ",20)),21,20)))),0)>$W2,"Late","Same day")) -> Same day | AF2: =IF($A2="","",IFERROR(INDEX(Validation!$C$193:$C$217,MATCH($A2,Validation!$A$193:$A$217,0)),IF(COUNTIF(Validation!$U$19:$U$178,$Z2)>0,$Z2,IF(COUNTIF(Validation!$S$19:$S$178,$AI2)=1,INDEX(Validation!$U$19:$U$178,MATCH($AI2,Validation!$S$19:$S$178,0)),$Z2)))) -> C LARA | AG2: =IF(COUNTA($A2:$U2)=0,"",IF($A2="","No name",IF($F2="","No date",IF($W2=0,"Date ilegible",IF(NOT(ISNUMBER($N2)),"Hours no numéricas",IF($AA2="NO MATCH","Person no identificada","OK")))))) -> OK | AH2: =IF($W2=0,"No date",IF($W2<Validation!$B$3,"Before period",IF($W2>Validation!$C$3,"After period","In period"))) -> In period | AI2: =IF($Y2="","",TRIM(RIGHT(SUBSTITUTE($Y2," ",REPT(" ",50)),50))) -> LARA | AJ2: =IF($A2="","",IF(NOT(ISERROR(MATCH($A2,Validation!$A$193:$A$217,0))),"Manual mapping",IF(COUNTIF(Validation!$U$19:$U$178,$Z2)>0,"Direct",IF(COUNTIF(Validation!$S$19:$S$178,$AI2)=1,"By surname","Unresolved")))) -> Direct | AK2: =IF($L2="","",IF(MATCH($L2,$L$2:$L$3000,0)<>ROW()-1,"",COUNT($AK$1:$AK1)+1)) | AL2: =IF($G2="","",IF(MATCH($G2,$G$2:$G$3000,0)<>ROW()-1,"",COUNT($AL$1:$AL1)+1)) -> 1 | AM2: =IF($H2="","",IF(MATCH($H2,$H$2:$H$3000,0)<>ROW()-1,"",COUNT($AM$1:$AM1)+1)) -> 1 | AN2: =IF($I2="","",IF(MATCH($I2,$I$2:$I$3000,0)<>ROW()-1,"",COUNT($AN$1:$AN1)+1)) -> 1 | AO2: =IF($Q2="","",IF(MATCH($Q2,$Q$2:$Q$3000,0)<>ROW()-1,"",COUNT($AO$1:$AO1)+1)) -> 1
A3: C Lara | B3: Approved | C3: L. Carollo | D3: 8/19/2026 | F3: 8/19/2026 | G3: Rocking WW Minerals, LLC | H3: RWW PRB Asset VDR | I3: Converse, WY | J3: 12-35N-70W | K3: Title | M3: NESE | N3: 0.125 | O3: 8/19/2026 1:42:49 PM | Q3: Whitney Wicks | R3: C Lara | S3: C Lara | T3: 8/19/2026 | U3: Pruned interest for 2 notecards. Selected subject land for notecards that didn't have it selected. Downloaded from iDoc and uploaded to AOI document where RWW received interest. | W3: =IF($F3="",0,IFERROR(IF(ISNUMBER($F3),INT($F3),DATE(VALUE(MID(SUBSTITUTE(LEFT($F3,FIND(" ",$F3&" ")-1),"/",REPT(" ",20)),41,20)),VALUE(LEFT(SUBSTITUTE(LEFT($F3,FIND(" ",$F3&" ")-1),"/",REPT(" ",20)),20)),VALUE(MID(SUBSTITUTE(LEFT($F3,FIND(" ",$F3&" ")-1),"/",REPT(" ",20)),21,20)))),0)) -> 46253 | X3: =IF(ISNUMBER($N3),$N3*Validation!$B$5,"") -> 1 | Y3: =IF($A3="","",SUBSTITUTE(SUBSTITUTE(SUBSTITUTE(SUBSTITUTE(SUBSTITUTE(SUBSTITUTE(SUBSTITUTE(UPPER(TRIM($A3)),"Á","A"),"É","E"),"Í","I"),"Ó","O"),"Ú","U"),"Ñ","N"),"Ü","U")) -> C LARA | Z3: =IF($Y3="","",LEFT($Y3,1)&" "&TRIM(RIGHT(SUBSTITUTE($Y3," ",REPT(" ",50)),50))) -> C LARA | AA3: =IF($AF3="","",IF(COUNTIF(Validation!$U$19:$U$178,$AF3)>0,"OK","NO MATCH")) -> OK | AB3: =IF($W3=0,"",IF(AND($W3>=Validation!$B$3,$W3<=Validation!$C$3),"Yes","No")) -> Yes | AC3: =IF($A3="","",$AF3&"|"&TEXT($W3,"yyyy-mm-dd")&"|"&$J3&"|"&$N3) -> C LARA|2026-08-19|12-35N-70W|0.125 | AD3: =IF($AC3="","",IF(COUNTIF($AC$2:$AC$3000,$AC3)>1,"REVIEW","OK")) -> OK | AE3: =IF(OR($W3=0,$O3=""),"",IF(IFERROR(IF(ISNUMBER($O3),INT($O3),DATE(VALUE(MID(SUBSTITUTE(LEFT($O3,FIND(" ",$O3&" ")-1),"/",REPT(" ",20)),41,20)),VALUE(LEFT(SUBSTITUTE(LEFT($O3,FIND(" ",$O3&" ")-1),"/",REPT(" ",20)),20)),VALUE(MID(SUBSTITUTE(LEFT($O3,FIND(" ",$O3&" ")-1),"/",REPT(" ",20)),21,20)))),0)>$W3,"Late","Same day")) -> Same day | AF3: =IF($A3="","",IFERROR(INDEX(Validation!$C$193:$C$217,MATCH($A3,Validation!$A$193:$A$217,0)),IF(COUNTIF(Validation!$U$19:$U$178,$Z3)>0,$Z3,IF(COUNTIF(Validation!$S$19:$S$178,$AI3)=1,INDEX(Validation!$U$19:$U$178,MATCH($AI3,Validation!$S$19:$S$178,0)),$Z3)))) -> C LARA | AG3: =IF(COUNTA($A3:$U3)=0,"",IF($A3="","No name",IF($F3="","No date",IF($W3=0,"Date ilegible",IF(NOT(ISNUMBER($N3)),"Hours no numéricas",IF($AA3="NO MATCH","Person no identificada","OK")))))) -> OK | AH3: =IF($W3=0,"No date",IF($W3<Validation!$B$3,"Before period",IF($W3>Validation!$C$3,"After period","In period"))) -> In period | AI3: =IF($Y3="","",TRIM(RIGHT(SUBSTITUTE($Y3," ",REPT(" ",50)),50))) -> LARA | AJ3: =IF($A3="","",IF(NOT(ISERROR(MATCH($A3,Validation!$A$193:$A$217,0))),"Manual mapping",IF(COUNTIF(Validation!$U$19:$U$178,$Z3)>0,"Direct",IF(COUNTIF(Validation!$S$19:$S$178,$AI3)=1,"By surname","Unresolved")))) -> Direct | AK3: =IF($L3="","",IF(MATCH($L3,$L$2:$L$3000,0)<>ROW()-1,"",COUNT($AK$1:$AK2)+1)) | AL3: =IF($G3="","",IF(MATCH($G3,$G$2:$G$3000,0)<>ROW()-1,"",COUNT($AL$1:$AL2)+1)) | AM3: =IF($H3="","",IF(MATCH($H3,$H$2:$H$3000,0)<>ROW()-1,"",COUNT($AM$1:$AM2)+1)) | AN3: =IF($I3="","",IF(MATCH($I3,$I$2:$I$3000,0)<>ROW()-1,"",COUNT($AN$1:$AN2)+1)) -> 2 | AO3: =IF($Q3="","",IF(MATCH($Q3,$Q$2:$Q$3000,0)<>ROW()-1,"",COUNT($AO$1:$AO2)+1))
A4: C Lara | B4: Approved | C4: L. Carollo | D4: 8/19/2026 | F4: 8/19/2026 | G4: Rocking WW Minerals, LLC | H4: RWW PRB Asset VDR | I4: Converse, WY | J4: 09-35N-69W | K4: Title | M4: NWNW, NENE, SW, SE | N4: 0.25 | O4: 8/20/2026 12:15:12 AM | Q4: Whitney Wicks | R4: C Lara | S4: C Lara | T4: 8/20/2026 | U4: Pruned interest for 2 notecards. Reviewed notecard by notecard and selected subject land for those who didn't have it selected. Created SW and SW polygons. Downloaded from iDoc and uploaded to AOI document where RWW received interest. Multiple notecards don't light-up in chain, issue starting at clients AOI. | W4: =IF($F4="",0,IFERROR(IF(ISNUMBER($F4),INT($F4),DATE(VALUE(MID(SUBSTITUTE(LEFT($F4,FIND(" ",$F4&" ")-1),"/",REPT(" ",20)),41,20)),VALUE(LEFT(SUBSTITUTE(LEFT($F4,FIND(" ",$F4&" ")-1),"/",REPT(" ",20)),20)),VALUE(MID(SUBSTITUTE(LEFT($F4,FIND(" ",$F4&" ")-1),"/",REPT(" ",20)),21,20)))),0)) -> 46253 | X4: =IF(ISNUMBER($N4),$N4*Validation!$B$5,"") -> 2 | Y4: =IF($A4="","",SUBSTITUTE(SUBSTITUTE(SUBSTITUTE(SUBSTITUTE(SUBSTITUTE(SUBSTITUTE(SUBSTITUTE(UPPER(TRIM($A4)),"Á","A"),"É","E"),"Í","I"),"Ó","O"),"Ú","U"),"Ñ","N"),"Ü","U")) -> C LARA | Z4: =IF($Y4="","",LEFT($Y4,1)&" "&TRIM(RIGHT(SUBSTITUTE($Y4," ",REPT(" ",50)),50))) -> C LARA | AA4: =IF($AF4="","",IF(COUNTIF(Validation!$U$19:$U$178,$AF4)>0,"OK","NO MATCH")) -> OK | AB4: =IF($W4=0,"",IF(AND($W4>=Validation!$B$3,$W4<=Validation!$C$3),"Yes","No")) -> Yes | AC4: =IF($A4="","",$AF4&"|"&TEXT($W4,"yyyy-mm-dd")&"|"&$J4&"|"&$N4) -> C LARA|2026-08-19|09-35N-69W|0.25 | AD4: =IF($AC4="","",IF(COUNTIF($AC$2:$AC$3000,$AC4)>1,"REVIEW","OK")) -> OK | AE4: =IF(OR($W4=0,$O4=""),"",IF(IFERROR(IF(ISNUMBER($O4),INT($O4),DATE(VALUE(MID(SUBSTITUTE(LEFT($O4,FIND(" ",$O4&" ")-1),"/",REPT(" ",20)),41,20)),VALUE(LEFT(SUBSTITUTE(LEFT($O4,FIND(" ",$O4&" ")-1),"/",REPT(" ",20)),20)),VALUE(MID(SUBSTITUTE(LEFT($O4,FIND(" ",$O4&" ")-1),"/",REPT(" ",20)),21,20)))),0)>$W4,"Late","Same day")) -> Late | AF4: =IF($A4="","",IFERROR(INDEX(Validation!$C$193:$C$217,MATCH($A4,Validation!$A$193:$A$217,0)),IF(COUNTIF(Validation!$U$19:$U$178,$Z4)>0,$Z4,IF(COUNTIF(Validation!$S$19:$S$178,$AI4)=1,INDEX(Validation!$U$19:$U$178,MATCH($AI4,Validation!$S$19:$S$178,0)),$Z4)))) -> C LARA | AG4: =IF(COUNTA($A4:$U4)=0,"",IF($A4="","No name",IF($F4="","No date",IF($W4=0,"Date ilegible",IF(NOT(ISNUMBER($N4)),"Hours no numéricas",IF($AA4="NO MATCH","Person no identificada","OK")))))) -> OK | AH4: =IF($W4=0,"No date",IF($W4<Validation!$B$3,"Before period",IF($W4>Validation!$C$3,"After period","In period"))) -> In period | AI4: =IF($Y4="","",TRIM(RIGHT(SUBSTITUTE($Y4," ",REPT(" ",50)),50))) -> LARA | AJ4: =IF($A4="","",IF(NOT(ISERROR(MATCH($A4,Validation!$A$193:$A$217,0))),"Manual mapping",IF(COUNTIF(Validation!$U$19:$U$178,$Z4)>0,"Direct",IF(COUNTIF(Validation!$S$19:$S$178,$AI4)=1,"By surname","Unresolved")))) -> Direct | AK4: =IF($L4="","",IF(MATCH($L4,$L$2:$L$3000,0)<>ROW()-1,"",COUNT($AK$1:$AK3)+1)) | AL4: =IF($G4="","",IF(MATCH($G4,$G$2:$G$3000,0)<>ROW()-1,"",COUNT($AL$1:$AL3)+1)) | AM4: =IF($H4="","",IF(MATCH($H4,$H$2:$H$3000,0)<>ROW()-1,"",COUNT($AM$1:$AM3)+1)) | AN4: =IF($I4="","",IF(MATCH($I4,$I$2:$I$3000,0)<>ROW()-1,"",COUNT($AN$1:$AN3)+1)) | AO4: =IF($Q4="","",IF(MATCH($Q4,$Q$2:$Q$3000,0)<>ROW()-1,"",COUNT($AO$1:$AO3)+1))
A5: C Lara | B5: Approved | C5: L. Carollo | D5: 8/19/2026 | F5: 8/19/2026 | G5: Rocking WW Minerals, LLC | H5: RWW PRB Asset VDR | I5: Campbell, WY | J5: 06-41N-73W | K5: Title | M5: NESE | N5: 0.125 | O5: 8/20/2026 12:17:58 AM | Q5: Whitney Wicks | R5: C Lara | S5: C Lara | T5: 8/20/2026 | U5: No need to prune interest. Selected subject land for notecards that didn't have it selected. Downloaded from iDoc and uploaded to AOI document where RWW received interest. | W5: =IF($F5="",0,IFERROR(IF(ISNUMBER($F5),INT($F5),DATE(VALUE(MID(SUBSTITUTE(LEFT($F5,FIND(" ",$F5&" ")-1),"/",REPT(" ",20)),41,20)),VALUE(LEFT(SUBSTITUTE(LEFT($F5,FIND(" ",$F5&" ")-1),"/",REPT(" ",20)),20)),VALUE(MID(SUBSTITUTE(LEFT($F5,FIND(" ",$F5&" ")-1),"/",REPT(" ",20)),21,20)))),0)) -> 46253 | X5: =IF(ISNUMBER($N5),$N5*Validation!$B$5,"") -> 1 | Y5: =IF($A5="","",SUBSTITUTE(SUBSTITUTE(SUBSTITUTE(SUBSTITUTE(SUBSTITUTE(SUBSTITUTE(SUBSTITUTE(UPPER(TRIM($A5)),"Á","A"),"É","E"),"Í","I"),"Ó","O"),"Ú","U"),"Ñ","N"),"Ü","U")) -> C LARA | Z5: =IF($Y5="","",LEFT($Y5,1)&" "&TRIM(RIGHT(SUBSTITUTE($Y5," ",REPT(" ",50)),50))) -> C LARA | AA5: =IF($AF5="","",IF(COUNTIF(Validation!$U$19:$U$178,$AF5)>0,"OK","NO MATCH")) -> OK | AB5: =IF($W5=0,"",IF(AND($W5>=Validation!$B$3,$W5<=Validation!$C$3),"Yes","No")) -> Yes | AC5: =IF($A5="","",$AF5&"|"&TEXT($W5,"yyyy-mm-dd")&"|"&$J5&"|"&$N5) -> C LARA|2026-08-19|06-41N-73W|0.125 | AD5: =IF($AC5="","",IF(COUNTIF($AC$2:$AC$3000,$AC5)>1,"REVIEW","OK")) -> OK | AE5: =IF(OR($W5=0,$O5=""),"",IF(IFERROR(IF(ISNUMBER($O5),INT($O5),DATE(VALUE(MID(SUBSTITUTE(LEFT($O5,FIND(" ",$O5&" ")-1),"/",REPT(" ",20)),41,20)),VALUE(LEFT(SUBSTITUTE(LEFT($O5,FIND(" ",$O5&" ")-1),"/",REPT(" ",20)),20)),VALUE(MID(SUBSTITUTE(LEFT($O5,FIND(" ",$O5&" ")-1),"/",REPT(" ",20)),21,20)))),0)>$W5,"Late","Same day")) -> Late | AF5: =IF($A5="","",IFERROR(INDEX(Validation!$C$193:$C$217,MATCH($A5,Validation!$A$193:$A$217,0)),IF(COUNTIF(Validation!$U$19:$U$178,$Z5)>0,$Z5,IF(COUNTIF(Validation!$S$19:$S$178,$AI5)=1,INDEX(Validation!$U$19:$U$178,MATCH($AI5,Validation!$S$19:$S$178,0)),$Z5)))) -> C LARA | AG5: =IF(COUNTA($A5:$U5)=0,"",IF($A5="","No name",IF($F5="","No date",IF($W5=0,"Date ilegible",IF(NOT(ISNUMBER($N5)),"Hours no numéricas",IF($AA5="NO MATCH","Person no identificada","OK")))))) -> OK | AH5: =IF($W5=0,"No date",IF($W5<Validation!$B$3,"Before period",IF($W5>Validation!$C$3,"After period","In period"))) -> In period | AI5: =IF($Y5="","",TRIM(RIGHT(SUBSTITUTE($Y5," ",REPT(" ",50)),50))) -> LARA | AJ5: =IF($A5="","",IF(NOT(ISERROR(MATCH($A5,Validation!$A$193:$A$217,0))),"Manual mapping",IF(COUNTIF(Validation!$U$19:$U$178,$Z5)>0,"Direct",IF(COUNTIF(Validation!$S$19:$S$178,$AI5)=1,"By surname","Unresolved")))) -> Direct | AK5: =IF($L5="","",IF(MATCH($L5,$L$2:$L$3000,0)<>ROW()-1,"",COUNT($AK$1:$AK4)+1)) | AL5: =IF($G5="","",IF(MATCH($G5,$G$2:$G$3000,0)<>ROW()-1,"",COUNT($AL$1:$AL4)+1)) | AM5: =IF($H5="","",IF(MATCH($H5,$H$2:$H$3000,0)<>ROW()-1,"",COUNT($AM$1:$AM4)+1)) | AN5: =IF($I5="","",IF(MATCH($I5,$I$2:$I$3000,0)<>ROW()-1,"",COUNT($AN$1:$AN4)+1)) | AO5: =IF($Q5="","",IF(MATCH($Q5,$Q$2:$Q$3000,0)<>ROW()-1,"",COUNT($AO$1:$AO4)+1))
A6: C Lara | B6: Approved | C6: L. Carollo | D6: 8/19/2026 | F6: 8/19/2026 | G6: Rocking WW Minerals, LLC | H6: RWW PRB Asset VDR | I6: Converse, WY | J6: 09-36N-71W | K6: Title | M6: SW | N6: 0.25 | O6: 8/20/2026 1:17:35 AM | Q6: Whitney Wicks | R6: C Lara | S6: C Lara | T6: 8/20/2026 | U6: Pruned interest for 6 notecards. Reviewed notecard by notecard and selected subject land for those who didn't have it selected. Downloaded from iDoc and uploaded to AOI document where RWW received interest. A couple notecards don't light-up in chain, issue starting at clients AOI. | W6: =IF($F6="",0,IFERROR(IF(ISNUMBER($F6),INT($F6),DATE(VALUE(MID(SUBSTITUTE(LEFT($F6,FIND(" ",$F6&" ")-1),"/",REPT(" ",20)),41,20)),VALUE(LEFT(SUBSTITUTE(LEFT($F6,FIND(" ",$F6&" ")-1),"/",REPT(" ",20)),20)),VALUE(MID(SUBSTITUTE(LEFT($F6,FIND(" ",$F6&" ")-1),"/",REPT(" ",20)),21,20)))),0)) -> 46253 | X6: =IF(ISNUMBER($N6),$N6*Validation!$B$5,"") -> 2 | Y6: =IF($A6="","",SUBSTITUTE(SUBSTITUTE(SUBSTITUTE(SUBSTITUTE(SUBSTITUTE(SUBSTITUTE(SUBSTITUTE(UPPER(TRIM($A6)),"Á","A"),"É","E"),"Í","I"),"Ó","O"),"Ú","U"),"Ñ","N"),"Ü","U")) -> C LARA | Z6: =IF($Y6="","",LEFT($Y6,1)&" "&TRIM(RIGHT(SUBSTITUTE($Y6," ",REPT(" ",50)),50))) -> C LARA | AA6: =IF($AF6="","",IF(COUNTIF(Validation!$U$19:$U$178,$AF6)>0,"OK","NO MATCH")) -> OK | AB6: =IF($W6=0,"",IF(AND($W6>=Validation!$B$3,$W6<=Validation!$C$3),"Yes","No")) -> Yes | AC6: =IF($A6="","",$AF6&"|"&TEXT($W6,"yyyy-mm-dd")&"|"&$J6&"|"&$N6) -> C LARA|2026-08-19|09-36N-71W|0.25 | AD6: =IF($AC6="","",IF(COUNTIF($AC$2:$AC$3000,$AC6)>1,"REVIEW","OK")) -> OK | AE6: =IF(OR($W6=0,$O6=""),"",IF(IFERROR(IF(ISNUMBER($O6),INT($O6),DATE(VALUE(MID(SUBSTITUTE(LEFT($O6,FIND(" ",$O6&" ")-1),"/",REPT(" ",20)),41,20)),VALUE(LEFT(SUBSTITUTE(LEFT($O6,FIND(" ",$O6&" ")-1),"/",REPT(" ",20)),20)),VALUE(MID(SUBSTITUTE(LEFT($O6,FIND(" ",$O6&" ")-1),"/",REPT(" ",20)),21,20)))),0)>$W6,"Late","Same day")) -> Late | AF6: =IF($A6="","",IFERROR(INDEX(Validation!$C$193:$C$217,MATCH($A6,Validation!$A$193:$A$217,0)),IF(COUNTIF(Validation!$U$19:$U$178,$Z6)>0,$Z6,IF(COUNTIF(Validation!$S$19:$S$178,$AI6)=1,INDEX(Validation!$U$19:$U$178,MATCH($AI6,Validation!$S$19:$S$178,0)),$Z6)))) -> C LARA | AG6: =IF(COUNTA($A6:$U6)=0,"",IF($A6="","No name",IF($F6="","No date",IF($W6=0,"Date ilegible",IF(NOT(ISNUMBER($N6)),"Hours no numéricas",IF($AA6="NO MATCH","Person no identificada","OK")))))) -> OK | AH6: =IF($W6=0,"No date",IF($W6<Validation!$B$3,"Before period",IF($W6>Validation!$C$3,"After period","In period"))) -> In period | AI6: =IF($Y6="","",TRIM(RIGHT(SUBSTITUTE($Y6," ",REPT(" ",50)),50))) -> LARA | AJ6: =IF($A6="","",IF(NOT(ISERROR(MATCH($A6,Validation!$A$193:$A$217,0))),"Manual mapping",IF(COUNTIF(Validation!$U$19:$U$178,$Z6)>0,"Direct",IF(COUNTIF(Validation!$S$19:$S$178,$AI6)=1,"By surname","Unresolved")))) -> Direct | AK6: =IF($L6="","",IF(MATCH($L6,$L$2:$L$3000,0)<>ROW()-1,"",COUNT($AK$1:$AK5)+1)) | AL6: =IF($G6="","",IF(MATCH($G6,$G$2:$G$3000,0)<>ROW()-1,"",COUNT($AL$1:$AL5)+1)) | AM6: =IF($H6="","",IF(MATCH($H6,$H$2:$H$3000,0)<>ROW()-1,"",COUNT($AM$1:$AM5)+1)) | AN6: =IF($I6="","",IF(MATCH($I6,$I$2:$I$3000,0)<>ROW()-1,"",COUNT($AN$1:$AN5)+1)) | AO6: =IF($Q6="","",IF(MATCH($Q6,$Q$2:$Q$3000,0)<>ROW()-1,"",COUNT($AO$1:$AO5)+1))
A7: C Lara | B7: Approved | C7: L. Carollo | D7: 8/19/2026 | F7: 8/19/2026 | G7: Rocking WW Minerals, LLC | H7: RWW PRB Asset VDR | I7: Converse, WY | J7: 01-34N-69W | K7: Title | M7: SWSW, Lot 4, SWNW, NWSW | N7: 0.25 | O7: 8/20/2026 2:27:00 AM | Q7: Whitney Wicks | R7: C Lara | S7: C Lara | T7: 8/20/2026 | U7: Pruned interest for 33 notecards. Reviewed notecard by notecard and selected subject land for those who didn't have it selected. Created polygons for Lot 4, SWNW, NWSW. Most notecards don't light-up in chain. Assignment set on hold. | W7: =IF($F7="",0,IFERROR(IF(ISNUMBER($F7),INT($F7),DATE(VALUE(MID(SUBSTITUTE(LEFT($F7,FIND(" ",$F7&" ")-1),"/",REPT(" ",20)),41,20)),VALUE(LEFT(SUBSTITUTE(LEFT($F7,FIND(" ",$F7&" ")-1),"/",REPT(" ",20)),20)),VALUE(MID(SUBSTITUTE(LEFT($F7,FIND(" ",$F7&" ")-1),"/",REPT(" ",20)),21,20)))),0)) -> 46253 | X7: =IF(ISNUMBER($N7),$N7*Validation!$B$5,"") -> 2 | Y7: =IF($A7="","",SUBSTITUTE(SUBSTITUTE(SUBSTITUTE(SUBSTITUTE(SUBSTITUTE(SUBSTITUTE(SUBSTITUTE(UPPER(TRIM($A7)),"Á","A"),"É","E"),"Í","I"),"Ó","O"),"Ú","U"),"Ñ","N"),"Ü","U")) -> C LARA | Z7: =IF($Y7="","",LEFT($Y7,1)&" "&TRIM(RIGHT(SUBSTITUTE($Y7," ",REPT(" ",50)),50))) -> C LARA | AA7: =IF($AF7="","",IF(COUNTIF(Validation!$U$19:$U$178,$AF7)>0,"OK","NO MATCH")) -> OK | AB7: =IF($W7=0,"",IF(AND($W7>=Validation!$B$3,$W7<=Validation!$C$3),"Yes","No")) -> Yes | AC7: =IF($A7="","",$AF7&"|"&TEXT($W7,"yyyy-mm-dd")&"|"&$J7&"|"&$N7) -> C LARA|2026-08-19|01-34N-69W|0.25 | AD7: =IF($AC7="","",IF(COUNTIF($AC$2:$AC$3000,$AC7)>1,"REVIEW","OK")) -> OK | AE7: =IF(OR($W7=0,$O7=""),"",IF(IFERROR(IF(ISNUMBER($O7),INT($O7),DATE(VALUE(MID(SUBSTITUTE(LEFT($O7,FIND(" ",$O7&" ")-1),"/",REPT(" ",20)),41,20)),VALUE(LEFT(SUBSTITUTE(LEFT($O7,FIND(" ",$O7&" ")-1),"/",REPT(" ",20)),20)),VALUE(MID(SUBSTITUTE(LEFT($O7,FIND(" ",$O7&" ")-1),"/",REPT(" ",20)),21,20)))),0)>$W7,"Late","Same day")) -> Late | AF7: =IF($A7="","",IFERROR(INDEX(Validation!$C$193:$C$217,MATCH($A7,Validation!$A$193:$A$217,0)),IF(COUNTIF(Validation!$U$19:$U$178,$Z7)>0,$Z7,IF(COUNTIF(Validation!$S$19:$S$178,$AI7)=1,INDEX(Validation!$U$19:$U$178,MATCH($AI7,Validation!$S$19:$S$178,0)),$Z7)))) -> C LARA | AG7: =IF(COUNTA($A7:$U7)=0,"",IF($A7="","No name",IF($F7="","No date",IF($W7=0,"Date ilegible",IF(NOT(ISNUMBER($N7)),"Hours no numéricas",IF($AA7="NO MATCH","Person no identificada","OK")))))) -> OK | AH7: =IF($W7=0,"No date",IF($W7<Validation!$B$3,"Before period",IF($W7>Validation!$C$3,"After period","In period"))) -> In period | AI7: =IF($Y7="","",TRIM(RIGHT(SUBSTITUTE($Y7," ",REPT(" ",50)),50))) -> LARA | AJ7: =IF($A7="","",IF(NOT(ISERROR(MATCH($A7,Validation!$A$193:$A$217,0))),"Manual mapping",IF(COUNTIF(Validation!$U$19:$U$178,$Z7)>0,"Direct",IF(COUNTIF(Validation!$S$19:$S$178,$AI7)=1,"By surname","Unresolved")))) -> Direct | AK7: =IF($L7="","",IF(MATCH($L7,$L$2:$L$3000,0)<>ROW()-1,"",COUNT($AK$1:$AK6)+1)) | AL7: =IF($G7="","",IF(MATCH($G7,$G$2:$G$3000,0)<>ROW()-1,"",COUNT($AL$1:$AL6)+1)) | AM7: =IF($H7="","",IF(MATCH($H7,$H$2:$H$3000,0)<>ROW()-1,"",COUNT($AM$1:$AM6)+1)) | AN7: =IF($I7="","",IF(MATCH($I7,$I$2:$I$3000,0)<>ROW()-1,"",COUNT($AN$1:$AN6)+1)) | AO7: =IF($Q7="","",IF(MATCH($Q7,$Q$2:$Q$3000,0)<>ROW()-1,"",COUNT($AO$1:$AO6)+1))
A8: C Lara | B8: Unapproved | F8: 8/19/2026 | G8: Rocking WW Minerals, LLC | H8: RWW PRB Asset VDR | I8: Campbell, WY | J8: 09-41N-73W | K8: Title | M8: SE, S2NE, NESW, NENE, SENW | N8: 0.25 | O8: 8/20/2026 3:21:09 AM | Q8: Whitney Wicks | R8: C Lara | S8: C Lara | T8: 8/20/2026 | U8: Pruned interest for 71 notecards. Reviewed notecard by notecard and selected subject land for those who didn't have it selected. Included missing documents from second AOI from clients. Other documents were already included, therefore, no need to clone second AOI on first. | W8: =IF($F8="",0,IFERROR(IF(ISNUMBER($F8),INT($F8),DATE(VALUE(MID(SUBSTITUTE(LEFT($F8,FIND(" ",$F8&" ")-1),"/",REPT(" ",20)),41,20)),VALUE(LEFT(SUBSTITUTE(LEFT($F8,FIND(" ",$F8&" ")-1),"/",REPT(" ",20)),20)),VALUE(MID(SUBSTITUTE(LEFT($F8,FIND(" ",$F8&" ")-1),"/",REPT(" ",20)),21,20)))),0)) -> 46253 | X8: =IF(ISNUMBER($N8),$N8*Validation!$B$5,"") -> 2 | Y8: =IF($A8="","",SUBSTITUTE(SUBSTITUTE(SUBSTITUTE(SUBSTITUTE(SUBSTITUTE(SUBSTITUTE(SUBSTITUTE(UPPER(TRIM($A8)),"Á","A"),"É","E"),"Í","I"),"Ó","O"),"Ú","U"),"Ñ","N"),"Ü","U")) -> C LARA | Z8: =IF($Y8="","",LEFT($Y8,1)&" "&TRIM(RIGHT(SUBSTITUTE($Y8," ",REPT(" ",50)),50))) -> C LARA | AA8: =IF($AF8="","",IF(COUNTIF(Validation!$U$19:$U$178,$AF8)>0,"OK","NO MATCH")) -> OK | AB8: =IF($W8=0,"",IF(AND($W8>=Validation!$B$3,$W8<=Validation!$C$3),"Yes","No")) -> Yes | AC8: =IF($A8="","",$AF8&"|"&TEXT($W8,"yyyy-mm-dd")&"|"&$J8&"|"&$N8) -> C LARA|2026-08-19|09-41N-73W|0.25 | AD8: =IF($AC8="","",IF(COUNTIF($AC$2:$AC$3000,$AC8)>1,"REVIEW","OK")) -> OK | AE8: =IF(OR($W8=0,$O8=""),"",IF(IFERROR(IF(ISNUMBER($O8),INT($O8),DATE(VALUE(MID(SUBSTITUTE(LEFT($O8,FIND(" ",$O8&" ")-1),"/",REPT(" ",20)),41,20)),VALUE(LEFT(SUBSTITUTE(LEFT($O8,FIND(" ",$O8&" ")-1),"/",REPT(" ",20)),20)),VALUE(MID(SUBSTITUTE(LEFT($O8,FIND(" ",$O8&" ")-1),"/",REPT(" ",20)),21,20)))),0)>$W8,"Late","Same day")) -> Late | AF8: =IF($A8="","",IFERROR(INDEX(Validation!$C$193:$C$217,MATCH($A8,Validation!$A$193:$A$217,0)),IF(COUNTIF(Validation!$U$19:$U$178,$Z8)>0,$Z8,IF(COUNTIF(Validation!$S$19:$S$178,$AI8)=1,INDEX(Validation!$U$19:$U$178,MATCH($AI8,Validation!$S$19:$S$178,0)),$Z8)))) -> C LARA | AG8: =IF(COUNTA($A8:$U8)=0,"",IF($A8="","No name",IF($F8="","No date",IF($W8=0,"Date ilegible",IF(NOT(ISNUMBER($N8)),"Hours no numéricas",IF($AA8="NO MATCH","Person no identificada","OK")))))) -> OK | AH8: =IF($W8=0,"No date",IF($W8<Validation!$B$3,"Before period",IF($W8>Validation!$C$3,"After period","In period"))) -> In period | AI8: =IF($Y8="","",TRIM(RIGHT(SUBSTITUTE($Y8," ",REPT(" ",50)),50))) -> LARA | AJ8: =IF($A8="","",IF(NOT(ISERROR(MATCH($A8,Validation!$A$193:$A$217,0))),"Manual mapping",IF(COUNTIF(Validation!$U$19:$U$178,$Z8)>0,"Direct",IF(COUNTIF(Validation!$S$19:$S$178,$AI8)=1,"By surname","Unresolved")))) -> Direct | AK8: =IF($L8="","",IF(MATCH($L8,$L$2:$L$3000,0)<>ROW()-1,"",COUNT($AK$1:$AK7)+1)) | AL8: =IF($G8="","",IF(MATCH($G8,$G$2:$G$3000,0)<>ROW()-1,"",COUNT($AL$1:$AL7)+1)) | AM8: =IF($H8="","",IF(MATCH($H8,$H$2:$H$3000,0)<>ROW()-1,"",COUNT($AM$1:$AM7)+1)) | AN8: =IF($I8="","",IF(MATCH($I8,$I$2:$I$3000,0)<>ROW()-1,"",COUNT($AN$1:$AN7)+1)) | AO8: =IF($Q8="","",IF(MATCH($Q8,$Q$2:$Q$3000,0)<>ROW()-1,"",COUNT($AO$1:$AO7)+1))
A9: C Mesa | B9: Approved | C9: L. Carollo | D9: 8/19/2026 | F9: 8/19/2026 | G9: Rocking WW Minerals, LLC | H9: RWW PRB Asset VDR | I9: Converse, WY | J9: 18-36N-70W | K9: Title | M9: Lot 3, S2NE, NESW | N9: 0.25 | O9: 8/19/2026 8:05:17 PM | Q9: Whitney Wicks | R9: C Mesa | S9: C Mesa | T9: 8/19/2026 | U9: Pruned the AOI from RWW Minerals to the source deed | W9: =IF($F9="",0,IFERROR(IF(ISNUMBER($F9),INT($F9),DATE(VALUE(MID(SUBSTITUTE(LEFT($F9,FIND(" ",$F9&" ")-1),"/",REPT(" ",20)),41,20)),VALUE(LEFT(SUBSTITUTE(LEFT($F9,FIND(" ",$F9&" ")-1),"/",REPT(" ",20)),20)),VALUE(MID(SUBSTITUTE(LEFT($F9,FIND(" ",$F9&" ")-1),"/",REPT(" ",20)),21,20)))),0)) -> 46253 | X9: =IF(ISNUMBER($N9),$N9*Validation!$B$5,"") -> 2 | Y9: =IF($A9="","",SUBSTITUTE(SUBSTITUTE(SUBSTITUTE(SUBSTITUTE(SUBSTITUTE(SUBSTITUTE(SUBSTITUTE(UPPER(TRIM($A9)),"Á","A"),"É","E"),"Í","I"),"Ó","O"),"Ú","U"),"Ñ","N"),"Ü","U")) -> C MESA | Z9: =IF($Y9="","",LEFT($Y9,1)&" "&TRIM(RIGHT(SUBSTITUTE($Y9," ",REPT(" ",50)),50))) -> C MESA | AA9: =IF($AF9="","",IF(COUNTIF(Validation!$U$19:$U$178,$AF9)>0,"OK","NO MATCH")) -> OK | AB9: =IF($W9=0,"",IF(AND($W9>=Validation!$B$3,$W9<=Validation!$C$3),"Yes","No")) -> Yes | AC9: =IF($A9="","",$AF9&"|"&TEXT($W9,"yyyy-mm-dd")&"|"&$J9&"|"&$N9) -> C MESA|2026-08-19|18-36N-70W|0.25 | AD9: =IF($AC9="","",IF(COUNTIF($AC$2:$AC$3000,$AC9)>1,"REVIEW","OK")) -> OK | AE9: =IF(OR($W9=0,$O9=""),"",IF(IFERROR(IF(ISNUMBER($O9),INT($O9),DATE(VALUE(MID(SUBSTITUTE(LEFT($O9,FIND(" ",$O9&" ")-1),"/",REPT(" ",20)),41,20)),VALUE(LEFT(SUBSTITUTE(LEFT($O9,FIND(" ",$O9&" ")-1),"/",REPT(" ",20)),20)),VALUE(MID(SUBSTITUTE(LEFT($O9,FIND(" ",$O9&" ")-1),"/",REPT(" ",20)),21,20)))),0)>$W9,"Late","Same day")) -> Same day | AF9: =IF($A9="","",IFERROR(INDEX(Validation!$C$193:$C$217,MATCH($A9,Validation!$A$193:$A$217,0)),IF(COUNTIF(Validation!$U$19:$U$178,$Z9)>0,$Z9,IF(COUNTIF(Validation!$S$19:$S$178,$AI9)=1,INDEX(Validation!$U$19:$U$178,MATCH($AI9,Validation!$S$19:$S$178,0)),$Z9)))) -> C MESA | AG9: =IF(COUNTA($A9:$U9)=0,"",IF($A9="","No name",IF($F9="","No date",IF($W9=0,"Date ilegible",IF(NOT(ISNUMBER($N9)),"Hours no numéricas",IF($AA9="NO MATCH","Person no identificada","OK")))))) -> OK | AH9: =IF($W9=0,"No date",IF($W9<Validation!$B$3,"Before period",IF($W9>Validation!$C$3,"After period","In period"))) -> In period | AI9: =IF($Y9="","",TRIM(RIGHT(SUBSTITUTE($Y9," ",REPT(" ",50)),50))) -> MESA | AJ9: =IF($A9="","",IF(NOT(ISERROR(MATCH($A9,Validation!$A$193:$A$217,0))),"Manual mapping",IF(COUNTIF(Validation!$U$19:$U$178,$Z9)>0,"Direct",IF(COUNTIF(Validation!$S$19:$S$178,$AI9)=1,"By surname","Unresolved")))) -> Direct | AK9: =IF($L9="","",IF(MATCH($L9,$L$2:$L$3000,0)<>ROW()-1,"",COUNT($AK$1:$AK8)+1)) | AL9: =IF($G9="","",IF(MATCH($G9,$G$2:$G$3000,0)<>ROW()-1,"",COUNT($AL$1:$AL8)+1)) | AM9: =IF($H9="","",IF(MATCH($H9,$H$2:$H$3000,0)<>ROW()-1,"",COUNT($AM$1:$AM8)+1)) | AN9: =IF($I9="","",IF(MATCH($I9,$I$2:$I$3000,0)<>ROW()-1,"",COUNT($AN$1:$AN8)+1)) | AO9: =IF($Q9="","",IF(MATCH($Q9,$Q$2:$Q$3000,0)<>ROW()-1,"",COUNT($AO$1:$AO8)+1))
A10: C Mesa | B10: Approved | C10: L. Carollo | D10: 8/19/2026 | F10: 8/19/2026 | G10: Rocking WW Minerals, LLC | H10: RWW PRB Asset VDR | I10: Converse, WY | J10: 05-34N-68W | K10: Title | M10: Lots 1, 2, S2NE ; Lots 3, 4, S2NW, SW | N10: 0.5 | O10: 8/19/2026 8:06:40 PM | Q10: Whitney Wicks | R10: C Mesa | S10: C Mesa | T10: 8/19/2026 | U10: Pruned the AOI from RWW Minerals to the source deed | W10: =IF($F10="",0,IFERROR(IF(ISNUMBER($F10),INT($F10),DATE(VALUE(MID(SUBSTITUTE(LEFT($F10,FIND(" ",$F10&" ")-1),"/",REPT(" ",20)),41,20)),VALUE(LEFT(SUBSTITUTE(LEFT($F10,FIND(" ",$F10&" ")-1),"/",REPT(" ",20)),20)),VALUE(MID(SUBSTITUTE(LEFT($F10,FIND(" ",$F10&" ")-1),"/",REPT(" ",20)),21,20)))),0)) -> 46253 | X10: =IF(ISNUMBER($N10),$N10*Validation!$B$5,"") -> 4 | Y10: =IF($A10="","",SUBSTITUTE(SUBSTITUTE(SUBSTITUTE(SUBSTITUTE(SUBSTITUTE(SUBSTITUTE(SUBSTITUTE(UPPER(TRIM($A10)),"Á","A"),"É","E"),"Í","I"),"Ó","O"),"Ú","U"),"Ñ","N"),"Ü","U")) -> C MESA | Z10: =IF($Y10="","",LEFT($Y10,1)&" "&TRIM(RIGHT(SUBSTITUTE($Y10," ",REPT(" ",50)),50))) -> C MESA | AA10: =IF($AF10="","",IF(COUNTIF(Validation!$U$19:$U$178,$AF10)>0,"OK","NO MATCH")) -> OK | AB10: =IF($W10=0,"",IF(AND($W10>=Validation!$B$3,$W10<=Validation!$C$3),"Yes","No")) -> Yes | AC10: =IF($A10="","",$AF10&"|"&TEXT($W10,"yyyy-mm-dd")&"|"&$J10&"|"&$N10) -> C MESA|2026-08-19|05-34N-68W|0.5 | AD10: =IF($AC10="","",IF(COUNTIF($AC$2:$AC$3000,$AC10)>1,"REVIEW","OK")) -> OK | AE10: =IF(OR($W10=0,$O10=""),"",IF(IFERROR(IF(ISNUMBER($O10),INT($O10),DATE(VALUE(MID(SUBSTITUTE(LEFT($O10,FIND(" ",$O10&" ")-1),"/",REPT(" ",20)),41,20)),VALUE(LEFT(SUBSTITUTE(LEFT($O10,FIND(" ",$O10&" ")-1),"/",REPT(" ",20)),20)),VALUE(MID(SUBSTITUTE(LEFT($O10,FIND(" ",$O10&" ")-1),"/",REPT(" ",20)),21,20)))),0)>$W10,"Late","Same day")) -> Same day | AF10: =IF($A10="","",IFERROR(INDEX(Validation!$C$193:$C$217,MATCH($A10,Validation!$A$193:$A$217,0)),IF(COUNTIF(Validation!$U$19:$U$178,$Z10)>0,$Z10,IF(COUNTIF(Validation!$S$19:$S$178,$AI10)=1,INDEX(Validation!$U$19:$U$178,MATCH($AI10,Validation!$S$19:$S$178,0)),$Z10)))) -> C MESA | AG10: =IF(COUNTA($A10:$U10)=0,"",IF($A10="","No name",IF($F10="","No date",IF($W10=0,"Date ilegible",IF(NOT(ISNUMBER($N10)),"Hours no numéricas",IF($AA10="NO MATCH","Person no identificada","OK")))))) -> OK | AH10: =IF($W10=0,"No date",IF($W10<Validation!$B$3,"Before period",IF($W10>Validation!$C$3,"After period","In period"))) -> In period | AI10: =IF($Y10="","",TRIM(RIGHT(SUBSTITUTE($Y10," ",REPT(" ",50)),50))) -> MESA | AJ10: =IF($A10="","",IF(NOT(ISERROR(MATCH($A10,Validation!$A$193:$A$217,0))),"Manual mapping",IF(COUNTIF(Validation!$U$19:$U$178,$Z10)>0,"Direct",IF(COUNTIF(Validation!$S$19:$S$178,$AI10)=1,"By surname","Unresolved")))) -> Direct | AK10: =IF($L10="","",IF(MATCH($L10,$L$2:$L$3000,0)<>ROW()-1,"",COUNT($AK$1:$AK9)+1)) | AL10: =IF($G10="","",IF(MATCH($G10,$G$2:$G$3000,0)<>ROW()-1,"",COUNT($AL$1:$AL9)+1)) | AM10: =IF($H10="","",IF(MATCH($H10,$H$2:$H$3000,0)<>ROW()-1,"",COUNT($AM$1:$AM9)+1)) | AN10: =IF($I10="","",IF(MATCH($I10,$I$2:$I$3000,0)<>ROW()-1,"",COUNT($AN$1:$AN9)+1)) | AO10: =IF($Q10="","",IF(MATCH($Q10,$Q$2:$Q$3000,0)<>ROW()-1,"",COUNT($AO$1:$AO9)+1))
A11: C Mesa | B11: Approved | C11: L. Carollo | D11: 8/19/2026 | F11: 8/19/2026 | G11: Rocking WW Minerals, LLC | H11: RWW PRB Asset VDR | I11: Converse, WY | J11: 05-35N-68W | K11: Title | M11: S2SW, S2SE | N11: 0.25 | O11: 8/19/2026 8:07:23 PM | Q11: Whitney Wicks | R11: C Mesa | S11: C Mesa | T11: 8/19/2026 | U11: Pruned the AOI from RWW Minerals to the source deed | W11: =IF($F11="",0,IFERROR(IF(ISNUMBER($F11),INT($F11),DATE(VALUE(MID(SUBSTITUTE(LEFT($F11,FIND(" ",$F11&" ")-1),"/",REPT(" ",20)),41,20)),VALUE(LEFT(SUBSTITUTE(LEFT($F11,FIND(" ",$F11&" ")-1),"/",REPT(" ",20)),20)),VALUE(MID(SUBSTITUTE(LEFT($F11,FIND(" ",$F11&" ")-1),"/",REPT(" ",20)),21,20)))),0)) -> 46253 | X11: =IF(ISNUMBER($N11),$N11*Validation!$B$5,"") -> 2 | Y11: =IF($A11="","",SUBSTITUTE(SUBSTITUTE(SUBSTITUTE(SUBSTITUTE(SUBSTITUTE(SUBSTITUTE(SUBSTITUTE(UPPER(TRIM($A11)),"Á","A"),"É","E"),"Í","I"),"Ó","O"),"Ú","U"),"Ñ","N"),"Ü","U")) -> C MESA | Z11: =IF($Y11="","",LEFT($Y11,1)&" "&TRIM(RIGHT(SUBSTITUTE($Y11," ",REPT(" ",50)),50))) -> C MESA | AA11: =IF($AF11="","",IF(COUNTIF(Validation!$U$19:$U$178,$AF11)>0,"OK","NO MATCH")) -> OK | AB11: =IF($W11=0,"",IF(AND($W11>=Validation!$B$3,$W11<=Validation!$C$3),"Yes","No")) -> Yes | AC11: =IF($A11="","",$AF11&"|"&TEXT($W11,"yyyy-mm-dd")&"|"&$J11&"|"&$N11) -> C MESA|2026-08-19|05-35N-68W|0.25 | AD11: =IF($AC11="","",IF(COUNTIF($AC$2:$AC$3000,$AC11)>1,"REVIEW","OK")) -> OK | AE11: =IF(OR($W11=0,$O11=""),"",IF(IFERROR(IF(ISNUMBER($O11),INT($O11),DATE(VALUE(MID(SUBSTITUTE(LEFT($O11,FIND(" ",$O11&" ")-1),"/",REPT(" ",20)),41,20)),VALUE(LEFT(SUBSTITUTE(LEFT($O11,FIND(" ",$O11&" ")-1),"/",REPT(" ",20)),20)),VALUE(MID(SUBSTITUTE(LEFT($O11,FIND(" ",$O11&" ")-1),"/",REPT(" ",20)),21,20)))),0)>$W11,"Late","Same day")) -> Same day | AF11: =IF($A11="","",IFERROR(INDEX(Validation!$C$193:$C$217,MATCH($A11,Validation!$A$193:$A$217,0)),IF(COUNTIF(Validation!$U$19:$U$178,$Z11)>0,$Z11,IF(COUNTIF(Validation!$S$19:$S$178,$AI11)=1,INDEX(Validation!$U$19:$U$178,MATCH($AI11,Validation!$S$19:$S$178,0)),$Z11)))) -> C MESA | AG11: =IF(COUNTA($A11:$U11)=0,"",IF($A11="","No name",IF($F11="","No date",IF($W11=0,"Date ilegible",IF(NOT(ISNUMBER($N11)),"Hours no numéricas",IF($AA11="NO MATCH","Person no identificada","OK")))))) -> OK | AH11: =IF($W11=0,"No date",IF($W11<Validation!$B$3,"Before period",IF($W11>Validation!$C$3,"After period","In period"))) -> In period | AI11: =IF($Y11="","",TRIM(RIGHT(SUBSTITUTE($Y11," ",REPT(" ",50)),50))) -> MESA | AJ11: =IF($A11="","",IF(NOT(ISERROR(MATCH($A11,Validation!$A$193:$A$217,0))),"Manual mapping",IF(COUNTIF(Validation!$U$19:$U$178,$Z11)>0,"Direct",IF(COUNTIF(Validation!$S$19:$S$178,$AI11)=1,"By surname","Unresolved")))) -> Direct | AK11: =IF($L11="","",IF(MATCH($L11,$L$2:$L$3000,0)<>ROW()-1,"",COUNT($AK$1:$AK10)+1)) | AL11: =IF($G11="","",IF(MATCH($G11,$G$2:$G$3000,0)<>ROW()-1,"",COUNT($AL$1:$AL10)+1)) | AM11: =IF($H11="","",IF(MATCH($H11,$H$2:$H$3000,0)<>ROW()-1,"",COUNT($AM$1:$AM10)+1)) | AN11: =IF($I11="","",IF(MATCH($I11,$I$2:$I$3000,0)<>ROW()-1,"",COUNT($AN$1:$AN10)+1)) | AO11: =IF($Q11="","",IF(MATCH($Q11,$Q$2:$Q$3000,0)<>ROW()-1,"",COUNT($AO$1:$AO10)+1))
A12: F Montañez | B12: Approved | C12: L. Carollo | D12: 8/19/2026 | F12: 8/19/2026 | G12: Rocking WW Minerals, LLC | H12: RWW PRB Asset VDR | I12: Converse, WY | J12: 00-00S-00W | K12: Title | N12: 0.125 | O12: 8/19/2026 8:26:15 PM | Q12: Whitney Wicks | R12: F Montañez | S12: F Montañez | T12: 8/19/2026 | U12: Onboarding to RWW project. | W12: =IF($F12="",0,IFERROR(IF(ISNUMBER($F12),INT($F12),DATE(VALUE(MID(SUBSTITUTE(LEFT($F12,FIND(" ",$F12&" ")-1),"/",REPT(" ",20)),41,20)),VALUE(LEFT(SUBSTITUTE(LEFT($F12,FIND(" ",$F12&" ")-1),"/",REPT(" ",20)),20)),VALUE(MID(SUBSTITUTE(LEFT($F12,FIND(" ",$F12&" ")-1),"/",REPT(" ",20)),21,20)))),0)) -> 46253 | X12: =IF(ISNUMBER($N12),$N12*Validation!$B$5,"") -> 1 | Y12: =IF($A12="","",SUBSTITUTE(SUBSTITUTE(SUBSTITUTE(SUBSTITUTE(SUBSTITUTE(SUBSTITUTE(SUBSTITUTE(UPPER(TRIM($A12)),"Á","A"),"É","E"),"Í","I"),"Ó","O"),"Ú","U"),"Ñ","N"),"Ü","U")) -> F MONTANEZ | Z12: =IF($Y12="","",LEFT($Y12,1)&" "&TRIM(RIGHT(SUBSTITUTE($Y12," ",REPT(" ",50)),50))) -> F MONTANEZ | AA12: =IF($AF12="","",IF(COUNTIF(Validation!$U$19:$U$178,$AF12)>0,"OK","NO MATCH")) -> OK | AB12: =IF($W12=0,"",IF(AND($W12>=Validation!$B$3,$W12<=Validation!$C$3),"Yes","No")) -> Yes | AC12: =IF($A12="","",$AF12&"|"&TEXT($W12,"yyyy-mm-dd")&"|"&$J12&"|"&$N12) -> F MONTANEZ|2026-08-19|00-00S-00W|0.125 | AD12: =IF($AC12="","",IF(COUNTIF($AC$2:$AC$3000,$AC12)>1,"REVIEW","OK")) -> OK | AE12: =IF(OR($W12=0,$O12=""),"",IF(IFERROR(IF(ISNUMBER($O12),INT($O12),DATE(VALUE(MID(SUBSTITUTE(LEFT($O12,FIND(" ",$O12&" ")-1),"/",REPT(" ",20)),41,20)),VALUE(LEFT(SUBSTITUTE(LEFT($O12,FIND(" ",$O12&" ")-1),"/",REPT(" ",20)),20)),VALUE(MID(SUBSTITUTE(LEFT($O12,FIND(" ",$O12&" ")-1),"/",REPT(" ",20)),21,20)))),0)>$W12,"Late","Same day")) -> Same day | AF12: =IF($A12="","",IFERROR(INDEX(Validation!$C$193:$C$217,MATCH($A12,Validation!$A$193:$A$217,0)),IF(COUNTIF(Validation!$U$19:$U$178,$Z12)>0,$Z12,IF(COUNTIF(Validation!$S$19:$S$178,$AI12)=1,INDEX(Validation!$U$19:$U$178,MATCH($AI12,Validation!$S$19:$S$178,0)),$Z12)))) -> F MONTANEZ | AG12: =IF(COUNTA($A12:$U12)=0,"",IF($A12="","No name",IF($F12="","No date",IF($W12=0,"Date ilegible",IF(NOT(ISNUMBER($N12)),"Hours no numéricas",IF($AA12="NO MATCH","Person no identificada","OK")))))) -> OK | AH12: =IF($W12=0,"No date",IF($W12<Validation!$B$3,"Before period",IF($W12>Validation!$C$3,"After period","In period"))) -> In period | AI12: =IF($Y12="","",TRIM(RIGHT(SUBSTITUTE($Y12," ",REPT(" ",50)),50))) -> MONTANEZ | AJ12: =IF($A12="","",IF(NOT(ISERROR(MATCH($A12,Validation!$A$193:$A$217,0))),"Manual mapping",IF(COUNTIF(Validation!$U$19:$U$178,$Z12)>0,"Direct",IF(COUNTIF(Validation!$S$19:$S$178,$AI12)=1,"By surname","Unresolved")))) -> Direct | AK12: =IF($L12="","",IF(MATCH($L12,$L$2:$L$3000,0)<>ROW()-1,"",COUNT($AK$1:$AK11)+1)) | AL12: =IF($G12="","",IF(MATCH($G12,$G$2:$G$3000,0)<>ROW()-1,"",COUNT($AL$1:$AL11)+1)) | AM12: =IF($H12="","",IF(MATCH($H12,$H$2:$H$3000,0)<>ROW()-1,"",COUNT($AM$1:$AM11)+1)) | AN12: =IF($I12="","",IF(MATCH($I12,$I$2:$I$3000,0)<>ROW()-1,"",COUNT($AN$1:$AN11)+1)) | AO12: =IF($Q12="","",IF(MATCH($Q12,$Q$2:$Q$3000,0)<>ROW()-1,"",COUNT($AO$1:$AO11)+1))
A13: F Montañez | B13: Approved | C13: L. Carollo | D13: 8/19/2026 | F13: 8/19/2026 | G13: Rocking WW Minerals, LLC | H13: RWW PRB Asset VDR | I13: Converse, WY | J13: 08-36N-70W | K13: Title | M13: SENW, NESW, NWSW, SWSW | N13: 0.125 | O13: 8/19/2026 8:27:42 PM | Q13: Whitney Wicks | R13: F Montañez | S13: F Montañez | T13: 8/19/2026 | U13: Progress in prune of mentioned legal description | W13: =IF($F13="",0,IFERROR(IF(ISNUMBER($F13),INT($F13),DATE(VALUE(MID(SUBSTITUTE(LEFT($F13,FIND(" ",$F13&" ")-1),"/",REPT(" ",20)),41,20)),VALUE(LEFT(SUBSTITUTE(LEFT($F13,FIND(" ",$F13&" ")-1),"/",REPT(" ",20)),20)),VALUE(MID(SUBSTITUTE(LEFT($F13,FIND(" ",$F13&" ")-1),"/",REPT(" ",20)),21,20)))),0)) -> 46253 | X13: =IF(ISNUMBER($N13),$N13*Validation!$B$5,"") -> 1 | Y13: =IF($A13="","",SUBSTITUTE(SUBSTITUTE(SUBSTITUTE(SUBSTITUTE(SUBSTITUTE(SUBSTITUTE(SUBSTITUTE(UPPER(TRIM($A13)),"Á","A"),"É","E"),"Í","I"),"Ó","O"),"Ú","U"),"Ñ","N"),"Ü","U")) -> F MONTANEZ | Z13: =IF($Y13="","",LEFT($Y13,1)&" "&TRIM(RIGHT(SUBSTITUTE($Y13," ",REPT(" ",50)),50))) -> F MONTANEZ | AA13: =IF($AF13="","",IF(COUNTIF(Validation!$U$19:$U$178,$AF13)>0,"OK","NO MATCH")) -> OK | AB13: =IF($W13=0,"",IF(AND($W13>=Validation!$B$3,$W13<=Validation!$C$3),"Yes","No")) -> Yes | AC13: =IF($A13="","",$AF13&"|"&TEXT($W13,"yyyy-mm-dd")&"|"&$J13&"|"&$N13) -> F MONTANEZ|2026-08-19|08-36N-70W|0.125 | AD13: =IF($AC13="","",IF(COUNTIF($AC$2:$AC$3000,$AC13)>1,"REVIEW","OK")) -> REVIEW | AE13: =IF(OR($W13=0,$O13=""),"",IF(IFERROR(IF(ISNUMBER($O13),INT($O13),DATE(VALUE(MID(SUBSTITUTE(LEFT($O13,FIND(" ",$O13&" ")-1),"/",REPT(" ",20)),41,20)),VALUE(LEFT(SUBSTITUTE(LEFT($O13,FIND(" ",$O13&" ")-1),"/",REPT(" ",20)),20)),VALUE(MID(SUBSTITUTE(LEFT($O13,FIND(" ",$O13&" ")-1),"/",REPT(" ",20)),21,20)))),0)>$W13,"Late","Same day")) -> Same day | AF13: =IF($A13="","",IFERROR(INDEX(Validation!$C$193:$C$217,MATCH($A13,Validation!$A$193:$A$217,0)),IF(COUNTIF(Validation!$U$19:$U$178,$Z13)>0,$Z13,IF(COUNTIF(Validation!$S$19:$S$178,$AI13)=1,INDEX(Validation!$U$19:$U$178,MATCH($AI13,Validation!$S$19:$S$178,0)),$Z13)))) -> F MONTANEZ | AG13: =IF(COUNTA($A13:$U13)=0,"",IF($A13="","No name",IF($F13="","No date",IF($W13=0,"Date ilegible",IF(NOT(ISNUMBER($N13)),"Hours no numéricas",IF($AA13="NO MATCH","Person no identificada","OK")))))) -> OK | AH13: =IF($W13=0,"No date",IF($W13<Validation!$B$3,"Before period",IF($W13>Validation!$C$3,"After period","In period"))) -> In period | AI13: =IF($Y13="","",TRIM(RIGHT(SUBSTITUTE($Y13," ",REPT(" ",50)),50))) -> MONTANEZ | AJ13: =IF($A13="","",IF(NOT(ISERROR(MATCH($A13,Validation!$A$193:$A$217,0))),"Manual mapping",IF(COUNTIF(Validation!$U$19:$U$178,$Z13)>0,"Direct",IF(COUNTIF(Validation!$S$19:$S$178,$AI13)=1,"By surname","Unresolved")))) -> Direct | AK13: =IF($L13="","",IF(MATCH($L13,$L$2:$L$3000,0)<>ROW()-1,"",COUNT($AK$1:$AK12)+1)) | AL13: =IF($G13="","",IF(MATCH($G13,$G$2:$G$3000,0)<>ROW()-1,"",COUNT($AL$1:$AL12)+1)) | AM13: =IF($H13="","",IF(MATCH($H13,$H$2:$H$3000,0)<>ROW()-1,"",COUNT($AM$1:$AM12)+1)) | AN13: =IF($I13="","",IF(MATCH($I13,$I$2:$I$3000,0)<>ROW()-1,"",COUNT($AN$1:$AN12)+1)) | AO13: =IF($Q13="","",IF(MATCH($Q13,$Q$2:$Q$3000,0)<>ROW()-1,"",COUNT($AO$1:$AO12)+1))
A14: F Montañez | B14: Approved | C14: L. Carollo | D14: 8/19/2026 | F14: 8/19/2026 | G14: Rocking WW Minerals, LLC | H14: RWW PRB Asset VDR | I14: Converse, WY | J14: 08-36N-70W | K14: Title | M14: SENW, NESW, NWSW, SWSW | N14: 0.125 | O14: 8/20/2026 2:58:40 AM | Q14: Whitney Wicks | R14: F Montañez | S14: F Montañez | T14: 8/20/2026 | U14: Progress in prune of mentioned legal description | W14: =IF($F14="",0,IFERROR(IF(ISNUMBER($F14),INT($F14),DATE(VALUE(MID(SUBSTITUTE(LEFT($F14,FIND(" ",$F14&" ")-1),"/",REPT(" ",20)),41,20)),VALUE(LEFT(SUBSTITUTE(LEFT($F14,FIND(" ",$F14&" ")-1),"/",REPT(" ",20)),20)),VALUE(MID(SUBSTITUTE(LEFT($F14,FIND(" ",$F14&" ")-1),"/",REPT(" ",20)),21,20)))),0)) -> 46253 | X14: =IF(ISNUMBER($N14),$N14*Validation!$B$5,"") -> 1 | Y14: =IF($A14="","",SUBSTITUTE(SUBSTITUTE(SUBSTITUTE(SUBSTITUTE(SUBSTITUTE(SUBSTITUTE(SUBSTITUTE(UPPER(TRIM($A14)),"Á","A"),"É","E"),"Í","I"),"Ó","O"),"Ú","U"),"Ñ","N"),"Ü","U")) -> F MONTANEZ | Z14: =IF($Y14="","",LEFT($Y14,1)&" "&TRIM(RIGHT(SUBSTITUTE($Y14," ",REPT(" ",50)),50))) -> F MONTANEZ | AA14: =IF($AF14="","",IF(COUNTIF(Validation!$U$19:$U$178,$AF14)>0,"OK","NO MATCH")) -> OK | AB14: =IF($W14=0,"",IF(AND($W14>=Validation!$B$3,$W14<=Validation!$C$3),"Yes","No")) -> Yes | AC14: =IF($A14="","",$AF14&"|"&TEXT($W14,"yyyy-mm-dd")&"|"&$J14&"|"&$N14) -> F MONTANEZ|2026-08-19|08-36N-70W|0.125 | AD14: =IF($AC14="","",IF(COUNTIF($AC$2:$AC$3000,$AC14)>1,"REVIEW","OK")) -> REVIEW | AE14: =IF(OR($W14=0,$O14=""),"",IF(IFERROR(IF(ISNUMBER($O14),INT($O14),DATE(VALUE(MID(SUBSTITUTE(LEFT($O14,FIND(" ",$O14&" ")-1),"/",REPT(" ",20)),41,20)),VALUE(LEFT(SUBSTITUTE(LEFT($O14,FIND(" ",$O14&" ")-1),"/",REPT(" ",20)),20)),VALUE(MID(SUBSTITUTE(LEFT($O14,FIND(" ",$O14&" ")-1),"/",REPT(" ",20)),21,20)))),0)>$W14,"Late","Same day")) -> Late | AF14: =IF($A14="","",IFERROR(INDEX(Validation!$C$193:$C$217,MATCH($A14,Validation!$A$193:$A$217,0)),IF(COUNTIF(Validation!$U$19:$U$178,$Z14)>0,$Z14,IF(COUNTIF(Validation!$S$19:$S$178,$AI14)=1,INDEX(Validation!$U$19:$U$178,MATCH($AI14,Validation!$S$19:$S$178,0)),$Z14)))) -> F MONTANEZ | AG14: =IF(COUNTA($A14:$U14)=0,"",IF($A14="","No name",IF($F14="","No date",IF($W14=0,"Date ilegible",IF(NOT(ISNUMBER($N14)),"Hours no numéricas",IF($AA14="NO MATCH","Person no identificada","OK")))))) -> OK | AH14: =IF($W14=0,"No date",IF($W14<Validation!$B$3,"Before period",IF($W14>Validation!$C$3,"After period","In period"))) -> In period | AI14: =IF($Y14="","",TRIM(RIGHT(SUBSTITUTE($Y14," ",REPT(" ",50)),50))) -> MONTANEZ | AJ14: =IF($A14="","",IF(NOT(ISERROR(MATCH($A14,Validation!$A$193:$A$217,0))),"Manual mapping",IF(COUNTIF(Validation!$U$19:$U$178,$Z14)>0,"Direct",IF(COUNTIF(Validation!$S$19:$S$178,$AI14)=1,"By surname","Unresolved")))) -> Direct | AK14: =IF($L14="","",IF(MATCH($L14,$L$2:$L$3000,0)<>ROW()-1,"",COUNT($AK$1:$AK13)+1)) | AL14: =IF($G14="","",IF(MATCH($G14,$G$2:$G$3000,0)<>ROW()-1,"",COUNT($AL$1:$AL13)+1)) | AM14: =IF($H14="","",IF(MATCH($H14,$H$2:$H$3000,0)<>ROW()-1,"",COUNT($AM$1:$AM13)+1)) | AN14: =IF($I14="","",IF(MATCH($I14,$I$2:$I$3000,0)<>ROW()-1,"",COUNT($AN$1:$AN13)+1)) | AO14: =IF($Q14="","",IF(MATCH($Q14,$Q$2:$Q$3000,0)<>ROW()-1,"",COUNT($AO$1:$AO13)+1))
A15: F Montañez | B15: Unapproved | F15: 8/19/2026 | G15: Rocking WW Minerals, LLC | H15: RWW PRB Asset VDR | I15: Converse, WY | J15: 08-36N-70W | K15: Title | M15: SENW, NESW, NWSW, SWSW | N15: 0.25 | O15: 8/20/2026 3:23:35 AM | Q15: Whitney Wicks | R15: F Montañez | S15: F Montañez | T15: 8/20/2026 | U15: Completed prune of mentioned legal description. 2 Original AOI from client, due to amistake when notecards were been deleted, Final AOI must be redone. | W15: =IF($F15="",0,IFERROR(IF(ISNUMBER($F15),INT($F15),DATE(VALUE(MID(SUBSTITUTE(LEFT($F15,FIND(" ",$F15&" ")-1),"/",REPT(" ",20)),41,20)),VALUE(LEFT(SUBSTITUTE(LEFT($F15,FIND(" ",$F15&" ")-1),"/",REPT(" ",20)),20)),VALUE(MID(SUBSTITUTE(LEFT($F15,FIND(" ",$F15&" ")-1),"/",REPT(" ",20)),21,20)))),0)) -> 46253 | X15: =IF(ISNUMBER($N15),$N15*Validation!$B$5,"") -> 2 | Y15: =IF($A15="","",SUBSTITUTE(SUBSTITUTE(SUBSTITUTE(SUBSTITUTE(SUBSTITUTE(SUBSTITUTE(SUBSTITUTE(UPPER(TRIM($A15)),"Á","A"),"É","E"),"Í","I"),"Ó","O"),"Ú","U"),"Ñ","N"),"Ü","U")) -> F MONTANEZ | Z15: =IF($Y15="","",LEFT($Y15,1)&" "&TRIM(RIGHT(SUBSTITUTE($Y15," ",REPT(" ",50)),50))) -> F MONTANEZ | AA15: =IF($AF15="","",IF(COUNTIF(Validation!$U$19:$U$178,$AF15)>0,"OK","NO MATCH")) -> OK | AB15: =IF($W15=0,"",IF(AND($W15>=Validation!$B$3,$W15<=Validation!$C$3),"Yes","No")) -> Yes | AC15: =IF($A15="","",$AF15&"|"&TEXT($W15,"yyyy-mm-dd")&"|"&$J15&"|"&$N15) -> F MONTANEZ|2026-08-19|08-36N-70W|0.25 | AD15: =IF($AC15="","",IF(COUNTIF($AC$2:$AC$3000,$AC15)>1,"REVIEW","OK")) -> OK | AE15: =IF(OR($W15=0,$O15=""),"",IF(IFERROR(IF(ISNUMBER($O15),INT($O15),DATE(VALUE(MID(SUBSTITUTE(LEFT($O15,FIND(" ",$O15&" ")-1),"/",REPT(" ",20)),41,20)),VALUE(LEFT(SUBSTITUTE(LEFT($O15,FIND(" ",$O15&" ")-1),"/",REPT(" ",20)),20)),VALUE(MID(SUBSTITUTE(LEFT($O15,FIND(" ",$O15&" ")-1),"/",REPT(" ",20)),21,20)))),0)>$W15,"Late","Same day")) -> Late | AF15: =IF($A15="","",IFERROR(INDEX(Validation!$C$193:$C$217,MATCH($A15,Validation!$A$193:$A$217,0)),IF(COUNTIF(Validation!$U$19:$U$178,$Z15)>0,$Z15,IF(COUNTIF(Validation!$S$19:$S$178,$AI15)=1,INDEX(Validation!$U$19:$U$178,MATCH($AI15,Validation!$S$19:$S$178,0)),$Z15)))) -> F MONTANEZ | AG15: =IF(COUNTA($A15:$U15)=0,"",IF($A15="","No name",IF($F15="","No date",IF($W15=0,"Date ilegible",IF(NOT(ISNUMBER($N15)),"Hours no numéricas",IF($AA15="NO MATCH","Person no identificada","OK")))))) -> OK | AH15: =IF($W15=0,"No date",IF($W15<Validation!$B$3,"Before period",IF($W15>Validation!$C$3,"After period","In period"))) -> In period | AI15: =IF($Y15="","",TRIM(RIGHT(SUBSTITUTE($Y15," ",REPT(" ",50)),50))) -> MONTANEZ | AJ15: =IF($A15="","",IF(NOT(ISERROR(MATCH($A15,Validation!$A$193:$A$217,0))),"Manual mapping",IF(COUNTIF(Validation!$U$19:$U$178,$Z15)>0,"Direct",IF(COUNTIF(Validation!$S$19:$S$178,$AI15)=1,"By surname","Unresolved")))) -> Direct | AK15: =IF($L15="","",IF(MATCH($L15,$L$2:$L$3000,0)<>ROW()-1,"",COUNT($AK$1:$AK14)+1)) | AL15: =IF($G15="","",IF(MATCH($G15,$G$2:$G$3000,0)<>ROW()-1,"",COUNT($AL$1:$AL14)+1)) | AM15: =IF($H15="","",IF(MATCH($H15,$H$2:$H$3000,0)<>ROW()-1,"",COUNT($AM$1:$AM14)+1)) | AN15: =IF($I15="","",IF(MATCH($I15,$I$2:$I$3000,0)<>ROW()-1,"",COUNT($AN$1:$AN14)+1)) | AO15: =IF($Q15="","",IF(MATCH($Q15,$Q$2:$Q$3000,0)<>ROW()-1,"",COUNT($AO$1:$AO14)+1))
A16: G Pereira | B16: Approved | C16: L. Carollo | D16: 8/19/2026 | F16: 8/19/2026 | G16: Rocking WW Minerals, LLC | H16: RWW PRB Asset VDR | I16: Converse, WY | J16: 07-34N-69W | K16: Title | M16: Lot 4, S2NE, E2SW, SE | N16: 0.5 | O16: 8/19/2026 9:01:19 PM | Q16: Whitney Wicks | R16: G Pereira | S16: G Pereira | T16: 8/19/2026 | U16: Clone AOI Pull and enter source deed Prune interest | W16: =IF($F16="",0,IFERROR(IF(ISNUMBER($F16),INT($F16),DATE(VALUE(MID(SUBSTITUTE(LEFT($F16,FIND(" ",$F16&" ")-1),"/",REPT(" ",20)),41,20)),VALUE(LEFT(SUBSTITUTE(LEFT($F16,FIND(" ",$F16&" ")-1),"/",REPT(" ",20)),20)),VALUE(MID(SUBSTITUTE(LEFT($F16,FIND(" ",$F16&" ")-1),"/",REPT(" ",20)),21,20)))),0)) -> 46253 | X16: =IF(ISNUMBER($N16),$N16*Validation!$B$5,"") -> 4 | Y16: =IF($A16="","",SUBSTITUTE(SUBSTITUTE(SUBSTITUTE(SUBSTITUTE(SUBSTITUTE(SUBSTITUTE(SUBSTITUTE(UPPER(TRIM($A16)),"Á","A"),"É","E"),"Í","I"),"Ó","O"),"Ú","U"),"Ñ","N"),"Ü","U")) -> G PEREIRA | Z16: =IF($Y16="","",LEFT($Y16,1)&" "&TRIM(RIGHT(SUBSTITUTE($Y16," ",REPT(" ",50)),50))) -> G PEREIRA | AA16: =IF($AF16="","",IF(COUNTIF(Validation!$U$19:$U$178,$AF16)>0,"OK","NO MATCH")) -> OK | AB16: =IF($W16=0,"",IF(AND($W16>=Validation!$B$3,$W16<=Validation!$C$3),"Yes","No")) -> Yes | AC16: =IF($A16="","",$AF16&"|"&TEXT($W16,"yyyy-mm-dd")&"|"&$J16&"|"&$N16) -> G PEREIRA|2026-08-19|07-34N-69W|0.5 | AD16: =IF($AC16="","",IF(COUNTIF($AC$2:$AC$3000,$AC16)>1,"REVIEW","OK")) -> OK | AE16: =IF(OR($W16=0,$O16=""),"",IF(IFERROR(IF(ISNUMBER($O16),INT($O16),DATE(VALUE(MID(SUBSTITUTE(LEFT($O16,FIND(" ",$O16&" ")-1),"/",REPT(" ",20)),41,20)),VALUE(LEFT(SUBSTITUTE(LEFT($O16,FIND(" ",$O16&" ")-1),"/",REPT(" ",20)),20)),VALUE(MID(SUBSTITUTE(LEFT($O16,FIND(" ",$O16&" ")-1),"/",REPT(" ",20)),21,20)))),0)>$W16,"Late","Same day")) -> Same day | AF16: =IF($A16="","",IFERROR(INDEX(Validation!$C$193:$C$217,MATCH($A16,Validation!$A$193:$A$217,0)),IF(COUNTIF(Validation!$U$19:$U$178,$Z16)>0,$Z16,IF(COUNTIF(Validation!$S$19:$S$178,$AI16)=1,INDEX(Validation!$U$19:$U$178,MATCH($AI16,Validation!$S$19:$S$178,0)),$Z16)))) -> G PEREIRA | AG16: =IF(COUNTA($A16:$U16)=0,"",IF($A16="","No name",IF($F16="","No date",IF($W16=0,"Date ilegible",IF(NOT(ISNUMBER($N16)),"Hours no numéricas",IF($AA16="NO MATCH","Person no identificada","OK")))))) -> OK | AH16: =IF($W16=0,"No date",IF($W16<Validation!$B$3,"Before period",IF($W16>Validation!$C$3,"After period","In period"))) -> In period | AI16: =IF($Y16="","",TRIM(RIGHT(SUBSTITUTE($Y16," ",REPT(" ",50)),50))) -> PEREIRA | AJ16: =IF($A16="","",IF(NOT(ISERROR(MATCH($A16,Validation!$A$193:$A$217,0))),"Manual mapping",IF(COUNTIF(Validation!$U$19:$U$178,$Z16)>0,"Direct",IF(COUNTIF(Validation!$S$19:$S$178,$AI16)=1,"By surname","Unresolved")))) -> Direct | AK16: =IF($L16="","",IF(MATCH($L16,$L$2:$L$3000,0)<>ROW()-1,"",COUNT($AK$1:$AK15)+1)) | AL16: =IF($G16="","",IF(MATCH($G16,$G$2:$G$3000,0)<>ROW()-1,"",COUNT($AL$1:$AL15)+1)) | AM16: =IF($H16="","",IF(MATCH($H16,$H$2:$H$3000,0)<>ROW()-1,"",COUNT($AM$1:$AM15)+1)) | AN16: =IF($I16="","",IF(MATCH($I16,$I$2:$I$3000,0)<>ROW()-1,"",COUNT($AN$1:$AN15)+1)) | AO16: =IF($Q16="","",IF(MATCH($Q16,$Q$2:$Q$3000,0)<>ROW()-1,"",COUNT($AO$1:$AO15)+1))
A17: G Pereira | B17: Unapproved | F17: 8/19/2026 | G17: Rocking WW Minerals, LLC | H17: RWW PRB Asset VDR | I17: Campbell, WY | J17: 20-42N-71W | K17: Title | M17: NESE | N17: 0.25 | O17: 8/20/2026 12:22:44 PM | Q17: Whitney Wicks | R17: G Pereira | S17: G Pereira | T17: 8/20/2026 | U17: Clone AOI Pull and enter source deed Prune interest | W17: =IF($F17="",0,IFERROR(IF(ISNUMBER($F17),INT($F17),DATE(VALUE(MID(SUBSTITUTE(LEFT($F17,FIND(" ",$F17&" ")-1),"/",REPT(" ",20)),41,20)),VALUE(LEFT(SUBSTITUTE(LEFT($F17,FIND(" ",$F17&" ")-1),"/",REPT(" ",20)),20)),VALUE(MID(SUBSTITUTE(LEFT($F17,FIND(" ",$F17&" ")-1),"/",REPT(" ",20)),21,20)))),0)) -> 46253 | X17: =IF(ISNUMBER($N17),$N17*Validation!$B$5,"") -> 2 | Y17: =IF($A17="","",SUBSTITUTE(SUBSTITUTE(SUBSTITUTE(SUBSTITUTE(SUBSTITUTE(SUBSTITUTE(SUBSTITUTE(UPPER(TRIM($A17)),"Á","A"),"É","E"),"Í","I"),"Ó","O"),"Ú","U"),"Ñ","N"),"Ü","U")) -> G PEREIRA | Z17: =IF($Y17="","",LEFT($Y17,1)&" "&TRIM(RIGHT(SUBSTITUTE($Y17," ",REPT(" ",50)),50))) -> G PEREIRA | AA17: =IF($AF17="","",IF(COUNTIF(Validation!$U$19:$U$178,$AF17)>0,"OK","NO MATCH")) -> OK | AB17: =IF($W17=0,"",IF(AND($W17>=Validation!$B$3,$W17<=Validation!$C$3),"Yes","No")) -> Yes | AC17: =IF($A17="","",$AF17&"|"&TEXT($W17,"yyyy-mm-dd")&"|"&$J17&"|"&$N17) -> G PEREIRA|2026-08-19|20-42N-71W|0.25 | AD17: =IF($AC17="","",IF(COUNTIF($AC$2:$AC$3000,$AC17)>1,"REVIEW","OK")) -> OK | AE17: =IF(OR($W17=0,$O17=""),"",IF(IFERROR(IF(ISNUMBER($O17),INT($O17),DATE(VALUE(MID(SUBSTITUTE(LEFT($O17,FIND(" ",$O17&" ")-1),"/",REPT(" ",20)),41,20)),VALUE(LEFT(SUBSTITUTE(LEFT($O17,FIND(" ",$O17&" ")-1),"/",REPT(" ",20)),20)),VALUE(MID(SUBSTITUTE(LEFT($O17,FIND(" ",$O17&" ")-1),"/",REPT(" ",20)),21,20)))),0)>$W17,"Late","Same day")) -> Late | AF17: =IF($A17="","",IFERROR(INDEX(Validation!$C$193:$C$217,MATCH($A17,Validation!$A$193:$A$217,0)),IF(COUNTIF(Validation!$U$19:$U$178,$Z17)>0,$Z17,IF(COUNTIF(Validation!$S$19:$S$178,$AI17)=1,INDEX(Validation!$U$19:$U$178,MATCH($AI17,Validation!$S$19:$S$178,0)),$Z17)))) -> G PEREIRA | AG17: =IF(COUNTA($A17:$U17)=0,"",IF($A17="","No name",IF($F17="","No date",IF($W17=0,"Date ilegible",IF(NOT(ISNUMBER($N17)),"Hours no numéricas",IF($AA17="NO MATCH","Person no identificada","OK")))))) -> OK | AH17: =IF($W17=0,"No date",IF($W17<Validation!$B$3,"Before period",IF($W17>Validation!$C$3,"After period","In period"))) -> In period | AI17: =IF($Y17="","",TRIM(RIGHT(SUBSTITUTE($Y17," ",REPT(" ",50)),50))) -> PEREIRA | AJ17: =IF($A17="","",IF(NOT(ISERROR(MATCH($A17,Validation!$A$193:$A$217,0))),"Manual mapping",IF(COUNTIF(Validation!$U$19:$U$178,$Z17)>0,"Direct",IF(COUNTIF(Validation!$S$19:$S$178,$AI17)=1,"By surname","Unresolved")))) -> Direct | AK17: =IF($L17="","",IF(MATCH($L17,$L$2:$L$3000,0)<>ROW()-1,"",COUNT($AK$1:$AK16)+1)) | AL17: =IF($G17="","",IF(MATCH($G17,$G$2:$G$3000,0)<>ROW()-1,"",COUNT($AL$1:$AL16)+1)) | AM17: =IF($H17="","",IF(MATCH($H17,$H$2:$H$3000,0)<>ROW()-1,"",COUNT($AM$1:$AM16)+1)) | AN17: =IF($I17="","",IF(MATCH($I17,$I$2:$I$3000,0)<>ROW()-1,"",COUNT($AN$1:$AN16)+1)) | AO17: =IF($Q17="","",IF(MATCH($Q17,$Q$2:$Q$3000,0)<>ROW()-1,"",COUNT($AO$1:$AO16)+1))
A18: J Abay | B18: Approved | C18: L. Carollo | D18: 8/19/2026 | F18: 8/19/2026 | G18: Rocking WW Minerals, LLC | H18: RWW PRB Asset VDR | I18: Converse, WY | J18: 07-38N-75W | K18: Title | M18: Lot 4, SESW, S2SE | N18: 0.125 | O18: 8/19/2026 7:54:13 PM | Q18: Whitney Wicks | R18: J Abay | S18: J Abay | T18: 8/19/2026 | U18: Clone AOI Pull and enter the source deed Prune interest Download Runsheet Download Lease Analysis Report | W18: =IF($F18="",0,IFERROR(IF(ISNUMBER($F18),INT($F18),DATE(VALUE(MID(SUBSTITUTE(LEFT($F18,FIND(" ",$F18&" ")-1),"/",REPT(" ",20)),41,20)),VALUE(LEFT(SUBSTITUTE(LEFT($F18,FIND(" ",$F18&" ")-1),"/",REPT(" ",20)),20)),VALUE(MID(SUBSTITUTE(LEFT($F18,FIND(" ",$F18&" ")-1),"/",REPT(" ",20)),21,20)))),0)) -> 46253 | X18: =IF(ISNUMBER($N18),$N18*Validation!$B$5,"") -> 1 | Y18: =IF($A18="","",SUBSTITUTE(SUBSTITUTE(SUBSTITUTE(SUBSTITUTE(SUBSTITUTE(SUBSTITUTE(SUBSTITUTE(UPPER(TRIM($A18)),"Á","A"),"É","E"),"Í","I"),"Ó","O"),"Ú","U"),"Ñ","N"),"Ü","U")) -> J ABAY | Z18: =IF($Y18="","",LEFT($Y18,1)&" "&TRIM(RIGHT(SUBSTITUTE($Y18," ",REPT(" ",50)),50))) -> J ABAY | AA18: =IF($AF18="","",IF(COUNTIF(Validation!$U$19:$U$178,$AF18)>0,"OK","NO MATCH")) -> OK | AB18: =IF($W18=0,"",IF(AND($W18>=Validation!$B$3,$W18<=Validation!$C$3),"Yes","No")) -> Yes | AC18: =IF($A18="","",$AF18&"|"&TEXT($W18,"yyyy-mm-dd")&"|"&$J18&"|"&$N18) -> J ABAY|2026-08-19|07-38N-75W|0.125 | AD18: =IF($AC18="","",IF(COUNTIF($AC$2:$AC$3000,$AC18)>1,"REVIEW","OK")) -> OK | AE18: =IF(OR($W18=0,$O18=""),"",IF(IFERROR(IF(ISNUMBER($O18),INT($O18),DATE(VALUE(MID(SUBSTITUTE(LEFT($O18,FIND(" ",$O18&" ")-1),"/",REPT(" ",20)),41,20)),VALUE(LEFT(SUBSTITUTE(LEFT($O18,FIND(" ",$O18&" ")-1),"/",REPT(" ",20)),20)),VALUE(MID(SUBSTITUTE(LEFT($O18,FIND(" ",$O18&" ")-1),"/",REPT(" ",20)),21,20)))),0)>$W18,"Late","Same day")) -> Same day | AF18: =IF($A18="","",IFERROR(INDEX(Validation!$C$193:$C$217,MATCH($A18,Validation!$A$193:$A$217,0)),IF(COUNTIF(Validation!$U$19:$U$178,$Z18)>0,$Z18,IF(COUNTIF(Validation!$S$19:$S$178,$AI18)=1,INDEX(Validation!$U$19:$U$178,MATCH($AI18,Validation!$S$19:$S$178,0)),$Z18)))) -> J ABAY | AG18: =IF(COUNTA($A18:$U18)=0,"",IF($A18="","No name",IF($F18="","No date",IF($W18=0,"Date ilegible",IF(NOT(ISNUMBER($N18)),"Hours no numéricas",IF($AA18="NO MATCH","Person no identificada","OK")))))) -> OK | AH18: =IF($W18=0,"No date",IF($W18<Validation!$B$3,"Before period",IF($W18>Validation!$C$3,"After period","In period"))) -> In period | AI18: =IF($Y18="","",TRIM(RIGHT(SUBSTITUTE($Y18," ",REPT(" ",50)),50))) -> ABAY | AJ18: =IF($A18="","",IF(NOT(ISERROR(MATCH($A18,Validation!$A$193:$A$217,0))),"Manual mapping",IF(COUNTIF(Validation!$U$19:$U$178,$Z18)>0,"Direct",IF(COUNTIF(Validation!$S$19:$S$178,$AI18)=1,"By surname","Unresolved")))) -> Direct | AK18: =IF($L18="","",IF(MATCH($L18,$L$2:$L$3000,0)<>ROW()-1,"",COUNT($AK$1:$AK17)+1)) | AL18: =IF($G18="","",IF(MATCH($G18,$G$2:$G$3000,0)<>ROW()-1,"",COUNT($AL$1:$AL17)+1)) | AM18: =IF($H18="","",IF(MATCH($H18,$H$2:$H$3000,0)<>ROW()-1,"",COUNT($AM$1:$AM17)+1)) | AN18: =IF($I18="","",IF(MATCH($I18,$I$2:$I$3000,0)<>ROW()-1,"",COUNT($AN$1:$AN17)+1)) | AO18: =IF($Q18="","",IF(MATCH($Q18,$Q$2:$Q$3000,0)<>ROW()-1,"",COUNT($AO$1:$AO17)+1))
A19: J Abay | B19: Approved | C19: L. Carollo | D19: 8/19/2026 | F19: 8/19/2026 | G19: Rocking WW Minerals, LLC | H19: RWW PRB Asset VDR | I19: Converse, WY | J19: 08-35N-69W | K19: Title | M19: SW4SE4 | N19: 0.125 | O19: 8/19/2026 7:55:55 PM | Q19: Whitney Wicks | R19: J Abay | S19: J Abay | T19: 8/19/2026 | U19: Reworked Clone AOI Pull and enter the source deed Prune interest | W19: =IF($F19="",0,IFERROR(IF(ISNUMBER($F19),INT($F19),DATE(VALUE(MID(SUBSTITUTE(LEFT($F19,FIND(" ",$F19&" ")-1),"/",REPT(" ",20)),41,20)),VALUE(LEFT(SUBSTITUTE(LEFT($F19,FIND(" ",$F19&" ")-1),"/",REPT(" ",20)),20)),VALUE(MID(SUBSTITUTE(LEFT($F19,FIND(" ",$F19&" ")-1),"/",REPT(" ",20)),21,20)))),0)) -> 46253 | X19: =IF(ISNUMBER($N19),$N19*Validation!$B$5,"") -> 1 | Y19: =IF($A19="","",SUBSTITUTE(SUBSTITUTE(SUBSTITUTE(SUBSTITUTE(SUBSTITUTE(SUBSTITUTE(SUBSTITUTE(UPPER(TRIM($A19)),"Á","A"),"É","E"),"Í","I"),"Ó","O"),"Ú","U"),"Ñ","N"),"Ü","U")) -> J ABAY | Z19: =IF($Y19="","",LEFT($Y19,1)&" "&TRIM(RIGHT(SUBSTITUTE($Y19," ",REPT(" ",50)),50))) -> J ABAY | AA19: =IF($AF19="","",IF(COUNTIF(Validation!$U$19:$U$178,$AF19)>0,"OK","NO MATCH")) -> OK | AB19: =IF($W19=0,"",IF(AND($W19>=Validation!$B$3,$W19<=Validation!$C$3),"Yes","No")) -> Yes | AC19: =IF($A19="","",$AF19&"|"&TEXT($W19,"yyyy-mm-dd")&"|"&$J19&"|"&$N19) -> J ABAY|2026-08-19|08-35N-69W|0.125 | AD19: =IF($AC19="","",IF(COUNTIF($AC$2:$AC$3000,$AC19)>1,"REVIEW","OK")) -> OK | AE19: =IF(OR($W19=0,$O19=""),"",IF(IFERROR(IF(ISNUMBER($O19),INT($O19),DATE(VALUE(MID(SUBSTITUTE(LEFT($O19,FIND(" ",$O19&" ")-1),"/",REPT(" ",20)),41,20)),VALUE(LEFT(SUBSTITUTE(LEFT($O19,FIND(" ",$O19&" ")-1),"/",REPT(" ",20)),20)),VALUE(MID(SUBSTITUTE(LEFT($O19,FIND(" ",$O19&" ")-1),"/",REPT(" ",20)),21,20)))),0)>$W19,"Late","Same day")) -> Same day | AF19: =IF($A19="","",IFERROR(INDEX(Validation!$C$193:$C$217,MATCH($A19,Validation!$A$193:$A$217,0)),IF(COUNTIF(Validation!$U$19:$U$178,$Z19)>0,$Z19,IF(COUNTIF(Validation!$S$19:$S$178,$AI19)=1,INDEX(Validation!$U$19:$U$178,MATCH($AI19,Validation!$S$19:$S$178,0)),$Z19)))) -> J ABAY | AG19: =IF(COUNTA($A19:$U19)=0,"",IF($A19="","No name",IF($F19="","No date",IF($W19=0,"Date ilegible",IF(NOT(ISNUMBER($N19)),"Hours no numéricas",IF($AA19="NO MATCH","Person no identificada","OK")))))) -> OK | AH19: =IF($W19=0,"No date",IF($W19<Validation!$B$3,"Before period",IF($W19>Validation!$C$3,"After period","In period"))) -> In period | AI19: =IF($Y19="","",TRIM(RIGHT(SUBSTITUTE($Y19," ",REPT(" ",50)),50))) -> ABAY | AJ19: =IF($A19="","",IF(NOT(ISERROR(MATCH($A19,Validation!$A$193:$A$217,0))),"Manual mapping",IF(COUNTIF(Validation!$U$19:$U$178,$Z19)>0,"Direct",IF(COUNTIF(Validation!$S$19:$S$178,$AI19)=1,"By surname","Unresolved")))) -> Direct | AK19: =IF($L19="","",IF(MATCH($L19,$L$2:$L$3000,0)<>ROW()-1,"",COUNT($AK$1:$AK18)+1)) | AL19: =IF($G19="","",IF(MATCH($G19,$G$2:$G$3000,0)<>ROW()-1,"",COUNT($AL$1:$AL18)+1)) | AM19: =IF($H19="","",IF(MATCH($H19,$H$2:$H$3000,0)<>ROW()-1,"",COUNT($AM$1:$AM18)+1)) | AN19: =IF($I19="","",IF(MATCH($I19,$I$2:$I$3000,0)<>ROW()-1,"",COUNT($AN$1:$AN18)+1)) | AO19: =IF($Q19="","",IF(MATCH($Q19,$Q$2:$Q$3000,0)<>ROW()-1,"",COUNT($AO$1:$AO18)+1))
A20: J Abay | B20: Approved | C20: L. Carollo | D20: 8/19/2026 | F20: 8/19/2026 | G20: Rocking WW Minerals, LLC | H20: RWW PRB Asset VDR | I20: Converse, WY | J20: 08-35N-68W | K20: Title | M20: N2SW, SWSW | N20: 0.125 | O20: 8/19/2026 7:56:12 PM | Q20: Whitney Wicks | R20: J Abay | S20: J Abay | T20: 8/19/2026 | U20: Reworked Clone AOI Pull and enter the source deed Prune interest | W20: =IF($F20="",0,IFERROR(IF(ISNUMBER($F20),INT($F20),DATE(VALUE(MID(SUBSTITUTE(LEFT($F20,FIND(" ",$F20&" ")-1),"/",REPT(" ",20)),41,20)),VALUE(LEFT(SUBSTITUTE(LEFT($F20,FIND(" ",$F20&" ")-1),"/",REPT(" ",20)),20)),VALUE(MID(SUBSTITUTE(LEFT($F20,FIND(" ",$F20&" ")-1),"/",REPT(" ",20)),21,20)))),0)) -> 46253 | X20: =IF(ISNUMBER($N20),$N20*Validation!$B$5,"") -> 1 | Y20: =IF($A20="","",SUBSTITUTE(SUBSTITUTE(SUBSTITUTE(SUBSTITUTE(SUBSTITUTE(SUBSTITUTE(SUBSTITUTE(UPPER(TRIM($A20)),"Á","A"),"É","E"),"Í","I"),"Ó","O"),"Ú","U"),"Ñ","N"),"Ü","U")) -> J ABAY | Z20: =IF($Y20="","",LEFT($Y20,1)&" "&TRIM(RIGHT(SUBSTITUTE($Y20," ",REPT(" ",50)),50))) -> J ABAY | AA20: =IF($AF20="","",IF(COUNTIF(Validation!$U$19:$U$178,$AF20)>0,"OK","NO MATCH")) -> OK | AB20: =IF($W20=0,"",IF(AND($W20>=Validation!$B$3,$W20<=Validation!$C$3),"Yes","No")) -> Yes | AC20: =IF($A20="","",$AF20&"|"&TEXT($W20,"yyyy-mm-dd")&"|"&$J20&"|"&$N20) -> J ABAY|2026-08-19|08-35N-68W|0.125 | AD20: =IF($AC20="","",IF(COUNTIF($AC$2:$AC$3000,$AC20)>1,"REVIEW","OK")) -> OK | AE20: =IF(OR($W20=0,$O20=""),"",IF(IFERROR(IF(ISNUMBER($O20),INT($O20),DATE(VALUE(MID(SUBSTITUTE(LEFT($O20,FIND(" ",$O20&" ")-1),"/",REPT(" ",20)),41,20)),VALUE(LEFT(SUBSTITUTE(LEFT($O20,FIND(" ",$O20&" ")-1),"/",REPT(" ",20)),20)),VALUE(MID(SUBSTITUTE(LEFT($O20,FIND(" ",$O20&" ")-1),"/",REPT(" ",20)),21,20)))),0)>$W20,"Late","Same day")) -> Same day | AF20: =IF($A20="","",IFERROR(INDEX(Validation!$C$193:$C$217,MATCH($A20,Validation!$A$193:$A$217,0)),IF(COUNTIF(Validation!$U$19:$U$178,$Z20)>0,$Z20,IF(COUNTIF(Validation!$S$19:$S$178,$AI20)=1,INDEX(Validation!$U$19:$U$178,MATCH($AI20,Validation!$S$19:$S$178,0)),$Z20)))) -> J ABAY | AG20: =IF(COUNTA($A20:$U20)=0,"",IF($A20="","No name",IF($F20="","No date",IF($W20=0,"Date ilegible",IF(NOT(ISNUMBER($N20)),"Hours no numéricas",IF($AA20="NO MATCH","Person no identificada","OK")))))) -> OK | AH20: =IF($W20=0,"No date",IF($W20<Validation!$B$3,"Before period",IF($W20>Validation!$C$3,"After period","In period"))) -> In period | AI20: =IF($Y20="","",TRIM(RIGHT(SUBSTITUTE($Y20," ",REPT(" ",50)),50))) -> ABAY | AJ20: =IF($A20="","",IF(NOT(ISERROR(MATCH($A20,Validation!$A$193:$A$217,0))),"Manual mapping",IF(COUNTIF(Validation!$U$19:$U$178,$Z20)>0,"Direct",IF(COUNTIF(Validation!$S$19:$S$178,$AI20)=1,"By surname","Unresolved")))) -> Direct | AK20: =IF($L20="","",IF(MATCH($L20,$L$2:$L$3000,0)<>ROW()-1,"",COUNT($AK$1:$AK19)+1)) | AL20: =IF($G20="","",IF(MATCH($G20,$G$2:$G$3000,0)<>ROW()-1,"",COUNT($AL$1:$AL19)+1)) | AM20: =IF($H20="","",IF(MATCH($H20,$H$2:$H$3000,0)<>ROW()-1,"",COUNT($AM$1:$AM19)+1)) | AN20: =IF($I20="","",IF(MATCH($I20,$I$2:$I$3000,0)<>ROW()-1,"",COUNT($AN$1:$AN19)+1)) | AO20: =IF($Q20="","",IF(MATCH($Q20,$Q$2:$Q$3000,0)<>ROW()-1,"",COUNT($AO$1:$AO19)+1))
A21: J Abay | B21: Approved | C21: L. Carollo | D21: 8/19/2026 | F21: 8/19/2026 | G21: Rocking WW Minerals, LLC | H21: RWW PRB Asset VDR | I21: Campbell, WY | J21: 06-41N-71W | K21: Title | M21: E2;_LOTS_8-9,14-15,16-17,22-23 | N21: 0.125 | O21: 8/19/2026 7:56:38 PM | Q21: Whitney Wicks | R21: J Abay | S21: J Abay | T21: 8/19/2026 | U21: Reworked Clone AOI Pull and enter the source deed Prune interest | W21: =IF($F21="",0,IFERROR(IF(ISNUMBER($F21),INT($F21),DATE(VALUE(MID(SUBSTITUTE(LEFT($F21,FIND(" ",$F21&" ")-1),"/",REPT(" ",20)),41,20)),VALUE(LEFT(SUBSTITUTE(LEFT($F21,FIND(" ",$F21&" ")-1),"/",REPT(" ",20)),20)),VALUE(MID(SUBSTITUTE(LEFT($F21,FIND(" ",$F21&" ")-1),"/",REPT(" ",20)),21,20)))),0)) -> 46253 | X21: =IF(ISNUMBER($N21),$N21*Validation!$B$5,"") -> 1 | Y21: =IF($A21="","",SUBSTITUTE(SUBSTITUTE(SUBSTITUTE(SUBSTITUTE(SUBSTITUTE(SUBSTITUTE(SUBSTITUTE(UPPER(TRIM($A21)),"Á","A"),"É","E"),"Í","I"),"Ó","O"),"Ú","U"),"Ñ","N"),"Ü","U")) -> J ABAY | Z21: =IF($Y21="","",LEFT($Y21,1)&" "&TRIM(RIGHT(SUBSTITUTE($Y21," ",REPT(" ",50)),50))) -> J ABAY | AA21: =IF($AF21="","",IF(COUNTIF(Validation!$U$19:$U$178,$AF21)>0,"OK","NO MATCH")) -> OK | AB21: =IF($W21=0,"",IF(AND($W21>=Validation!$B$3,$W21<=Validation!$C$3),"Yes","No")) -> Yes | AC21: =IF($A21="","",$AF21&"|"&TEXT($W21,"yyyy-mm-dd")&"|"&$J21&"|"&$N21) -> J ABAY|2026-08-19|06-41N-71W|0.125 | AD21: =IF($AC21="","",IF(COUNTIF($AC$2:$AC$3000,$AC21)>1,"REVIEW","OK")) -> OK | AE21: =IF(OR($W21=0,$O21=""),"",IF(IFERROR(IF(ISNUMBER($O21),INT($O21),DATE(VALUE(MID(SUBSTITUTE(LEFT($O21,FIND(" ",$O21&" ")-1),"/",REPT(" ",20)),41,20)),VALUE(LEFT(SUBSTITUTE(LEFT($O21,FIND(" ",$O21&" ")-1),"/",REPT(" ",20)),20)),VALUE(MID(SUBSTITUTE(LEFT($O21,FIND(" ",$O21&" ")-1),"/",REPT(" ",20)),21,20)))),0)>$W21,"Late","Same day")) -> Same day | AF21: =IF($A21="","",IFERROR(INDEX(Validation!$C$193:$C$217,MATCH($A21,Validation!$A$193:$A$217,0)),IF(COUNTIF(Validation!$U$19:$U$178,$Z21)>0,$Z21,IF(COUNTIF(Validation!$S$19:$S$178,$AI21)=1,INDEX(Validation!$U$19:$U$178,MATCH($AI21,Validation!$S$19:$S$178,0)),$Z21)))) -> J ABAY | AG21: =IF(COUNTA($A21:$U21)=0,"",IF($A21="","No name",IF($F21="","No date",IF($W21=0,"Date ilegible",IF(NOT(ISNUMBER($N21)),"Hours no numéricas",IF($AA21="NO MATCH","Person no identificada","OK")))))) -> OK | AH21: =IF($W21=0,"No date",IF($W21<Validation!$B$3,"Before period",IF($W21>Validation!$C$3,"After period","In period"))) -> In period | AI21: =IF($Y21="","",TRIM(RIGHT(SUBSTITUTE($Y21," ",REPT(" ",50)),50))) -> ABAY | AJ21: =IF($A21="","",IF(NOT(ISERROR(MATCH($A21,Validation!$A$193:$A$217,0))),"Manual mapping",IF(COUNTIF(Validation!$U$19:$U$178,$Z21)>0,"Direct",IF(COUNTIF(Validation!$S$19:$S$178,$AI21)=1,"By surname","Unresolved")))) -> Direct | AK21: =IF($L21="","",IF(MATCH($L21,$L$2:$L$3000,0)<>ROW()-1,"",COUNT($AK$1:$AK20)+1)) | AL21: =IF($G21="","",IF(MATCH($G21,$G$2:$G$3000,0)<>ROW()-1,"",COUNT($AL$1:$AL20)+1)) | AM21: =IF($H21="","",IF(MATCH($H21,$H$2:$H$3000,0)<>ROW()-1,"",COUNT($AM$1:$AM20)+1)) | AN21: =IF($I21="","",IF(MATCH($I21,$I$2:$I$3000,0)<>ROW()-1,"",COUNT($AN$1:$AN20)+1)) | AO21: =IF($Q21="","",IF(MATCH($Q21,$Q$2:$Q$3000,0)<>ROW()-1,"",COUNT($AO$1:$AO20)+1))
A22: J Abay | B22: Approved | C22: L. Carollo | D22: 8/19/2026 | F22: 8/19/2026 | G22: Rocking WW Minerals, LLC | H22: RWW PRB Asset VDR | I22: Campbell, WY | J22: 06-41N-72W | K22: Title | M22: ALL | N22: 0.125 | O22: 8/19/2026 7:57:04 PM | Q22: Whitney Wicks | R22: J Abay | S22: J Abay | T22: 8/19/2026 | U22: Koch, Kathy Reworked Clone AOI Pull and enter the source deed Prune interest | W22: =IF($F22="",0,IFERROR(IF(ISNUMBER($F22),INT($F22),DATE(VALUE(MID(SUBSTITUTE(LEFT($F22,FIND(" ",$F22&" ")-1),"/",REPT(" ",20)),41,20)),VALUE(LEFT(SUBSTITUTE(LEFT($F22,FIND(" ",$F22&" ")-1),"/",REPT(" ",20)),20)),VALUE(MID(SUBSTITUTE(LEFT($F22,FIND(" ",$F22&" ")-1),"/",REPT(" ",20)),21,20)))),0)) -> 46253 | X22: =IF(ISNUMBER($N22),$N22*Validation!$B$5,"") -> 1 | Y22: =IF($A22="","",SUBSTITUTE(SUBSTITUTE(SUBSTITUTE(SUBSTITUTE(SUBSTITUTE(SUBSTITUTE(SUBSTITUTE(UPPER(TRIM($A22)),"Á","A"),"É","E"),"Í","I"),"Ó","O"),"Ú","U"),"Ñ","N"),"Ü","U")) -> J ABAY | Z22: =IF($Y22="","",LEFT($Y22,1)&" "&TRIM(RIGHT(SUBSTITUTE($Y22," ",REPT(" ",50)),50))) -> J ABAY | AA22: =IF($AF22="","",IF(COUNTIF(Validation!$U$19:$U$178,$AF22)>0,"OK","NO MATCH")) -> OK | AB22: =IF($W22=0,"",IF(AND($W22>=Validation!$B$3,$W22<=Validation!$C$3),"Yes","No")) -> Yes | AC22: =IF($A22="","",$AF22&"|"&TEXT($W22,"yyyy-mm-dd")&"|"&$J22&"|"&$N22) -> J ABAY|2026-08-19|06-41N-72W|0.125 | AD22: =IF($AC22="","",IF(COUNTIF($AC$2:$AC$3000,$AC22)>1,"REVIEW","OK")) -> REVIEW | AE22: =IF(OR($W22=0,$O22=""),"",IF(IFERROR(IF(ISNUMBER($O22),INT($O22),DATE(VALUE(MID(SUBSTITUTE(LEFT($O22,FIND(" ",$O22&" ")-1),"/",REPT(" ",20)),41,20)),VALUE(LEFT(SUBSTITUTE(LEFT($O22,FIND(" ",$O22&" ")-1),"/",REPT(" ",20)),20)),VALUE(MID(SUBSTITUTE(LEFT($O22,FIND(" ",$O22&" ")-1),"/",REPT(" ",20)),21,20)))),0)>$W22,"Late","Same day")) -> Same day | AF22: =IF($A22="","",IFERROR(INDEX(Validation!$C$193:$C$217,MATCH($A22,Validation!$A$193:$A$217,0)),IF(COUNTIF(Validation!$U$19:$U$178,$Z22)>0,$Z22,IF(COUNTIF(Validation!$S$19:$S$178,$AI22)=1,INDEX(Validation!$U$19:$U$178,MATCH($AI22,Validation!$S$19:$S$178,0)),$Z22)))) -> J ABAY | AG22: =IF(COUNTA($A22:$U22)=0,"",IF($A22="","No name",IF($F22="","No date",IF($W22=0,"Date ilegible",IF(NOT(ISNUMBER($N22)),"Hours no numéricas",IF($AA22="NO MATCH","Person no identificada","OK")))))) -> OK | AH22: =IF($W22=0,"No date",IF($W22<Validation!$B$3,"Before period",IF($W22>Validation!$C$3,"After period","In period"))) -> In period | AI22: =IF($Y22="","",TRIM(RIGHT(SUBSTITUTE($Y22," ",REPT(" ",50)),50))) -> ABAY | AJ22: =IF($A22="","",IF(NOT(ISERROR(MATCH($A22,Validation!$A$193:$A$217,0))),"Manual mapping",IF(COUNTIF(Validation!$U$19:$U$178,$Z22)>0,"Direct",IF(COUNTIF(Validation!$S$19:$S$178,$AI22)=1,"By surname","Unresolved")))) -> Direct | AK22: =IF($L22="","",IF(MATCH($L22,$L$2:$L$3000,0)<>ROW()-1,"",COUNT($AK$1:$AK21)+1)) | AL22: =IF($G22="","",IF(MATCH($G22,$G$2:$G$3000,0)<>ROW()-1,"",COUNT($AL$1:$AL21)+1)) | AM22: =IF($H22="","",IF(MATCH($H22,$H$2:$H$3000,0)<>ROW()-1,"",COUNT($AM$1:$AM21)+1)) | AN22: =IF($I22="","",IF(MATCH($I22,$I$2:$I$3000,0)<>ROW()-1,"",COUNT($AN$1:$AN21)+1)) | AO22: =IF($Q22="","",IF(MATCH($Q22,$Q$2:$Q$3000,0)<>ROW()-1,"",COUNT($AO$1:$AO21)+1))
A23: J Abay | B23: Approved | C23: L. Carollo | D23: 8/19/2026 | F23: 8/19/2026 | G23: Rocking WW Minerals, LLC | H23: RWW PRB Asset VDR | I23: Campbell, WY | J23: 06-41N-72W | K23: Title | M23: ALL | N23: 0.125 | O23: 8/19/2026 7:57:20 PM | Q23: Whitney Wicks | R23: J Abay | S23: J Abay | T23: 8/19/2026 | U23: Anderson Minerals Deal Reworked Clone AOI Pull and enter the source deed Prune interest | W23: =IF($F23="",0,IFERROR(IF(ISNUMBER($F23),INT($F23),DATE(VALUE(MID(SUBSTITUTE(LEFT($F23,FIND(" ",$F23&" ")-1),"/",REPT(" ",20)),41,20)),VALUE(LEFT(SUBSTITUTE(LEFT($F23,FIND(" ",$F23&" ")-1),"/",REPT(" ",20)),20)),VALUE(MID(SUBSTITUTE(LEFT($F23,FIND(" ",$F23&" ")-1),"/",REPT(" ",20)),21,20)))),0)) -> 46253 | X23: =IF(ISNUMBER($N23),$N23*Validation!$B$5,"") -> 1 | Y23: =IF($A23="","",SUBSTITUTE(SUBSTITUTE(SUBSTITUTE(SUBSTITUTE(SUBSTITUTE(SUBSTITUTE(SUBSTITUTE(UPPER(TRIM($A23)),"Á","A"),"É","E"),"Í","I"),"Ó","O"),"Ú","U"),"Ñ","N"),"Ü","U")) -> J ABAY | Z23: =IF($Y23="","",LEFT($Y23,1)&" "&TRIM(RIGHT(SUBSTITUTE($Y23," ",REPT(" ",50)),50))) -> J ABAY | AA23: =IF($AF23="","",IF(COUNTIF(Validation!$U$19:$U$178,$AF23)>0,"OK","NO MATCH")) -> OK | AB23: =IF($W23=0,"",IF(AND($W23>=Validation!$B$3,$W23<=Validation!$C$3),"Yes","No")) -> Yes | AC23: =IF($A23="","",$AF23&"|"&TEXT($W23,"yyyy-mm-dd")&"|"&$J23&"|"&$N23) -> J ABAY|2026-08-19|06-41N-72W|0.125 | AD23: =IF($AC23="","",IF(COUNTIF($AC$2:$AC$3000,$AC23)>1,"REVIEW","OK")) -> REVIEW | AE23: =IF(OR($W23=0,$O23=""),"",IF(IFERROR(IF(ISNUMBER($O23),INT($O23),DATE(VALUE(MID(SUBSTITUTE(LEFT($O23,FIND(" ",$O23&" ")-1),"/",REPT(" ",20)),41,20)),VALUE(LEFT(SUBSTITUTE(LEFT($O23,FIND(" ",$O23&" ")-1),"/",REPT(" ",20)),20)),VALUE(MID(SUBSTITUTE(LEFT($O23,FIND(" ",$O23&" ")-1),"/",REPT(" ",20)),21,20)))),0)>$W23,"Late","Same day")) -> Same day | AF23: =IF($A23="","",IFERROR(INDEX(Validation!$C$193:$C$217,MATCH($A23,Validation!$A$193:$A$217,0)),IF(COUNTIF(Validation!$U$19:$U$178,$Z23)>0,$Z23,IF(COUNTIF(Validation!$S$19:$S$178,$AI23)=1,INDEX(Validation!$U$19:$U$178,MATCH($AI23,Validation!$S$19:$S$178,0)),$Z23)))) -> J ABAY | AG23: =IF(COUNTA($A23:$U23)=0,"",IF($A23="","No name",IF($F23="","No date",IF($W23=0,"Date ilegible",IF(NOT(ISNUMBER($N23)),"Hours no numéricas",IF($AA23="NO MATCH","Person no identificada","OK")))))) -> OK | AH23: =IF($W23=0,"No date",IF($W23<Validation!$B$3,"Before period",IF($W23>Validation!$C$3,"After period","In period"))) -> In period | AI23: =IF($Y23="","",TRIM(RIGHT(SUBSTITUTE($Y23," ",REPT(" ",50)),50))) -> ABAY | AJ23: =IF($A23="","",IF(NOT(ISERROR(MATCH($A23,Validation!$A$193:$A$217,0))),"Manual mapping",IF(COUNTIF(Validation!$U$19:$U$178,$Z23)>0,"Direct",IF(COUNTIF(Validation!$S$19:$S$178,$AI23)=1,"By surname","Unresolved")))) -> Direct | AK23: =IF($L23="","",IF(MATCH($L23,$L$2:$L$3000,0)<>ROW()-1,"",COUNT($AK$1:$AK22)+1)) | AL23: =IF($G23="","",IF(MATCH($G23,$G$2:$G$3000,0)<>ROW()-1,"",COUNT($AL$1:$AL22)+1)) | AM23: =IF($H23="","",IF(MATCH($H23,$H$2:$H$3000,0)<>ROW()-1,"",COUNT($AM$1:$AM22)+1)) | AN23: =IF($I23="","",IF(MATCH($I23,$I$2:$I$3000,0)<>ROW()-1,"",COUNT($AN$1:$AN22)+1)) | AO23: =IF($Q23="","",IF(MATCH($Q23,$Q$2:$Q$3000,0)<>ROW()-1,"",COUNT($AO$1:$AO22)+1))
A24: J Abay | B24: Approved | C24: L. Carollo | D24: 8/19/2026 | F24: 8/19/2026 | G24: Rocking WW Minerals, LLC | H24: RWW PRB Asset VDR | I24: Campbell, WY | J24: 06-41N-72W | K24: Title | M24: Lots 1-2, S2NE | N24: 0.125 | O24: 8/19/2026 7:57:32 PM | Q24: Whitney Wicks | R24: J Abay | S24: J Abay | T24: 8/19/2026 | U24: Anderson Minerals Deal Reworked Clone AOI Pull and enter the source deed Prune interest | W24: =IF($F24="",0,IFERROR(IF(ISNUMBER($F24),INT($F24),DATE(VALUE(MID(SUBSTITUTE(LEFT($F24,FIND(" ",$F24&" ")-1),"/",REPT(" ",20)),41,20)),VALUE(LEFT(SUBSTITUTE(LEFT($F24,FIND(" ",$F24&" ")-1),"/",REPT(" ",20)),20)),VALUE(MID(SUBSTITUTE(LEFT($F24,FIND(" ",$F24&" ")-1),"/",REPT(" ",20)),21,20)))),0)) -> 46253 | X24: =IF(ISNUMBER($N24),$N24*Validation!$B$5,"") -> 1 | Y24: =IF($A24="","",SUBSTITUTE(SUBSTITUTE(SUBSTITUTE(SUBSTITUTE(SUBSTITUTE(SUBSTITUTE(SUBSTITUTE(UPPER(TRIM($A24)),"Á","A"),"É","E"),"Í","I"),"Ó","O"),"Ú","U"),"Ñ","N"),"Ü","U")) -> J ABAY | Z24: =IF($Y24="","",LEFT($Y24,1)&" "&TRIM(RIGHT(SUBSTITUTE($Y24," ",REPT(" ",50)),50))) -> J ABAY | AA24: =IF($AF24="","",IF(COUNTIF(Validation!$U$19:$U$178,$AF24)>0,"OK","NO MATCH")) -> OK | AB24: =IF($W24=0,"",IF(AND($W24>=Validation!$B$3,$W24<=Validation!$C$3),"Yes","No")) -> Yes | AC24: =IF($A24="","",$AF24&"|"&TEXT($W24,"yyyy-mm-dd")&"|"&$J24&"|"&$N24) -> J ABAY|2026-08-19|06-41N-72W|0.125 | AD24: =IF($AC24="","",IF(COUNTIF($AC$2:$AC$3000,$AC24)>1,"REVIEW","OK")) -> REVIEW | AE24: =IF(OR($W24=0,$O24=""),"",IF(IFERROR(IF(ISNUMBER($O24),INT($O24),DATE(VALUE(MID(SUBSTITUTE(LEFT($O24,FIND(" ",$O24&" ")-1),"/",REPT(" ",20)),41,20)),VALUE(LEFT(SUBSTITUTE(LEFT($O24,FIND(" ",$O24&" ")-1),"/",REPT(" ",20)),20)),VALUE(MID(SUBSTITUTE(LEFT($O24,FIND(" ",$O24&" ")-1),"/",REPT(" ",20)),21,20)))),0)>$W24,"Late","Same day")) -> Same day | AF24: =IF($A24="","",IFERROR(INDEX(Validation!$C$193:$C$217,MATCH($A24,Validation!$A$193:$A$217,0)),IF(COUNTIF(Validation!$U$19:$U$178,$Z24)>0,$Z24,IF(COUNTIF(Validation!$S$19:$S$178,$AI24)=1,INDEX(Validation!$U$19:$U$178,MATCH($AI24,Validation!$S$19:$S$178,0)),$Z24)))) -> J ABAY | AG24: =IF(COUNTA($A24:$U24)=0,"",IF($A24="","No name",IF($F24="","No date",IF($W24=0,"Date ilegible",IF(NOT(ISNUMBER($N24)),"Hours no numéricas",IF($AA24="NO MATCH","Person no identificada","OK")))))) -> OK | AH24: =IF($W24=0,"No date",IF($W24<Validation!$B$3,"Before period",IF($W24>Validation!$C$3,"After period","In period"))) -> In period | AI24: =IF($Y24="","",TRIM(RIGHT(SUBSTITUTE($Y24," ",REPT(" ",50)),50))) -> ABAY | AJ24: =IF($A24="","",IF(NOT(ISERROR(MATCH($A24,Validation!$A$193:$A$217,0))),"Manual mapping",IF(COUNTIF(Validation!$U$19:$U$178,$Z24)>0,"Direct",IF(COUNTIF(Validation!$S$19:$S$178,$AI24)=1,"By surname","Unresolved")))) -> Direct | AK24: =IF($L24="","",IF(MATCH($L24,$L$2:$L$3000,0)<>ROW()-1,"",COUNT($AK$1:$AK23)+1)) | AL24: =IF($G24="","",IF(MATCH($G24,$G$2:$G$3000,0)<>ROW()-1,"",COUNT($AL$1:$AL23)+1)) | AM24: =IF($H24="","",IF(MATCH($H24,$H$2:$H$3000,0)<>ROW()-1,"",COUNT($AM$1:$AM23)+1)) | AN24: =IF($I24="","",IF(MATCH($I24,$I$2:$I$3000,0)<>ROW()-1,"",COUNT($AN$1:$AN23)+1)) | AO24: =IF($Q24="","",IF(MATCH($Q24,$Q$2:$Q$3000,0)<>ROW()-1,"",COUNT($AO$1:$AO23)+1))
A25: J Abay | B25: Approved | C25: L. Carollo | D25: 8/19/2026 | F25: 8/19/2026 | G25: Rocking WW Minerals, LLC | H25: RWW PRB Asset VDR | I25: Campbell, WY | J25: 07-41N-72W | K25: Title | M25: Lots 5, 10, 15, 17 | N25: 0.125 | O25: 8/19/2026 7:58:02 PM | Q25: Whitney Wicks | R25: J Abay | S25: J Abay | T25: 8/19/2026 | U25: Clone AOI Pull and enter the source deed Prune interest | W25: =IF($F25="",0,IFERROR(IF(ISNUMBER($F25),INT($F25),DATE(VALUE(MID(SUBSTITUTE(LEFT($F25,FIND(" ",$F25&" ")-1),"/",REPT(" ",20)),41,20)),VALUE(LEFT(SUBSTITUTE(LEFT($F25,FIND(" ",$F25&" ")-1),"/",REPT(" ",20)),20)),VALUE(MID(SUBSTITUTE(LEFT($F25,FIND(" ",$F25&" ")-1),"/",REPT(" ",20)),21,20)))),0)) -> 46253 | X25: =IF(ISNUMBER($N25),$N25*Validation!$B$5,"") -> 1 | Y25: =IF($A25="","",SUBSTITUTE(SUBSTITUTE(SUBSTITUTE(SUBSTITUTE(SUBSTITUTE(SUBSTITUTE(SUBSTITUTE(UPPER(TRIM($A25)),"Á","A"),"É","E"),"Í","I"),"Ó","O"),"Ú","U"),"Ñ","N"),"Ü","U")) -> J ABAY | Z25: =IF($Y25="","",LEFT($Y25,1)&" "&TRIM(RIGHT(SUBSTITUTE($Y25," ",REPT(" ",50)),50))) -> J ABAY | AA25: =IF($AF25="","",IF(COUNTIF(Validation!$U$19:$U$178,$AF25)>0,"OK","NO MATCH")) -> OK | AB25: =IF($W25=0,"",IF(AND($W25>=Validation!$B$3,$W25<=Validation!$C$3),"Yes","No")) -> Yes | AC25: =IF($A25="","",$AF25&"|"&TEXT($W25,"yyyy-mm-dd")&"|"&$J25&"|"&$N25) -> J ABAY|2026-08-19|07-41N-72W|0.125 | AD25: =IF($AC25="","",IF(COUNTIF($AC$2:$AC$3000,$AC25)>1,"REVIEW","OK")) -> OK | AE25: =IF(OR($W25=0,$O25=""),"",IF(IFERROR(IF(ISNUMBER($O25),INT($O25),DATE(VALUE(MID(SUBSTITUTE(LEFT($O25,FIND(" ",$O25&" ")-1),"/",REPT(" ",20)),41,20)),VALUE(LEFT(SUBSTITUTE(LEFT($O25,FIND(" ",$O25&" ")-1),"/",REPT(" ",20)),20)),VALUE(MID(SUBSTITUTE(LEFT($O25,FIND(" ",$O25&" ")-1),"/",REPT(" ",20)),21,20)))),0)>$W25,"Late","Same day")) -> Same day | AF25: =IF($A25="","",IFERROR(INDEX(Validation!$C$193:$C$217,MATCH($A25,Validation!$A$193:$A$217,0)),IF(COUNTIF(Validation!$U$19:$U$178,$Z25)>0,$Z25,IF(COUNTIF(Validation!$S$19:$S$178,$AI25)=1,INDEX(Validation!$U$19:$U$178,MATCH($AI25,Validation!$S$19:$S$178,0)),$Z25)))) -> J ABAY | AG25: =IF(COUNTA($A25:$U25)=0,"",IF($A25="","No name",IF($F25="","No date",IF($W25=0,"Date ilegible",IF(NOT(ISNUMBER($N25)),"Hours no numéricas",IF($AA25="NO MATCH","Person no identificada","OK")))))) -> OK | AH25: =IF($W25=0,"No date",IF($W25<Validation!$B$3,"Before period",IF($W25>Validation!$C$3,"After period","In period"))) -> In period | AI25: =IF($Y25="","",TRIM(RIGHT(SUBSTITUTE($Y25," ",REPT(" ",50)),50))) -> ABAY | AJ25: =IF($A25="","",IF(NOT(ISERROR(MATCH($A25,Validation!$A$193:$A$217,0))),"Manual mapping",IF(COUNTIF(Validation!$U$19:$U$178,$Z25)>0,"Direct",IF(COUNTIF(Validation!$S$19:$S$178,$AI25)=1,"By surname","Unresolved")))) -> Direct | AK25: =IF($L25="","",IF(MATCH($L25,$L$2:$L$3000,0)<>ROW()-1,"",COUNT($AK$1:$AK24)+1)) | AL25: =IF($G25="","",IF(MATCH($G25,$G$2:$G$3000,0)<>ROW()-1,"",COUNT($AL$1:$AL24)+1)) | AM25: =IF($H25="","",IF(MATCH($H25,$H$2:$H$3000,0)<>ROW()-1,"",COUNT($AM$1:$AM24)+1)) | AN25: =IF($I25="","",IF(MATCH($I25,$I$2:$I$3000,0)<>ROW()-1,"",COUNT($AN$1:$AN24)+1)) | AO25: =IF($Q25="","",IF(MATCH($Q25,$Q$2:$Q$3000,0)<>ROW()-1,"",COUNT($AO$1:$AO24)+1))
A26: J Abay | B26: Unapproved | F26: 8/19/2026 | G26: Rocking WW Minerals, LLC | H26: RWW PRB Asset VDR | I26: Converse, WY | J26: 07-41N-71W | K26: Title | M26: Lots 5, 12; 7-10; 15-18 | N26: 0.25 | O26: 8/20/2026 5:10:58 AM | Q26: Whitney Wicks | R26: J Abay | S26: J Abay | T26: 8/20/2026 | U26: (Lots 5, 12 ; W2 ; Lots 7, 8, 9, 10, 15, 16, 17, 18) Clone AOI Pull and enter the source deed Prune interest I had to review three AOIs and fix the source deeds | W26: =IF($F26="",0,IFERROR(IF(ISNUMBER($F26),INT($F26),DATE(VALUE(MID(SUBSTITUTE(LEFT($F26,FIND(" ",$F26&" ")-1),"/",REPT(" ",20)),41,20)),VALUE(LEFT(SUBSTITUTE(LEFT($F26,FIND(" ",$F26&" ")-1),"/",REPT(" ",20)),20)),VALUE(MID(SUBSTITUTE(LEFT($F26,FIND(" ",$F26&" ")-1),"/",REPT(" ",20)),21,20)))),0)) -> 46253 | X26: =IF(ISNUMBER($N26),$N26*Validation!$B$5,"") -> 2 | Y26: =IF($A26="","",SUBSTITUTE(SUBSTITUTE(SUBSTITUTE(SUBSTITUTE(SUBSTITUTE(SUBSTITUTE(SUBSTITUTE(UPPER(TRIM($A26)),"Á","A"),"É","E"),"Í","I"),"Ó","O"),"Ú","U"),"Ñ","N"),"Ü","U")) -> J ABAY | Z26: =IF($Y26="","",LEFT($Y26,1)&" "&TRIM(RIGHT(SUBSTITUTE($Y26," ",REPT(" ",50)),50))) -> J ABAY | AA26: =IF($AF26="","",IF(COUNTIF(Validation!$U$19:$U$178,$AF26)>0,"OK","NO MATCH")) -> OK | AB26: =IF($W26=0,"",IF(AND($W26>=Validation!$B$3,$W26<=Validation!$C$3),"Yes","No")) -> Yes | AC26: =IF($A26="","",$AF26&"|"&TEXT($W26,"yyyy-mm-dd")&"|"&$J26&"|"&$N26) -> J ABAY|2026-08-19|07-41N-71W|0.25 | AD26: =IF($AC26="","",IF(COUNTIF($AC$2:$AC$3000,$AC26)>1,"REVIEW","OK")) -> OK | AE26: =IF(OR($W26=0,$O26=""),"",IF(IFERROR(IF(ISNUMBER($O26),INT($O26),DATE(VALUE(MID(SUBSTITUTE(LEFT($O26,FIND(" ",$O26&" ")-1),"/",REPT(" ",20)),41,20)),VALUE(LEFT(SUBSTITUTE(LEFT($O26,FIND(" ",$O26&" ")-1),"/",REPT(" ",20)),20)),VALUE(MID(SUBSTITUTE(LEFT($O26,FIND(" ",$O26&" ")-1),"/",REPT(" ",20)),21,20)))),0)>$W26,"Late","Same day")) -> Late | AF26: =IF($A26="","",IFERROR(INDEX(Validation!$C$193:$C$217,MATCH($A26,Validation!$A$193:$A$217,0)),IF(COUNTIF(Validation!$U$19:$U$178,$Z26)>0,$Z26,IF(COUNTIF(Validation!$S$19:$S$178,$AI26)=1,INDEX(Validation!$U$19:$U$178,MATCH($AI26,Validation!$S$19:$S$178,0)),$Z26)))) -> J ABAY | AG26: =IF(COUNTA($A26:$U26)=0,"",IF($A26="","No name",IF($F26="","No date",IF($W26=0,"Date ilegible",IF(NOT(ISNUMBER($N26)),"Hours no numéricas",IF($AA26="NO MATCH","Person no identificada","OK")))))) -> OK | AH26: =IF($W26=0,"No date",IF($W26<Validation!$B$3,"Before period",IF($W26>Validation!$C$3,"After period","In period"))) -> In period | AI26: =IF($Y26="","",TRIM(RIGHT(SUBSTITUTE($Y26," ",REPT(" ",50)),50))) -> ABAY | AJ26: =IF($A26="","",IF(NOT(ISERROR(MATCH($A26,Validation!$A$193:$A$217,0))),"Manual mapping",IF(COUNTIF(Validation!$U$19:$U$178,$Z26)>0,"Direct",IF(COUNTIF(Validation!$S$19:$S$178,$AI26)=1,"By surname","Unresolved")))) -> Direct | AK26: =IF($L26="","",IF(MATCH($L26,$L$2:$L$3000,0)<>ROW()-1,"",COUNT($AK$1:$AK25)+1)) | AL26: =IF($G26="","",IF(MATCH($G26,$G$2:$G$3000,0)<>ROW()-1,"",COUNT($AL$1:$AL25)+1)) | AM26: =IF($H26="","",IF(MATCH($H26,$H$2:$H$3000,0)<>ROW()-1,"",COUNT($AM$1:$AM25)+1)) | AN26: =IF($I26="","",IF(MATCH($I26,$I$2:$I$3000,0)<>ROW()-1,"",COUNT($AN$1:$AN25)+1)) | AO26: =IF($Q26="","",IF(MATCH($Q26,$Q$2:$Q$3000,0)<>ROW()-1,"",COUNT($AO$1:$AO25)+1))
A27: J Abay | B27: Unapproved | F27: 8/19/2026 | G27: Rocking WW Minerals, LLC | H27: RWW PRB Asset VDR | I27: Campbell, WY | J27: 08-41N-69W | K27: Title | M27: E2NE | N27: 0.125 | O27: 8/20/2026 5:37:14 AM | Q27: Whitney Wicks | R27: J Abay | S27: J Abay | T27: 8/20/2026 | U27: Clone AOI Pull and enter the source deed Prune interest | W27: =IF($F27="",0,IFERROR(IF(ISNUMBER($F27),INT($F27),DATE(VALUE(MID(SUBSTITUTE(LEFT($F27,FIND(" ",$F27&" ")-1),"/",REPT(" ",20)),41,20)),VALUE(LEFT(SUBSTITUTE(LEFT($F27,FIND(" ",$F27&" ")-1),"/",REPT(" ",20)),20)),VALUE(MID(SUBSTITUTE(LEFT($F27,FIND(" ",$F27&" ")-1),"/",REPT(" ",20)),21,20)))),0)) -> 46253 | X27: =IF(ISNUMBER($N27),$N27*Validation!$B$5,"") -> 1 | Y27: =IF($A27="","",SUBSTITUTE(SUBSTITUTE(SUBSTITUTE(SUBSTITUTE(SUBSTITUTE(SUBSTITUTE(SUBSTITUTE(UPPER(TRIM($A27)),"Á","A"),"É","E"),"Í","I"),"Ó","O"),"Ú","U"),"Ñ","N"),"Ü","U")) -> J ABAY | Z27: =IF($Y27="","",LEFT($Y27,1)&" "&TRIM(RIGHT(SUBSTITUTE($Y27," ",REPT(" ",50)),50))) -> J ABAY | AA27: =IF($AF27="","",IF(COUNTIF(Validation!$U$19:$U$178,$AF27)>0,"OK","NO MATCH")) -> OK | AB27: =IF($W27=0,"",IF(AND($W27>=Validation!$B$3,$W27<=Validation!$C$3),"Yes","No")) -> Yes | AC27: =IF($A27="","",$AF27&"|"&TEXT($W27,"yyyy-mm-dd")&"|"&$J27&"|"&$N27) -> J ABAY|2026-08-19|08-41N-69W|0.125 | AD27: =IF($AC27="","",IF(COUNTIF($AC$2:$AC$3000,$AC27)>1,"REVIEW","OK")) -> OK | AE27: =IF(OR($W27=0,$O27=""),"",IF(IFERROR(IF(ISNUMBER($O27),INT($O27),DATE(VALUE(MID(SUBSTITUTE(LEFT($O27,FIND(" ",$O27&" ")-1),"/",REPT(" ",20)),41,20)),VALUE(LEFT(SUBSTITUTE(LEFT($O27,FIND(" ",$O27&" ")-1),"/",REPT(" ",20)),20)),VALUE(MID(SUBSTITUTE(LEFT($O27,FIND(" ",$O27&" ")-1),"/",REPT(" ",20)),21,20)))),0)>$W27,"Late","Same day")) -> Late | AF27: =IF($A27="","",IFERROR(INDEX(Validation!$C$193:$C$217,MATCH($A27,Validation!$A$193:$A$217,0)),IF(COUNTIF(Validation!$U$19:$U$178,$Z27)>0,$Z27,IF(COUNTIF(Validation!$S$19:$S$178,$AI27)=1,INDEX(Validation!$U$19:$U$178,MATCH($AI27,Validation!$S$19:$S$178,0)),$Z27)))) -> J ABAY | AG27: =IF(COUNTA($A27:$U27)=0,"",IF($A27="","No name",IF($F27="","No date",IF($W27=0,"Date ilegible",IF(NOT(ISNUMBER($N27)),"Hours no numéricas",IF($AA27="NO MATCH","Person no identificada","OK")))))) -> OK | AH27: =IF($W27=0,"No date",IF($W27<Validation!$B$3,"Before period",IF($W27>Validation!$C$3,"After period","In period"))) -> In period | AI27: =IF($Y27="","",TRIM(RIGHT(SUBSTITUTE($Y27," ",REPT(" ",50)),50))) -> ABAY | AJ27: =IF($A27="","",IF(NOT(ISERROR(MATCH($A27,Validation!$A$193:$A$217,0))),"Manual mapping",IF(COUNTIF(Validation!$U$19:$U$178,$Z27)>0,"Direct",IF(COUNTIF(Validation!$S$19:$S$178,$AI27)=1,"By surname","Unresolved")))) -> Direct | AK27: =IF($L27="","",IF(MATCH($L27,$L$2:$L$3000,0)<>ROW()-1,"",COUNT($AK$1:$AK26)+1)) | AL27: =IF($G27="","",IF(MATCH($G27,$G$2:$G$3000,0)<>ROW()-1,"",COUNT($AL$1:$AL26)+1)) | AM27: =IF($H27="","",IF(MATCH($H27,$H$2:$H$3000,0)<>ROW()-1,"",COUNT($AM$1:$AM26)+1)) | AN27: =IF($I27="","",IF(MATCH($I27,$I$2:$I$3000,0)<>ROW()-1,"",COUNT($AN$1:$AN26)+1)) | AO27: =IF($Q27="","",IF(MATCH($Q27,$Q$2:$Q$3000,0)<>ROW()-1,"",COUNT($AO$1:$AO26)+1))
A28: J Abay | B28: Unapproved | F28: 8/19/2026 | G28: Rocking WW Minerals, LLC | H28: RWW PRB Asset VDR | I28: Converse, WY | J28: 08-38N-75W | K28: Title | M28: W2NE, NW, NESW, NWSE | N28: 0.125 | O28: 8/20/2026 5:56:42 AM | Q28: Whitney Wicks | R28: J Abay | S28: J Abay | T28: 8/20/2026 | U28: Clone AOI Pull and enter the source deed Prune interest | W28: =IF($F28="",0,IFERROR(IF(ISNUMBER($F28),INT($F28),DATE(VALUE(MID(SUBSTITUTE(LEFT($F28,FIND(" ",$F28&" ")-1),"/",REPT(" ",20)),41,20)),VALUE(LEFT(SUBSTITUTE(LEFT($F28,FIND(" ",$F28&" ")-1),"/",REPT(" ",20)),20)),VALUE(MID(SUBSTITUTE(LEFT($F28,FIND(" ",$F28&" ")-1),"/",REPT(" ",20)),21,20)))),0)) -> 46253 | X28: =IF(ISNUMBER($N28),$N28*Validation!$B$5,"") -> 1 | Y28: =IF($A28="","",SUBSTITUTE(SUBSTITUTE(SUBSTITUTE(SUBSTITUTE(SUBSTITUTE(SUBSTITUTE(SUBSTITUTE(UPPER(TRIM($A28)),"Á","A"),"É","E"),"Í","I"),"Ó","O"),"Ú","U"),"Ñ","N"),"Ü","U")) -> J ABAY | Z28: =IF($Y28="","",LEFT($Y28,1)&" "&TRIM(RIGHT(SUBSTITUTE($Y28," ",REPT(" ",50)),50))) -> J ABAY | AA28: =IF($AF28="","",IF(COUNTIF(Validation!$U$19:$U$178,$AF28)>0,"OK","NO MATCH")) -> OK | AB28: =IF($W28=0,"",IF(AND($W28>=Validation!$B$3,$W28<=Validation!$C$3),"Yes","No")) -> Yes | AC28: =IF($A28="","",$AF28&"|"&TEXT($W28,"yyyy-mm-dd")&"|"&$J28&"|"&$N28) -> J ABAY|2026-08-19|08-38N-75W|0.125 | AD28: =IF($AC28="","",IF(COUNTIF($AC$2:$AC$3000,$AC28)>1,"REVIEW","OK")) -> OK | AE28: =IF(OR($W28=0,$O28=""),"",IF(IFERROR(IF(ISNUMBER($O28),INT($O28),DATE(VALUE(MID(SUBSTITUTE(LEFT($O28,FIND(" ",$O28&" ")-1),"/",REPT(" ",20)),41,20)),VALUE(LEFT(SUBSTITUTE(LEFT($O28,FIND(" ",$O28&" ")-1),"/",REPT(" ",20)),20)),VALUE(MID(SUBSTITUTE(LEFT($O28,FIND(" ",$O28&" ")-1),"/",REPT(" ",20)),21,20)))),0)>$W28,"Late","Same day")) -> Late | AF28: =IF($A28="","",IFERROR(INDEX(Validation!$C$193:$C$217,MATCH($A28,Validation!$A$193:$A$217,0)),IF(COUNTIF(Validation!$U$19:$U$178,$Z28)>0,$Z28,IF(COUNTIF(Validation!$S$19:$S$178,$AI28)=1,INDEX(Validation!$U$19:$U$178,MATCH($AI28,Validation!$S$19:$S$178,0)),$Z28)))) -> J ABAY | AG28: =IF(COUNTA($A28:$U28)=0,"",IF($A28="","No name",IF($F28="","No date",IF($W28=0,"Date ilegible",IF(NOT(ISNUMBER($N28)),"Hours no numéricas",IF($AA28="NO MATCH","Person no identificada","OK")))))) -> OK | AH28: =IF($W28=0,"No date",IF($W28<Validation!$B$3,"Before period",IF($W28>Validation!$C$3,"After period","In period"))) -> In period | AI28: =IF($Y28="","",TRIM(RIGHT(SUBSTITUTE($Y28," ",REPT(" ",50)),50))) -> ABAY | AJ28: =IF($A28="","",IF(NOT(ISERROR(MATCH($A28,Validation!$A$193:$A$217,0))),"Manual mapping",IF(COUNTIF(Validation!$U$19:$U$178,$Z28)>0,"Direct",IF(COUNTIF(Validation!$S$19:$S$178,$AI28)=1,"By surname","Unresolved")))) -> Direct | AK28: =IF($L28="","",IF(MATCH($L28,$L$2:$L$3000,0)<>ROW()-1,"",COUNT($AK$1:$AK27)+1)) | AL28: =IF($G28="","",IF(MATCH($G28,$G$2:$G$3000,0)<>ROW()-1,"",COUNT($AL$1:$AL27)+1)) | AM28: =IF($H28="","",IF(MATCH($H28,$H$2:$H$3000,0)<>ROW()-1,"",COUNT($AM$1:$AM27)+1)) | AN28: =IF($I28="","",IF(MATCH($I28,$I$2:$I$3000,0)<>ROW()-1,"",COUNT($AN$1:$AN27)+1)) | AO28: =IF($Q28="","",IF(MATCH($Q28,$Q$2:$Q$3000,0)<>ROW()-1,"",COUNT($AO$1:$AO27)+1))
A29: J Castillo | B29: Approved | C29: L. Carollo | D29: 8/19/2026 | F29: 8/19/2026 | G29: Rocking WW Minerals, LLC | H29: RWW PRB Asset VDR | I29: Converse, WY | J29: 06-35N-70W | K29: Title | M29: Lots 1&2, SENE4 | N29: 0.125 | O29: 8/19/2026 8:38:42 PM | Q29: Whitney Wicks | R29: J Castillo | S29: J Castillo | T29: 8/19/2026 | U29: This AOI was corrected according to the RWW BPO Team meeting | W29: =IF($F29="",0,IFERROR(IF(ISNUMBER($F29),INT($F29),DATE(VALUE(MID(SUBSTITUTE(LEFT($F29,FIND(" ",$F29&" ")-1),"/",REPT(" ",20)),41,20)),VALUE(LEFT(SUBSTITUTE(LEFT($F29,FIND(" ",$F29&" ")-1),"/",REPT(" ",20)),20)),VALUE(MID(SUBSTITUTE(LEFT($F29,FIND(" ",$F29&" ")-1),"/",REPT(" ",20)),21,20)))),0)) -> 46253 | X29: =IF(ISNUMBER($N29),$N29*Validation!$B$5,"") -> 1 | Y29: =IF($A29="","",SUBSTITUTE(SUBSTITUTE(SUBSTITUTE(SUBSTITUTE(SUBSTITUTE(SUBSTITUTE(SUBSTITUTE(UPPER(TRIM($A29)),"Á","A"),"É","E"),"Í","I"),"Ó","O"),"Ú","U"),"Ñ","N"),"Ü","U")) -> J CASTILLO | Z29: =IF($Y29="","",LEFT($Y29,1)&" "&TRIM(RIGHT(SUBSTITUTE($Y29," ",REPT(" ",50)),50))) -> J CASTILLO | AA29: =IF($AF29="","",IF(COUNTIF(Validation!$U$19:$U$178,$AF29)>0,"OK","NO MATCH")) -> OK | AB29: =IF($W29=0,"",IF(AND($W29>=Validation!$B$3,$W29<=Validation!$C$3),"Yes","No")) -> Yes | AC29: =IF($A29="","",$AF29&"|"&TEXT($W29,"yyyy-mm-dd")&"|"&$J29&"|"&$N29) -> J CASTILLO|2026-08-19|06-35N-70W|0.125 | AD29: =IF($AC29="","",IF(COUNTIF($AC$2:$AC$3000,$AC29)>1,"REVIEW","OK")) -> REVIEW | AE29: =IF(OR($W29=0,$O29=""),"",IF(IFERROR(IF(ISNUMBER($O29),INT($O29),DATE(VALUE(MID(SUBSTITUTE(LEFT($O29,FIND(" ",$O29&" ")-1),"/",REPT(" ",20)),41,20)),VALUE(LEFT(SUBSTITUTE(LEFT($O29,FIND(" ",$O29&" ")-1),"/",REPT(" ",20)),20)),VALUE(MID(SUBSTITUTE(LEFT($O29,FIND(" ",$O29&" ")-1),"/",REPT(" ",20)),21,20)))),0)>$W29,"Late","Same day")) -> Same day | AF29: =IF($A29="","",IFERROR(INDEX(Validation!$C$193:$C$217,MATCH($A29,Validation!$A$193:$A$217,0)),IF(COUNTIF(Validation!$U$19:$U$178,$Z29)>0,$Z29,IF(COUNTIF(Validation!$S$19:$S$178,$AI29)=1,INDEX(Validation!$U$19:$U$178,MATCH($AI29,Validation!$S$19:$S$178,0)),$Z29)))) -> J CASTILLO | AG29: =IF(COUNTA($A29:$U29)=0,"",IF($A29="","No name",IF($F29="","No date",IF($W29=0,"Date ilegible",IF(NOT(ISNUMBER($N29)),"Hours no numéricas",IF($AA29="NO MATCH","Person no identificada","OK")))))) -> OK | AH29: =IF($W29=0,"No date",IF($W29<Validation!$B$3,"Before period",IF($W29>Validation!$C$3,"After period","In period"))) -> In period | AI29: =IF($Y29="","",TRIM(RIGHT(SUBSTITUTE($Y29," ",REPT(" ",50)),50))) -> CASTILLO | AJ29: =IF($A29="","",IF(NOT(ISERROR(MATCH($A29,Validation!$A$193:$A$217,0))),"Manual mapping",IF(COUNTIF(Validation!$U$19:$U$178,$Z29)>0,"Direct",IF(COUNTIF(Validation!$S$19:$S$178,$AI29)=1,"By surname","Unresolved")))) -> Direct | AK29: =IF($L29="","",IF(MATCH($L29,$L$2:$L$3000,0)<>ROW()-1,"",COUNT($AK$1:$AK28)+1)) | AL29: =IF($G29="","",IF(MATCH($G29,$G$2:$G$3000,0)<>ROW()-1,"",COUNT($AL$1:$AL28)+1)) | AM29: =IF($H29="","",IF(MATCH($H29,$H$2:$H$3000,0)<>ROW()-1,"",COUNT($AM$1:$AM28)+1)) | AN29: =IF($I29="","",IF(MATCH($I29,$I$2:$I$3000,0)<>ROW()-1,"",COUNT($AN$1:$AN28)+1)) | AO29: =IF($Q29="","",IF(MATCH($Q29,$Q$2:$Q$3000,0)<>ROW()-1,"",COUNT($AO$1:$AO28)+1))
A30: J Castillo | B30: Approved | C30: L. Carollo | D30: 8/19/2026 | F30: 8/19/2026 | G30: Rocking WW Minerals, LLC | H30: RWW PRB Asset VDR | I30: Converse, WY | J30: 06-35N-70W | K30: Title | M30: Lots 3, 4 & 5 SENW | N30: 0.125 | O30: 8/19/2026 8:39:20 PM | Q30: Whitney Wicks | R30: J Castillo | S30: J Castillo | T30: 8/19/2026 | U30: This AOI was corrected according to the RWW BPO Team meeting | W30: =IF($F30="",0,IFERROR(IF(ISNUMBER($F30),INT($F30),DATE(VALUE(MID(SUBSTITUTE(LEFT($F30,FIND(" ",$F30&" ")-1),"/",REPT(" ",20)),41,20)),VALUE(LEFT(SUBSTITUTE(LEFT($F30,FIND(" ",$F30&" ")-1),"/",REPT(" ",20)),20)),VALUE(MID(SUBSTITUTE(LEFT($F30,FIND(" ",$F30&" ")-1),"/",REPT(" ",20)),21,20)))),0)) -> 46253 | X30: =IF(ISNUMBER($N30),$N30*Validation!$B$5,"") -> 1 | Y30: =IF($A30="","",SUBSTITUTE(SUBSTITUTE(SUBSTITUTE(SUBSTITUTE(SUBSTITUTE(SUBSTITUTE(SUBSTITUTE(UPPER(TRIM($A30)),"Á","A"),"É","E"),"Í","I"),"Ó","O"),"Ú","U"),"Ñ","N"),"Ü","U")) -> J CASTILLO | Z30: =IF($Y30="","",LEFT($Y30,1)&" "&TRIM(RIGHT(SUBSTITUTE($Y30," ",REPT(" ",50)),50))) -> J CASTILLO | AA30: =IF($AF30="","",IF(COUNTIF(Validation!$U$19:$U$178,$AF30)>0,"OK","NO MATCH")) -> OK | AB30: =IF($W30=0,"",IF(AND($W30>=Validation!$B$3,$W30<=Validation!$C$3),"Yes","No")) -> Yes | AC30: =IF($A30="","",$AF30&"|"&TEXT($W30,"yyyy-mm-dd")&"|"&$J30&"|"&$N30) -> J CASTILLO|2026-08-19|06-35N-70W|0.125 | AD30: =IF($AC30="","",IF(COUNTIF($AC$2:$AC$3000,$AC30)>1,"REVIEW","OK")) -> REVIEW | AE30: =IF(OR($W30=0,$O30=""),"",IF(IFERROR(IF(ISNUMBER($O30),INT($O30),DATE(VALUE(MID(SUBSTITUTE(LEFT($O30,FIND(" ",$O30&" ")-1),"/",REPT(" ",20)),41,20)),VALUE(LEFT(SUBSTITUTE(LEFT($O30,FIND(" ",$O30&" ")-1),"/",REPT(" ",20)),20)),VALUE(MID(SUBSTITUTE(LEFT($O30,FIND(" ",$O30&" ")-1),"/",REPT(" ",20)),21,20)))),0)>$W30,"Late","Same day")) -> Same day | AF30: =IF($A30="","",IFERROR(INDEX(Validation!$C$193:$C$217,MATCH($A30,Validation!$A$193:$A$217,0)),IF(COUNTIF(Validation!$U$19:$U$178,$Z30)>0,$Z30,IF(COUNTIF(Validation!$S$19:$S$178,$AI30)=1,INDEX(Validation!$U$19:$U$178,MATCH($AI30,Validation!$S$19:$S$178,0)),$Z30)))) -> J CASTILLO | AG30: =IF(COUNTA($A30:$U30)=0,"",IF($A30="","No name",IF($F30="","No date",IF($W30=0,"Date ilegible",IF(NOT(ISNUMBER($N30)),"Hours no numéricas",IF($AA30="NO MATCH","Person no identificada","OK")))))) -> OK | AH30: =IF($W30=0,"No date",IF($W30<Validation!$B$3,"Before period",IF($W30>Validation!$C$3,"After period","In period"))) -> In period | AI30: =IF($Y30="","",TRIM(RIGHT(SUBSTITUTE($Y30," ",REPT(" ",50)),50))) -> CASTILLO | AJ30: =IF($A30="","",IF(NOT(ISERROR(MATCH($A30,Validation!$A$193:$A$217,0))),"Manual mapping",IF(COUNTIF(Validation!$U$19:$U$178,$Z30)>0,"Direct",IF(COUNTIF(Validation!$S$19:$S$178,$AI30)=1,"By surname","Unresolved")))) -> Direct | AK30: =IF($L30="","",IF(MATCH($L30,$L$2:$L$3000,0)<>ROW()-1,"",COUNT($AK$1:$AK29)+1)) | AL30: =IF($G30="","",IF(MATCH($G30,$G$2:$G$3000,0)<>ROW()-1,"",COUNT($AL$1:$AL29)+1)) | AM30: =IF($H30="","",IF(MATCH($H30,$H$2:$H$3000,0)<>ROW()-1,"",COUNT($AM$1:$AM29)+1)) | AN30: =IF($I30="","",IF(MATCH($I30,$I$2:$I$3000,0)<>ROW()-1,"",COUNT($AN$1:$AN29)+1)) | AO30: =IF($Q30="","",IF(MATCH($Q30,$Q$2:$Q$3000,0)<>ROW()-1,"",COUNT($AO$1:$AO29)+1))
A31: J Castillo | B31: Approved | C31: L. Carollo | D31: 8/19/2026 | F31: 8/19/2026 | G31: Rocking WW Minerals, LLC | H31: RWW PRB Asset VDR | I31: Converse, WY | J31: 07-34N-68W | K31: Title | M31: Lot 4, SENW, SESW | N31: 0.125 | O31: 8/19/2026 8:39:52 PM | Q31: Whitney Wicks | R31: J Castillo | S31: J Castillo | T31: 8/19/2026 | U31: This AOI was corrected according to the RWW BPO Team meeting | W31: =IF($F31="",0,IFERROR(IF(ISNUMBER($F31),INT($F31),DATE(VALUE(MID(SUBSTITUTE(LEFT($F31,FIND(" ",$F31&" ")-1),"/",REPT(" ",20)),41,20)),VALUE(LEFT(SUBSTITUTE(LEFT($F31,FIND(" ",$F31&" ")-1),"/",REPT(" ",20)),20)),VALUE(MID(SUBSTITUTE(LEFT($F31,FIND(" ",$F31&" ")-1),"/",REPT(" ",20)),21,20)))),0)) -> 46253 | X31: =IF(ISNUMBER($N31),$N31*Validation!$B$5,"") -> 1 | Y31: =IF($A31="","",SUBSTITUTE(SUBSTITUTE(SUBSTITUTE(SUBSTITUTE(SUBSTITUTE(SUBSTITUTE(SUBSTITUTE(UPPER(TRIM($A31)),"Á","A"),"É","E"),"Í","I"),"Ó","O"),"Ú","U"),"Ñ","N"),"Ü","U")) -> J CASTILLO | Z31: =IF($Y31="","",LEFT($Y31,1)&" "&TRIM(RIGHT(SUBSTITUTE($Y31," ",REPT(" ",50)),50))) -> J CASTILLO | AA31: =IF($AF31="","",IF(COUNTIF(Validation!$U$19:$U$178,$AF31)>0,"OK","NO MATCH")) -> OK | AB31: =IF($W31=0,"",IF(AND($W31>=Validation!$B$3,$W31<=Validation!$C$3),"Yes","No")) -> Yes | AC31: =IF($A31="","",$AF31&"|"&TEXT($W31,"yyyy-mm-dd")&"|"&$J31&"|"&$N31) -> J CASTILLO|2026-08-19|07-34N-68W|0.125 | AD31: =IF($AC31="","",IF(COUNTIF($AC$2:$AC$3000,$AC31)>1,"REVIEW","OK")) -> OK | AE31: =IF(OR($W31=0,$O31=""),"",IF(IFERROR(IF(ISNUMBER($O31),INT($O31),DATE(VALUE(MID(SUBSTITUTE(LEFT($O31,FIND(" ",$O31&" ")-1),"/",REPT(" ",20)),41,20)),VALUE(LEFT(SUBSTITUTE(LEFT($O31,FIND(" ",$O31&" ")-1),"/",REPT(" ",20)),20)),VALUE(MID(SUBSTITUTE(LEFT($O31,FIND(" ",$O31&" ")-1),"/",REPT(" ",20)),21,20)))),0)>$W31,"Late","Same day")) -> Same day | AF31: =IF($A31="","",IFERROR(INDEX(Validation!$C$193:$C$217,MATCH($A31,Validation!$A$193:$A$217,0)),IF(COUNTIF(Validation!$U$19:$U$178,$Z31)>0,$Z31,IF(COUNTIF(Validation!$S$19:$S$178,$AI31)=1,INDEX(Validation!$U$19:$U$178,MATCH($AI31,Validation!$S$19:$S$178,0)),$Z31)))) -> J CASTILLO | AG31: =IF(COUNTA($A31:$U31)=0,"",IF($A31="","No name",IF($F31="","No date",IF($W31=0,"Date ilegible",IF(NOT(ISNUMBER($N31)),"Hours no numéricas",IF($AA31="NO MATCH","Person no identificada","OK")))))) -> OK | AH31: =IF($W31=0,"No date",IF($W31<Validation!$B$3,"Before period",IF($W31>Validation!$C$3,"After period","In period"))) -> In period | AI31: =IF($Y31="","",TRIM(RIGHT(SUBSTITUTE($Y31," ",REPT(" ",50)),50))) -> CASTILLO | AJ31: =IF($A31="","",IF(NOT(ISERROR(MATCH($A31,Validation!$A$193:$A$217,0))),"Manual mapping",IF(COUNTIF(Validation!$U$19:$U$178,$Z31)>0,"Direct",IF(COUNTIF(Validation!$S$19:$S$178,$AI31)=1,"By surname","Unresolved")))) -> Direct | AK31: =IF($L31="","",IF(MATCH($L31,$L$2:$L$3000,0)<>ROW()-1,"",COUNT($AK$1:$AK30)+1)) | AL31: =IF($G31="","",IF(MATCH($G31,$G$2:$G$3000,0)<>ROW()-1,"",COUNT($AL$1:$AL30)+1)) | AM31: =IF($H31="","",IF(MATCH($H31,$H$2:$H$3000,0)<>ROW()-1,"",COUNT($AM$1:$AM30)+1)) | AN31: =IF($I31="","",IF(MATCH($I31,$I$2:$I$3000,0)<>ROW()-1,"",COUNT($AN$1:$AN30)+1)) | AO31: =IF($Q31="","",IF(MATCH($Q31,$Q$2:$Q$3000,0)<>ROW()-1,"",COUNT($AO$1:$AO30)+1))
A32: J Castillo | B32: Approved | C32: L. Carollo | D32: 8/19/2026 | F32: 8/19/2026 | G32: Rocking WW Minerals, LLC | H32: RWW PRB Asset VDR | I32: Converse, WY | J32: 06-35N-70W | K32: Title | M32: Lot 3 | N32: 0.125 | O32: 8/19/2026 8:40:06 PM | Q32: Whitney Wicks | R32: J Castillo | S32: J Castillo | T32: 8/19/2026 | U32: This AOI was corrected according to the RWW BPO Team meeting | W32: =IF($F32="",0,IFERROR(IF(ISNUMBER($F32),INT($F32),DATE(VALUE(MID(SUBSTITUTE(LEFT($F32,FIND(" ",$F32&" ")-1),"/",REPT(" ",20)),41,20)),VALUE(LEFT(SUBSTITUTE(LEFT($F32,FIND(" ",$F32&" ")-1),"/",REPT(" ",20)),20)),VALUE(MID(SUBSTITUTE(LEFT($F32,FIND(" ",$F32&" ")-1),"/",REPT(" ",20)),21,20)))),0)) -> 46253 | X32: =IF(ISNUMBER($N32),$N32*Validation!$B$5,"") -> 1 | Y32: =IF($A32="","",SUBSTITUTE(SUBSTITUTE(SUBSTITUTE(SUBSTITUTE(SUBSTITUTE(SUBSTITUTE(SUBSTITUTE(UPPER(TRIM($A32)),"Á","A"),"É","E"),"Í","I"),"Ó","O"),"Ú","U"),"Ñ","N"),"Ü","U")) -> J CASTILLO | Z32: =IF($Y32="","",LEFT($Y32,1)&" "&TRIM(RIGHT(SUBSTITUTE($Y32," ",REPT(" ",50)),50))) -> J CASTILLO | AA32: =IF($AF32="","",IF(COUNTIF(Validation!$U$19:$U$178,$AF32)>0,"OK","NO MATCH")) -> OK | AB32: =IF($W32=0,"",IF(AND($W32>=Validation!$B$3,$W32<=Validation!$C$3),"Yes","No")) -> Yes | AC32: =IF($A32="","",$AF32&"|"&TEXT($W32,"yyyy-mm-dd")&"|"&$J32&"|"&$N32) -> J CASTILLO|2026-08-19|06-35N-70W|0.125 | AD32: =IF($AC32="","",IF(COUNTIF($AC$2:$AC$3000,$AC32)>1,"REVIEW","OK")) -> REVIEW | AE32: =IF(OR($W32=0,$O32=""),"",IF(IFERROR(IF(ISNUMBER($O32),INT($O32),DATE(VALUE(MID(SUBSTITUTE(LEFT($O32,FIND(" ",$O32&" ")-1),"/",REPT(" ",20)),41,20)),VALUE(LEFT(SUBSTITUTE(LEFT($O32,FIND(" ",$O32&" ")-1),"/",REPT(" ",20)),20)),VALUE(MID(SUBSTITUTE(LEFT($O32,FIND(" ",$O32&" ")-1),"/",REPT(" ",20)),21,20)))),0)>$W32,"Late","Same day")) -> Same day | AF32: =IF($A32="","",IFERROR(INDEX(Validation!$C$193:$C$217,MATCH($A32,Validation!$A$193:$A$217,0)),IF(COUNTIF(Validation!$U$19:$U$178,$Z32)>0,$Z32,IF(COUNTIF(Validation!$S$19:$S$178,$AI32)=1,INDEX(Validation!$U$19:$U$178,MATCH($AI32,Validation!$S$19:$S$178,0)),$Z32)))) -> J CASTILLO | AG32: =IF(COUNTA($A32:$U32)=0,"",IF($A32="","No name",IF($F32="","No date",IF($W32=0,"Date ilegible",IF(NOT(ISNUMBER($N32)),"Hours no numéricas",IF($AA32="NO MATCH","Person no identificada","OK")))))) -> OK | AH32: =IF($W32=0,"No date",IF($W32<Validation!$B$3,"Before period",IF($W32>Validation!$C$3,"After period","In period"))) -> In period | AI32: =IF($Y32="","",TRIM(RIGHT(SUBSTITUTE($Y32," ",REPT(" ",50)),50))) -> CASTILLO | AJ32: =IF($A32="","",IF(NOT(ISERROR(MATCH($A32,Validation!$A$193:$A$217,0))),"Manual mapping",IF(COUNTIF(Validation!$U$19:$U$178,$Z32)>0,"Direct",IF(COUNTIF(Validation!$S$19:$S$178,$AI32)=1,"By surname","Unresolved")))) -> Direct | AK32: =IF($L32="","",IF(MATCH($L32,$L$2:$L$3000,0)<>ROW()-1,"",COUNT($AK$1:$AK31)+1)) | AL32: =IF($G32="","",IF(MATCH($G32,$G$2:$G$3000,0)<>ROW()-1,"",COUNT($AL$1:$AL31)+1)) | AM32: =IF($H32="","",IF(MATCH($H32,$H$2:$H$3000,0)<>ROW()-1,"",COUNT($AM$1:$AM31)+1)) | AN32: =IF($I32="","",IF(MATCH($I32,$I$2:$I$3000,0)<>ROW()-1,"",COUNT($AN$1:$AN31)+1)) | AO32: =IF($Q32="","",IF(MATCH($Q32,$Q$2:$Q$3000,0)<>ROW()-1,"",COUNT($AO$1:$AO31)+1))
A33: J Castillo | B33: Approved | C33: L. Carollo | D33: 8/19/2026 | F33: 8/19/2026 | G33: Rocking WW Minerals, LLC | H33: RWW PRB Asset VDR | I33: Converse, WY | J33: 07-35N-68W | K33: Title | M33: (NENW ; E2NE, E2SE ; Lots 3, 4) | N33: 0.25 | O33: 8/19/2026 8:41:39 PM | Q33: Whitney Wicks | R33: J Castillo | S33: J Castillo | T33: 8/19/2026 | U33: The entire chain was prunned and the polygons were checked. Additionally, all the documents were added to the Asana Card. | W33: =IF($F33="",0,IFERROR(IF(ISNUMBER($F33),INT($F33),DATE(VALUE(MID(SUBSTITUTE(LEFT($F33,FIND(" ",$F33&" ")-1),"/",REPT(" ",20)),41,20)),VALUE(LEFT(SUBSTITUTE(LEFT($F33,FIND(" ",$F33&" ")-1),"/",REPT(" ",20)),20)),VALUE(MID(SUBSTITUTE(LEFT($F33,FIND(" ",$F33&" ")-1),"/",REPT(" ",20)),21,20)))),0)) -> 46253 | X33: =IF(ISNUMBER($N33),$N33*Validation!$B$5,"") -> 2 | Y33: =IF($A33="","",SUBSTITUTE(SUBSTITUTE(SUBSTITUTE(SUBSTITUTE(SUBSTITUTE(SUBSTITUTE(SUBSTITUTE(UPPER(TRIM($A33)),"Á","A"),"É","E"),"Í","I"),"Ó","O"),"Ú","U"),"Ñ","N"),"Ü","U")) -> J CASTILLO | Z33: =IF($Y33="","",LEFT($Y33,1)&" "&TRIM(RIGHT(SUBSTITUTE($Y33," ",REPT(" ",50)),50))) -> J CASTILLO | AA33: =IF($AF33="","",IF(COUNTIF(Validation!$U$19:$U$178,$AF33)>0,"OK","NO MATCH")) -> OK | AB33: =IF($W33=0,"",IF(AND($W33>=Validation!$B$3,$W33<=Validation!$C$3),"Yes","No")) -> Yes | AC33: =IF($A33="","",$AF33&"|"&TEXT($W33,"yyyy-mm-dd")&"|"&$J33&"|"&$N33) -> J CASTILLO|2026-08-19|07-35N-68W|0.25 | AD33: =IF($AC33="","",IF(COUNTIF($AC$2:$AC$3000,$AC33)>1,"REVIEW","OK")) -> OK | AE33: =IF(OR($W33=0,$O33=""),"",IF(IFERROR(IF(ISNUMBER($O33),INT($O33),DATE(VALUE(MID(SUBSTITUTE(LEFT($O33,FIND(" ",$O33&" ")-1),"/",REPT(" ",20)),41,20)),VALUE(LEFT(SUBSTITUTE(LEFT($O33,FIND(" ",$O33&" ")-1),"/",REPT(" ",20)),20)),VALUE(MID(SUBSTITUTE(LEFT($O33,FIND(" ",$O33&" ")-1),"/",REPT(" ",20)),21,20)))),0)>$W33,"Late","Same day")) -> Same day | AF33: =IF($A33="","",IFERROR(INDEX(Validation!$C$193:$C$217,MATCH($A33,Validation!$A$193:$A$217,0)),IF(COUNTIF(Validation!$U$19:$U$178,$Z33)>0,$Z33,IF(COUNTIF(Validation!$S$19:$S$178,$AI33)=1,INDEX(Validation!$U$19:$U$178,MATCH($AI33,Validation!$S$19:$S$178,0)),$Z33)))) -> J CASTILLO | AG33: =IF(COUNTA($A33:$U33)=0,"",IF($A33="","No name",IF($F33="","No date",IF($W33=0,"Date ilegible",IF(NOT(ISNUMBER($N33)),"Hours no numéricas",IF($AA33="NO MATCH","Person no identificada","OK")))))) -> OK | AH33: =IF($W33=0,"No date",IF($W33<Validation!$B$3,"Before period",IF($W33>Validation!$C$3,"After period","In period"))) -> In period | AI33: =IF($Y33="","",TRIM(RIGHT(SUBSTITUTE($Y33," ",REPT(" ",50)),50))) -> CASTILLO | AJ33: =IF($A33="","",IF(NOT(ISERROR(MATCH($A33,Validation!$A$193:$A$217,0))),"Manual mapping",IF(COUNTIF(Validation!$U$19:$U$178,$Z33)>0,"Direct",IF(COUNTIF(Validation!$S$19:$S$178,$AI33)=1,"By surname","Unresolved")))) -> Direct | AK33: =IF($L33="","",IF(MATCH($L33,$L$2:$L$3000,0)<>ROW()-1,"",COUNT($AK$1:$AK32)+1)) | AL33: =IF($G33="","",IF(MATCH($G33,$G$2:$G$3000,0)<>ROW()-1,"",COUNT($AL$1:$AL32)+1)) | AM33: =IF($H33="","",IF(MATCH($H33,$H$2:$H$3000,0)<>ROW()-1,"",COUNT($AM$1:$AM32)+1)) | AN33: =IF($I33="","",IF(MATCH($I33,$I$2:$I$3000,0)<>ROW()-1,"",COUNT($AN$1:$AN32)+1)) | AO33: =IF($Q33="","",IF(MATCH($Q33,$Q$2:$Q$3000,0)<>ROW()-1,"",COUNT($AO$1:$AO32)+1))
A34: J Castillo | B34: Approved | C34: L. Carollo | D34: 8/19/2026 | F34: 8/19/2026 | G34: Rocking WW Minerals, LLC | H34: RWW PRB Asset VDR | I34: Converse, WY | J34: 07-36N-69W | K34: Title | M34: Lot 2, NE, E2NW, NESW | N34: 0.25 | O34: 8/19/2026 8:46:17 PM | Q34: Whitney Wicks | R34: J Castillo | S34: J Castillo | T34: 8/19/2026 | U34: The entire chain was prunned and the polygons were checked. Additionally, all the documents were added to the Asana Card. | W34: =IF($F34="",0,IFERROR(IF(ISNUMBER($F34),INT($F34),DATE(VALUE(MID(SUBSTITUTE(LEFT($F34,FIND(" ",$F34&" ")-1),"/",REPT(" ",20)),41,20)),VALUE(LEFT(SUBSTITUTE(LEFT($F34,FIND(" ",$F34&" ")-1),"/",REPT(" ",20)),20)),VALUE(MID(SUBSTITUTE(LEFT($F34,FIND(" ",$F34&" ")-1),"/",REPT(" ",20)),21,20)))),0)) -> 46253 | X34: =IF(ISNUMBER($N34),$N34*Validation!$B$5,"") -> 2 | Y34: =IF($A34="","",SUBSTITUTE(SUBSTITUTE(SUBSTITUTE(SUBSTITUTE(SUBSTITUTE(SUBSTITUTE(SUBSTITUTE(UPPER(TRIM($A34)),"Á","A"),"É","E"),"Í","I"),"Ó","O"),"Ú","U"),"Ñ","N"),"Ü","U")) -> J CASTILLO | Z34: =IF($Y34="","",LEFT($Y34,1)&" "&TRIM(RIGHT(SUBSTITUTE($Y34," ",REPT(" ",50)),50))) -> J CASTILLO | AA34: =IF($AF34="","",IF(COUNTIF(Validation!$U$19:$U$178,$AF34)>0,"OK","NO MATCH")) -> OK | AB34: =IF($W34=0,"",IF(AND($W34>=Validation!$B$3,$W34<=Validation!$C$3),"Yes","No")) -> Yes | AC34: =IF($A34="","",$AF34&"|"&TEXT($W34,"yyyy-mm-dd")&"|"&$J34&"|"&$N34) -> J CASTILLO|2026-08-19|07-36N-69W|0.25 | AD34: =IF($AC34="","",IF(COUNTIF($AC$2:$AC$3000,$AC34)>1,"REVIEW","OK")) -> OK | AE34: =IF(OR($W34=0,$O34=""),"",IF(IFERROR(IF(ISNUMBER($O34),INT($O34),DATE(VALUE(MID(SUBSTITUTE(LEFT($O34,FIND(" ",$O34&" ")-1),"/",REPT(" ",20)),41,20)),VALUE(LEFT(SUBSTITUTE(LEFT($O34,FIND(" ",$O34&" ")-1),"/",REPT(" ",20)),20)),VALUE(MID(SUBSTITUTE(LEFT($O34,FIND(" ",$O34&" ")-1),"/",REPT(" ",20)),21,20)))),0)>$W34,"Late","Same day")) -> Same day | AF34: =IF($A34="","",IFERROR(INDEX(Validation!$C$193:$C$217,MATCH($A34,Validation!$A$193:$A$217,0)),IF(COUNTIF(Validation!$U$19:$U$178,$Z34)>0,$Z34,IF(COUNTIF(Validation!$S$19:$S$178,$AI34)=1,INDEX(Validation!$U$19:$U$178,MATCH($AI34,Validation!$S$19:$S$178,0)),$Z34)))) -> J CASTILLO | AG34: =IF(COUNTA($A34:$U34)=0,"",IF($A34="","No name",IF($F34="","No date",IF($W34=0,"Date ilegible",IF(NOT(ISNUMBER($N34)),"Hours no numéricas",IF($AA34="NO MATCH","Person no identificada","OK")))))) -> OK | AH34: =IF($W34=0,"No date",IF($W34<Validation!$B$3,"Before period",IF($W34>Validation!$C$3,"After period","In period"))) -> In period | AI34: =IF($Y34="","",TRIM(RIGHT(SUBSTITUTE($Y34," ",REPT(" ",50)),50))) -> CASTILLO | AJ34: =IF($A34="","",IF(NOT(ISERROR(MATCH($A34,Validation!$A$193:$A$217,0))),"Manual mapping",IF(COUNTIF(Validation!$U$19:$U$178,$Z34)>0,"Direct",IF(COUNTIF(Validation!$S$19:$S$178,$AI34)=1,"By surname","Unresolved")))) -> Direct | AK34: =IF($L34="","",IF(MATCH($L34,$L$2:$L$3000,0)<>ROW()-1,"",COUNT($AK$1:$AK33)+1)) | AL34: =IF($G34="","",IF(MATCH($G34,$G$2:$G$3000,0)<>ROW()-1,"",COUNT($AL$1:$AL33)+1)) | AM34: =IF($H34="","",IF(MATCH($H34,$H$2:$H$3000,0)<>ROW()-1,"",COUNT($AM$1:$AM33)+1)) | AN34: =IF($I34="","",IF(MATCH($I34,$I$2:$I$3000,0)<>ROW()-1,"",COUNT($AN$1:$AN33)+1)) | AO34: =IF($Q34="","",IF(MATCH($Q34,$Q$2:$Q$3000,0)<>ROW()-1,"",COUNT($AO$1:$AO33)+1))
A35: J Rincon | B35: Approved | C35: L. Carollo | D35: 8/19/2026 | F35: 8/19/2026 | G35: Rocking WW Minerals, LLC | H35: RWW PRB Asset VDR | I35: Converse, WY | J35: 03-36N-71W | K35: Title | M35: 3-36N-71W | N35: 0.125 | O35: 8/19/2026 1:25:23 PM | Q35: Whitney Wicks | R35: J Rincon | S35: J Rincon | T35: 8/19/2026 | U35: Completed prune of mentioned legal description. Some notecards does not light up as the grantors are strangers in title, also some notecards does not have document. | W35: =IF($F35="",0,IFERROR(IF(ISNUMBER($F35),INT($F35),DATE(VALUE(MID(SUBSTITUTE(LEFT($F35,FIND(" ",$F35&" ")-1),"/",REPT(" ",20)),41,20)),VALUE(LEFT(SUBSTITUTE(LEFT($F35,FIND(" ",$F35&" ")-1),"/",REPT(" ",20)),20)),VALUE(MID(SUBSTITUTE(LEFT($F35,FIND(" ",$F35&" ")-1),"/",REPT(" ",20)),21,20)))),0)) -> 46253 | X35: =IF(ISNUMBER($N35),$N35*Validation!$B$5,"") -> 1 | Y35: =IF($A35="","",SUBSTITUTE(SUBSTITUTE(SUBSTITUTE(SUBSTITUTE(SUBSTITUTE(SUBSTITUTE(SUBSTITUTE(UPPER(TRIM($A35)),"Á","A"),"É","E"),"Í","I"),"Ó","O"),"Ú","U"),"Ñ","N"),"Ü","U")) -> J RINCON | Z35: =IF($Y35="","",LEFT($Y35,1)&" "&TRIM(RIGHT(SUBSTITUTE($Y35," ",REPT(" ",50)),50))) -> J RINCON | AA35: =IF($AF35="","",IF(COUNTIF(Validation!$U$19:$U$178,$AF35)>0,"OK","NO MATCH")) -> OK | AB35: =IF($W35=0,"",IF(AND($W35>=Validation!$B$3,$W35<=Validation!$C$3),"Yes","No")) -> Yes | AC35: =IF($A35="","",$AF35&"|"&TEXT($W35,"yyyy-mm-dd")&"|"&$J35&"|"&$N35) -> J RINCON|2026-08-19|03-36N-71W|0.125 | AD35: =IF($AC35="","",IF(COUNTIF($AC$2:$AC$3000,$AC35)>1,"REVIEW","OK")) -> OK | AE35: =IF(OR($W35=0,$O35=""),"",IF(IFERROR(IF(ISNUMBER($O35),INT($O35),DATE(VALUE(MID(SUBSTITUTE(LEFT($O35,FIND(" ",$O35&" ")-1),"/",REPT(" ",20)),41,20)),VALUE(LEFT(SUBSTITUTE(LEFT($O35,FIND(" ",$O35&" ")-1),"/",REPT(" ",20)),20)),VALUE(MID(SUBSTITUTE(LEFT($O35,FIND(" ",$O35&" ")-1),"/",REPT(" ",20)),21,20)))),0)>$W35,"Late","Same day")) -> Same day | AF35: =IF($A35="","",IFERROR(INDEX(Validation!$C$193:$C$217,MATCH($A35,Validation!$A$193:$A$217,0)),IF(COUNTIF(Validation!$U$19:$U$178,$Z35)>0,$Z35,IF(COUNTIF(Validation!$S$19:$S$178,$AI35)=1,INDEX(Validation!$U$19:$U$178,MATCH($AI35,Validation!$S$19:$S$178,0)),$Z35)))) -> J RINCON | AG35: =IF(COUNTA($A35:$U35)=0,"",IF($A35="","No name",IF($F35="","No date",IF($W35=0,"Date ilegible",IF(NOT(ISNUMBER($N35)),"Hours no numéricas",IF($AA35="NO MATCH","Person no identificada","OK")))))) -> OK | AH35: =IF($W35=0,"No date",IF($W35<Validation!$B$3,"Before period",IF($W35>Validation!$C$3,"After period","In period"))) -> In period | AI35: =IF($Y35="","",TRIM(RIGHT(SUBSTITUTE($Y35," ",REPT(" ",50)),50))) -> RINCON | AJ35: =IF($A35="","",IF(NOT(ISERROR(MATCH($A35,Validation!$A$193:$A$217,0))),"Manual mapping",IF(COUNTIF(Validation!$U$19:$U$178,$Z35)>0,"Direct",IF(COUNTIF(Validation!$S$19:$S$178,$AI35)=1,"By surname","Unresolved")))) -> Direct | AK35: =IF($L35="","",IF(MATCH($L35,$L$2:$L$3000,0)<>ROW()-1,"",COUNT($AK$1:$AK34)+1)) | AL35: =IF($G35="","",IF(MATCH($G35,$G$2:$G$3000,0)<>ROW()-1,"",COUNT($AL$1:$AL34)+1)) | AM35: =IF($H35="","",IF(MATCH($H35,$H$2:$H$3000,0)<>ROW()-1,"",COUNT($AM$1:$AM34)+1)) | AN35: =IF($I35="","",IF(MATCH($I35,$I$2:$I$3000,0)<>ROW()-1,"",COUNT($AN$1:$AN34)+1)) | AO35: =IF($Q35="","",IF(MATCH($Q35,$Q$2:$Q$3000,0)<>ROW()-1,"",COUNT($AO$1:$AO34)+1))
A36: J Rincon | B36: Approved | C36: L. Carollo | D36: 8/19/2026 | F36: 8/19/2026 | G36: Rocking WW Minerals, LLC | H36: RWW PRB Asset VDR | I36: Converse, WY | J36: 36-35N-69W | K36: Title | M36: 36-35N-69W | N36: 0.125 | O36: 8/19/2026 1:47:03 PM | Q36: Whitney Wicks | R36: J Rincon | S36: J Rincon | T36: 8/19/2026 | U36: Completed prune of mentioned legal description. | W36: =IF($F36="",0,IFERROR(IF(ISNUMBER($F36),INT($F36),DATE(VALUE(MID(SUBSTITUTE(LEFT($F36,FIND(" ",$F36&" ")-1),"/",REPT(" ",20)),41,20)),VALUE(LEFT(SUBSTITUTE(LEFT($F36,FIND(" ",$F36&" ")-1),"/",REPT(" ",20)),20)),VALUE(MID(SUBSTITUTE(LEFT($F36,FIND(" ",$F36&" ")-1),"/",REPT(" ",20)),21,20)))),0)) -> 46253 | X36: =IF(ISNUMBER($N36),$N36*Validation!$B$5,"") -> 1 | Y36: =IF($A36="","",SUBSTITUTE(SUBSTITUTE(SUBSTITUTE(SUBSTITUTE(SUBSTITUTE(SUBSTITUTE(SUBSTITUTE(UPPER(TRIM($A36)),"Á","A"),"É","E"),"Í","I"),"Ó","O"),"Ú","U"),"Ñ","N"),"Ü","U")) -> J RINCON | Z36: =IF($Y36="","",LEFT($Y36,1)&" "&TRIM(RIGHT(SUBSTITUTE($Y36," ",REPT(" ",50)),50))) -> J RINCON | AA36: =IF($AF36="","",IF(COUNTIF(Validation!$U$19:$U$178,$AF36)>0,"OK","NO MATCH")) -> OK | AB36: =IF($W36=0,"",IF(AND($W36>=Validation!$B$3,$W36<=Validation!$C$3),"Yes","No")) -> Yes | AC36: =IF($A36="","",$AF36&"|"&TEXT($W36,"yyyy-mm-dd")&"|"&$J36&"|"&$N36) -> J RINCON|2026-08-19|36-35N-69W|0.125 | AD36: =IF($AC36="","",IF(COUNTIF($AC$2:$AC$3000,$AC36)>1,"REVIEW","OK")) -> OK | AE36: =IF(OR($W36=0,$O36=""),"",IF(IFERROR(IF(ISNUMBER($O36),INT($O36),DATE(VALUE(MID(SUBSTITUTE(LEFT($O36,FIND(" ",$O36&" ")-1),"/",REPT(" ",20)),41,20)),VALUE(LEFT(SUBSTITUTE(LEFT($O36,FIND(" ",$O36&" ")-1),"/",REPT(" ",20)),20)),VALUE(MID(SUBSTITUTE(LEFT($O36,FIND(" ",$O36&" ")-1),"/",REPT(" ",20)),21,20)))),0)>$W36,"Late","Same day")) -> Same day | AF36: =IF($A36="","",IFERROR(INDEX(Validation!$C$193:$C$217,MATCH($A36,Validation!$A$193:$A$217,0)),IF(COUNTIF(Validation!$U$19:$U$178,$Z36)>0,$Z36,IF(COUNTIF(Validation!$S$19:$S$178,$AI36)=1,INDEX(Validation!$U$19:$U$178,MATCH($AI36,Validation!$S$19:$S$178,0)),$Z36)))) -> J RINCON | AG36: =IF(COUNTA($A36:$U36)=0,"",IF($A36="","No name",IF($F36="","No date",IF($W36=0,"Date ilegible",IF(NOT(ISNUMBER($N36)),"Hours no numéricas",IF($AA36="NO MATCH","Person no identificada","OK")))))) -> OK | AH36: =IF($W36=0,"No date",IF($W36<Validation!$B$3,"Before period",IF($W36>Validation!$C$3,"After period","In period"))) -> In period | AI36: =IF($Y36="","",TRIM(RIGHT(SUBSTITUTE($Y36," ",REPT(" ",50)),50))) -> RINCON | AJ36: =IF($A36="","",IF(NOT(ISERROR(MATCH($A36,Validation!$A$193:$A$217,0))),"Manual mapping",IF(COUNTIF(Validation!$U$19:$U$178,$Z36)>0,"Direct",IF(COUNTIF(Validation!$S$19:$S$178,$AI36)=1,"By surname","Unresolved")))) -> Direct | AK36: =IF($L36="","",IF(MATCH($L36,$L$2:$L$3000,0)<>ROW()-1,"",COUNT($AK$1:$AK35)+1)) | AL36: =IF($G36="","",IF(MATCH($G36,$G$2:$G$3000,0)<>ROW()-1,"",COUNT($AL$1:$AL35)+1)) | AM36: =IF($H36="","",IF(MATCH($H36,$H$2:$H$3000,0)<>ROW()-1,"",COUNT($AM$1:$AM35)+1)) | AN36: =IF($I36="","",IF(MATCH($I36,$I$2:$I$3000,0)<>ROW()-1,"",COUNT($AN$1:$AN35)+1)) | AO36: =IF($Q36="","",IF(MATCH($Q36,$Q$2:$Q$3000,0)<>ROW()-1,"",COUNT($AO$1:$AO35)+1))
A37: J Rincon | B37: Approved | C37: L. Carollo | D37: 8/19/2026 | F37: 8/19/2026 | G37: Rocking WW Minerals, LLC | H37: RWW PRB Asset VDR | I37: Converse, WY | J37: 36-36N-71W | K37: Title | M37: 36-36N-71W | N37: 0.125 | O37: 8/19/2026 1:47:40 PM | Q37: Whitney Wicks | R37: J Rincon | S37: J Rincon | T37: 8/19/2026 | U37: Completed prune of mentioned legal description. | W37: =IF($F37="",0,IFERROR(IF(ISNUMBER($F37),INT($F37),DATE(VALUE(MID(SUBSTITUTE(LEFT($F37,FIND(" ",$F37&" ")-1),"/",REPT(" ",20)),41,20)),VALUE(LEFT(SUBSTITUTE(LEFT($F37,FIND(" ",$F37&" ")-1),"/",REPT(" ",20)),20)),VALUE(MID(SUBSTITUTE(LEFT($F37,FIND(" ",$F37&" ")-1),"/",REPT(" ",20)),21,20)))),0)) -> 46253 | X37: =IF(ISNUMBER($N37),$N37*Validation!$B$5,"") -> 1 | Y37: =IF($A37="","",SUBSTITUTE(SUBSTITUTE(SUBSTITUTE(SUBSTITUTE(SUBSTITUTE(SUBSTITUTE(SUBSTITUTE(UPPER(TRIM($A37)),"Á","A"),"É","E"),"Í","I"),"Ó","O"),"Ú","U"),"Ñ","N"),"Ü","U")) -> J RINCON | Z37: =IF($Y37="","",LEFT($Y37,1)&" "&TRIM(RIGHT(SUBSTITUTE($Y37," ",REPT(" ",50)),50))) -> J RINCON | AA37: =IF($AF37="","",IF(COUNTIF(Validation!$U$19:$U$178,$AF37)>0,"OK","NO MATCH")) -> OK | AB37: =IF($W37=0,"",IF(AND($W37>=Validation!$B$3,$W37<=Validation!$C$3),"Yes","No")) -> Yes | AC37: =IF($A37="","",$AF37&"|"&TEXT($W37,"yyyy-mm-dd")&"|"&$J37&"|"&$N37) -> J RINCON|2026-08-19|36-36N-71W|0.125 | AD37: =IF($AC37="","",IF(COUNTIF($AC$2:$AC$3000,$AC37)>1,"REVIEW","OK")) -> OK | AE37: =IF(OR($W37=0,$O37=""),"",IF(IFERROR(IF(ISNUMBER($O37),INT($O37),DATE(VALUE(MID(SUBSTITUTE(LEFT($O37,FIND(" ",$O37&" ")-1),"/",REPT(" ",20)),41,20)),VALUE(LEFT(SUBSTITUTE(LEFT($O37,FIND(" ",$O37&" ")-1),"/",REPT(" ",20)),20)),VALUE(MID(SUBSTITUTE(LEFT($O37,FIND(" ",$O37&" ")-1),"/",REPT(" ",20)),21,20)))),0)>$W37,"Late","Same day")) -> Same day | AF37: =IF($A37="","",IFERROR(INDEX(Validation!$C$193:$C$217,MATCH($A37,Validation!$A$193:$A$217,0)),IF(COUNTIF(Validation!$U$19:$U$178,$Z37)>0,$Z37,IF(COUNTIF(Validation!$S$19:$S$178,$AI37)=1,INDEX(Validation!$U$19:$U$178,MATCH($AI37,Validation!$S$19:$S$178,0)),$Z37)))) -> J RINCON | AG37: =IF(COUNTA($A37:$U37)=0,"",IF($A37="","No name",IF($F37="","No date",IF($W37=0,"Date ilegible",IF(NOT(ISNUMBER($N37)),"Hours no numéricas",IF($AA37="NO MATCH","Person no identificada","OK")))))) -> OK | AH37: =IF($W37=0,"No date",IF($W37<Validation!$B$3,"Before period",IF($W37>Validation!$C$3,"After period","In period"))) -> In period | AI37: =IF($Y37="","",TRIM(RIGHT(SUBSTITUTE($Y37," ",REPT(" ",50)),50))) -> RINCON | AJ37: =IF($A37="","",IF(NOT(ISERROR(MATCH($A37,Validation!$A$193:$A$217,0))),"Manual mapping",IF(COUNTIF(Validation!$U$19:$U$178,$Z37)>0,"Direct",IF(COUNTIF(Validation!$S$19:$S$178,$AI37)=1,"By surname","Unresolved")))) -> Direct | AK37: =IF($L37="","",IF(MATCH($L37,$L$2:$L$3000,0)<>ROW()-1,"",COUNT($AK$1:$AK36)+1)) | AL37: =IF($G37="","",IF(MATCH($G37,$G$2:$G$3000,0)<>ROW()-1,"",COUNT($AL$1:$AL36)+1)) | AM37: =IF($H37="","",IF(MATCH($H37,$H$2:$H$3000,0)<>ROW()-1,"",COUNT($AM$1:$AM36)+1)) | AN37: =IF($I37="","",IF(MATCH($I37,$I$2:$I$3000,0)<>ROW()-1,"",COUNT($AN$1:$AN36)+1)) | AO37: =IF($Q37="","",IF(MATCH($Q37,$Q$2:$Q$3000,0)<>ROW()-1,"",COUNT($AO$1:$AO36)+1))
A38: J Rincon | B38: Approved | C38: L. Carollo | D38: 8/19/2026 | F38: 8/19/2026 | G38: Rocking WW Minerals, LLC | H38: RWW PRB Asset VDR | I38: Campbell, WY | J38: 06-41N-72W | K38: Title | M38: 6-41N-72W (Lots 8, 9, 10, 11, 12, 13, 14 | N38: 0.375 | O38: 8/19/2026 7:12:55 PM | Q38: Whitney Wicks | R38: J Rincon | S38: J Rincon | T38: 8/19/2026 | U38: Completed prune of mentioned legal description. A notecard does not light up as the grantor is a stranger in title, this interest is conveyed to Rocking WW | W38: =IF($F38="",0,IFERROR(IF(ISNUMBER($F38),INT($F38),DATE(VALUE(MID(SUBSTITUTE(LEFT($F38,FIND(" ",$F38&" ")-1),"/",REPT(" ",20)),41,20)),VALUE(LEFT(SUBSTITUTE(LEFT($F38,FIND(" ",$F38&" ")-1),"/",REPT(" ",20)),20)),VALUE(MID(SUBSTITUTE(LEFT($F38,FIND(" ",$F38&" ")-1),"/",REPT(" ",20)),21,20)))),0)) -> 46253 | X38: =IF(ISNUMBER($N38),$N38*Validation!$B$5,"") -> 3 | Y38: =IF($A38="","",SUBSTITUTE(SUBSTITUTE(SUBSTITUTE(SUBSTITUTE(SUBSTITUTE(SUBSTITUTE(SUBSTITUTE(UPPER(TRIM($A38)),"Á","A"),"É","E"),"Í","I"),"Ó","O"),"Ú","U"),"Ñ","N"),"Ü","U")) -> J RINCON | Z38: =IF($Y38="","",LEFT($Y38,1)&" "&TRIM(RIGHT(SUBSTITUTE($Y38," ",REPT(" ",50)),50))) -> J RINCON | AA38: =IF($AF38="","",IF(COUNTIF(Validation!$U$19:$U$178,$AF38)>0,"OK","NO MATCH")) -> OK | AB38: =IF($W38=0,"",IF(AND($W38>=Validation!$B$3,$W38<=Validation!$C$3),"Yes","No")) -> Yes | AC38: =IF($A38="","",$AF38&"|"&TEXT($W38,"yyyy-mm-dd")&"|"&$J38&"|"&$N38) -> J RINCON|2026-08-19|06-41N-72W|0.375 | AD38: =IF($AC38="","",IF(COUNTIF($AC$2:$AC$3000,$AC38)>1,"REVIEW","OK")) -> OK | AE38: =IF(OR($W38=0,$O38=""),"",IF(IFERROR(IF(ISNUMBER($O38),INT($O38),DATE(VALUE(MID(SUBSTITUTE(LEFT($O38,FIND(" ",$O38&" ")-1),"/",REPT(" ",20)),41,20)),VALUE(LEFT(SUBSTITUTE(LEFT($O38,FIND(" ",$O38&" ")-1),"/",REPT(" ",20)),20)),VALUE(MID(SUBSTITUTE(LEFT($O38,FIND(" ",$O38&" ")-1),"/",REPT(" ",20)),21,20)))),0)>$W38,"Late","Same day")) -> Same day | AF38: =IF($A38="","",IFERROR(INDEX(Validation!$C$193:$C$217,MATCH($A38,Validation!$A$193:$A$217,0)),IF(COUNTIF(Validation!$U$19:$U$178,$Z38)>0,$Z38,IF(COUNTIF(Validation!$S$19:$S$178,$AI38)=1,INDEX(Validation!$U$19:$U$178,MATCH($AI38,Validation!$S$19:$S$178,0)),$Z38)))) -> J RINCON | AG38: =IF(COUNTA($A38:$U38)=0,"",IF($A38="","No name",IF($F38="","No date",IF($W38=0,"Date ilegible",IF(NOT(ISNUMBER($N38)),"Hours no numéricas",IF($AA38="NO MATCH","Person no identificada","OK")))))) -> OK | AH38: =IF($W38=0,"No date",IF($W38<Validation!$B$3,"Before period",IF($W38>Validation!$C$3,"After period","In period"))) -> In period | AI38: =IF($Y38="","",TRIM(RIGHT(SUBSTITUTE($Y38," ",REPT(" ",50)),50))) -> RINCON | AJ38: =IF($A38="","",IF(NOT(ISERROR(MATCH($A38,Validation!$A$193:$A$217,0))),"Manual mapping",IF(COUNTIF(Validation!$U$19:$U$178,$Z38)>0,"Direct",IF(COUNTIF(Validation!$S$19:$S$178,$AI38)=1,"By surname","Unresolved")))) -> Direct | AK38: =IF($L38="","",IF(MATCH($L38,$L$2:$L$3000,0)<>ROW()-1,"",COUNT($AK$1:$AK37)+1)) | AL38: =IF($G38="","",IF(MATCH($G38,$G$2:$G$3000,0)<>ROW()-1,"",COUNT($AL$1:$AL37)+1)) | AM38: =IF($H38="","",IF(MATCH($H38,$H$2:$H$3000,0)<>ROW()-1,"",COUNT($AM$1:$AM37)+1)) | AN38: =IF($I38="","",IF(MATCH($I38,$I$2:$I$3000,0)<>ROW()-1,"",COUNT($AN$1:$AN37)+1)) | AO38: =IF($Q38="","",IF(MATCH($Q38,$Q$2:$Q$3000,0)<>ROW()-1,"",COUNT($AO$1:$AO37)+1))
A39: J Rincon | B39: Approved | C39: L. Carollo | D39: 8/19/2026 | F39: 8/19/2026 | G39: Rocking WW Minerals, LLC | H39: RWW PRB Asset VDR | I39: Campbell, WY | J39: 06-41N-71W | K39: Title | M39: 6-41N-71W (Lots 8, 9, 14, 15, 16, 17, 22, 23, E2) | N39: 0.25 | O39: 8/19/2026 7:31:16 PM | Q39: Whitney Wicks | R39: J Rincon | S39: J Rincon | T39: 8/19/2026 | U39: Completed prune of mentioned legal description. | W39: =IF($F39="",0,IFERROR(IF(ISNUMBER($F39),INT($F39),DATE(VALUE(MID(SUBSTITUTE(LEFT($F39,FIND(" ",$F39&" ")-1),"/",REPT(" ",20)),41,20)),VALUE(LEFT(SUBSTITUTE(LEFT($F39,FIND(" ",$F39&" ")-1),"/",REPT(" ",20)),20)),VALUE(MID(SUBSTITUTE(LEFT($F39,FIND(" ",$F39&" ")-1),"/",REPT(" ",20)),21,20)))),0)) -> 46253 | X39: =IF(ISNUMBER($N39),$N39*Validation!$B$5,"") -> 2 | Y39: =IF($A39="","",SUBSTITUTE(SUBSTITUTE(SUBSTITUTE(SUBSTITUTE(SUBSTITUTE(SUBSTITUTE(SUBSTITUTE(UPPER(TRIM($A39)),"Á","A"),"É","E"),"Í","I"),"Ó","O"),"Ú","U"),"Ñ","N"),"Ü","U")) -> J RINCON | Z39: =IF($Y39="","",LEFT($Y39,1)&" "&TRIM(RIGHT(SUBSTITUTE($Y39," ",REPT(" ",50)),50))) -> J RINCON | AA39: =IF($AF39="","",IF(COUNTIF(Validation!$U$19:$U$178,$AF39)>0,"OK","NO MATCH")) -> OK | AB39: =IF($W39=0,"",IF(AND($W39>=Validation!$B$3,$W39<=Validation!$C$3),"Yes","No")) -> Yes | AC39: =IF($A39="","",$AF39&"|"&TEXT($W39,"yyyy-mm-dd")&"|"&$J39&"|"&$N39) -> J RINCON|2026-08-19|06-41N-71W|0.25 | AD39: =IF($AC39="","",IF(COUNTIF($AC$2:$AC$3000,$AC39)>1,"REVIEW","OK")) -> OK | AE39: =IF(OR($W39=0,$O39=""),"",IF(IFERROR(IF(ISNUMBER($O39),INT($O39),DATE(VALUE(MID(SUBSTITUTE(LEFT($O39,FIND(" ",$O39&" ")-1),"/",REPT(" ",20)),41,20)),VALUE(LEFT(SUBSTITUTE(LEFT($O39,FIND(" ",$O39&" ")-1),"/",REPT(" ",20)),20)),VALUE(MID(SUBSTITUTE(LEFT($O39,FIND(" ",$O39&" ")-1),"/",REPT(" ",20)),21,20)))),0)>$W39,"Late","Same day")) -> Same day | AF39: =IF($A39="","",IFERROR(INDEX(Validation!$C$193:$C$217,MATCH($A39,Validation!$A$193:$A$217,0)),IF(COUNTIF(Validation!$U$19:$U$178,$Z39)>0,$Z39,IF(COUNTIF(Validation!$S$19:$S$178,$AI39)=1,INDEX(Validation!$U$19:$U$178,MATCH($AI39,Validation!$S$19:$S$178,0)),$Z39)))) -> J RINCON | AG39: =IF(COUNTA($A39:$U39)=0,"",IF($A39="","No name",IF($F39="","No date",IF($W39=0,"Date ilegible",IF(NOT(ISNUMBER($N39)),"Hours no numéricas",IF($AA39="NO MATCH","Person no identificada","OK")))))) -> OK | AH39: =IF($W39=0,"No date",IF($W39<Validation!$B$3,"Before period",IF($W39>Validation!$C$3,"After period","In period"))) -> In period | AI39: =IF($Y39="","",TRIM(RIGHT(SUBSTITUTE($Y39," ",REPT(" ",50)),50))) -> RINCON | AJ39: =IF($A39="","",IF(NOT(ISERROR(MATCH($A39,Validation!$A$193:$A$217,0))),"Manual mapping",IF(COUNTIF(Validation!$U$19:$U$178,$Z39)>0,"Direct",IF(COUNTIF(Validation!$S$19:$S$178,$AI39)=1,"By surname","Unresolved")))) -> Direct | AK39: =IF($L39="","",IF(MATCH($L39,$L$2:$L$3000,0)<>ROW()-1,"",COUNT($AK$1:$AK38)+1)) | AL39: =IF($G39="","",IF(MATCH($G39,$G$2:$G$3000,0)<>ROW()-1,"",COUNT($AL$1:$AL38)+1)) | AM39: =IF($H39="","",IF(MATCH($H39,$H$2:$H$3000,0)<>ROW()-1,"",COUNT($AM$1:$AM38)+1)) | AN39: =IF($I39="","",IF(MATCH($I39,$I$2:$I$3000,0)<>ROW()-1,"",COUNT($AN$1:$AN38)+1)) | AO39: =IF($Q39="","",IF(MATCH($Q39,$Q$2:$Q$3000,0)<>ROW()-1,"",COUNT($AO$1:$AO38)+1))
A40: J Rincon | B40: Approved | C40: L. Carollo | D40: 8/19/2026 | F40: 8/19/2026 | G40: Rocking WW Minerals, LLC | H40: RWW PRB Asset VDR | I40: Converse, WY | J40: 06-35N-70W | K40: Title | M40: 6-35N-70W (NESW ; Lots 1, 2, S2NE ; Lots 3... | N40: 0.25 | O40: 8/20/2026 1:32:40 AM | Q40: Whitney Wicks | R40: J Rincon | S40: J Rincon | T40: 8/20/2026 | U40: Completed prune of mentioned legal description. Merged and verified information from 11 AOIs. | W40: =IF($F40="",0,IFERROR(IF(ISNUMBER($F40),INT($F40),DATE(VALUE(MID(SUBSTITUTE(LEFT($F40,FIND(" ",$F40&" ")-1),"/",REPT(" ",20)),41,20)),VALUE(LEFT(SUBSTITUTE(LEFT($F40,FIND(" ",$F40&" ")-1),"/",REPT(" ",20)),20)),VALUE(MID(SUBSTITUTE(LEFT($F40,FIND(" ",$F40&" ")-1),"/",REPT(" ",20)),21,20)))),0)) -> 46253 | X40: =IF(ISNUMBER($N40),$N40*Validation!$B$5,"") -> 2 | Y40: =IF($A40="","",SUBSTITUTE(SUBSTITUTE(SUBSTITUTE(SUBSTITUTE(SUBSTITUTE(SUBSTITUTE(SUBSTITUTE(UPPER(TRIM($A40)),"Á","A"),"É","E"),"Í","I"),"Ó","O"),"Ú","U"),"Ñ","N"),"Ü","U")) -> J RINCON | Z40: =IF($Y40="","",LEFT($Y40,1)&" "&TRIM(RIGHT(SUBSTITUTE($Y40," ",REPT(" ",50)),50))) -> J RINCON | AA40: =IF($AF40="","",IF(COUNTIF(Validation!$U$19:$U$178,$AF40)>0,"OK","NO MATCH")) -> OK | AB40: =IF($W40=0,"",IF(AND($W40>=Validation!$B$3,$W40<=Validation!$C$3),"Yes","No")) -> Yes | AC40: =IF($A40="","",$AF40&"|"&TEXT($W40,"yyyy-mm-dd")&"|"&$J40&"|"&$N40) -> J RINCON|2026-08-19|06-35N-70W|0.25 | AD40: =IF($AC40="","",IF(COUNTIF($AC$2:$AC$3000,$AC40)>1,"REVIEW","OK")) -> OK | AE40: =IF(OR($W40=0,$O40=""),"",IF(IFERROR(IF(ISNUMBER($O40),INT($O40),DATE(VALUE(MID(SUBSTITUTE(LEFT($O40,FIND(" ",$O40&" ")-1),"/",REPT(" ",20)),41,20)),VALUE(LEFT(SUBSTITUTE(LEFT($O40,FIND(" ",$O40&" ")-1),"/",REPT(" ",20)),20)),VALUE(MID(SUBSTITUTE(LEFT($O40,FIND(" ",$O40&" ")-1),"/",REPT(" ",20)),21,20)))),0)>$W40,"Late","Same day")) -> Late | AF40: =IF($A40="","",IFERROR(INDEX(Validation!$C$193:$C$217,MATCH($A40,Validation!$A$193:$A$217,0)),IF(COUNTIF(Validation!$U$19:$U$178,$Z40)>0,$Z40,IF(COUNTIF(Validation!$S$19:$S$178,$AI40)=1,INDEX(Validation!$U$19:$U$178,MATCH($AI40,Validation!$S$19:$S$178,0)),$Z40)))) -> J RINCON | AG40: =IF(COUNTA($A40:$U40)=0,"",IF($A40="","No name",IF($F40="","No date",IF($W40=0,"Date ilegible",IF(NOT(ISNUMBER($N40)),"Hours no numéricas",IF($AA40="NO MATCH","Person no identificada","OK")))))) -> OK | AH40: =IF($W40=0,"No date",IF($W40<Validation!$B$3,"Before period",IF($W40>Validation!$C$3,"After period","In period"))) -> In period | AI40: =IF($Y40="","",TRIM(RIGHT(SUBSTITUTE($Y40," ",REPT(" ",50)),50))) -> RINCON | AJ40: =IF($A40="","",IF(NOT(ISERROR(MATCH($A40,Validation!$A$193:$A$217,0))),"Manual mapping",IF(COUNTIF(Validation!$U$19:$U$178,$Z40)>0,"Direct",IF(COUNTIF(Validation!$S$19:$S$178,$AI40)=1,"By surname","Unresolved")))) -> Direct | AK40: =IF($L40="","",IF(MATCH($L40,$L$2:$L$3000,0)<>ROW()-1,"",COUNT($AK$1:$AK39)+1)) | AL40: =IF($G40="","",IF(MATCH($G40,$G$2:$G$3000,0)<>ROW()-1,"",COUNT($AL$1:$AL39)+1)) | AM40: =IF($H40="","",IF(MATCH($H40,$H$2:$H$3000,0)<>ROW()-1,"",COUNT($AM$1:$AM39)+1)) | AN40: =IF($I40="","",IF(MATCH($I40,$I$2:$I$3000,0)<>ROW()-1,"",COUNT($AN$1:$AN39)+1)) | AO40: =IF($Q40="","",IF(MATCH($Q40,$Q$2:$Q$3000,0)<>ROW()-1,"",COUNT($AO$1:$AO39)+1))
... A42: J Rincon | B42: Approved | C42: L. Carollo | D42: 8/19/2026 | F42: 8/19/2026 | G42: Rocking WW Minerals, LLC | H42: RWW PRB Asset VDR | I42: Converse, WY | J42: 09-35N-70W | K42: Title | M42: 9-35N-70W (NW) | N42: 0.125 | O42: 8/20/2026 2:00:31 AM | Q42: Whitney Wicks | R42: J Rincon | S42: J Rincon | T42: 8/20/2026 | U42: Completed prune of mentioned legal description. Merged and verified information from 3 AOIs. | W42: =IF($F42="",0,IFERROR(IF(ISNUMBER($F42),INT($F42),DATE(VALUE(MID(SUBSTITUTE(LEFT($F42,FIND(" ",$F42&" ")-1),"/",REPT(" ",20)),41,20)),VALUE(LEFT(SUBSTITUTE(LEFT($F42,FIND(" ",$F42&" ")-1),"/",REPT(" ",20)),20)),VALUE(MID(SUBSTITUTE(LEFT($F42,FIND(" ",$F42&" ")-1),"/",REPT(" ",20)),21,20)))),0)) -> 46253 | X42: =IF(ISNUMBER($N42),$N42*Validation!$B$5,"") -> 1 | Y42: =IF($A42="","",SUBSTITUTE(SUBSTITUTE(SUBSTITUTE(SUBSTITUTE(SUBSTITUTE(SUBSTITUTE(SUBSTITUTE(UPPER(TRIM($A42)),"Á","A"),"É","E"),"Í","I"),"Ó","O"),"Ú","U"),"Ñ","N"),"Ü","U")) -> J RINCON | Z42: =IF($Y42="","",LEFT($Y42,1)&" "&TRIM(RIGHT(SUBSTITUTE($Y42," ",REPT(" ",50)),50))) -> J RINCON | AA42: =IF($AF42="","",IF(COUNTIF(Validation!$U$19:$U$178,$AF42)>0,"OK","NO MATCH")) -> OK | AB42: =IF($W42=0,"",IF(AND($W42>=Validation!$B$3,$W42<=Validation!$C$3),"Yes","No")) -> Yes | AC42: =IF($A42="","",$AF42&"|"&TEXT($W42,"yyyy-mm-dd")&"|"&$J42&"|"&$N42) -> J RINCON|2026-08-19|09-35N-70W|0.125 | AD42: =IF($AC42="","",IF(COUNTIF($AC$2:$AC$3000,$AC42)>1,"REVIEW","OK")) -> OK | AE42: =IF(OR($W42=0,$O42=""),"",IF(IFERROR(IF(ISNUMBER($O42),INT($O42),DATE(VALUE(MID(SUBSTITUTE(LEFT($O42,FIND(" ",$O42&" ")-1),"/",REPT(" ",20)),41,20)),VALUE(LEFT(SUBSTITUTE(LEFT($O42,FIND(" ",$O42&" ")-1),"/",REPT(" ",20)),20)),VALUE(MID(SUBSTITUTE(LEFT($O42,FIND(" ",$O42&" ")-1),"/",REPT(" ",20)),21,20)))),0)>$W42,"Late","Same day")) -> Late | AF42: =IF($A42="","",IFERROR(INDEX(Validation!$C$193:$C$217,MATCH($A42,Validation!$A$193:$A$217,0)),IF(COUNTIF(Validation!$U$19:$U$178,$Z42)>0,$Z42,IF(COUNTIF(Validation!$S$19:$S$178,$AI42)=1,INDEX(Validation!$U$19:$U$178,MATCH($AI42,Validation!$S$19:$S$178,0)),$Z42)))) -> J RINCON | AG42: =IF(COUNTA($A42:$U42)=0,"",IF($A42="","No name",IF($F42="","No date",IF($W42=0,"Date ilegible",IF(NOT(ISNUMBER($N42)),"Hours no numéricas",IF($AA42="NO MATCH","Person no identificada","OK")))))) -> OK | AH42: =IF($W42=0,"No date",IF($W42<Validation!$B$3,"Before period",IF($W42>Validation!$C$3,"After period","In period"))) -> In period | AI42: =IF($Y42="","",TRIM(RIGHT(SUBSTITUTE($Y42," ",REPT(" ",50)),50))) -> RINCON | AJ42: =IF($A42="","",IF(NOT(ISERROR(MATCH($A42,Validation!$A$193:$A$217,0))),"Manual mapping",IF(COUNTIF(Validation!$U$19:$U$178,$Z42)>0,"Direct",IF(COUNTIF(Validation!$S$19:$S$178,$AI42)=1,"By surname","Unresolved")))) -> Direct | AK42: =IF($L42="","",IF(MATCH($L42,$L$2:$L$3000,0)<>ROW()-1,"",COUNT($AK$1:$AK41)+1)) | AL42: =IF($G42="","",IF(MATCH($G42,$G$2:$G$3000,0)<>ROW()-1,"",COUNT($AL$1:$AL41)+1)) | AM42: =IF($H42="","",IF(MATCH($H42,$H$2:$H$3000,0)<>ROW()-1,"",COUNT($AM$1:$AM41)+1)) | AN42: =IF($I42="","",IF(MATCH($I42,$I$2:$I$3000,0)<>ROW()-1,"",COUNT($AN$1:$AN41)+1)) | AO42: =IF($Q42="","",IF(MATCH($Q42,$Q$2:$Q$3000,0)<>ROW()-1,"",COUNT($AO$1:$AO41)+1))
A43: J S Bermudez | B43: Approved | C43: L. Carollo | D43: 8/19/2026 | F43: 8/19/2026 | G43: Rocking WW Minerals, LLC | H43: RWW PRB Asset VDR | I43: Campbell, WY | K43: Data Processing | N43: 1 | O43: 8/19/2026 8:36:37 PM | Q43: Whitney Wicks | R43: J S Bermudez | S43: L. Carollo | T43: 8/20/2026 | U43: Working fixing the spreadsheet, the code and automation of asana and landman information | W43: =IF($F43="",0,IFERROR(IF(ISNUMBER($F43),INT($F43),DATE(VALUE(MID(SUBSTITUTE(LEFT($F43,FIND(" ",$F43&" ")-1),"/",REPT(" ",20)),41,20)),VALUE(LEFT(SUBSTITUTE(LEFT($F43,FIND(" ",$F43&" ")-1),"/",REPT(" ",20)),20)),VALUE(MID(SUBSTITUTE(LEFT($F43,FIND(" ",$F43&" ")-1),"/",REPT(" ",20)),21,20)))),0)) -> 46253 | X43: =IF(ISNUMBER($N43),$N43*Validation!$B$5,"") -> 8 | Y43: =IF($A43="","",SUBSTITUTE(SUBSTITUTE(SUBSTITUTE(SUBSTITUTE(SUBSTITUTE(SUBSTITUTE(SUBSTITUTE(UPPER(TRIM($A43)),"Á","A"),"É","E"),"Í","I"),"Ó","O"),"Ú","U"),"Ñ","N"),"Ü","U")) -> J S BERMUDEZ | Z43: =IF($Y43="","",LEFT($Y43,1)&" "&TRIM(RIGHT(SUBSTITUTE($Y43," ",REPT(" ",50)),50))) -> J BERMUDEZ | AA43: =IF($AF43="","",IF(COUNTIF(Validation!$U$19:$U$178,$AF43)>0,"OK","NO MATCH")) -> OK | AB43: =IF($W43=0,"",IF(AND($W43>=Validation!$B$3,$W43<=Validation!$C$3),"Yes","No")) -> Yes | AC43: =IF($A43="","",$AF43&"|"&TEXT($W43,"yyyy-mm-dd")&"|"&$J43&"|"&$N43) -> J BERMUDEZ|2026-08-19||1 | AD43: =IF($AC43="","",IF(COUNTIF($AC$2:$AC$3000,$AC43)>1,"REVIEW","OK")) -> OK | AE43: =IF(OR($W43=0,$O43=""),"",IF(IFERROR(IF(ISNUMBER($O43),INT($O43),DATE(VALUE(MID(SUBSTITUTE(LEFT($O43,FIND(" ",$O43&" ")-1),"/",REPT(" ",20)),41,20)),VALUE(LEFT(SUBSTITUTE(LEFT($O43,FIND(" ",$O43&" ")-1),"/",REPT(" ",20)),20)),VALUE(MID(SUBSTITUTE(LEFT($O43,FIND(" ",$O43&" ")-1),"/",REPT(" ",20)),21,20)))),0)>$W43,"Late","Same day")) -> Same day | AF43: =IF($A43="","",IFERROR(INDEX(Validation!$C$193:$C$217,MATCH($A43,Validation!$A$193:$A$217,0)),IF(COUNTIF(Validation!$U$19:$U$178,$Z43)>0,$Z43,IF(COUNTIF(Validation!$S$19:$S$178,$AI43)=1,INDEX(Validation!$U$19:$U$178,MATCH($AI43,Validation!$S$19:$S$178,0)),$Z43)))) -> J BERMUDEZ | AG43: =IF(COUNTA($A43:$U43)=0,"",IF($A43="","No name",IF($F43="","No date",IF($W43=0,"Date ilegible",IF(NOT(ISNUMBER($N43)),"Hours no numéricas",IF($AA43="NO MATCH","Person no identificada","OK")))))) -> OK | AH43: =IF($W43=0,"No date",IF($W43<Validation!$B$3,"Before period",IF($W43>Validation!$C$3,"After period","In period"))) -> In period | AI43: =IF($Y43="","",TRIM(RIGHT(SUBSTITUTE($Y43," ",REPT(" ",50)),50))) -> BERMUDEZ | AJ43: =IF($A43="","",IF(NOT(ISERROR(MATCH($A43,Validation!$A$193:$A$217,0))),"Manual mapping",IF(COUNTIF(Validation!$U$19:$U$178,$Z43)>0,"Direct",IF(COUNTIF(Validation!$S$19:$S$178,$AI43)=1,"By surname","Unresolved")))) -> Direct | AK43: =IF($L43="","",IF(MATCH($L43,$L$2:$L$3000,0)<>ROW()-1,"",COUNT($AK$1:$AK42)+1)) | AL43: =IF($G43="","",IF(MATCH($G43,$G$2:$G$3000,0)<>ROW()-1,"",COUNT($AL$1:$AL42)+1)) | AM43: =IF($H43="","",IF(MATCH($H43,$H$2:$H$3000,0)<>ROW()-1,"",COUNT($AM$1:$AM42)+1)) | AN43: =IF($I43="","",IF(MATCH($I43,$I$2:$I$3000,0)<>ROW()-1,"",COUNT($AN$1:$AN42)+1)) | AO43: =IF($Q43="","",IF(MATCH($Q43,$Q$2:$Q$3000,0)<>ROW()-1,"",COUNT($AO$1:$AO42)+1))
A44: J Valbuena | B44: Approved | C44: L. Carollo | D44: 8/19/2026 | F44: 8/19/2026 | G44: Rocking WW Minerals, LLC | H44: RWW PRB Asset VDR | I44: Campbell, WY | J44: 07-42N-71W | K44: Title | M44: Lot_4_(nka_Lot_27) | N44: 0.125 | O44: 8/19/2026 7:43:54 PM | Q44: Whitney Wicks | R44: J Valbuena | S44: J Valbuena | T44: 8/19/2026 | U44: Clone AOI Pull and enter the source deed Prune interest Download Runsheet Download Lease Analysis Report | W44: =IF($F44="",0,IFERROR(IF(ISNUMBER($F44),INT($F44),DATE(VALUE(MID(SUBSTITUTE(LEFT($F44,FIND(" ",$F44&" ")-1),"/",REPT(" ",20)),41,20)),VALUE(LEFT(SUBSTITUTE(LEFT($F44,FIND(" ",$F44&" ")-1),"/",REPT(" ",20)),20)),VALUE(MID(SUBSTITUTE(LEFT($F44,FIND(" ",$F44&" ")-1),"/",REPT(" ",20)),21,20)))),0)) -> 46253 | X44: =IF(ISNUMBER($N44),$N44*Validation!$B$5,"") -> 1 | Y44: =IF($A44="","",SUBSTITUTE(SUBSTITUTE(SUBSTITUTE(SUBSTITUTE(SUBSTITUTE(SUBSTITUTE(SUBSTITUTE(UPPER(TRIM($A44)),"Á","A"),"É","E"),"Í","I"),"Ó","O"),"Ú","U"),"Ñ","N"),"Ü","U")) -> J VALBUENA | Z44: =IF($Y44="","",LEFT($Y44,1)&" "&TRIM(RIGHT(SUBSTITUTE($Y44," ",REPT(" ",50)),50))) -> J VALBUENA | AA44: =IF($AF44="","",IF(COUNTIF(Validation!$U$19:$U$178,$AF44)>0,"OK","NO MATCH")) -> OK | AB44: =IF($W44=0,"",IF(AND($W44>=Validation!$B$3,$W44<=Validation!$C$3),"Yes","No")) -> Yes | AC44: =IF($A44="","",$AF44&"|"&TEXT($W44,"yyyy-mm-dd")&"|"&$J44&"|"&$N44) -> J VALBUENA|2026-08-19|07-42N-71W|0.125 | AD44: =IF($AC44="","",IF(COUNTIF($AC$2:$AC$3000,$AC44)>1,"REVIEW","OK")) -> REVIEW | AE44: =IF(OR($W44=0,$O44=""),"",IF(IFERROR(IF(ISNUMBER($O44),INT($O44),DATE(VALUE(MID(SUBSTITUTE(LEFT($O44,FIND(" ",$O44&" ")-1),"/",REPT(" ",20)),41,20)),VALUE(LEFT(SUBSTITUTE(LEFT($O44,FIND(" ",$O44&" ")-1),"/",REPT(" ",20)),20)),VALUE(MID(SUBSTITUTE(LEFT($O44,FIND(" ",$O44&" ")-1),"/",REPT(" ",20)),21,20)))),0)>$W44,"Late","Same day")) -> Same day | AF44: =IF($A44="","",IFERROR(INDEX(Validation!$C$193:$C$217,MATCH($A44,Validation!$A$193:$A$217,0)),IF(COUNTIF(Validation!$U$19:$U$178,$Z44)>0,$Z44,IF(COUNTIF(Validation!$S$19:$S$178,$AI44)=1,INDEX(Validation!$U$19:$U$178,MATCH($AI44,Validation!$S$19:$S$178,0)),$Z44)))) -> J VALBUENA | AG44: =IF(COUNTA($A44:$U44)=0,"",IF($A44="","No name",IF($F44="","No date",IF($W44=0,"Date ilegible",IF(NOT(ISNUMBER($N44)),"Hours no numéricas",IF($AA44="NO MATCH","Person no identificada","OK")))))) -> OK | AH44: =IF($W44=0,"No date",IF($W44<Validation!$B$3,"Before period",IF($W44>Validation!$C$3,"After period","In period"))) -> In period | AI44: =IF($Y44="","",TRIM(RIGHT(SUBSTITUTE($Y44," ",REPT(" ",50)),50))) -> VALBUENA | AJ44: =IF($A44="","",IF(NOT(ISERROR(MATCH($A44,Validation!$A$193:$A$217,0))),"Manual mapping",IF(COUNTIF(Validation!$U$19:$U$178,$Z44)>0,"Direct",IF(COUNTIF(Validation!$S$19:$S$178,$AI44)=1,"By surname","Unresolved")))) -> Direct | AK44: =IF($L44="","",IF(MATCH($L44,$L$2:$L$3000,0)<>ROW()-1,"",COUNT($AK$1:$AK43)+1)) | AL44: =IF($G44="","",IF(MATCH($G44,$G$2:$G$3000,0)<>ROW()-1,"",COUNT($AL$1:$AL43)+1)) | AM44: =IF($H44="","",IF(MATCH($H44,$H$2:$H$3000,0)<>ROW()-1,"",COUNT($AM$1:$AM43)+1)) | AN44: =IF($I44="","",IF(MATCH($I44,$I$2:$I$3000,0)<>ROW()-1,"",COUNT($AN$1:$AN43)+1)) | AO44: =IF($Q44="","",IF(MATCH($Q44,$Q$2:$Q$3000,0)<>ROW()-1,"",COUNT($AO$1:$AO43)+1))
A45: J Valbuena | B45: Approved | C45: L. Carollo | D45: 8/19/2026 | F45: 8/19/2026 | G45: Rocking WW Minerals, LLC | H45: RWW PRB Asset VDR | I45: Campbell, WY | J45: 07-42N-71W | K45: Title | M45: Lot_3,_E2SW4,_W2SE4_(nka_Lots,_24,_25,_26,_28,_29) | N45: 0.125 | O45: 8/19/2026 7:44:15 PM | Q45: Whitney Wicks | R45: J Valbuena | S45: J Valbuena | T45: 8/19/2026 | U45: Clone AOI Pull and enter the source deed Prune interest Download Runsheet Download Lease Analysis Report | W45: =IF($F45="",0,IFERROR(IF(ISNUMBER($F45),INT($F45),DATE(VALUE(MID(SUBSTITUTE(LEFT($F45,FIND(" ",$F45&" ")-1),"/",REPT(" ",20)),41,20)),VALUE(LEFT(SUBSTITUTE(LEFT($F45,FIND(" ",$F45&" ")-1),"/",REPT(" ",20)),20)),VALUE(MID(SUBSTITUTE(LEFT($F45,FIND(" ",$F45&" ")-1),"/",REPT(" ",20)),21,20)))),0)) -> 46253 | X45: =IF(ISNUMBER($N45),$N45*Validation!$B$5,"") -> 1 | Y45: =IF($A45="","",SUBSTITUTE(SUBSTITUTE(SUBSTITUTE(SUBSTITUTE(SUBSTITUTE(SUBSTITUTE(SUBSTITUTE(UPPER(TRIM($A45)),"Á","A"),"É","E"),"Í","I"),"Ó","O"),"Ú","U"),"Ñ","N"),"Ü","U")) -> J VALBUENA | Z45: =IF($Y45="","",LEFT($Y45,1)&" "&TRIM(RIGHT(SUBSTITUTE($Y45," ",REPT(" ",50)),50))) -> J VALBUENA | AA45: =IF($AF45="","",IF(COUNTIF(Validation!$U$19:$U$178,$AF45)>0,"OK","NO MATCH")) -> OK | AB45: =IF($W45=0,"",IF(AND($W45>=Validation!$B$3,$W45<=Validation!$C$3),"Yes","No")) -> Yes | AC45: =IF($A45="","",$AF45&"|"&TEXT($W45,"yyyy-mm-dd")&"|"&$J45&"|"&$N45) -> J VALBUENA|2026-08-19|07-42N-71W|0.125 | AD45: =IF($AC45="","",IF(COUNTIF($AC$2:$AC$3000,$AC45)>1,"REVIEW","OK")) -> REVIEW | AE45: =IF(OR($W45=0,$O45=""),"",IF(IFERROR(IF(ISNUMBER($O45),INT($O45),DATE(VALUE(MID(SUBSTITUTE(LEFT($O45,FIND(" ",$O45&" ")-1),"/",REPT(" ",20)),41,20)),VALUE(LEFT(SUBSTITUTE(LEFT($O45,FIND(" ",$O45&" ")-1),"/",REPT(" ",20)),20)),VALUE(MID(SUBSTITUTE(LEFT($O45,FIND(" ",$O45&" ")-1),"/",REPT(" ",20)),21,20)))),0)>$W45,"Late","Same day")) -> Same day | AF45: =IF($A45="","",IFERROR(INDEX(Validation!$C$193:$C$217,MATCH($A45,Validation!$A$193:$A$217,0)),IF(COUNTIF(Validation!$U$19:$U$178,$Z45)>0,$Z45,IF(COUNTIF(Validation!$S$19:$S$178,$AI45)=1,INDEX(Validation!$U$19:$U$178,MATCH($AI45,Validation!$S$19:$S$178,0)),$Z45)))) -> J VALBUENA | AG45: =IF(COUNTA($A45:$U45)=0,"",IF($A45="","No name",IF($F45="","No date",IF($W45=0,"Date ilegible",IF(NOT(ISNUMBER($N45)),"Hours no numéricas",IF($AA45="NO MATCH","Person no identificada","OK")))))) -> OK | AH45: =IF($W45=0,"No date",IF($W45<Validation!$B$3,"Before period",IF($W45>Validation!$C$3,"After period","In period"))) -> In period | AI45: =IF($Y45="","",TRIM(RIGHT(SUBSTITUTE($Y45," ",REPT(" ",50)),50))) -> VALBUENA | AJ45: =IF($A45="","",IF(NOT(ISERROR(MATCH($A45,Validation!$A$193:$A$217,0))),"Manual mapping",IF(COUNTIF(Validation!$U$19:$U$178,$Z45)>0,"Direct",IF(COUNTIF(Validation!$S$19:$S$178,$AI45)=1,"By surname","Unresolved")))) -> Direct | AK45: =IF($L45="","",IF(MATCH($L45,$L$2:$L$3000,0)<>ROW()-1,"",COUNT($AK$1:$AK44)+1)) | AL45: =IF($G45="","",IF(MATCH($G45,$G$2:$G$3000,0)<>ROW()-1,"",COUNT($AL$1:$AL44)+1)) | AM45: =IF($H45="","",IF(MATCH($H45,$H$2:$H$3000,0)<>ROW()-1,"",COUNT($AM$1:$AM44)+1)) | AN45: =IF($I45="","",IF(MATCH($I45,$I$2:$I$3000,0)<>ROW()-1,"",COUNT($AN$1:$AN44)+1)) | AO45: =IF($Q45="","",IF(MATCH($Q45,$Q$2:$Q$3000,0)<>ROW()-1,"",COUNT($AO$1:$AO44)+1))
A46: J Valbuena | B46: Approved | C46: L. Carollo | D46: 8/19/2026 | F46: 8/19/2026 | G46: Rocking WW Minerals, LLC | H46: RWW PRB Asset VDR | I46: Campbell, WY | J46: 07-41N-72W | K46: Title | M46: ALL | N46: 0.125 | O46: 8/19/2026 7:44:39 PM | Q46: Whitney Wicks | R46: J Valbuena | S46: J Valbuena | T46: 8/19/2026 | U46: Clone AOI Pull and enter the source deed Prune interest Download Runsheet Download Lease Analysis Report | W46: =IF($F46="",0,IFERROR(IF(ISNUMBER($F46),INT($F46),DATE(VALUE(MID(SUBSTITUTE(LEFT($F46,FIND(" ",$F46&" ")-1),"/",REPT(" ",20)),41,20)),VALUE(LEFT(SUBSTITUTE(LEFT($F46,FIND(" ",$F46&" ")-1),"/",REPT(" ",20)),20)),VALUE(MID(SUBSTITUTE(LEFT($F46,FIND(" ",$F46&" ")-1),"/",REPT(" ",20)),21,20)))),0)) -> 46253 | X46: =IF(ISNUMBER($N46),$N46*Validation!$B$5,"") -> 1 | Y46: =IF($A46="","",SUBSTITUTE(SUBSTITUTE(SUBSTITUTE(SUBSTITUTE(SUBSTITUTE(SUBSTITUTE(SUBSTITUTE(UPPER(TRIM($A46)),"Á","A"),"É","E"),"Í","I"),"Ó","O"),"Ú","U"),"Ñ","N"),"Ü","U")) -> J VALBUENA | Z46: =IF($Y46="","",LEFT($Y46,1)&" "&TRIM(RIGHT(SUBSTITUTE($Y46," ",REPT(" ",50)),50))) -> J VALBUENA | AA46: =IF($AF46="","",IF(COUNTIF(Validation!$U$19:$U$178,$AF46)>0,"OK","NO MATCH")) -> OK | AB46: =IF($W46=0,"",IF(AND($W46>=Validation!$B$3,$W46<=Validation!$C$3),"Yes","No")) -> Yes | AC46: =IF($A46="","",$AF46&"|"&TEXT($W46,"yyyy-mm-dd")&"|"&$J46&"|"&$N46) -> J VALBUENA|2026-08-19|07-41N-72W|0.125 | AD46: =IF($AC46="","",IF(COUNTIF($AC$2:$AC$3000,$AC46)>1,"REVIEW","OK")) -> REVIEW | AE46: =IF(OR($W46=0,$O46=""),"",IF(IFERROR(IF(ISNUMBER($O46),INT($O46),DATE(VALUE(MID(SUBSTITUTE(LEFT($O46,FIND(" ",$O46&" ")-1),"/",REPT(" ",20)),41,20)),VALUE(LEFT(SUBSTITUTE(LEFT($O46,FIND(" ",$O46&" ")-1),"/",REPT(" ",20)),20)),VALUE(MID(SUBSTITUTE(LEFT($O46,FIND(" ",$O46&" ")-1),"/",REPT(" ",20)),21,20)))),0)>$W46,"Late","Same day")) -> Same day | AF46: =IF($A46="","",IFERROR(INDEX(Validation!$C$193:$C$217,MATCH($A46,Validation!$A$193:$A$217,0)),IF(COUNTIF(Validation!$U$19:$U$178,$Z46)>0,$Z46,IF(COUNTIF(Validation!$S$19:$S$178,$AI46)=1,INDEX(Validation!$U$19:$U$178,MATCH($AI46,Validation!$S$19:$S$178,0)),$Z46)))) -> J VALBUENA | AG46: =IF(COUNTA($A46:$U46)=0,"",IF($A46="","No name",IF($F46="","No date",IF($W46=0,"Date ilegible",IF(NOT(ISNUMBER($N46)),"Hours no numéricas",IF($AA46="NO MATCH","Person no identificada","OK")))))) -> OK | AH46: =IF($W46=0,"No date",IF($W46<Validation!$B$3,"Before period",IF($W46>Validation!$C$3,"After period","In period"))) -> In period | AI46: =IF($Y46="","",TRIM(RIGHT(SUBSTITUTE($Y46," ",REPT(" ",50)),50))) -> VALBUENA | AJ46: =IF($A46="","",IF(NOT(ISERROR(MATCH($A46,Validation!$A$193:$A$217,0))),"Manual mapping",IF(COUNTIF(Validation!$U$19:$U$178,$Z46)>0,"Direct",IF(COUNTIF(Validation!$S$19:$S$178,$AI46)=1,"By surname","Unresolved")))) -> Direct | AK46: =IF($L46="","",IF(MATCH($L46,$L$2:$L$3000,0)<>ROW()-1,"",COUNT($AK$1:$AK45)+1)) | AL46: =IF($G46="","",IF(MATCH($G46,$G$2:$G$3000,0)<>ROW()-1,"",COUNT($AL$1:$AL45)+1)) | AM46: =IF($H46="","",IF(MATCH($H46,$H$2:$H$3000,0)<>ROW()-1,"",COUNT($AM$1:$AM45)+1)) | AN46: =IF($I46="","",IF(MATCH($I46,$I$2:$I$3000,0)<>ROW()-1,"",COUNT($AN$1:$AN45)+1)) | AO46: =IF($Q46="","",IF(MATCH($Q46,$Q$2:$Q$3000,0)<>ROW()-1,"",COUNT($AO$1:$AO45)+1))
A47: J Valbuena | B47: Approved | C47: L. Carollo | D47: 8/19/2026 | F47: 8/19/2026 | G47: Rocking WW Minerals, LLC | H47: RWW PRB Asset VDR | I47: Campbell, WY | J47: 07-41N-72W | K47: Title | M47: Lots 18 (40.82), 20 (40.45), fka SESW, SESE | N47: 0.125 | O47: 8/19/2026 7:45:34 PM | Q47: Whitney Wicks | R47: J Valbuena | S47: J Valbuena | T47: 8/19/2026 | U47: Clone AOI Pull and enter the source deed Prune interest Download Runsheet Download Lease Analysis Report | W47: =IF($F47="",0,IFERROR(IF(ISNUMBER($F47),INT($F47),DATE(VALUE(MID(SUBSTITUTE(LEFT($F47,FIND(" ",$F47&" ")-1),"/",REPT(" ",20)),41,20)),VALUE(LEFT(SUBSTITUTE(LEFT($F47,FIND(" ",$F47&" ")-1),"/",REPT(" ",20)),20)),VALUE(MID(SUBSTITUTE(LEFT($F47,FIND(" ",$F47&" ")-1),"/",REPT(" ",20)),21,20)))),0)) -> 46253 | X47: =IF(ISNUMBER($N47),$N47*Validation!$B$5,"") -> 1 | Y47: =IF($A47="","",SUBSTITUTE(SUBSTITUTE(SUBSTITUTE(SUBSTITUTE(SUBSTITUTE(SUBSTITUTE(SUBSTITUTE(UPPER(TRIM($A47)),"Á","A"),"É","E"),"Í","I"),"Ó","O"),"Ú","U"),"Ñ","N"),"Ü","U")) -> J VALBUENA | Z47: =IF($Y47="","",LEFT($Y47,1)&" "&TRIM(RIGHT(SUBSTITUTE($Y47," ",REPT(" ",50)),50))) -> J VALBUENA | AA47: =IF($AF47="","",IF(COUNTIF(Validation!$U$19:$U$178,$AF47)>0,"OK","NO MATCH")) -> OK | AB47: =IF($W47=0,"",IF(AND($W47>=Validation!$B$3,$W47<=Validation!$C$3),"Yes","No")) -> Yes | AC47: =IF($A47="","",$AF47&"|"&TEXT($W47,"yyyy-mm-dd")&"|"&$J47&"|"&$N47) -> J VALBUENA|2026-08-19|07-41N-72W|0.125 | AD47: =IF($AC47="","",IF(COUNTIF($AC$2:$AC$3000,$AC47)>1,"REVIEW","OK")) -> REVIEW | AE47: =IF(OR($W47=0,$O47=""),"",IF(IFERROR(IF(ISNUMBER($O47),INT($O47),DATE(VALUE(MID(SUBSTITUTE(LEFT($O47,FIND(" ",$O47&" ")-1),"/",REPT(" ",20)),41,20)),VALUE(LEFT(SUBSTITUTE(LEFT($O47,FIND(" ",$O47&" ")-1),"/",REPT(" ",20)),20)),VALUE(MID(SUBSTITUTE(LEFT($O47,FIND(" ",$O47&" ")-1),"/",REPT(" ",20)),21,20)))),0)>$W47,"Late","Same day")) -> Same day | AF47: =IF($A47="","",IFERROR(INDEX(Validation!$C$193:$C$217,MATCH($A47,Validation!$A$193:$A$217,0)),IF(COUNTIF(Validation!$U$19:$U$178,$Z47)>0,$Z47,IF(COUNTIF(Validation!$S$19:$S$178,$AI47)=1,INDEX(Validation!$U$19:$U$178,MATCH($AI47,Validation!$S$19:$S$178,0)),$Z47)))) -> J VALBUENA | AG47: =IF(COUNTA($A47:$U47)=0,"",IF($A47="","No name",IF($F47="","No date",IF($W47=0,"Date ilegible",IF(NOT(ISNUMBER($N47)),"Hours no numéricas",IF($AA47="NO MATCH","Person no identificada","OK")))))) -> OK | AH47: =IF($W47=0,"No date",IF($W47<Validation!$B$3,"Before period",IF($W47>Validation!$C$3,"After period","In period"))) -> In period | AI47: =IF($Y47="","",TRIM(RIGHT(SUBSTITUTE($Y47," ",REPT(" ",50)),50))) -> VALBUENA | AJ47: =IF($A47="","",IF(NOT(ISERROR(MATCH($A47,Validation!$A$193:$A$217,0))),"Manual mapping",IF(COUNTIF(Validation!$U$19:$U$178,$Z47)>0,"Direct",IF(COUNTIF(Validation!$S$19:$S$178,$AI47)=1,"By surname","Unresolved")))) -> Direct | AK47: =IF($L47="","",IF(MATCH($L47,$L$2:$L$3000,0)<>ROW()-1,"",COUNT($AK$1:$AK46)+1)) | AL47: =IF($G47="","",IF(MATCH($G47,$G$2:$G$3000,0)<>ROW()-1,"",COUNT($AL$1:$AL46)+1)) | AM47: =IF($H47="","",IF(MATCH($H47,$H$2:$H$3000,0)<>ROW()-1,"",COUNT($AM$1:$AM46)+1)) | AN47: =IF($I47="","",IF(MATCH($I47,$I$2:$I$3000,0)<>ROW()-1,"",COUNT($AN$1:$AN46)+1)) | AO47: =IF($Q47="","",IF(MATCH($Q47,$Q$2:$Q$3000,0)<>ROW()-1,"",COUNT($AO$1:$AO46)+1))
A48: J Valbuena | B48: Approved | C48: L. Carollo | D48: 8/19/2026 | F48: 8/19/2026 | G48: Rocking WW Minerals, LLC | H48: RWW PRB Asset VDR | I48: Campbell, WY | J48: 07-41N-72W | K48: Title | M48: Lots 5,10,15,17 | N48: 0.125 | O48: 8/19/2026 7:45:53 PM | Q48: Whitney Wicks | R48: J Valbuena | S48: J Valbuena | T48: 8/19/2026 | U48: Clone AOI Pull and enter the source deed Prune interest Download Runsheet Download Lease Analysis Report | W48: =IF($F48="",0,IFERROR(IF(ISNUMBER($F48),INT($F48),DATE(VALUE(MID(SUBSTITUTE(LEFT($F48,FIND(" ",$F48&" ")-1),"/",REPT(" ",20)),41,20)),VALUE(LEFT(SUBSTITUTE(LEFT($F48,FIND(" ",$F48&" ")-1),"/",REPT(" ",20)),20)),VALUE(MID(SUBSTITUTE(LEFT($F48,FIND(" ",$F48&" ")-1),"/",REPT(" ",20)),21,20)))),0)) -> 46253 | X48: =IF(ISNUMBER($N48),$N48*Validation!$B$5,"") -> 1 | Y48: =IF($A48="","",SUBSTITUTE(SUBSTITUTE(SUBSTITUTE(SUBSTITUTE(SUBSTITUTE(SUBSTITUTE(SUBSTITUTE(UPPER(TRIM($A48)),"Á","A"),"É","E"),"Í","I"),"Ó","O"),"Ú","U"),"Ñ","N"),"Ü","U")) -> J VALBUENA | Z48: =IF($Y48="","",LEFT($Y48,1)&" "&TRIM(RIGHT(SUBSTITUTE($Y48," ",REPT(" ",50)),50))) -> J VALBUENA | AA48: =IF($AF48="","",IF(COUNTIF(Validation!$U$19:$U$178,$AF48)>0,"OK","NO MATCH")) -> OK | AB48: =IF($W48=0,"",IF(AND($W48>=Validation!$B$3,$W48<=Validation!$C$3),"Yes","No")) -> Yes | AC48: =IF($A48="","",$AF48&"|"&TEXT($W48,"yyyy-mm-dd")&"|"&$J48&"|"&$N48) -> J VALBUENA|2026-08-19|07-41N-72W|0.125 | AD48: =IF($AC48="","",IF(COUNTIF($AC$2:$AC$3000,$AC48)>1,"REVIEW","OK")) -> REVIEW | AE48: =IF(OR($W48=0,$O48=""),"",IF(IFERROR(IF(ISNUMBER($O48),INT($O48),DATE(VALUE(MID(SUBSTITUTE(LEFT($O48,FIND(" ",$O48&" ")-1),"/",REPT(" ",20)),41,20)),VALUE(LEFT(SUBSTITUTE(LEFT($O48,FIND(" ",$O48&" ")-1),"/",REPT(" ",20)),20)),VALUE(MID(SUBSTITUTE(LEFT($O48,FIND(" ",$O48&" ")-1),"/",REPT(" ",20)),21,20)))),0)>$W48,"Late","Same day")) -> Same day | AF48: =IF($A48="","",IFERROR(INDEX(Validation!$C$193:$C$217,MATCH($A48,Validation!$A$193:$A$217,0)),IF(COUNTIF(Validation!$U$19:$U$178,$Z48)>0,$Z48,IF(COUNTIF(Validation!$S$19:$S$178,$AI48)=1,INDEX(Validation!$U$19:$U$178,MATCH($AI48,Validation!$S$19:$S$178,0)),$Z48)))) -> J VALBUENA | AG48: =IF(COUNTA($A48:$U48)=0,"",IF($A48="","No name",IF($F48="","No date",IF($W48=0,"Date ilegible",IF(NOT(ISNUMBER($N48)),"Hours no numéricas",IF($AA48="NO MATCH","Person no identificada","OK")))))) -> OK | AH48: =IF($W48=0,"No date",IF($W48<Validation!$B$3,"Before period",IF($W48>Validation!$C$3,"After period","In period"))) -> In period | AI48: =IF($Y48="","",TRIM(RIGHT(SUBSTITUTE($Y48," ",REPT(" ",50)),50))) -> VALBUENA | AJ48: =IF($A48="","",IF(NOT(ISERROR(MATCH($A48,Validation!$A$193:$A$217,0))),"Manual mapping",IF(COUNTIF(Validation!$U$19:$U$178,$Z48)>0,"Direct",IF(COUNTIF(Validation!$S$19:$S$178,$AI48)=1,"By surname","Unresolved")))) -> Direct | AK48: =IF($L48="","",IF(MATCH($L48,$L$2:$L$3000,0)<>ROW()-1,"",COUNT($AK$1:$AK47)+1)) | AL48: =IF($G48="","",IF(MATCH($G48,$G$2:$G$3000,0)<>ROW()-1,"",COUNT($AL$1:$AL47)+1)) | AM48: =IF($H48="","",IF(MATCH($H48,$H$2:$H$3000,0)<>ROW()-1,"",COUNT($AM$1:$AM47)+1)) | AN48: =IF($I48="","",IF(MATCH($I48,$I$2:$I$3000,0)<>ROW()-1,"",COUNT($AN$1:$AN47)+1)) | AO48: =IF($Q48="","",IF(MATCH($Q48,$Q$2:$Q$3000,0)<>ROW()-1,"",COUNT($AO$1:$AO47)+1))
A49: J Valbuena | B49: Approved | C49: L. Carollo | D49: 8/19/2026 | F49: 8/19/2026 | G49: Rocking WW Minerals, LLC | H49: RWW PRB Asset VDR | I49: Converse, WY | J49: 09-35N-69W | K49: Title | M49: NE4NE4, S2 | N49: 0.125 | O49: 8/19/2026 7:46:33 PM | Q49: Whitney Wicks | R49: J Valbuena | S49: J Valbuena | T49: 8/19/2026 | U49: Clone AOI Pull and enter the source deed Prune interest Download Runsheet Download Lease Analysis Report | W49: =IF($F49="",0,IFERROR(IF(ISNUMBER($F49),INT($F49),DATE(VALUE(MID(SUBSTITUTE(LEFT($F49,FIND(" ",$F49&" ")-1),"/",REPT(" ",20)),41,20)),VALUE(LEFT(SUBSTITUTE(LEFT($F49,FIND(" ",$F49&" ")-1),"/",REPT(" ",20)),20)),VALUE(MID(SUBSTITUTE(LEFT($F49,FIND(" ",$F49&" ")-1),"/",REPT(" ",20)),21,20)))),0)) -> 46253 | X49: =IF(ISNUMBER($N49),$N49*Validation!$B$5,"") -> 1 | Y49: =IF($A49="","",SUBSTITUTE(SUBSTITUTE(SUBSTITUTE(SUBSTITUTE(SUBSTITUTE(SUBSTITUTE(SUBSTITUTE(UPPER(TRIM($A49)),"Á","A"),"É","E"),"Í","I"),"Ó","O"),"Ú","U"),"Ñ","N"),"Ü","U")) -> J VALBUENA | Z49: =IF($Y49="","",LEFT($Y49,1)&" "&TRIM(RIGHT(SUBSTITUTE($Y49," ",REPT(" ",50)),50))) -> J VALBUENA | AA49: =IF($AF49="","",IF(COUNTIF(Validation!$U$19:$U$178,$AF49)>0,"OK","NO MATCH")) -> OK | AB49: =IF($W49=0,"",IF(AND($W49>=Validation!$B$3,$W49<=Validation!$C$3),"Yes","No")) -> Yes | AC49: =IF($A49="","",$AF49&"|"&TEXT($W49,"yyyy-mm-dd")&"|"&$J49&"|"&$N49) -> J VALBUENA|2026-08-19|09-35N-69W|0.125 | AD49: =IF($AC49="","",IF(COUNTIF($AC$2:$AC$3000,$AC49)>1,"REVIEW","OK")) -> OK | AE49: =IF(OR($W49=0,$O49=""),"",IF(IFERROR(IF(ISNUMBER($O49),INT($O49),DATE(VALUE(MID(SUBSTITUTE(LEFT($O49,FIND(" ",$O49&" ")-1),"/",REPT(" ",20)),41,20)),VALUE(LEFT(SUBSTITUTE(LEFT($O49,FIND(" ",$O49&" ")-1),"/",REPT(" ",20)),20)),VALUE(MID(SUBSTITUTE(LEFT($O49,FIND(" ",$O49&" ")-1),"/",REPT(" ",20)),21,20)))),0)>$W49,"Late","Same day")) -> Same day | AF49: =IF($A49="","",IFERROR(INDEX(Validation!$C$193:$C$217,MATCH($A49,Validation!$A$193:$A$217,0)),IF(COUNTIF(Validation!$U$19:$U$178,$Z49)>0,$Z49,IF(COUNTIF(Validation!$S$19:$S$178,$AI49)=1,INDEX(Validation!$U$19:$U$178,MATCH($AI49,Validation!$S$19:$S$178,0)),$Z49)))) -> J VALBUENA | AG49: =IF(COUNTA($A49:$U49)=0,"",IF($A49="","No name",IF($F49="","No date",IF($W49=0,"Date ilegible",IF(NOT(ISNUMBER($N49)),"Hours no numéricas",IF($AA49="NO MATCH","Person no identificada","OK")))))) -> OK | AH49: =IF($W49=0,"No date",IF($W49<Validation!$B$3,"Before period",IF($W49>Validation!$C$3,"After period","In period"))) -> In period | AI49: =IF($Y49="","",TRIM(RIGHT(SUBSTITUTE($Y49," ",REPT(" ",50)),50))) -> VALBUENA | AJ49: =IF($A49="","",IF(NOT(ISERROR(MATCH($A49,Validation!$A$193:$A$217,0))),"Manual mapping",IF(COUNTIF(Validation!$U$19:$U$178,$Z49)>0,"Direct",IF(COUNTIF(Validation!$S$19:$S$178,$AI49)=1,"By surname","Unresolved")))) -> Direct | AK49: =IF($L49="","",IF(MATCH($L49,$L$2:$L$3000,0)<>ROW()-1,"",COUNT($AK$1:$AK48)+1)) | AL49: =IF($G49="","",IF(MATCH($G49,$G$2:$G$3000,0)<>ROW()-1,"",COUNT($AL$1:$AL48)+1)) | AM49: =IF($H49="","",IF(MATCH($H49,$H$2:$H$3000,0)<>ROW()-1,"",COUNT($AM$1:$AM48)+1)) | AN49: =IF($I49="","",IF(MATCH($I49,$I$2:$I$3000,0)<>ROW()-1,"",COUNT($AN$1:$AN48)+1)) | AO49: =IF($Q49="","",IF(MATCH($Q49,$Q$2:$Q$3000,0)<>ROW()-1,"",COUNT($AO$1:$AO48)+1))
A50: J Valbuena | B50: Approved | C50: L. Carollo | D50: 8/19/2026 | F50: 8/19/2026 | G50: Rocking WW Minerals, LLC | H50: RWW PRB Asset VDR | I50: Converse, WY | J50: 07-34N-68W | K50: Title | M50: Lot 4, SENW, SESW ; Lot 3 ; NESW ; Lots... | N50: 0.125 | O50: 8/19/2026 7:47:54 PM | Q50: Whitney Wicks | R50: J Valbuena | S50: J Valbuena | T50: 8/19/2026 | U50: Clone AOI Pull and enter the source deed Prune interest Download Runsheet Download Lease Analysis Report | W50: =IF($F50="",0,IFERROR(IF(ISNUMBER($F50),INT($F50),DATE(VALUE(MID(SUBSTITUTE(LEFT($F50,FIND(" ",$F50&" ")-1),"/",REPT(" ",20)),41,20)),VALUE(LEFT(SUBSTITUTE(LEFT($F50,FIND(" ",$F50&" ")-1),"/",REPT(" ",20)),20)),VALUE(MID(SUBSTITUTE(LEFT($F50,FIND(" ",$F50&" ")-1),"/",REPT(" ",20)),21,20)))),0)) -> 46253 | X50: =IF(ISNUMBER($N50),$N50*Validation!$B$5,"") -> 1 | Y50: =IF($A50="","",SUBSTITUTE(SUBSTITUTE(SUBSTITUTE(SUBSTITUTE(SUBSTITUTE(SUBSTITUTE(SUBSTITUTE(UPPER(TRIM($A50)),"Á","A"),"É","E"),"Í","I"),"Ó","O"),"Ú","U"),"Ñ","N"),"Ü","U")) -> J VALBUENA | Z50: =IF($Y50="","",LEFT($Y50,1)&" "&TRIM(RIGHT(SUBSTITUTE($Y50," ",REPT(" ",50)),50))) -> J VALBUENA | AA50: =IF($AF50="","",IF(COUNTIF(Validation!$U$19:$U$178,$AF50)>0,"OK","NO MATCH")) -> OK | AB50: =IF($W50=0,"",IF(AND($W50>=Validation!$B$3,$W50<=Validation!$C$3),"Yes","No")) -> Yes | AC50: =IF($A50="","",$AF50&"|"&TEXT($W50,"yyyy-mm-dd")&"|"&$J50&"|"&$N50) -> J VALBUENA|2026-08-19|07-34N-68W|0.125 | AD50: =IF($AC50="","",IF(COUNTIF($AC$2:$AC$3000,$AC50)>1,"REVIEW","OK")) -> OK | AE50: =IF(OR($W50=0,$O50=""),"",IF(IFERROR(IF(ISNUMBER($O50),INT($O50),DATE(VALUE(MID(SUBSTITUTE(LEFT($O50,FIND(" ",$O50&" ")-1),"/",REPT(" ",20)),41,20)),VALUE(LEFT(SUBSTITUTE(LEFT($O50,FIND(" ",$O50&" ")-1),"/",REPT(" ",20)),20)),VALUE(MID(SUBSTITUTE(LEFT($O50,FIND(" ",$O50&" ")-1),"/",REPT(" ",20)),21,20)))),0)>$W50,"Late","Same day")) -> Same day | AF50: =IF($A50="","",IFERROR(INDEX(Validation!$C$193:$C$217,MATCH($A50,Validation!$A$193:$A$217,0)),IF(COUNTIF(Validation!$U$19:$U$178,$Z50)>0,$Z50,IF(COUNTIF(Validation!$S$19:$S$178,$AI50)=1,INDEX(Validation!$U$19:$U$178,MATCH($AI50,Validation!$S$19:$S$178,0)),$Z50)))) -> J VALBUENA | AG50: =IF(COUNTA($A50:$U50)=0,"",IF($A50="","No name",IF($F50="","No date",IF($W50=0,"Date ilegible",IF(NOT(ISNUMBER($N50)),"Hours no numéricas",IF($AA50="NO MATCH","Person no identificada","OK")))))) -> OK | AH50: =IF($W50=0,"No date",IF($W50<Validation!$B$3,"Before period",IF($W50>Validation!$C$3,"After period","In period"))) -> In period | AI50: =IF($Y50="","",TRIM(RIGHT(SUBSTITUTE($Y50," ",REPT(" ",50)),50))) -> VALBUENA | AJ50: =IF($A50="","",IF(NOT(ISERROR(MATCH($A50,Validation!$A$193:$A$217,0))),"Manual mapping",IF(COUNTIF(Validation!$U$19:$U$178,$Z50)>0,"Direct",IF(COUNTIF(Validation!$S$19:$S$178,$AI50)=1,"By surname","Unresolved")))) -> Direct | AK50: =IF($L50="","",IF(MATCH($L50,$L$2:$L$3000,0)<>ROW()-1,"",COUNT($AK$1:$AK49)+1)) | AL50: =IF($G50="","",IF(MATCH($G50,$G$2:$G$3000,0)<>ROW()-1,"",COUNT($AL$1:$AL49)+1)) | AM50: =IF($H50="","",IF(MATCH($H50,$H$2:$H$3000,0)<>ROW()-1,"",COUNT($AM$1:$AM49)+1)) | AN50: =IF($I50="","",IF(MATCH($I50,$I$2:$I$3000,0)<>ROW()-1,"",COUNT($AN$1:$AN49)+1)) | AO50: =IF($Q50="","",IF(MATCH($Q50,$Q$2:$Q$3000,0)<>ROW()-1,"",COUNT($AO$1:$AO49)+1))
A51: J Valbuena | B51: Approved | C51: L. Carollo | D51: 8/19/2026 | F51: 8/19/2026 | G51: Rocking WW Minerals, LLC | H51: RWW PRB Asset VDR | I51: Campbell, WY | J51: 07-41N-72W | K51: Title | M51: Lots 18, 20 | N51: 0.125 | O51: 8/19/2026 7:48:55 PM | Q51: Whitney Wicks | R51: J Valbuena | S51: J Valbuena | T51: 8/19/2026 | U51: Clone AOI Pull and enter the source deed Prune interest Download Runsheet Download Lease Analysis Report New Asset final | W51: =IF($F51="",0,IFERROR(IF(ISNUMBER($F51),INT($F51),DATE(VALUE(MID(SUBSTITUTE(LEFT($F51,FIND(" ",$F51&" ")-1),"/",REPT(" ",20)),41,20)),VALUE(LEFT(SUBSTITUTE(LEFT($F51,FIND(" ",$F51&" ")-1),"/",REPT(" ",20)),20)),VALUE(MID(SUBSTITUTE(LEFT($F51,FIND(" ",$F51&" ")-1),"/",REPT(" ",20)),21,20)))),0)) -> 46253 | X51: =IF(ISNUMBER($N51),$N51*Validation!$B$5,"") -> 1 | Y51: =IF($A51="","",SUBSTITUTE(SUBSTITUTE(SUBSTITUTE(SUBSTITUTE(SUBSTITUTE(SUBSTITUTE(SUBSTITUTE(UPPER(TRIM($A51)),"Á","A"),"É","E"),"Í","I"),"Ó","O"),"Ú","U"),"Ñ","N"),"Ü","U")) -> J VALBUENA | Z51: =IF($Y51="","",LEFT($Y51,1)&" "&TRIM(RIGHT(SUBSTITUTE($Y51," ",REPT(" ",50)),50))) -> J VALBUENA | AA51: =IF($AF51="","",IF(COUNTIF(Validation!$U$19:$U$178,$AF51)>0,"OK","NO MATCH")) -> OK | AB51: =IF($W51=0,"",IF(AND($W51>=Validation!$B$3,$W51<=Validation!$C$3),"Yes","No")) -> Yes | AC51: =IF($A51="","",$AF51&"|"&TEXT($W51,"yyyy-mm-dd")&"|"&$J51&"|"&$N51) -> J VALBUENA|2026-08-19|07-41N-72W|0.125 | AD51: =IF($AC51="","",IF(COUNTIF($AC$2:$AC$3000,$AC51)>1,"REVIEW","OK")) -> REVIEW | AE51: =IF(OR($W51=0,$O51=""),"",IF(IFERROR(IF(ISNUMBER($O51),INT($O51),DATE(VALUE(MID(SUBSTITUTE(LEFT($O51,FIND(" ",$O51&" ")-1),"/",REPT(" ",20)),41,20)),VALUE(LEFT(SUBSTITUTE(LEFT($O51,FIND(" ",$O51&" ")-1),"/",REPT(" ",20)),20)),VALUE(MID(SUBSTITUTE(LEFT($O51,FIND(" ",$O51&" ")-1),"/",REPT(" ",20)),21,20)))),0)>$W51,"Late","Same day")) -> Same day | AF51: =IF($A51="","",IFERROR(INDEX(Validation!$C$193:$C$217,MATCH($A51,Validation!$A$193:$A$217,0)),IF(COUNTIF(Validation!$U$19:$U$178,$Z51)>0,$Z51,IF(COUNTIF(Validation!$S$19:$S$178,$AI51)=1,INDEX(Validation!$U$19:$U$178,MATCH($AI51,Validation!$S$19:$S$178,0)),$Z51)))) -> J VALBUENA | AG51: =IF(COUNTA($A51:$U51)=0,"",IF($A51="","No name",IF($F51="","No date",IF($W51=0,"Date ilegible",IF(NOT(ISNUMBER($N51)),"Hours no numéricas",IF($AA51="NO MATCH","Person no identificada","OK")))))) -> OK | AH51: =IF($W51=0,"No date",IF($W51<Validation!$B$3,"Before period",IF($W51>Validation!$C$3,"After period","In period"))) -> In period | AI51: =IF($Y51="","",TRIM(RIGHT(SUBSTITUTE($Y51," ",REPT(" ",50)),50))) -> VALBUENA | AJ51: =IF($A51="","",IF(NOT(ISERROR(MATCH($A51,Validation!$A$193:$A$217,0))),"Manual mapping",IF(COUNTIF(Validation!$U$19:$U$178,$Z51)>0,"Direct",IF(COUNTIF(Validation!$S$19:$S$178,$AI51)=1,"By surname","Unresolved")))) -> Direct | AK51: =IF($L51="","",IF(MATCH($L51,$L$2:$L$3000,0)<>ROW()-1,"",COUNT($AK$1:$AK50)+1)) | AL51: =IF($G51="","",IF(MATCH($G51,$G$2:$G$3000,0)<>ROW()-1,"",COUNT($AL$1:$AL50)+1)) | AM51: =IF($H51="","",IF(MATCH($H51,$H$2:$H$3000,0)<>ROW()-1,"",COUNT($AM$1:$AM50)+1)) | AN51: =IF($I51="","",IF(MATCH($I51,$I$2:$I$3000,0)<>ROW()-1,"",COUNT($AN$1:$AN50)+1)) | AO51: =IF($Q51="","",IF(MATCH($Q51,$Q$2:$Q$3000,0)<>ROW()-1,"",COUNT($AO$1:$AO50)+1))
A52: N Espitia | B52: Approved | C52: L. Carollo | D52: 8/19/2026 | F52: 8/19/2026 | G52: Rocking WW Minerals, LLC | H52: RWW PRB Asset VDR | I52: Converse, WY | J52: 07-38N-75W | K52: Title | M52: Lot 4, SESW, S2SE | N52: 0.125 | O52: 8/19/2026 8:52:05 PM | Q52: Whitney Wicks | R52: N Espitia | S52: N Espitia | T52: 8/19/2026 | U52: Completed prune of mentioned legal (section). | W52: =IF($F52="",0,IFERROR(IF(ISNUMBER($F52),INT($F52),DATE(VALUE(MID(SUBSTITUTE(LEFT($F52,FIND(" ",$F52&" ")-1),"/",REPT(" ",20)),41,20)),VALUE(LEFT(SUBSTITUTE(LEFT($F52,FIND(" ",$F52&" ")-1),"/",REPT(" ",20)),20)),VALUE(MID(SUBSTITUTE(LEFT($F52,FIND(" ",$F52&" ")-1),"/",REPT(" ",20)),21,20)))),0)) -> 46253 | X52: =IF(ISNUMBER($N52),$N52*Validation!$B$5,"") -> 1 | Y52: =IF($A52="","",SUBSTITUTE(SUBSTITUTE(SUBSTITUTE(SUBSTITUTE(SUBSTITUTE(SUBSTITUTE(SUBSTITUTE(UPPER(TRIM($A52)),"Á","A"),"É","E"),"Í","I"),"Ó","O"),"Ú","U"),"Ñ","N"),"Ü","U")) -> N ESPITIA | Z52: =IF($Y52="","",LEFT($Y52,1)&" "&TRIM(RIGHT(SUBSTITUTE($Y52," ",REPT(" ",50)),50))) -> N ESPITIA | AA52: =IF($AF52="","",IF(COUNTIF(Validation!$U$19:$U$178,$AF52)>0,"OK","NO MATCH")) -> OK | AB52: =IF($W52=0,"",IF(AND($W52>=Validation!$B$3,$W52<=Validation!$C$3),"Yes","No")) -> Yes | AC52: =IF($A52="","",$AF52&"|"&TEXT($W52,"yyyy-mm-dd")&"|"&$J52&"|"&$N52) -> N ESPITIA|2026-08-19|07-38N-75W|0.125 | AD52: =IF($AC52="","",IF(COUNTIF($AC$2:$AC$3000,$AC52)>1,"REVIEW","OK")) -> OK | AE52: =IF(OR($W52=0,$O52=""),"",IF(IFERROR(IF(ISNUMBER($O52),INT($O52),DATE(VALUE(MID(SUBSTITUTE(LEFT($O52,FIND(" ",$O52&" ")-1),"/",REPT(" ",20)),41,20)),VALUE(LEFT(SUBSTITUTE(LEFT($O52,FIND(" ",$O52&" ")-1),"/",REPT(" ",20)),20)),VALUE(MID(SUBSTITUTE(LEFT($O52,FIND(" ",$O52&" ")-1),"/",REPT(" ",20)),21,20)))),0)>$W52,"Late","Same day")) -> Same day | AF52: =IF($A52="","",IFERROR(INDEX(Validation!$C$193:$C$217,MATCH($A52,Validation!$A$193:$A$217,0)),IF(COUNTIF(Validation!$U$19:$U$178,$Z52)>0,$Z52,IF(COUNTIF(Validation!$S$19:$S$178,$AI52)=1,INDEX(Validation!$U$19:$U$178,MATCH($AI52,Validation!$S$19:$S$178,0)),$Z52)))) -> N ESPITIA | AG52: =IF(COUNTA($A52:$U52)=0,"",IF($A52="","No name",IF($F52="","No date",IF($W52=0,"Date ilegible",IF(NOT(ISNUMBER($N52)),"Hours no numéricas",IF($AA52="NO MATCH","Person no identificada","OK")))))) -> OK | AH52: =IF($W52=0,"No date",IF($W52<Validation!$B$3,"Before period",IF($W52>Validation!$C$3,"After period","In period"))) -> In period | AI52: =IF($Y52="","",TRIM(RIGHT(SUBSTITUTE($Y52," ",REPT(" ",50)),50))) -> ESPITIA | AJ52: =IF($A52="","",IF(NOT(ISERROR(MATCH($A52,Validation!$A$193:$A$217,0))),"Manual mapping",IF(COUNTIF(Validation!$U$19:$U$178,$Z52)>0,"Direct",IF(COUNTIF(Validation!$S$19:$S$178,$AI52)=1,"By surname","Unresolved")))) -> Direct | AK52: =IF($L52="","",IF(MATCH($L52,$L$2:$L$3000,0)<>ROW()-1,"",COUNT($AK$1:$AK51)+1)) | AL52: =IF($G52="","",IF(MATCH($G52,$G$2:$G$3000,0)<>ROW()-1,"",COUNT($AL$1:$AL51)+1)) | AM52: =IF($H52="","",IF(MATCH($H52,$H$2:$H$3000,0)<>ROW()-1,"",COUNT($AM$1:$AM51)+1)) | AN52: =IF($I52="","",IF(MATCH($I52,$I$2:$I$3000,0)<>ROW()-1,"",COUNT($AN$1:$AN51)+1)) | AO52: =IF($Q52="","",IF(MATCH($Q52,$Q$2:$Q$3000,0)<>ROW()-1,"",COUNT($AO$1:$AO51)+1))
A53: N Espitia | B53: Approved | C53: L. Carollo | D53: 8/19/2026 | F53: 8/19/2026 | G53: Rocking WW Minerals, LLC | H53: RWW PRB Asset VDR | I53: Converse, WY | J53: 07-36N-70W | K53: Title | M53: Lots 1,2; E2, E2W2 | N53: 0.125 | O53: 8/19/2026 8:52:26 PM | Q53: Whitney Wicks | R53: N Espitia | S53: N Espitia | T53: 8/19/2026 | U53: Completed prune of mentioned legal (section). | W53: =IF($F53="",0,IFERROR(IF(ISNUMBER($F53),INT($F53),DATE(VALUE(MID(SUBSTITUTE(LEFT($F53,FIND(" ",$F53&" ")-1),"/",REPT(" ",20)),41,20)),VALUE(LEFT(SUBSTITUTE(LEFT($F53,FIND(" ",$F53&" ")-1),"/",REPT(" ",20)),20)),VALUE(MID(SUBSTITUTE(LEFT($F53,FIND(" ",$F53&" ")-1),"/",REPT(" ",20)),21,20)))),0)) -> 46253 | X53: =IF(ISNUMBER($N53),$N53*Validation!$B$5,"") -> 1 | Y53: =IF($A53="","",SUBSTITUTE(SUBSTITUTE(SUBSTITUTE(SUBSTITUTE(SUBSTITUTE(SUBSTITUTE(SUBSTITUTE(UPPER(TRIM($A53)),"Á","A"),"É","E"),"Í","I"),"Ó","O"),"Ú","U"),"Ñ","N"),"Ü","U")) -> N ESPITIA | Z53: =IF($Y53="","",LEFT($Y53,1)&" "&TRIM(RIGHT(SUBSTITUTE($Y53," ",REPT(" ",50)),50))) -> N ESPITIA | AA53: =IF($AF53="","",IF(COUNTIF(Validation!$U$19:$U$178,$AF53)>0,"OK","NO MATCH")) -> OK | AB53: =IF($W53=0,"",IF(AND($W53>=Validation!$B$3,$W53<=Validation!$C$3),"Yes","No")) -> Yes | AC53: =IF($A53="","",$AF53&"|"&TEXT($W53,"yyyy-mm-dd")&"|"&$J53&"|"&$N53) -> N ESPITIA|2026-08-19|07-36N-70W|0.125 | AD53: =IF($AC53="","",IF(COUNTIF($AC$2:$AC$3000,$AC53)>1,"REVIEW","OK")) -> OK | AE53: =IF(OR($W53=0,$O53=""),"",IF(IFERROR(IF(ISNUMBER($O53),INT($O53),DATE(VALUE(MID(SUBSTITUTE(LEFT($O53,FIND(" ",$O53&" ")-1),"/",REPT(" ",20)),41,20)),VALUE(LEFT(SUBSTITUTE(LEFT($O53,FIND(" ",$O53&" ")-1),"/",REPT(" ",20)),20)),VALUE(MID(SUBSTITUTE(LEFT($O53,FIND(" ",$O53&" ")-1),"/",REPT(" ",20)),21,20)))),0)>$W53,"Late","Same day")) -> Same day | AF53: =IF($A53="","",IFERROR(INDEX(Validation!$C$193:$C$217,MATCH($A53,Validation!$A$193:$A$217,0)),IF(COUNTIF(Validation!$U$19:$U$178,$Z53)>0,$Z53,IF(COUNTIF(Validation!$S$19:$S$178,$AI53)=1,INDEX(Validation!$U$19:$U$178,MATCH($AI53,Validation!$S$19:$S$178,0)),$Z53)))) -> N ESPITIA | AG53: =IF(COUNTA($A53:$U53)=0,"",IF($A53="","No name",IF($F53="","No date",IF($W53=0,"Date ilegible",IF(NOT(ISNUMBER($N53)),"Hours no numéricas",IF($AA53="NO MATCH","Person no identificada","OK")))))) -> OK | AH53: =IF($W53=0,"No date",IF($W53<Validation!$B$3,"Before period",IF($W53>Validation!$C$3,"After period","In period"))) -> In period | AI53: =IF($Y53="","",TRIM(RIGHT(SUBSTITUTE($Y53," ",REPT(" ",50)),50))) -> ESPITIA | AJ53: =IF($A53="","",IF(NOT(ISERROR(MATCH($A53,Validation!$A$193:$A$217,0))),"Manual mapping",IF(COUNTIF(Validation!$U$19:$U$178,$Z53)>0,"Direct",IF(COUNTIF(Validation!$S$19:$S$178,$AI53)=1,"By surname","Unresolved")))) -> Direct | AK53: =IF($L53="","",IF(MATCH($L53,$L$2:$L$3000,0)<>ROW()-1,"",COUNT($AK$1:$AK52)+1)) | AL53: =IF($G53="","",IF(MATCH($G53,$G$2:$G$3000,0)<>ROW()-1,"",COUNT($AL$1:$AL52)+1)) | AM53: =IF($H53="","",IF(MATCH($H53,$H$2:$H$3000,0)<>ROW()-1,"",COUNT($AM$1:$AM52)+1)) | AN53: =IF($I53="","",IF(MATCH($I53,$I$2:$I$3000,0)<>ROW()-1,"",COUNT($AN$1:$AN52)+1)) | AO53: =IF($Q53="","",IF(MATCH($Q53,$Q$2:$Q$3000,0)<>ROW()-1,"",COUNT($AO$1:$AO52)+1))
A54: N Espitia | B54: Approved | C54: L. Carollo | D54: 8/19/2026 | F54: 8/19/2026 | G54: Rocking WW Minerals, LLC | H54: RWW PRB Asset VDR | I54: Converse, WY | J54: 08-36N-69W | K54: Title | M54: N2 | N54: 0.25 | O54: 8/19/2026 8:53:06 PM | Q54: Whitney Wicks | R54: N Espitia | S54: N Espitia | T54: 8/19/2026 | U54: Completed prune of mentioned legal (section). | W54: =IF($F54="",0,IFERROR(IF(ISNUMBER($F54),INT($F54),DATE(VALUE(MID(SUBSTITUTE(LEFT($F54,FIND(" ",$F54&" ")-1),"/",REPT(" ",20)),41,20)),VALUE(LEFT(SUBSTITUTE(LEFT($F54,FIND(" ",$F54&" ")-1),"/",REPT(" ",20)),20)),VALUE(MID(SUBSTITUTE(LEFT($F54,FIND(" ",$F54&" ")-1),"/",REPT(" ",20)),21,20)))),0)) -> 46253 | X54: =IF(ISNUMBER($N54),$N54*Validation!$B$5,"") -> 2 | Y54: =IF($A54="","",SUBSTITUTE(SUBSTITUTE(SUBSTITUTE(SUBSTITUTE(SUBSTITUTE(SUBSTITUTE(SUBSTITUTE(UPPER(TRIM($A54)),"Á","A"),"É","E"),"Í","I"),"Ó","O"),"Ú","U"),"Ñ","N"),"Ü","U")) -> N ESPITIA | Z54: =IF($Y54="","",LEFT($Y54,1)&" "&TRIM(RIGHT(SUBSTITUTE($Y54," ",REPT(" ",50)),50))) -> N ESPITIA | AA54: =IF($AF54="","",IF(COUNTIF(Validation!$U$19:$U$178,$AF54)>0,"OK","NO MATCH")) -> OK | AB54: =IF($W54=0,"",IF(AND($W54>=Validation!$B$3,$W54<=Validation!$C$3),"Yes","No")) -> Yes | AC54: =IF($A54="","",$AF54&"|"&TEXT($W54,"yyyy-mm-dd")&"|"&$J54&"|"&$N54) -> N ESPITIA|2026-08-19|08-36N-69W|0.25 | AD54: =IF($AC54="","",IF(COUNTIF($AC$2:$AC$3000,$AC54)>1,"REVIEW","OK")) -> OK | AE54: =IF(OR($W54=0,$O54=""),"",IF(IFERROR(IF(ISNUMBER($O54),INT($O54),DATE(VALUE(MID(SUBSTITUTE(LEFT($O54,FIND(" ",$O54&" ")-1),"/",REPT(" ",20)),41,20)),VALUE(LEFT(SUBSTITUTE(LEFT($O54,FIND(" ",$O54&" ")-1),"/",REPT(" ",20)),20)),VALUE(MID(SUBSTITUTE(LEFT($O54,FIND(" ",$O54&" ")-1),"/",REPT(" ",20)),21,20)))),0)>$W54,"Late","Same day")) -> Same day | AF54: =IF($A54="","",IFERROR(INDEX(Validation!$C$193:$C$217,MATCH($A54,Validation!$A$193:$A$217,0)),IF(COUNTIF(Validation!$U$19:$U$178,$Z54)>0,$Z54,IF(COUNTIF(Validation!$S$19:$S$178,$AI54)=1,INDEX(Validation!$U$19:$U$178,MATCH($AI54,Validation!$S$19:$S$178,0)),$Z54)))) -> N ESPITIA | AG54: =IF(COUNTA($A54:$U54)=0,"",IF($A54="","No name",IF($F54="","No date",IF($W54=0,"Date ilegible",IF(NOT(ISNUMBER($N54)),"Hours no numéricas",IF($AA54="NO MATCH","Person no identificada","OK")))))) -> OK | AH54: =IF($W54=0,"No date",IF($W54<Validation!$B$3,"Before period",IF($W54>Validation!$C$3,"After period","In period"))) -> In period | AI54: =IF($Y54="","",TRIM(RIGHT(SUBSTITUTE($Y54," ",REPT(" ",50)),50))) -> ESPITIA | AJ54: =IF($A54="","",IF(NOT(ISERROR(MATCH($A54,Validation!$A$193:$A$217,0))),"Manual mapping",IF(COUNTIF(Validation!$U$19:$U$178,$Z54)>0,"Direct",IF(COUNTIF(Validation!$S$19:$S$178,$AI54)=1,"By surname","Unresolved")))) -> Direct | AK54: =IF($L54="","",IF(MATCH($L54,$L$2:$L$3000,0)<>ROW()-1,"",COUNT($AK$1:$AK53)+1)) | AL54: =IF($G54="","",IF(MATCH($G54,$G$2:$G$3000,0)<>ROW()-1,"",COUNT($AL$1:$AL53)+1)) | AM54: =IF($H54="","",IF(MATCH($H54,$H$2:$H$3000,0)<>ROW()-1,"",COUNT($AM$1:$AM53)+1)) | AN54: =IF($I54="","",IF(MATCH($I54,$I$2:$I$3000,0)<>ROW()-1,"",COUNT($AN$1:$AN53)+1)) | AO54: =IF($Q54="","",IF(MATCH($Q54,$Q$2:$Q$3000,0)<>ROW()-1,"",COUNT($AO$1:$AO53)+1))
A55: N Espitia | B55: Approved | C55: L. Carollo | D55: 8/19/2026 | F55: 8/19/2026 | G55: Rocking WW Minerals, LLC | H55: RWW PRB Asset VDR | I55: Converse, WY | J55: 08-36N-70W | K55: Title | M55: W2NE, NENW, NWNW, SWNW, N2SE | N55: 0.25 | O55: 8/19/2026 8:53:21 PM | Q55: Whitney Wicks | R55: N Espitia | S55: N Espitia | T55: 8/19/2026 | U55: Completed prune of mentioned legal (section). | W55: =IF($F55="",0,IFERROR(IF(ISNUMBER($F55),INT($F55),DATE(VALUE(MID(SUBSTITUTE(LEFT($F55,FIND(" ",$F55&" ")-1),"/",REPT(" ",20)),41,20)),VALUE(LEFT(SUBSTITUTE(LEFT($F55,FIND(" ",$F55&" ")-1),"/",REPT(" ",20)),20)),VALUE(MID(SUBSTITUTE(LEFT($F55,FIND(" ",$F55&" ")-1),"/",REPT(" ",20)),21,20)))),0)) -> 46253 | X55: =IF(ISNUMBER($N55),$N55*Validation!$B$5,"") -> 2 | Y55: =IF($A55="","",SUBSTITUTE(SUBSTITUTE(SUBSTITUTE(SUBSTITUTE(SUBSTITUTE(SUBSTITUTE(SUBSTITUTE(UPPER(TRIM($A55)),"Á","A"),"É","E"),"Í","I"),"Ó","O"),"Ú","U"),"Ñ","N"),"Ü","U")) -> N ESPITIA | Z55: =IF($Y55="","",LEFT($Y55,1)&" "&TRIM(RIGHT(SUBSTITUTE($Y55," ",REPT(" ",50)),50))) -> N ESPITIA | AA55: =IF($AF55="","",IF(COUNTIF(Validation!$U$19:$U$178,$AF55)>0,"OK","NO MATCH")) -> OK | AB55: =IF($W55=0,"",IF(AND($W55>=Validation!$B$3,$W55<=Validation!$C$3),"Yes","No")) -> Yes | AC55: =IF($A55="","",$AF55&"|"&TEXT($W55,"yyyy-mm-dd")&"|"&$J55&"|"&$N55) -> N ESPITIA|2026-08-19|08-36N-70W|0.25 | AD55: =IF($AC55="","",IF(COUNTIF($AC$2:$AC$3000,$AC55)>1,"REVIEW","OK")) -> OK | AE55: =IF(OR($W55=0,$O55=""),"",IF(IFERROR(IF(ISNUMBER($O55),INT($O55),DATE(VALUE(MID(SUBSTITUTE(LEFT($O55,FIND(" ",$O55&" ")-1),"/",REPT(" ",20)),41,20)),VALUE(LEFT(SUBSTITUTE(LEFT($O55,FIND(" ",$O55&" ")-1),"/",REPT(" ",20)),20)),VALUE(MID(SUBSTITUTE(LEFT($O55,FIND(" ",$O55&" ")-1),"/",REPT(" ",20)),21,20)))),0)>$W55,"Late","Same day")) -> Same day | AF55: =IF($A55="","",IFERROR(INDEX(Validation!$C$193:$C$217,MATCH($A55,Validation!$A$193:$A$217,0)),IF(COUNTIF(Validation!$U$19:$U$178,$Z55)>0,$Z55,IF(COUNTIF(Validation!$S$19:$S$178,$AI55)=1,INDEX(Validation!$U$19:$U$178,MATCH($AI55,Validation!$S$19:$S$178,0)),$Z55)))) -> N ESPITIA | AG55: =IF(COUNTA($A55:$U55)=0,"",IF($A55="","No name",IF($F55="","No date",IF($W55=0,"Date ilegible",IF(NOT(ISNUMBER($N55)),"Hours no numéricas",IF($AA55="NO MATCH","Person no identificada","OK")))))) -> OK | AH55: =IF($W55=0,"No date",IF($W55<Validation!$B$3,"Before period",IF($W55>Validation!$C$3,"After period","In period"))) -> In period | AI55: =IF($Y55="","",TRIM(RIGHT(SUBSTITUTE($Y55," ",REPT(" ",50)),50))) -> ESPITIA | AJ55: =IF($A55="","",IF(NOT(ISERROR(MATCH($A55,Validation!$A$193:$A$217,0))),"Manual mapping",IF(COUNTIF(Validation!$U$19:$U$178,$Z55)>0,"Direct",IF(COUNTIF(Validation!$S$19:$S$178,$AI55)=1,"By surname","Unresolved")))) -> Direct | AK55: =IF($L55="","",IF(MATCH($L55,$L$2:$L$3000,0)<>ROW()-1,"",COUNT($AK$1:$AK54)+1)) | AL55: =IF($G55="","",IF(MATCH($G55,$G$2:$G$3000,0)<>ROW()-1,"",COUNT($AL$1:$AL54)+1)) | AM55: =IF($H55="","",IF(MATCH($H55,$H$2:$H$3000,0)<>ROW()-1,"",COUNT($AM$1:$AM54)+1)) | AN55: =IF($I55="","",IF(MATCH($I55,$I$2:$I$3000,0)<>ROW()-1,"",COUNT($AN$1:$AN54)+1)) | AO55: =IF($Q55="","",IF(MATCH($Q55,$Q$2:$Q$3000,0)<>ROW()-1,"",COUNT($AO$1:$AO54)+1))
A56: N Espitia | B56: Approved | C56: L. Carollo | D56: 8/19/2026 | F56: 8/19/2026 | G56: Rocking WW Minerals, LLC | H56: RWW PRB Asset VDR | I56: Converse, WY | J56: 08-36N-70W | K56: Title | M56: NWNW, SWNW, SENW | N56: 0.125 | O56: 8/19/2026 8:53:59 PM | Q56: Whitney Wicks | R56: N Espitia | S56: N Espitia | T56: 8/19/2026 | U56: Started prunining of mentioned legal (section). | W56: =IF($F56="",0,IFERROR(IF(ISNUMBER($F56),INT($F56),DATE(VALUE(MID(SUBSTITUTE(LEFT($F56,FIND(" ",$F56&" ")-1),"/",REPT(" ",20)),41,20)),VALUE(LEFT(SUBSTITUTE(LEFT($F56,FIND(" ",$F56&" ")-1),"/",REPT(" ",20)),20)),VALUE(MID(SUBSTITUTE(LEFT($F56,FIND(" ",$F56&" ")-1),"/",REPT(" ",20)),21,20)))),0)) -> 46253 | X56: =IF(ISNUMBER($N56),$N56*Validation!$B$5,"") -> 1 | Y56: =IF($A56="","",SUBSTITUTE(SUBSTITUTE(SUBSTITUTE(SUBSTITUTE(SUBSTITUTE(SUBSTITUTE(SUBSTITUTE(UPPER(TRIM($A56)),"Á","A"),"É","E"),"Í","I"),"Ó","O"),"Ú","U"),"Ñ","N"),"Ü","U")) -> N ESPITIA | Z56: =IF($Y56="","",LEFT($Y56,1)&" "&TRIM(RIGHT(SUBSTITUTE($Y56," ",REPT(" ",50)),50))) -> N ESPITIA | AA56: =IF($AF56="","",IF(COUNTIF(Validation!$U$19:$U$178,$AF56)>0,"OK","NO MATCH")) -> OK | AB56: =IF($W56=0,"",IF(AND($W56>=Validation!$B$3,$W56<=Validation!$C$3),"Yes","No")) -> Yes | AC56: =IF($A56="","",$AF56&"|"&TEXT($W56,"yyyy-mm-dd")&"|"&$J56&"|"&$N56) -> N ESPITIA|2026-08-19|08-36N-70W|0.125 | AD56: =IF($AC56="","",IF(COUNTIF($AC$2:$AC$3000,$AC56)>1,"REVIEW","OK")) -> OK | AE56: =IF(OR($W56=0,$O56=""),"",IF(IFERROR(IF(ISNUMBER($O56),INT($O56),DATE(VALUE(MID(SUBSTITUTE(LEFT($O56,FIND(" ",$O56&" ")-1),"/",REPT(" ",20)),41,20)),VALUE(LEFT(SUBSTITUTE(LEFT($O56,FIND(" ",$O56&" ")-1),"/",REPT(" ",20)),20)),VALUE(MID(SUBSTITUTE(LEFT($O56,FIND(" ",$O56&" ")-1),"/",REPT(" ",20)),21,20)))),0)>$W56,"Late","Same day")) -> Same day | AF56: =IF($A56="","",IFERROR(INDEX(Validation!$C$193:$C$217,MATCH($A56,Validation!$A$193:$A$217,0)),IF(COUNTIF(Validation!$U$19:$U$178,$Z56)>0,$Z56,IF(COUNTIF(Validation!$S$19:$S$178,$AI56)=1,INDEX(Validation!$U$19:$U$178,MATCH($AI56,Validation!$S$19:$S$178,0)),$Z56)))) -> N ESPITIA | AG56: =IF(COUNTA($A56:$U56)=0,"",IF($A56="","No name",IF($F56="","No date",IF($W56=0,"Date ilegible",IF(NOT(ISNUMBER($N56)),"Hours no numéricas",IF($AA56="NO MATCH","Person no identificada","OK")))))) -> OK | AH56: =IF($W56=0,"No date",IF($W56<Validation!$B$3,"Before period",IF($W56>Validation!$C$3,"After period","In period"))) -> In period | AI56: =IF($Y56="","",TRIM(RIGHT(SUBSTITUTE($Y56," ",REPT(" ",50)),50))) -> ESPITIA | AJ56: =IF($A56="","",IF(NOT(ISERROR(MATCH($A56,Validation!$A$193:$A$217,0))),"Manual mapping",IF(COUNTIF(Validation!$U$19:$U$178,$Z56)>0,"Direct",IF(COUNTIF(Validation!$S$19:$S$178,$AI56)=1,"By surname","Unresolved")))) -> Direct | AK56: =IF($L56="","",IF(MATCH($L56,$L$2:$L$3000,0)<>ROW()-1,"",COUNT($AK$1:$AK55)+1)) | AL56: =IF($G56="","",IF(MATCH($G56,$G$2:$G$3000,0)<>ROW()-1,"",COUNT($AL$1:$AL55)+1)) | AM56: =IF($H56="","",IF(MATCH($H56,$H$2:$H$3000,0)<>ROW()-1,"",COUNT($AM$1:$AM55)+1)) | AN56: =IF($I56="","",IF(MATCH($I56,$I$2:$I$3000,0)<>ROW()-1,"",COUNT($AN$1:$AN55)+1)) | AO56: =IF($Q56="","",IF(MATCH($Q56,$Q$2:$Q$3000,0)<>ROW()-1,"",COUNT($AO$1:$AO55)+1))
A57: N Espitia | B57: Approved | C57: L. Carollo | D57: 8/19/2026 | F57: 8/19/2026 | G57: Rocking WW Minerals, LLC | H57: RWW PRB Asset VDR | I57: Converse, WY | K57: Project Management | M57: Project management | N57: 0.125 | O57: 8/19/2026 8:59:14 PM | Q57: Whitney Wicks | R57: N Espitia | S57: N Espitia | T57: 8/19/2026 | U57: Supported project by assigning, answering questions, etc. | W57: =IF($F57="",0,IFERROR(IF(ISNUMBER($F57),INT($F57),DATE(VALUE(MID(SUBSTITUTE(LEFT($F57,FIND(" ",$F57&" ")-1),"/",REPT(" ",20)),41,20)),VALUE(LEFT(SUBSTITUTE(LEFT($F57,FIND(" ",$F57&" ")-1),"/",REPT(" ",20)),20)),VALUE(MID(SUBSTITUTE(LEFT($F57,FIND(" ",$F57&" ")-1),"/",REPT(" ",20)),21,20)))),0)) -> 46253 | X57: =IF(ISNUMBER($N57),$N57*Validation!$B$5,"") -> 1 | Y57: =IF($A57="","",SUBSTITUTE(SUBSTITUTE(SUBSTITUTE(SUBSTITUTE(SUBSTITUTE(SUBSTITUTE(SUBSTITUTE(UPPER(TRIM($A57)),"Á","A"),"É","E"),"Í","I"),"Ó","O"),"Ú","U"),"Ñ","N"),"Ü","U")) -> N ESPITIA | Z57: =IF($Y57="","",LEFT($Y57,1)&" "&TRIM(RIGHT(SUBSTITUTE($Y57," ",REPT(" ",50)),50))) -> N ESPITIA | AA57: =IF($AF57="","",IF(COUNTIF(Validation!$U$19:$U$178,$AF57)>0,"OK","NO MATCH")) -> OK | AB57: =IF($W57=0,"",IF(AND($W57>=Validation!$B$3,$W57<=Validation!$C$3),"Yes","No")) -> Yes | AC57: =IF($A57="","",$AF57&"|"&TEXT($W57,"yyyy-mm-dd")&"|"&$J57&"|"&$N57) -> N ESPITIA|2026-08-19||0.125 | AD57: =IF($AC57="","",IF(COUNTIF($AC$2:$AC$3000,$AC57)>1,"REVIEW","OK")) -> OK | AE57: =IF(OR($W57=0,$O57=""),"",IF(IFERROR(IF(ISNUMBER($O57),INT($O57),DATE(VALUE(MID(SUBSTITUTE(LEFT($O57,FIND(" ",$O57&" ")-1),"/",REPT(" ",20)),41,20)),VALUE(LEFT(SUBSTITUTE(LEFT($O57,FIND(" ",$O57&" ")-1),"/",REPT(" ",20)),20)),VALUE(MID(SUBSTITUTE(LEFT($O57,FIND(" ",$O57&" ")-1),"/",REPT(" ",20)),21,20)))),0)>$W57,"Late","Same day")) -> Same day | AF57: =IF($A57="","",IFERROR(INDEX(Validation!$C$193:$C$217,MATCH($A57,Validation!$A$193:$A$217,0)),IF(COUNTIF(Validation!$U$19:$U$178,$Z57)>0,$Z57,IF(COUNTIF(Validation!$S$19:$S$178,$AI57)=1,INDEX(Validation!$U$19:$U$178,MATCH($AI57,Validation!$S$19:$S$178,0)),$Z57)))) -> N ESPITIA | AG57: =IF(COUNTA($A57:$U57)=0,"",IF($A57="","No name",IF($F57="","No date",IF($W57=0,"Date ilegible",IF(NOT(ISNUMBER($N57)),"Hours no numéricas",IF($AA57="NO MATCH","Person no identificada","OK")))))) -> OK | AH57: =IF($W57=0,"No date",IF($W57<Validation!$B$3,"Before period",IF($W57>Validation!$C$3,"After period","In period"))) -> In period | AI57: =IF($Y57="","",TRIM(RIGHT(SUBSTITUTE($Y57," ",REPT(" ",50)),50))) -> ESPITIA | AJ57: =IF($A57="","",IF(NOT(ISERROR(MATCH($A57,Validation!$A$193:$A$217,0))),"Manual mapping",IF(COUNTIF(Validation!$U$19:$U$178,$Z57)>0,"Direct",IF(COUNTIF(Validation!$S$19:$S$178,$AI57)=1,"By surname","Unresolved")))) -> Direct | AK57: =IF($L57="","",IF(MATCH($L57,$L$2:$L$3000,0)<>ROW()-1,"",COUNT($AK$1:$AK56)+1)) | AL57: =IF($G57="","",IF(MATCH($G57,$G$2:$G$3000,0)<>ROW()-1,"",COUNT($AL$1:$AL56)+1)) | AM57: =IF($H57="","",IF(MATCH($H57,$H$2:$H$3000,0)<>ROW()-1,"",COUNT($AM$1:$AM56)+1)) | AN57: =IF($I57="","",IF(MATCH($I57,$I$2:$I$3000,0)<>ROW()-1,"",COUNT($AN$1:$AN56)+1)) | AO57: =IF($Q57="","",IF(MATCH($Q57,$Q$2:$Q$3000,0)<>ROW()-1,"",COUNT($AO$1:$AO56)+1))
A58: N Espitia | B58: Approved | C58: L. Carollo | D58: 8/19/2026 | F58: 8/19/2026 | G58: Rocking WW Minerals, LLC | H58: RWW PRB Asset VDR | I58: Campbell, WY | J58: 01-41N-74W | K58: Title | M58: E2 | N58: 0.125 | O58: 8/20/2026 3:05:13 AM | Q58: Whitney Wicks | R58: N Espitia | S58: N Espitia | T58: 8/20/2026 | U58: Completed prune of mentioned legal (section). | W58: =IF($F58="",0,IFERROR(IF(ISNUMBER($F58),INT($F58),DATE(VALUE(MID(SUBSTITUTE(LEFT($F58,FIND(" ",$F58&" ")-1),"/",REPT(" ",20)),41,20)),VALUE(LEFT(SUBSTITUTE(LEFT($F58,FIND(" ",$F58&" ")-1),"/",REPT(" ",20)),20)),VALUE(MID(SUBSTITUTE(LEFT($F58,FIND(" ",$F58&" ")-1),"/",REPT(" ",20)),21,20)))),0)) -> 46253 | X58: =IF(ISNUMBER($N58),$N58*Validation!$B$5,"") -> 1 | Y58: =IF($A58="","",SUBSTITUTE(SUBSTITUTE(SUBSTITUTE(SUBSTITUTE(SUBSTITUTE(SUBSTITUTE(SUBSTITUTE(UPPER(TRIM($A58)),"Á","A"),"É","E"),"Í","I"),"Ó","O"),"Ú","U"),"Ñ","N"),"Ü","U")) -> N ESPITIA | Z58: =IF($Y58="","",LEFT($Y58,1)&" "&TRIM(RIGHT(SUBSTITUTE($Y58," ",REPT(" ",50)),50))) -> N ESPITIA | AA58: =IF($AF58="","",IF(COUNTIF(Validation!$U$19:$U$178,$AF58)>0,"OK","NO MATCH")) -> OK | AB58: =IF($W58=0,"",IF(AND($W58>=Validation!$B$3,$W58<=Validation!$C$3),"Yes","No")) -> Yes | AC58: =IF($A58="","",$AF58&"|"&TEXT($W58,"yyyy-mm-dd")&"|"&$J58&"|"&$N58) -> N ESPITIA|2026-08-19|01-41N-74W|0.125 | AD58: =IF($AC58="","",IF(COUNTIF($AC$2:$AC$3000,$AC58)>1,"REVIEW","OK")) -> OK | AE58: =IF(OR($W58=0,$O58=""),"",IF(IFERROR(IF(ISNUMBER($O58),INT($O58),DATE(VALUE(MID(SUBSTITUTE(LEFT($O58,FIND(" ",$O58&" ")-1),"/",REPT(" ",20)),41,20)),VALUE(LEFT(SUBSTITUTE(LEFT($O58,FIND(" ",$O58&" ")-1),"/",REPT(" ",20)),20)),VALUE(MID(SUBSTITUTE(LEFT($O58,FIND(" ",$O58&" ")-1),"/",REPT(" ",20)),21,20)))),0)>$W58,"Late","Same day")) -> Late | AF58: =IF($A58="","",IFERROR(INDEX(Validation!$C$193:$C$217,MATCH($A58,Validation!$A$193:$A$217,0)),IF(COUNTIF(Validation!$U$19:$U$178,$Z58)>0,$Z58,IF(COUNTIF(Validation!$S$19:$S$178,$AI58)=1,INDEX(Validation!$U$19:$U$178,MATCH($AI58,Validation!$S$19:$S$178,0)),$Z58)))) -> N ESPITIA | AG58: =IF(COUNTA($A58:$U58)=0,"",IF($A58="","No name",IF($F58="","No date",IF($W58=0,"Date ilegible",IF(NOT(ISNUMBER($N58)),"Hours no numéricas",IF($AA58="NO MATCH","Person no identificada","OK")))))) -> OK | AH58: =IF($W58=0,"No date",IF($W58<Validation!$B$3,"Before period",IF($W58>Validation!$C$3,"After period","In period"))) -> In period | AI58: =IF($Y58="","",TRIM(RIGHT(SUBSTITUTE($Y58," ",REPT(" ",50)),50))) -> ESPITIA | AJ58: =IF($A58="","",IF(NOT(ISERROR(MATCH($A58,Validation!$A$193:$A$217,0))),"Manual mapping",IF(COUNTIF(Validation!$U$19:$U$178,$Z58)>0,"Direct",IF(COUNTIF(Validation!$S$19:$S$178,$AI58)=1,"By surname","Unresolved")))) -> Direct | AK58: =IF($L58="","",IF(MATCH($L58,$L$2:$L$3000,0)<>ROW()-1,"",COUNT($AK$1:$AK57)+1)) | AL58: =IF($G58="","",IF(MATCH($G58,$G$2:$G$3000,0)<>ROW()-1,"",COUNT($AL$1:$AL57)+1)) | AM58: =IF($H58="","",IF(MATCH($H58,$H$2:$H$3000,0)<>ROW()-1,"",COUNT($AM$1:$AM57)+1)) | AN58: =IF($I58="","",IF(MATCH($I58,$I$2:$I$3000,0)<>ROW()-1,"",COUNT($AN$1:$AN57)+1)) | AO58: =IF($Q58="","",IF(MATCH($Q58,$Q$2:$Q$3000,0)<>ROW()-1,"",COUNT($AO$1:$AO57)+1))
A59: N Espitia | B59: Approved | C59: L. Carollo | D59: 8/19/2026 | F59: 8/19/2026 | G59: Rocking WW Minerals, LLC | H59: RWW PRB Asset VDR | I59: Converse, WY | J59: 22-39N-73W | K59: Title | M59: NENW ; NWNW ; S2NW, SW | N59: 0.125 | O59: 8/20/2026 3:06:05 AM | Q59: Whitney Wicks | R59: N Espitia | S59: N Espitia | T59: 8/20/2026 | U59: Completed prune of mentioned legal (section). Completed as well 24-36N-70W (SW) | W59: =IF($F59="",0,IFERROR(IF(ISNUMBER($F59),INT($F59),DATE(VALUE(MID(SUBSTITUTE(LEFT($F59,FIND(" ",$F59&" ")-1),"/",REPT(" ",20)),41,20)),VALUE(LEFT(SUBSTITUTE(LEFT($F59,FIND(" ",$F59&" ")-1),"/",REPT(" ",20)),20)),VALUE(MID(SUBSTITUTE(LEFT($F59,FIND(" ",$F59&" ")-1),"/",REPT(" ",20)),21,20)))),0)) -> 46253 | X59: =IF(ISNUMBER($N59),$N59*Validation!$B$5,"") -> 1 | Y59: =IF($A59="","",SUBSTITUTE(SUBSTITUTE(SUBSTITUTE(SUBSTITUTE(SUBSTITUTE(SUBSTITUTE(SUBSTITUTE(UPPER(TRIM($A59)),"Á","A"),"É","E"),"Í","I"),"Ó","O"),"Ú","U"),"Ñ","N"),"Ü","U")) -> N ESPITIA | Z59: =IF($Y59="","",LEFT($Y59,1)&" "&TRIM(RIGHT(SUBSTITUTE($Y59," ",REPT(" ",50)),50))) -> N ESPITIA | AA59: =IF($AF59="","",IF(COUNTIF(Validation!$U$19:$U$178,$AF59)>0,"OK","NO MATCH")) -> OK | AB59: =IF($W59=0,"",IF(AND($W59>=Validation!$B$3,$W59<=Validation!$C$3),"Yes","No")) -> Yes | AC59: =IF($A59="","",$AF59&"|"&TEXT($W59,"yyyy-mm-dd")&"|"&$J59&"|"&$N59) -> N ESPITIA|2026-08-19|22-39N-73W|0.125 | AD59: =IF($AC59="","",IF(COUNTIF($AC$2:$AC$3000,$AC59)>1,"REVIEW","OK")) -> OK | AE59: =IF(OR($W59=0,$O59=""),"",IF(IFERROR(IF(ISNUMBER($O59),INT($O59),DATE(VALUE(MID(SUBSTITUTE(LEFT($O59,FIND(" ",$O59&" ")-1),"/",REPT(" ",20)),41,20)),VALUE(LEFT(SUBSTITUTE(LEFT($O59,FIND(" ",$O59&" ")-1),"/",REPT(" ",20)),20)),VALUE(MID(SUBSTITUTE(LEFT($O59,FIND(" ",$O59&" ")-1),"/",REPT(" ",20)),21,20)))),0)>$W59,"Late","Same day")) -> Late | AF59: =IF($A59="","",IFERROR(INDEX(Validation!$C$193:$C$217,MATCH($A59,Validation!$A$193:$A$217,0)),IF(COUNTIF(Validation!$U$19:$U$178,$Z59)>0,$Z59,IF(COUNTIF(Validation!$S$19:$S$178,$AI59)=1,INDEX(Validation!$U$19:$U$178,MATCH($AI59,Validation!$S$19:$S$178,0)),$Z59)))) -> N ESPITIA | AG59: =IF(COUNTA($A59:$U59)=0,"",IF($A59="","No name",IF($F59="","No date",IF($W59=0,"Date ilegible",IF(NOT(ISNUMBER($N59)),"Hours no numéricas",IF($AA59="NO MATCH","Person no identificada","OK")))))) -> OK | AH59: =IF($W59=0,"No date",IF($W59<Validation!$B$3,"Before period",IF($W59>Validation!$C$3,"After period","In period"))) -> In period | AI59: =IF($Y59="","",TRIM(RIGHT(SUBSTITUTE($Y59," ",REPT(" ",50)),50))) -> ESPITIA | AJ59: =IF($A59="","",IF(NOT(ISERROR(MATCH($A59,Validation!$A$193:$A$217,0))),"Manual mapping",IF(COUNTIF(Validation!$U$19:$U$178,$Z59)>0,"Direct",IF(COUNTIF(Validation!$S$19:$S$178,$AI59)=1,"By surname","Unresolved")))) -> Direct | AK59: =IF($L59="","",IF(MATCH($L59,$L$2:$L$3000,0)<>ROW()-1,"",COUNT($AK$1:$AK58)+1)) | AL59: =IF($G59="","",IF(MATCH($G59,$G$2:$G$3000,0)<>ROW()-1,"",COUNT($AL$1:$AL58)+1)) | AM59: =IF($H59="","",IF(MATCH($H59,$H$2:$H$3000,0)<>ROW()-1,"",COUNT($AM$1:$AM58)+1)) | AN59: =IF($I59="","",IF(MATCH($I59,$I$2:$I$3000,0)<>ROW()-1,"",COUNT($AN$1:$AN58)+1)) | AO59: =IF($Q59="","",IF(MATCH($Q59,$Q$2:$Q$3000,0)<>ROW()-1,"",COUNT($AO$1:$AO58)+1))
